Workbook
Name Xперемен: #REF!
Name Yперемен: #REF!

Sheet Базовый сценарий >>

Sheet ОПУ БС
B2: Отчёт о прибылях и убытках за год, тыс. руб. | K2: Сезонность >>
C3: 2025 | D3: 2026 | E3: 2027 | F3: 2028 | G3: 2029 | H3: 2030 | I3: 2031 | L3: Янв | M3: Фев | N3: Мар | O3: Апр | P3: Май | Q3: Июн | R3: Июл | S3: Авг | T3: Сен | U3: Окт | V3: Ноя | W3: Дек
B4: Выручка от реализации | C4: =C5+C33+C35+C37+C39 -> 848093.51 | D4: =D5+D33+D35+D37+D39 -> 1029160.5 | E4: =E5+E33+E35+E37+E39 -> 1337307.8 | F4: =F5+F33+F35+F37+F39 -> 1750307.9 | G4: =G5+G33+G35+G37+G39 -> 2314273.9 | H4: =H5+H33+H35+H37+H39 -> 3061607.5 | I4: =I5+I33+I35+I37+I39 -> 4051713.8
B5: Готовая продукция | C5: =C6+C19+C32 -> 825093.51 | D5: =D6+D19+D32 -> 1005125.5 | E5: =E6+E19+E32 -> 1312311.4 | F5: =F6+F19+F32 -> 1724311.7 | G5: =G6+G19+G32 -> 2287237.8 | H5: =H6+H19+H32 -> 3033490 | I5: =I6+I19+I32 -> 4022471.5
B6: МАГАЗИНЫ | C6: =C7+C11 -> 536737.92 | D6: =D7+D11 -> 617702.66 | E6: =E7+E11 -> 762435.39 | F6: =F7+F11 -> 975440.83 | G6: =G7+G11 -> 1296452.5 | H6: =H7+H11 -> 1766359.9 | I6: =I7+I11 -> 2432435.5
B7: Сухари | C7: =SUM(C8:C10) -> 431286.58 | D7: =SUM(D8:D10) -> 499957.61 | E7: =SUM(E8:E10) -> 620323.12 | F7: =SUM(F8:F10) -> 803774.19 | G7: =SUM(G8:G10) -> 1080616.8 | H7: =SUM(H8:H10) -> 1488114.3 | I7: =SUM(I8:I10) -> 2067087.6
B8: Классика | C8: 213143.11 | D8: 250999.85 | E8: 315949.42 | F8: 415333.41 | G8: 566503.83 | H8: 791484.92 | I8: 1115405.8 | L8: 0.76 | M8: 0.83 | N8: 0.93 | O8: 0.93 | P8: 0.95 | Q8: 1.01 | R8: 1.16 | S8: 1.13 | T8: 1.05 | U8: 0.99 | V8: 1.01 | W8: 1.25
B9: Острые | C9: 168540.3 | D9: 192462.27 | E9: 235433.99 | F9: 300569.75 | G9: 397904.99 | H9: 539255.08 | I9: 736757.15 | L9: 0.76 | M9: 0.86 | N9: 0.93 | O9: 0.93 | P9: 0.95 | Q9: 1.01 | R9: 1.16 | S9: 1.13 | T9: 1.05 | U9: 0.99 | V9: 0.98 | W9: 1.25
B10: ЭкстраХруст | C10: 49603.174 | D10: 56495.492 | E10: 68939.71 | F10: 87871.026 | G10: 116207.94 | H10: 157374.34 | I10: 214924.63 | L10: 0.76 | M10: 0.83 | N10: 0.95 | O10: 0.93 | P10: 0.95 | Q10: 1.01 | R10: 1.16 | S10: 1.13 | T10: 1.05 | U10: 0.99 | V10: 0.99 | W10: 1.25
B11: Соусы | C11: =SUM(C12:C18) -> 105451.34 | D11: =SUM(D12:D18) -> 117745.05 | E11: =SUM(E12:E18) -> 142112.27 | F11: =SUM(F12:F18) -> 171666.64 | G11: =SUM(G12:G18) -> 215835.71 | H11: =SUM(H12:H18) -> 278245.53 | I11: =SUM(I12:I18) -> 365347.95
B12: Кетчуп | C12: 35955.672 | D12: 41326.004 | E12: 49287.659 | F12: 61118.917 | G12: 78530.264 | H12: 103233.34 | I12: 136925.63 | L12: 0.76 | M12: 0.83 | N12: 0.93 | O12: 0.93 | P12: 0.84 | Q12: 1.01 | R12: 1.16 | S12: 1.13 | T12: 1.05 | U12: 0.99 | V12: 1.12 | W12: 1.25
B13: Горчица | C13: 18859.743 | D13: 21872.28 | E13: 27513.339 | F13: 36222.164 | G13: 49499.643 | H13: 69502.33 | I13: 97827.769 | L13: 0.76 | M13: 0.83 | N13: 0.93 | O13: 0.93 | P13: 0.95 | Q13: 0.73 | R13: 1.16 | S13: 1.13 | T13: 1.05 | U13: 0.99 | V13: 1.29 | W13: 1.25
B14: Сырный | C14: 30906.192 | D14: 32789.261 | E14: 40128.51 | F14: 43846 | G14: 49428.26 | H14: 56041.056 | I14: 65864.64 | L14: 0.76 | M14: 0.83 | N14: 0.93 | O14: 0.93 | P14: 0.95 | Q14: 1.01 | R14: 1.18 | S14: 1.13 | T14: 1.05 | U14: 0.99 | V14: 0.99 | W14: 1.25
B15: Кисло-сладкий | C15: 8274.8802 | D15: 9202.7589 | E15: 10683.105 | F15: 12944.522 | G15: 16292.428 | H15: 20974.209 | I15: 27382.164 | L15: 0.76 | M15: 0.83 | N15: 0.93 | O15: 0.93 | P15: 0.95 | Q15: 1.01 | R15: 1.16 | S15: 0.89 | T15: 1.05 | U15: 0.99 | V15: 1.25 | W15: 1.25
B16: Чесночный | C16: 5067.1018 | D16: 5587.2302 | E16: 6541.1412 | F16: 8025.1043 | G16: 10250.603 | H16: 13409.065 | I16: 17788.246 | L16: 0.76 | M16: 0.83 | N16: 0.93 | O16: 0.93 | P16: 0.95 | Q16: 1.01 | R16: 1.16 | S16: 1.13 | T16: 0.91 | U16: 0.99 | V16: 1.15 | W16: 1.25
B17: Коктейльный | C17: 5737.9697 | D17: 6298.1548 | E17: 7274.0341 | F17: 8790.4503 | G17: 11053.702 | H17: 14233.764 | I17: 18594.078 | L17: 0.76 | M17: 0.83 | N17: 0.93 | O17: 0.93 | P17: 0.95 | Q17: 1.01 | R17: 1.16 | S17: 1.13 | T17: 1.05 | U17: 0.95 | V17: 1.05 | W17: 1.25
B18: Медовая горчица | C18: 649.78131 | D18: 669.3575 | E18: 684.47688 | F18: 719.47949 | G18: 780.80758 | H18: 851.76668 | I18: 965.42644 | L18: 0.76 | M18: 0.83 | N18: 0.93 | O18: 0.93 | P18: 0.95 | Q18: 1.01 | R18: 1.16 | S18: 1.13 | T18: 1.05 | U18: 0.99 | V18: 1.01 | W18: 1.25
B19: РЕСТОРАНЫ | C19: =C20+C24 -> 288355.59 | D19: =D20+D24 -> 387422.86 | E19: =E20+E24 -> 549875.99 | F19: =F20+F24 -> 748870.82 | G19: =G20+G24 -> 990785.34 | H19: =H20+H24 -> 1267130.1 | I19: =I20+I24 -> 1590036
B20: Сухари | C20: =SUM(C21:C23) -> 242066.69 | D20: =SUM(D21:D23) -> 333984.13 | E20: =SUM(E21:E23) -> 478821.7 | F20: =SUM(F21:F23) -> 657923.12 | G20: =SUM(G21:G23) -> 875729.66 | H20: =SUM(H21:H23) -> 1125376.7 | I20: =SUM(I21:I23) -> 1416140.9
B21: Классика | C21: 114234.52 | D21: 158773.58 | E21: 234946.57 | F21: 331811.84 | G21: 452080.13 | H21: 592906.56 | I21: 760015.7 | L21: 0.76 | M21: 0.83 | N21: 0.93 | O21: 0.93 | P21: 0.95 | Q21: 1.01 | R21: 1.16 | S21: 1.13 | T21: 1.05 | U21: 0.99 | V21: 1.01 | W21: 1.25
B22: Острые | C22: 99489.426 | D22: 131998.03 | E22: 177753.59 | F22: 230708.41 | G22: 292182.89 | H22: 359006.98 | I22: 436038.83 | L22: 0.76 | M22: 0.83 | N22: 0.93 | O22: 0.93 | P22: 0.95 | Q22: 1.01 | R22: 1.16 | S22: 1.13 | T22: 1.05 | U22: 0.89 | V22: 1.11 | W22: 1.25
B23: ЭкстраХруст | C23: 28342.744 | D23: 43212.523 | E23: 66121.546 | F23: 95402.872 | G23: 131466.64 | H23: 173463.17 | I23: 220086.39 | L23: 0.76 | M23: 0.83 | N23: 0.93 | O23: 0.93 | P23: 0.95 | Q23: 1.01 | R23: 1.16 | S23: 1.13 | T23: 0.67 | U23: 0.99 | V23: 1.39 | W23: 1.25
B24: Соусы | C24: =SUM(C25:C31) -> 46288.904 | D24: =SUM(D25:D31) -> 53438.728 | E24: =SUM(E25:E31) -> 71054.291 | F24: =SUM(F25:F31) -> 90947.706 | G24: =SUM(G25:G31) -> 115055.68 | H24: =SUM(H25:H31) -> 141753.4 | I24: =SUM(I25:I31) -> 173895.11
B25: Кетчуп | C25: 19270.215 | D25: 23470.152 | E25: 32272.751 | F25: 42908.759 | G25: 55478.312 | H25: 69218.867 | I25: 85290.054 | L25: 0.57 | M25: 0.83 | N25: 0.93 | O25: 0.93 | P25: 0.95 | Q25: 1.01 | R25: 0.91 | S25: 1.13 | T25: 1.05 | U25: 0.99 | V25: 1.45 | W25: 1.25
B26: Горчица | C26: 8095.0354 | D26: 6947.5664 | E26: 8218.9423 | F26: 9815.9527 | G26: 11730.837 | H26: 13764.371 | I26: 16315.872 | L26: 0.76 | M26: 0.87 | N26: 0.93 | O26: 0.93 | P26: 0.95 | Q26: 1.01 | R26: 1.16 | S26: 1.13 | T26: 1.05 | U26: 0.99 | V26: 0.97 | W26: 1.25
B27: Сырный | C27: 9427.5003 | D27: 10001.904 | E27: 12240.639 | F27: 13374.607 | G27: 15077.397 | H27: 17094.538 | I27: 20091.085 | L27: 0.76 | M27: 0.83 | N27: 0.95 | O27: 0.93 | P27: 0.95 | Q27: 1.01 | R27: 1.16 | S27: 1.13 | T27: 1.05 | U27: 0.99 | V27: 0.99 | W27: 1.25
B28: Кисло-сладкий | C28: 3812.1718 | D28: 4359.0779 | E28: 5344.2174 | F28: 6434.4769 | G28: 7691.2539 | H28: 8984.0904 | I28: 10620.319 | L28: 0.76 | M28: 0.83 | N28: 0.93 | O28: 0.89 | P28: 0.95 | Q28: 1.01 | R28: 1.16 | S28: 1.13 | T28: 1.05 | U28: 0.99 | V28: 1.05 | W28: 1.25
B29: Чесночный | C29: 2309.7683 | D29: 3950.4806 | E29: 6427.7061 | F29: 9648.4778 | G29: 13682.324 | H29: 18409.146 | I29: 23915.533 | L29: 0.76 | M29: 0.83 | N29: 0.93 | O29: 0.93 | P29: 0.93 | Q29: 1.01 | R29: 1.16 | S29: 1.13 | T29: 1.05 | U29: 0.99 | V29: 1.03 | W29: 1.25
B30: Коктейльный | C30: 2412.4702 | D30: 3531.5393 | E30: 5147.0245 | F30: 7108.3836 | G30: 9437.6904 | H30: 12007.925 | I30: 14980.663 | L30: 0.76 | M30: 0.83 | N30: 0.93 | O30: 0.93 | P30: 0.95 | Q30: 1 | R30: 1.16 | S30: 1.13 | T30: 1.05 | U30: 0.99 | V30: 1.02 | W30: 1.25
B31: Медовая горчица | C31: 961.74303 | D31: 1178.0075 | E31: 1403.0099 | F31: 1657.0483 | G31: 1957.8691 | H31: 2274.4645 | I31: 2681.5827 | L31: 0.76 | M31: 0.83 | N31: 0.93 | O31: 0.93 | P31: 0.95 | Q31: 1.01 | R31: 1.01 | S31: 1.13 | T31: 1.05 | U31: 0.99 | V31: 1.16 | W31: 1.25
B32: ВНЕ НАПРАВЛЕНИЙ | C32: 0 | D32: 0 | E32: 0 | F32: 0 | G32: 0 | H32: 0 | I32: 0 | L32: 0.76 | M32: 0.83 | N32: 0.93 | O32: 0.93 | P32: 0.95 | Q32: 1.01 | R32: 1.16 | S32: 1.18 | T32: 1.05 | U32: 0.99 | V32: 0.96 | W32: 1.25
B33: Товары для перепродажи | C33: =C34 -> 2400 | D33: =D34 -> 2508 | E33: =E34 -> 2608.32 | F33: =F34 -> 2712.6528 | G33: =G34 -> 2821.1589 | H33: =H34 -> 2934.0053 | I33: =I34 -> 3051.3655
B34: ВНЕ НАПРАВЛЕНИЙ | C34: 2400 | D34: 2508 | E34: 2608.32 | F34: 2712.6528 | G34: 2821.1589 | H34: 2934.0053 | I34: 3051.3655 | L34: 0.76 | M34: 0.83 | N34: 0.93 | O34: 0.93 | P34: 0.95 | Q34: 1.01 | R34: 1.16 | S34: 1.13 | T34: 1.05 | U34: 0.99 | V34: 1.01 | W34: 1.25
B35: Услуги | C35: =C36 -> 8000 | D35: =D36 -> 8360 | E35: =E36 -> 8694.4 | F35: =F36 -> 9042.176 | G35: =G36 -> 9403.863 | H35: =H36 -> 9780.0176 | I35: =I36 -> 10171.218
B36: ВНЕ НАПРАВЛЕНИЙ | C36: 8000 | D36: 8360 | E36: 8694.4 | F36: 9042.176 | G36: 9403.863 | H36: 9780.0176 | I36: 10171.218 | L36: 0.76 | M36: 0.83 | N36: 0.93 | O36: 0.93 | P36: 0.95 | Q36: 1.01 | R36: 1.16 | S36: 1.13 | T36: 1.05 | U36: 0.99 | V36: 1.01 | W36: 1.25
B37: Субаренда | C37: =C38 -> 5600 | D37: =D38 -> 5852 | E37: =E38 -> 6086.08 | F37: =F38 -> 6329.5232 | G37: =G38 -> 6582.7041 | H37: =H38 -> 6846.0123 | I37: =I38 -> 7119.8528
B38: ВНЕ НАПРАВЛЕНИЙ | C38: 5600 | D38: 5852 | E38: 6086.08 | F38: 6329.5232 | G38: 6582.7041 | H38: 6846.0123 | I38: 7119.8528 | L38: 0.76 | M38: 0.83 | N38: 0.93 | O38: 0.93 | P38: 0.95 | Q38: 1.01 | R38: 1.16 | S38: 1.13 | T38: 1.05 | U38: 0.99 | V38: 1.01 | W38: 1.25
B39: Прочая реализация | C39: =C40 -> 7000 | D39: =D40 -> 7315 | E39: =E40 -> 7607.6 | F39: =F40 -> 7911.904 | G39: =G40 -> 8228.3802 | H39: =H40 -> 8557.5154 | I39: =I40 -> 8899.816
B40: ВНЕ НАПРАВЛЕНИЙ | C40: 7000 | D40: 7315 | E40: 7607.6 | F40: 7911.904 | G40: 8228.3802 | H40: 8557.5154 | I40: 8899.816 | L40: 0.76 | M40: 0.83 | N40: 0.93 | O40: 0.93 | P40: 0.95 | Q40: 1.01 | R40: 1.16 | S40: 1.13 | T40: 1.05 | U40: 0.99 | V40: 1.01 | W40: 1.25
B41: Себестоимость реализации: | C41: =C42+C70+C72+C74+C76 -> 597965.46 | D41: =D42+D70+D72+D74+D76 -> 724905.86 | E41: =E42+E70+E72+E74+E76 -> 940788.69 | F41: =F42+F70+F72+F74+F76 -> 1195589.5 | G41: =G42+G70+G72+G74+G76 -> 1487812.1 | H41: =H42+H70+H72+H74+H76 -> 1845033 | I41: =I42+I70+I72+I74+I76 -> 2198071.2
B42: Готовая продукция | C42: =C43+C56+C69 -> 577565.46 | D42: =D43+D56+D69 -> 703587.86 | E42: =E43+E56+E69 -> 918617.97 | F42: =F43+F56+F69 -> 1172531.9 | G42: =G43+G56+G69 -> 1463832.2 | H42: =H43+H56+H69 -> 1820094 | I42: =I43+I56+I69 -> 2172134.6
B43: МАГАЗИНЫ | C43: =C44+C48 -> 375716.55 | D43: =D44+D48 -> 432391.86 | E43: =E44+E48 -> 533704.77 | F43: =F44+F48 -> 663299.76 | G43: =G44+G48 -> 829729.58 | H43: =H44+H48 -> 1059815.9 | I43: =I44+I48 -> 1313515.2
B44: Сухари | C44: =SUM(C45:C47) -> 301900.61 | D44: =SUM(D45:D47) -> 349970.33 | E44: =SUM(E45:E47) -> 434226.19 | F44: =SUM(F45:F47) -> 546566.45 | G44: =SUM(G45:G47) -> 691594.73 | H44: =SUM(H45:H47) -> 892868.6 | I44: =SUM(I45:I47) -> 1116227.3
B45: Классика | C45: 149200.17 | D45: 175699.9 | E45: 221164.6 | F45: 282426.72 | G45: 362562.45 | H45: 474890.95 | I45: 602319.13 | L45: 0.76 | M45: 0.83 | N45: 0.93 | O45: 0.93 | P45: 0.95 | Q45: 1.01 | R45: 1.16 | S45: 1.13 | T45: 1.05 | U45: 0.99 | V45: 1.01 | W45: 1.25
B46: Острые | C46: 117978.21 | D46: 134723.59 | E46: 164803.79 | F46: 204387.43 | G46: 254659.2 | H46: 323553.05 | I46: 397848.86 | L46: 0.76 | M46: 0.86 | N46: 0.93 | O46: 0.93 | P46: 0.95 | Q46: 1.01 | R46: 1.16 | S46: 1.13 | T46: 1.05 | U46: 0.99 | V46: 0.98 | W46: 1.25
B47: ЭкстраХруст | C47: 34722.222 | D47: 39546.844 | E47: 48257.797 | F47: 59752.298 | G47: 74373.082 | H47: 94424.601 | I47: 116059.3 | L47: 0.76 | M47: 0.83 | N47: 0.95 | O47: 0.93 | P47: 0.95 | Q47: 1.01 | R47: 1.16 | S47: 1.13 | T47: 1.05 | U47: 0.99 | V47: 0.99 | W47: 1.25
B48: Соусы | C48: =SUM(C49:C55) -> 73815.938 | D48: =SUM(D49:D55) -> 82421.532 | E48: =SUM(E49:E55) -> 99478.586 | F48: =SUM(F49:F55) -> 116733.31 | G48: =SUM(G49:G55) -> 138134.85 | H48: =SUM(H49:H55) -> 166947.32 | I48: =SUM(I49:I55) -> 197287.9
B49: Кетчуп | C49: 25168.97 | D49: 28928.203 | E49: 34501.361 | F49: 41560.864 | G49: 50259.369 | H49: 61940.003 | I49: 73939.841 | L49: 0.76 | M49: 0.83 | N49: 0.93 | O49: 0.93 | P49: 0.84 | Q49: 1.01 | R49: 1.16 | S49: 1.13 | T49: 1.05 | U49: 0.99 | V49: 1.12 | W49: 1.25
B50: Горчица | C50: 13201.82 | D50: 15310.596 | E50: 19259.338 | F50: 24631.071 | G50: 31679.771 | H50: 41701.398 | I50: 52826.995 | L50: 0.76 | M50: 0.83 | N50: 0.93 | O50: 0.93 | P50: 0.95 | Q50: 0.73 | R50: 1.16 | S50: 1.13 | T50: 1.05 | U50: 0.99 | V50: 1.29 | W50: 1.25
B51: Сырный | C51: 21634.334 | D51: 22952.483 | E51: 28089.957 | F51: 29815.28 | G51: 31634.086 | H51: 33624.634 | I51: 35566.906 | L51: 0.76 | M51: 0.83 | N51: 0.93 | O51: 0.93 | P51: 0.95 | Q51: 1.01 | R51: 1.18 | S51: 1.13 | T51: 1.05 | U51: 0.99 | V51: 0.99 | W51: 1.25
B52: Кисло-сладкий | C52: 5792.4161 | D52: 6441.9312 | E52: 7478.1737 | F52: 8802.2749 | G52: 10427.154 | H52: 12584.525 | I52: 14786.368 | L52: 0.76 | M52: 0.83 | N52: 0.93 | O52: 0.93 | P52: 0.95 | Q52: 1.01 | R52: 1.16 | S52: 0.89 | T52: 1.05 | U52: 0.99 | V52: 1.25 | W52: 1.25
B53: Чесночный | C53: 3546.9713 | D53: 3911.0611 | E53: 4578.7988 | F53: 5457.071 | G53: 6560.3858 | H53: 8045.4393 | I53: 9605.6531 | L53: 0.76 | M53: 0.83 | N53: 0.93 | O53: 0.93 | P53: 0.95 | Q53: 1.01 | R53: 1.16 | S53: 1.13 | T53: 0.91 | U53: 0.99 | V53: 1.15 | W53: 1.25
B54: Коктейльный | C54: 4016.5788 | D54: 4408.7084 | E54: 5091.8239 | F54: 5977.5062 | G54: 7074.369 | H54: 8540.2583 | I54: 10040.802 | L54: 0.76 | M54: 0.83 | N54: 0.93 | O54: 0.93 | P54: 0.95 | Q54: 1.01 | R54: 1.16 | S54: 1.13 | T54: 1.05 | U54: 0.95 | V54: 1.05 | W54: 1.25
B55: Медовая горчица | C55: 454.84692 | D55: 468.55025 | E55: 479.13382 | F55: 489.24605 | G55: 499.71685 | H55: 511.06001 | I55: 521.33028 | L55: 0.76 | M55: 0.83 | N55: 0.93 | O55: 0.93 | P55: 0.95 | Q55: 1.01 | R55: 1.16 | S55: 1.13 | T55: 1.05 | U55: 0.99 | V55: 1.01 | W55: 1.25
B56: РЕСТОРАНЫ | C56: =C57+C61 -> 201848.91 | D56: =D57+D61 -> 271196 | E56: =E57+E61 -> 384913.2 | F56: =F57+F61 -> 509232.16 | G56: =G57+G61 -> 634102.62 | H56: =H57+H61 -> 760278.06 | I56: =I57+I61 -> 858619.45
B57: Сухари | C57: =SUM(C58:C60) -> 169446.68 | D57: =SUM(D58:D60) -> 233788.89 | E57: =SUM(E58:E60) -> 335175.19 | F57: =SUM(F58:F60) -> 447387.72 | G57: =SUM(G58:G60) -> 560466.98 | H57: =SUM(H58:H60) -> 675226.02 | I57: =SUM(I58:I60) -> 764716.09
B58: Классика | C58: 79964.162 | D58: 111141.51 | E58: 164462.6 | F58: 225632.05 | G58: 289331.29 | H58: 355743.94 | I58: 410408.48 | L58: 0.76 | M58: 0.83 | N58: 0.93 | O58: 0.93 | P58: 0.95 | Q58: 1.01 | R58: 1.16 | S58: 1.13 | T58: 1.05 | U58: 0.99 | V58: 1.01 | W58: 1.25
B59: Острые | C59: 69642.599 | D59: 92398.618 | E59: 124427.51 | F59: 156881.72 | G59: 186997.05 | H59: 215404.19 | I59: 235460.97 | L59: 0.76 | M59: 0.83 | N59: 0.93 | O59: 0.93 | P59: 0.95 | Q59: 1.01 | R59: 1.16 | S59: 1.13 | T59: 1.05 | U59: 0.89 | V59: 1.11 | W59: 1.25
B60: ЭкстраХруст | C60: 19839.921 | D60: 30248.766 | E60: 46285.082 | F60: 64873.953 | G60: 84138.646 | H60: 104077.9 | I60: 118846.65 | L60: 0.76 | M60: 0.83 | N60: 0.93 | O60: 0.93 | P60: 0.95 | Q60: 1.01 | R60: 1.16 | S60: 1.13 | T60: 0.67 | U60: 0.99 | V60: 1.39 | W60: 1.25
B61: Соусы | C61: =SUM(C62:C68) -> 32402.233 | D61: =SUM(D62:D68) -> 37407.11 | E61: =SUM(E62:E68) -> 49738.004 | F61: =SUM(F62:F68) -> 61844.44 | G61: =SUM(G62:G68) -> 73635.637 | H61: =SUM(H62:H68) -> 85052.041 | I61: =SUM(I62:I68) -> 93903.359
B62: Кетчуп | C62: 13489.15 | D62: 16429.107 | E62: 22590.926 | F62: 29177.956 | G62: 35506.119 | H62: 41531.32 | I62: 46056.629 | L62: 0.57 | M62: 0.83 | N62: 0.93 | O62: 0.93 | P62: 0.95 | Q62: 1.01 | R62: 0.91 | S62: 1.13 | T62: 1.05 | U62: 0.99 | V62: 1.45 | W62: 1.25
B63: Горчица | C63: 5666.5248 | D63: 4863.2965 | E63: 5753.2596 | F63: 6674.8478 | G63: 7507.7358 | H63: 8258.6225 | I63: 8810.5709 | L63: 0.76 | M63: 0.87 | N63: 0.93 | O63: 0.93 | P63: 0.95 | Q63: 1.01 | R63: 1.16 | S63: 1.13 | T63: 1.05 | U63: 0.99 | V63: 0.97 | W63: 1.25
B64: Сырный | C64: 6599.2502 | D64: 7001.3328 | E64: 8568.4473 | F64: 9094.733 | G64: 9649.5342 | H64: 10256.723 | I64: 10849.186 | L64: 0.76 | M64: 0.83 | N64: 0.95 | O64: 0.93 | P64: 0.95 | Q64: 1.01 | R64: 1.16 | S64: 1.13 | T64: 1.05 | U64: 0.99 | V64: 0.99 | W64: 1.25
B65: Кисло-сладкий | C65: 2668.5203 | D65: 3051.3545 | E65: 3740.9522 | F65: 4375.4443 | G65: 4922.4025 | H65: 5390.4543 | I65: 5734.9725 | L65: 0.76 | M65: 0.83 | N65: 0.93 | O65: 0.89 | P65: 0.95 | Q65: 1.01 | R65: 1.16 | S65: 1.13 | T65: 1.05 | U65: 0.99 | V65: 1.05 | W65: 1.25
B66: Чесночный | C66: 1616.8378 | D66: 2765.3364 | E66: 4499.3943 | F66: 6560.9649 | G66: 8756.6874 | H66: 11045.487 | I66: 12914.388 | L66: 0.76 | M66: 0.83 | N66: 0.93 | O66: 0.93 | P66: 0.93 | Q66: 1.01 | R66: 1.16 | S66: 1.13 | T66: 1.05 | U66: 0.99 | V66: 1.03 | W66: 1.25
B67: Коктейльный | C67: 1688.7292 | D67: 2472.0775 | E67: 3602.9171 | F67: 4833.7009 | G67: 6040.1219 | H67: 7204.7549 | I67: 8089.5579 | L67: 0.76 | M67: 0.83 | N67: 0.93 | O67: 0.93 | P67: 0.95 | Q67: 1 | R67: 1.16 | S67: 1.13 | T67: 1.05 | U67: 0.99 | V67: 1.02 | W67: 1.25
B68: Медовая горчица | C68: 673.22012 | D68: 824.60528 | E68: 982.10696 | F68: 1126.7928 | G68: 1253.0362 | H68: 1364.6787 | I68: 1448.0547 | L68: 0.76 | M68: 0.83 | N68: 0.93 | O68: 0.93 | P68: 0.95 | Q68: 1.01 | R68: 1.01 | S68: 1.13 | T68: 1.05 | U68: 0.99 | V68: 1.16 | W68: 1.25
B69: ВНЕ НАПРАВЛЕНИЙ | C69: 0 | D69: 0 | E69: 0 | F69: 0 | G69: 0 | H69: 0 | I69: 0 | L69: 0.76 | M69: 0.83 | N69: 0.93 | O69: 0.93 | P69: 0.95 | Q69: 1.01 | R69: 1.16 | S69: 1.18 | T69: 1.05 | U69: 0.99 | V69: 0.96 | W69: 1.25
B70: Товары для перепродажи | C70: =C71 -> 2000 | D70: =D71 -> 2090 | E70: =E71 -> 2173.6 | F70: =F71 -> 2260.544 | G70: =G71 -> 2350.9658 | H70: =H71 -> 2445.0044 | I70: =I71 -> 2542.8046
B71: ВНЕ НАПРАВЛЕНИЙ | C71: 2000 | D71: 2090 | E71: 2173.6 | F71: 2260.544 | G71: 2350.9658 | H71: 2445.0044 | I71: 2542.8046 | L71: 0.76 | M71: 0.83 | N71: 0.93 | O71: 0.93 | P71: 0.95 | Q71: 1.01 | R71: 1.16 | S71: 1.13 | T71: 1.05 | U71: 0.99 | V71: 1.01 | W71: 1.25
B72: Услуги | C72: =C73 -> 7400 | D72: =D73 -> 7733 | E72: =E73 -> 8042.32 | F72: =F73 -> 8364.0128 | G72: =G73 -> 8698.5733 | H72: =H73 -> 9046.5162 | I72: =I73 -> 9408.3769
B73: ВНЕ НАПРАВЛЕНИЙ | C73: 7400 | D73: 7733 | E73: 8042.32 | F73: 8364.0128 | G73: 8698.5733 | H73: 9046.5162 | I73: 9408.3769 | L73: 0.76 | M73: 0.83 | N73: 0.93 | O73: 0.93 | P73: 0.95 | Q73: 1.01 | R73: 1.16 | S73: 1.13 | T73: 1.05 | U73: 0.99 | V73: 1.01 | W73: 1.25
B74: Субаренда | C74: =C75 -> 5000 | D74: =D75 -> 5225 | E74: =E75 -> 5434 | F74: =F75 -> 5651.36 | G74: =G75 -> 5877.4144 | H74: =H75 -> 6112.511 | I74: =I75 -> 6357.0114
B75: ВНЕ НАПРАВЛЕНИЙ | C75: 5000 | D75: 5225 | E75: 5434 | F75: 5651.36 | G75: 5877.4144 | H75: 6112.511 | I75: 6357.0114 | L75: 0.76 | M75: 0.83 | N75: 0.93 | O75: 0.93 | P75: 0.95 | Q75: 1.01 | R75: 1.16 | S75: 1.13 | T75: 1.05 | U75: 0.99 | V75: 1.01 | W75: 1.25
B76: Прочая реализация | C76: =C77 -> 6000 | D76: =D77 -> 6270 | E76: =E77 -> 6520.8 | F76: =F77 -> 6781.632 | G76: =G77 -> 7052.8973 | H76: =H77 -> 7335.0132 | I76: =I77 -> 7628.4137
B77: ВНЕ НАПРАВЛЕНИЙ | C77: 6000 | D77: 6270 | E77: 6520.8 | F77: 6781.632 | G77: 7052.8973 | H77: 7335.0132 | I77: 7628.4137 | L77: 0.76 | M77: 0.83 | N77: 0.93 | O77: 0.93 | P77: 0.95 | Q77: 1.01 | R77: 1.16 | S77: 1.13 | T77: 1.05 | U77: 0.99 | V77: 1.01 | W77: 1.25
B78: Валовая прибыль | C78: =C79+C107+C109+C111+C113 -> 250128.05 | D78: =D79+D107+D109+D111+D113 -> 304254.65 | E78: =E79+E107+E109+E111+E113 -> 396519.42 | F78: =F79+F107+F109+F111+F113 -> 554718.33 | G78: =G79+G107+G109+G111+G113 -> 826461.68 | H78: =H79+H107+H109+H111+H113 -> 1216574.5 | I78: =I79+I107+I109+I111+I113 -> 1853643
B79: Готовая продукция | C79: =C80+C93+C106 -> 247528.05 | D79: =D80+D93+D106 -> 301537.65 | E79: =E80+E93+E106 -> 393693.42 | F79: =F80+F93+F106 -> 551779.73 | G79: =G80+G93+G106 -> 823405.61 | H79: =H80+H93+H106 -> 1213396 | I79: =I80+I93+I106 -> 1850336.9
B80: МАГАЗИНЫ | C80: =C81+C85 -> 161021.38 | D80: =D81+D85 -> 185310.8 | E80: =E81+E85 -> 228730.62 | F80: =F81+F85 -> 312141.06 | G80: =G81+G85 -> 466722.89 | H80: =H81+H85 -> 706543.95 | I80: =I81+I85 -> 1118920.3
B81: Сухари | C81: =SUM(C82:C84) -> 129385.97 | D81: =SUM(D82:D84) -> 149987.28 | E81: =SUM(E82:E84) -> 186096.94 | F81: =SUM(F82:F84) -> 257207.74 | G81: =SUM(G82:G84) -> 389022.04 | H81: =SUM(H82:H84) -> 595245.73 | I81: =SUM(I82:I84) -> 950860.28
B82: Классика | C82: =C8-C45 -> 63942.932 | D82: =D8-D45 -> 75299.955 | E82: =E8-E45 -> 94784.827 | F82: =F8-F45 -> 132906.69 | G82: =G8-G45 -> 203941.38 | H82: =H8-H45 -> 316593.97 | I82: =I8-I45 -> 513086.66
B83: Острые | C83: =C9-C46 -> 50562.09 | D83: =D9-D46 -> 57738.68 | E83: =E9-E46 -> 70630.197 | F83: =F9-F46 -> 96182.321 | G83: =G9-G46 -> 143245.8 | H83: =H9-H46 -> 215702.03 | I83: =I9-I46 -> 338908.29
B84: ЭкстраХруст | C84: =C10-C47 -> 14880.952 | D84: =D10-D47 -> 16948.648 | E84: =E10-E47 -> 20681.913 | F84: =F10-F47 -> 28118.728 | G84: =G10-G47 -> 41834.859 | H84: =H10-H47 -> 62949.734 | I84: =I10-I47 -> 98865.328
B85: Соусы | C85: =SUM(C86:C92) -> 31635.402 | D85: =SUM(D86:D92) -> 35323.514 | E85: =SUM(E86:E92) -> 42633.68 | F85: =SUM(F86:F92) -> 54933.324 | G85: =SUM(G86:G92) -> 77700.854 | H85: =SUM(H86:H92) -> 111298.21 | I85: =SUM(I86:I92) -> 168060.06
B86: Кетчуп | C86: =C12-C49 -> 10786.702 | D86: =D12-D49 -> 12397.801 | E86: =E12-E49 -> 14786.298 | F86: =F12-F49 -> 19558.054 | G86: =G12-G49 -> 28270.895 | H86: =H12-H49 -> 41293.335 | I86: =I12-I49 -> 62985.79
B87: Горчица | C87: =C13-C50 -> 5657.923 | D87: =D13-D50 -> 6561.6841 | E87: =E13-E50 -> 8254.0018 | F87: =F13-F50 -> 11591.092 | G87: =G13-G50 -> 17819.871 | H87: =H13-H50 -> 27800.932 | I87: =I13-I50 -> 45000.774
B88: Сырный | C88: =C14-C51 -> 9271.8576 | D88: =D14-D51 -> 9836.7783 | E88: =E14-E51 -> 12038.553 | F88: =F14-F51 -> 14030.72 | G88: =G14-G51 -> 17794.173 | H88: =H14-H51 -> 22416.422 | I88: =I14-I51 -> 30297.735
B89: Кисло-сладкий | C89: =C15-C52 -> 2482.4641 | D89: =D15-D52 -> 2760.8277 | E89: =E15-E52 -> 3204.9316 | F89: =F15-F52 -> 4142.247 | G89: =G15-G52 -> 5865.274 | H89: =H15-H52 -> 8389.6835 | I89: =I15-I52 -> 12595.795
B90: Чесночный | C90: =C16-C53 -> 1520.1306 | D90: =D16-D53 -> 1676.1691 | E90: =E16-E53 -> 1962.3424 | F90: =F16-F53 -> 2568.0334 | G90: =G16-G53 -> 3690.217 | H90: =H16-H53 -> 5363.6262 | I90: =I16-I53 -> 8182.5933
B91: Коктейльный | C91: =C17-C54 -> 1721.3909 | D91: =D17-D54 -> 1889.4464 | E91: =E17-E54 -> 2182.2102 | F91: =F17-F54 -> 2812.9441 | G91: =G17-G54 -> 3979.3326 | H91: =H17-H54 -> 5693.5055 | I91: =I17-I54 -> 8553.2757
B92: Медовая горчица | C92: =C18-C55 -> 194.93439 | D92: =D18-D55 -> 200.80725 | E92: =E18-E55 -> 205.34306 | F92: =F18-F55 -> 230.23344 | G92: =G18-G55 -> 281.09073 | H92: =H18-H55 -> 340.70667 | I92: =I18-I55 -> 444.09616
B93: РЕСТОРАНЫ | C93: =C94+C98 -> 86506.678 | D93: =D94+D98 -> 116226.86 | E93: =E94+E98 -> 164962.8 | F93: =F94+F98 -> 239638.66 | G93: =G94+G98 -> 356682.72 | H93: =H94+H98 -> 506852.04 | I93: =I94+I98 -> 731416.57
B94: Сухари | C94: =SUM(C95:C97) -> 72620.006 | D94: =SUM(D95:D97) -> 100195.24 | E94: =SUM(E95:E97) -> 143646.51 | F94: =SUM(F95:F97) -> 210535.4 | G94: =SUM(G95:G97) -> 315262.68 | H94: =SUM(H95:H97) -> 450150.68 | I94: =SUM(I95:I97) -> 651424.82
B95: Классика | C95: =C21-C58 -> 34270.355 | D95: =D21-D58 -> 47632.074 | E95: =E21-E58 -> 70483.972 | F95: =F21-F58 -> 106179.79 | G95: =G21-G58 -> 162748.85 | H95: =H21-H58 -> 237162.62 | I95: =I21-I58 -> 349607.22
B96: Острые | C96: =C22-C59 -> 29846.828 | D96: =D22-D59 -> 39599.408 | E96: =E22-E59 -> 53326.076 | F96: =F22-F59 -> 73826.691 | G96: =G22-G59 -> 105185.84 | H96: =H22-H59 -> 143602.79 | I96: =I22-I59 -> 200577.86
B97: ЭкстраХруст | C97: =C23-C60 -> 8502.8232 | D97: =D23-D60 -> 12963.757 | E97: =E23-E60 -> 19836.464 | F97: =F23-F60 -> 30528.919 | G97: =G23-G60 -> 47327.989 | H97: =H23-H60 -> 69385.268 | I97: =I23-I60 -> 101239.74
B98: Соусы | C98: =SUM(C99:C105) -> 13886.671 | D98: =SUM(D99:D105) -> 16031.618 | E98: =SUM(E99:E105) -> 21316.287 | F98: =SUM(F99:F105) -> 29103.266 | G98: =SUM(G99:G105) -> 41420.046 | H98: =SUM(H99:H105) -> 56701.361 | I98: =SUM(I99:I105) -> 79991.75
B99: Кетчуп | C99: =C25-C62 -> 5781.0644 | D99: =D25-D62 -> 7041.0457 | E99: =E25-E62 -> 9681.8254 | F99: =F25-F62 -> 13730.803 | G99: =G25-G62 -> 19972.192 | H99: =H25-H62 -> 27687.547 | I99: =I25-I62 -> 39233.425
B100: Горчица | C100: =C26-C63 -> 2428.5106 | D100: =D26-D63 -> 2084.2699 | E100: =E26-E63 -> 2465.6827 | F100: =F26-F63 -> 3141.1049 | G100: =G26-G63 -> 4223.1014 | H100: =H26-H63 -> 5505.7484 | I100: =I26-I63 -> 7505.3011
B101: Сырный | C101: =C27-C64 -> 2828.2501 | D101: =D27-D64 -> 3000.5712 | E101: =E27-E64 -> 3672.1917 | F101: =F27-F64 -> 4279.8743 | G101: =G27-G64 -> 5427.863 | H101: =H27-H64 -> 6837.8152 | I101: =I27-I64 -> 9241.8989
...

Sheet Негативный сценарий >>

Sheet Вводные
B2: Рисковые события:
L3: Да
B4: 1 | C4: В июне 2027 года планируется смена поставщика растительного масла «Юг-17», которое используется для производства соусов всей линейки «Микси», с ростом закупочных цен: – доля расходов на растительное масло в себестоимости производства соусов составляет 8%; – в июне 2027 года есть риск смены поставщика с ростом цен на данный компонент в размере 11%, и далее с увеличением цен ещё на 3% с начала каждого следующего года от текущих расходов на себестоимость; – доля расходов на растительное масло в себестоимости производства соусов у данного поставщика начнёт сокращаться на 2 процентных пункта каждый год, начиная с 2029 года.
L5: Да
B6: 2 | C6: К 2028 году существует риск сдвигов сроков получения оплат от контрагента — магазина «ПроВкусно», которому «Микси» поставляет часть сухарей: – данному контрагенту поставляют сухари линейки «Классика» и «ЭкстраХруст»; – доля продаж «ПроВкусно» в общей доле реализации по начислениям (вы можете использовать данные из ОПУ для выполнения своих расчётов) сухарей составляет 60% в линейне «Классика» и 75% в линейке «ЭкстраХруст»; – резерв под сомнительную дебиторскую задолженность начисляется в следующем порядке: просрочка оплат от 0 до 15 дней в размере 5% от суммы неполученного платежа, 16–30 дней в размере 15%, 31–60 дней в размере 30%, свыше 60 дней в размере 60%; – резерв начисляется вне направлений в прочие внереализационные расходы; – график сдигов платежей для начисления резерва под плохую дебиторскую задолженность следующий: в 2028 году в среднем «ПроВкусно» просрочит все платежи на 13 дней, начиная с сентября; в 2029 году весь год просрочки составят в среднем 27 дней; с 2030 года и далее просрочки составят 31 день.
L7: Да
B8: 3 | C8: Существует риск, что, начиная с 2028 года, прогнозный показатель инфляции на телевизионные маркетинговые расходы будет хуже на 4 процентных пункта: – базовый темп инфляции, который применён в исходной модели, составляет 3,5% для всех периодов; – телевизионная реклама откручивается только для линейки сухарей, поставляемых в магазины.
B9: 4 | C9: При расчете налога на прибыль важно помнить, что компания уплачивает его без привязки к направлениям бизнеса, поэтому убыток, образовавшийся по одному из направлений бизнеса уменьшает общую налогооблагаемую базу по всей компании.

Sheet Последовательность расчётов
B2: Последовательность расчётов
B3: [1] | C3: На вкладке «1. ОПУ НС» рассчитайте данные по месяцам, исходя из вводных по сезонности, которые даны на вкладке ОПУ БС в колонках L–W.
B4: [2] | C4: Проверьте, что ячейки Check в колонках CR–CX стали зелёными. Если ваши расчёты верны, можно двигаться дальше.
B5: [3] | C5: Внесите данные в колонки corrections по всем рисковым событиям.
B6: [4] | C6: Произведите необходимые расчёты в колонках negative scenario.
B7: [5] | C7: Проверьте, что ячейки Check в колонках JE–JK стали зелёными. Если ваши расчёты верны, можно двигаться дальше.
B8: [6] | C8: На вкладке «2. Факторы и выводы» внесите данные по накопленному итогу EBITDA за 2027–2031 гг., рассчитайте отклонение по статьям в абсолютах и в процентах.
B9: [7] | C9: Сверьте, что ваши данные сходятся с вкладкой «1.ОПУ НС».
B10: [8] | C10: Рассчитайте факторы рисков на накопленный показатель EBITDA за 2027–2031 гг.: в абсолютах вам необходимо выйти на разницу между базовым и негативным сценариями, в процентах — рассчитать вклад каждого фактора в общее изменение по абсолюту.
B11: [9] | C11: Рассчитайте факторы рисков на накопленный показатель EBITDA margin: в абсолютах вам необходимо выйти на разницу между базовым и негативным сценариями, в процентах — рассчитать вклад каждого фактора в общее изменение по показателю EBITDA margin.
B12: [10] | C12: Постройте «водопадные» (каскадные) графики напротив каждого факторного анализа: для обоих факторников постройте «водопады» по абсолютным отклонения, а для второго факторника также постройте «водопад» по отклонению показателя EBITDA margin.

Sheet 1. ОПУ НС
B2: Отчёт о прибылях и убытках за год, тыс. руб.
C3: Янв'25 | D3: Фев'25 | E3: Мар'25 | F3: Апр'25 | G3: Май'25 | H3: Июн'25 | I3: Июл'25 | J3: Авг'25 | K3: Сен'25 | L3: Окт'25 | M3: Ноя'25 | N3: Дек'25 | O3: 2025 | P3: Янв'26 | Q3: Фев'26 | R3: Мар'26 | S3: Апр'26 | T3: Май'26 | U3: Июн'26 | V3: Июл'26 | W3: Авг'26 | X3: Сен'26 | Y3: Окт'26 | Z3: Ноя'26 | AA3: Дек'26 | AB3: 2026 | AC3: Янв'27 | AD3: Фев'27 | AE3: Мар'27 | AF3: Апр'27 | AG3: Май'27 | AH3: Июн'27 | AI3: Июл'27 | AJ3: Авг'27 | AK3: Сен'27 | AL3: Окт'27 | AM3: Ноя'27 | AN3: Дек'27 | AO3: 2027 | AP3: Янв'28 | AQ3: Фев'28 | AR3: Мар'28 | AS3: Апр'28 | AT3: Май'28 | AU3: Июн'28 | AV3: Июл'28 | AW3: Авг'28 | AX3: Сен'28 | AY3: Окт'28 | AZ3: Ноя'28 | BA3: Дек'28 | BB3: 2028 | BC3: Янв'29 | BD3: Фев'29 | BE3: Мар'29 | BF3: Апр'29 | BG3: Май'29 | BH3: Июн'29 | BI3: Июл'29 | BJ3: Авг'29 | BK3: Сен'29 | BL3: Окт'29 | BM3: Ноя'29 | BN3: Дек'29 | BO3: 2029 | BP3: Янв'30 | BQ3: Фев'30 | BR3: Мар'30 | BS3: Апр'30 | BT3: Май'30 | BU3: Июн'30 | BV3: Июл'30 | BW3: Авг'30 | BX3: Сен'30 | BY3: Окт'30 | BZ3: Ноя'30 | CA3: Дек'30 | CB3: 2030 | CC3: Янв'31 | CD3: Фев'31 | CE3: Мар'31 | CF3: Апр'31 | CG3: Май'31 | CH3: Июн'31 | CI3: Июл'31 | CJ3: Авг'31 | CK3: Сен'31 | CL3: Окт'31 | CM3: Ноя'31 | CN3: Дек'31 | CO3: 2031 | CQ3: сheck >> | CR3: 2025 | CS3: 2026 | CT3: 2027 | CU3: 2028 | CV3: 2029 | CW3: 2030 | CX3: 2031 | CZ3: corrections >> | DA3: Янв'27 | DB3: Фев'27 | DC3: Мар'27 | DD3: Апр'27 | DE3: Май'27 | DF3: Июн'27 | DG3: Июл'27 | DH3: Авг'27 | DI3: Сен'27 | DJ3: Окт'27 | DK3: Ноя'27 | DL3: Дек'27 | DM3: 2027 | DN3: Янв'28 | DO3: Фев'28 | DP3: Мар'28 | DQ3: Апр'28 | DR3: Май'28 | DS3: Июн'28 | DT3: Июл'28 | DU3: Авг'28 | DV3: Сен'28 | DW3: Окт'28 | DX3: Ноя'28 | DY3: Дек'28 | DZ3: 2028 | EA3: Янв'29 | EB3: Фев'29 | EC3: Мар'29 | ED3: Апр'29 | EE3: Май'29 | EF3: Июн'29 | EG3: Июл'29 | EH3: Авг'29 | EI3: Сен'29 | EJ3: Окт'29 | EK3: Ноя'29 | EL3: Дек'29 | EM3: 2029 | EN3: Янв'30 | EO3: Фев'30 | EP3: Мар'30 | EQ3: Апр'30 | ER3: Май'30 | ES3: Июн'30 | ET3: Июл'30 | EU3: Авг'30 | EV3: Сен'30 | EW3: Окт'30 | EX3: Ноя'30 | EY3: Дек'30 | EZ3: 2030 | FA3: Янв'31 | FB3: Фев'31 | FC3: Мар'31 | FD3: Апр'31 | FE3: Май'31 | FF3: Июн'31 | FG3: Июл'31 | FH3: Авг'31 | FI3: Сен'31 | FJ3: Окт'31 | FK3: Ноя'31 | FL3: Дек'31 | FM3: 2031 | FO3: negative scenario > | FP3: Янв'25 | FQ3: Фев'25 | FR3: Мар'25 | FS3: Апр'25 | FT3: Май'25 | FU3: Июн'25 | FV3: Июл'25 | FW3: Авг'25 | FX3: Сен'25 | FY3: Окт'25 | FZ3: Ноя'25 | GA3: Дек'25 | GB3: 2025 | GC3: Янв'26 | GD3: Фев'26 | GE3: Мар'26 | GF3: Апр'26 | GG3: Май'26 | GH3: Июн'26 | GI3: Июл'26 | GJ3: Авг'26 | GK3: Сен'26 | GL3: Окт'26 | GM3: Ноя'26 | GN3: Дек'26 | GO3: 2026 | GP3: Янв'27 | GQ3: Фев'27 | GR3: Мар'27 | GS3: Апр'27 | GT3: Май'27 | GU3: Июн'27 | GV3: Июл'27 | GW3: Авг'27 | GX3: Сен'27 | GY3: Окт'27 | GZ3: Ноя'27 | HA3: Дек'27 | HB3: 2027 | HC3: Янв'28 | HD3: Фев'28 | HE3: Мар'28 | HF3: Апр'28 | HG3: Май'28 | HH3: Июн'28 | HI3: Июл'28 | HJ3: Авг'28 | HK3: Сен'28 | HL3: Окт'28 | HM3: Ноя'28 | HN3: Дек'28 | HO3: 2028 | HP3: Янв'29 | HQ3: Фев'29 | HR3: Мар'29 | HS3: Апр'29 | HT3: Май'29 | HU3: Июн'29 | HV3: Июл'29 | HW3: Авг'29 | HX3: Сен'29 | HY3: Окт'29 | HZ3: Ноя'29 | IA3: Дек'29 | IB3: 2029 | IC3: Янв'30 | ID3: Фев'30 | IE3: Мар'30 | IF3: Апр'30 | IG3: Май'30 | IH3: Июн'30 | II3: Июл'30 | IJ3: Авг'30 | IK3: Сен'30 | IL3: Окт'30 | IM3: Ноя'30 | IN3: Дек'30 | IO3: 2030 | IP3: Янв'31 | IQ3: Фев'31 | IR3: Мар'31 | IS3: Апр'31 | IT3: Май'31 | IU3: Июн'31 | IV3: Июл'31 | IW3: Авг'31 | IX3: Сен'31 | IY3: Окт'31 | IZ3: Ноя'31 | JA3: Дек'31 | JB3: 2031 | JD3: check >> | JE3: 2025 | JF3: 2026 | JG3: 2027 | JH3: 2028 | JI3: 2029 | JJ3: 2030 | JK3: 2031
B4: Выручка от реализации | C4: =C5+C33+C35+C37+C39 -> 53407.478 | D4: =D5+D33+D35+D37+D39 -> 59108.136 | E4: =E5+E33+E35+E37+E39 -> 65825.632 | F4: =F5+F33+F35+F37+F39 -> 65714.54 | G4: =G5+G33+G35+G37+G39 -> 66807.293 | H4: =H5+H33+H35+H37+H39 -> 70939.133 | I4: =I5+I33+I35+I37+I39 -> 81620.399 | J4: =J5+J33+J35+J37+J39 -> 79696.642 | ... N4: =N5+N33+N35+N37+N39 -> 88343.074 | O4: =SUM(C4:N4) -> 848093.51 | P4: =P5+P33+P35+P37+P39 -> 64808.555 | Q4: =Q5+Q33+Q35+Q37+Q39 -> 71687.917 | R4: =R5+R33+R35+R37+R39 -> 79870.769 | S4: =S5+S33+S35+S37+S39 -> 79745.41 | T4: =T5+T33+T35+T37+T39 -> 81089.802 | U4: =U5+U33+U35+U37+U39 -> 86107.714 | V4: =V5+V33+V35+V37+V39 -> 99036.479 | W4: =W5+W33+W35+W37+W39 -> 96728.56 | ... AA4: =AA5+AA33+AA35+AA37+AA39 -> 107204.22 | AB4: =SUM(P4:AA4) -> 1029160.5 | AC4: =AC5+AC33+AC35+AC37+AC39 -> 84185.174 | AD4: =AD5+AD33+AD35+AD37+AD39 -> 93113.103 | AE4: =AE5+AE33+AE35+AE37+AE39 -> 103776.65 | AF4: =AF5+AF33+AF35+AF37+AF39 -> 103623.54 | AG4: =AG5+AG33+AG35+AG37+AG39 -> 105407.68 | AH4: =AH5+AH33+AH35+AH37+AH39 -> 111910.47 | AI4: =AI5+AI33+AI35+AI37+AI39 -> 128650.08 | AJ4: =AJ5+AJ33+AJ35+AJ37+AJ39 -> 125716.15 | ... AN4: =AN5+AN33+AN35+AN37+AN39 -> 139302.89 | AO4: =SUM(AC4:AN4) -> 1337307.8 | AP4: =AP5+AP33+AP35+AP37+AP39 -> 110173.45 | AQ4: =AQ5+AQ33+AQ35+AQ37+AQ39 -> 121847.11 | AR4: =AR5+AR33+AR35+AR37+AR39 -> 135817.61 | AS4: =AS5+AS33+AS35+AS37+AS39 -> 135627.41 | AT4: =AT5+AT33+AT35+AT37+AT39 -> 137989.71 | AU4: =AU5+AU33+AU35+AU37+AU39 -> 146466.47 | AV4: =AV5+AV33+AV35+AV37+AV39 -> 168354.86 | AW4: =AW5+AW33+AW35+AW37+AW39 -> 164561.77 | ... BA4: =BA5+BA33+BA35+BA37+BA39 -> 182323.74 | BB4: =SUM(AP4:BA4) -> 1750307.9 | BC4: =BC5+BC33+BC35+BC37+BC39 -> 145692.28 | BD4: =BD5+BD33+BD35+BD37+BD39 -> 161104.48 | BE4: =BE5+BE33+BE35+BE37+BE39 -> 179575.04 | BF4: =BF5+BF33+BF35+BF37+BF39 -> 179330.59 | BG4: =BG5+BG33+BG35+BG37+BG39 -> 182470.69 | BH4: =BH5+BH33+BH35+BH37+BH39 -> 193621.87 | BI4: =BI5+BI33+BI35+BI37+BI39 -> 222615.25 | BJ4: =BJ5+BJ33+BJ35+BJ37+BJ39 -> 217601.61 | ... BN4: =BN5+BN33+BN35+BN37+BN39 -> 241070.2 | BO4: =SUM(BC4:BN4) -> 2314273.9 | BP4: =BP5+BP33+BP35+BP37+BP39 -> 192805.84 | BQ4: =BQ5+BQ33+BQ35+BQ37+BQ39 -> 213155.21 | BR4: =BR5+BR33+BR35+BR37+BR39 -> 237565.36 | BS4: =BS5+BS33+BS35+BS37+BS39 -> 237244.64 | BT4: =BT5+BT33+BT35+BT37+BT39 -> 241400.27 | BU4: =BU5+BU33+BU35+BU37+BU39 -> 256053.57 | BV4: =BV5+BV33+BV35+BV37+BV39 -> 294578.31 | BW4: =BW5+BW33+BW35+BW37+BW39 -> 287881.89 | ... CA4: =CA5+CA33+CA35+CA37+CA39 -> 318917.45 | CB4: =SUM(BP4:CA4) -> 3061607.5 | CC4: =CC5+CC33+CC35+CC37+CC39 -> 255258.11 | CD4: =CD5+CD33+CD35+CD37+CD39 -> 282139.82 | CE4: =CE5+CE33+CE35+CE37+CE39 -> 314399.51 | CF4: =CF5+CF33+CF35+CF37+CF39 -> 313972.42 | CG4: =CG5+CG33+CG35+CG37+CG39 -> 319465.66 | CH4: =CH5+CH33+CH35+CH37+CH39 -> 338724.11 | CI4: =CI5+CI33+CI35+CI37+CI39 -> 389965.05 | CJ4: =CJ5+CJ33+CJ35+CJ37+CJ39 -> 380988.74 | ... CN4: =CN5+CN33+CN35+CN37+CN39 -> 422053.52 | CO4: =SUM(CC4:CN4) -> 4051713.8 | CR4: =O4-'ОПУ БС'!C4 -> 0 | CS4: =AB4-'ОПУ БС'!D4 -> 0 | CT4: =AO4-'ОПУ БС'!E4 -> 0 | CU4: =BB4-'ОПУ БС'!F4 -> 0 | CV4: =BO4-'ОПУ БС'!G4 -> 0 | CW4: =CB4-'ОПУ БС'!H4 -> 0 | CX4: =CO4-'ОПУ БС'!I4 -> 0 | DA4: =DA5+DA33+DA35+DA37+DA39 -> 0 | DB4: =DB5+DB33+DB35+DB37+DB39 -> 0 | DC4: =DC5+DC33+DC35+DC37+DC39 -> 0 | DD4: =DD5+DD33+DD35+DD37+DD39 -> 0 | DE4: =DE5+DE33+DE35+DE37+DE39 -> 0 | DF4: =DF5+DF33+DF35+DF37+DF39 -> 0 | DG4: =DG5+DG33+DG35+DG37+DG39 -> 0 | DH4: =DH5+DH33+DH35+DH37+DH39 -> 0 | ... DL4: =DL5+DL33+DL35+DL37+DL39 -> 0 | DM4: =SUM(DA4:DL4) -> 0 | DN4: =DN5+DN33+DN35+DN37+DN39 -> 0 | DO4: =DO5+DO33+DO35+DO37+DO39 -> 0 | DP4: =DP5+DP33+DP35+DP37+DP39 -> 0 | DQ4: =DQ5+DQ33+DQ35+DQ37+DQ39 -> 0 | DR4: =DR5+DR33+DR35+DR37+DR39 -> 0 | DS4: =DS5+DS33+DS35+DS37+DS39 -> 0 | DT4: =DT5+DT33+DT35+DT37+DT39 -> 0 | DU4: =DU5+DU33+DU35+DU37+DU39 -> 0 | ... DY4: =DY5+DY33+DY35+DY37+DY39 -> 0 | DZ4: =SUM(DN4:DY4) -> 0 | EA4: =EA5+EA33+EA35+EA37+EA39 -> 0 | EB4: =EB5+EB33+EB35+EB37+EB39 -> 0 | EC4: =EC5+EC33+EC35+EC37+EC39 -> 0 | ED4: =ED5+ED33+ED35+ED37+ED39 -> 0 | EE4: =EE5+EE33+EE35+EE37+EE39 -> 0 | EF4: =EF5+EF33+EF35+EF37+EF39 -> 0 | EG4: =EG5+EG33+EG35+EG37+EG39 -> 0 | EH4: =EH5+EH33+EH35+EH37+EH39 -> 0 | ... EL4: =EL5+EL33+EL35+EL37+EL39 -> 0 | EM4: =SUM(EA4:EL4) -> 0 | EN4: =EN5+EN33+EN35+EN37+EN39 -> 0 | EO4: =EO5+EO33+EO35+EO37+EO39 -> 0 | EP4: =EP5+EP33+EP35+EP37+EP39 -> 0 | EQ4: =EQ5+EQ33+EQ35+EQ37+EQ39 -> 0 | ER4: =ER5+ER33+ER35+ER37+ER39 -> 0 | ES4: =ES5+ES33+ES35+ES37+ES39 -> 0 | ET4: =ET5+ET33+ET35+ET37+ET39 -> 0 | EU4: =EU5+EU33+EU35+EU37+EU39 -> 0 | ... EY4: =EY5+EY33+EY35+EY37+EY39 -> 0 | EZ4: =SUM(EN4:EY4) -> 0 | FA4: =FA5+FA33+FA35+FA37+FA39 -> 0 | FB4: =FB5+FB33+FB35+FB37+FB39 -> 0 | FC4: =FC5+FC33+FC35+FC37+FC39 -> 0 | FD4: =FD5+FD33+FD35+FD37+FD39 -> 0 | FE4: =FE5+FE33+FE35+FE37+FE39 -> 0 | FF4: =FF5+FF33+FF35+FF37+FF39 -> 0 | FG4: =FG5+FG33+FG35+FG37+FG39 -> 0 | FH4: =FH5+FH33+FH35+FH37+FH39 -> 0 | ... FL4: =FL5+FL33+FL35+FL37+FL39 -> 0 | FM4: =SUM(FA4:FL4) -> 0 | FP4: =FP5+FP33+FP35+FP37+FP39 -> 53407.478 | FQ4: =FQ5+FQ33+FQ35+FQ37+FQ39 -> 59108.136 | FR4: =FR5+FR33+FR35+FR37+FR39 -> 65825.632 | FS4: =FS5+FS33+FS35+FS37+FS39 -> 65714.54 | FT4: =FT5+FT33+FT35+FT37+FT39 -> 66807.293 | FU4: =FU5+FU33+FU35+FU37+FU39 -> 70939.133 | FV4: =FV5+FV33+FV35+FV37+FV39 -> 81620.399 | FW4: =FW5+FW33+FW35+FW37+FW39 -> 79696.642 | ... GA4: =GA5+GA33+GA35+GA37+GA39 -> 88343.074 | GB4: 0 | GC4: =GC5+GC33+GC35+GC37+GC39 -> 64808.555 | GD4: =GD5+GD33+GD35+GD37+GD39 -> 71687.917 | GE4: =GE5+GE33+GE35+GE37+GE39 -> 79870.769 | GF4: =GF5+GF33+GF35+GF37+GF39 -> 79745.41 | GG4: =GG5+GG33+GG35+GG37+GG39 -> 81089.802 | GH4: =GH5+GH33+GH35+GH37+GH39 -> 86107.714 | GI4: =GI5+GI33+GI35+GI37+GI39 -> 99036.479 | GJ4: =GJ5+GJ33+GJ35+GJ37+GJ39 -> 96728.56 | ... GN4: =GN5+GN33+GN35+GN37+GN39 -> 107204.22 | GO4: 0 | GP4: =GP5+GP33+GP35+GP37+GP39 -> 84185.174 | GQ4: =GQ5+GQ33+GQ35+GQ37+GQ39 -> 93113.103 | GR4: =GR5+GR33+GR35+GR37+GR39 -> 103776.65 | GS4: =GS5+GS33+GS35+GS37+GS39 -> 103623.54 | GT4: =GT5+GT33+GT35+GT37+GT39 -> 105407.68 | GU4: =GU5+GU33+GU35+GU37+GU39 -> 111910.47 | GV4: =GV5+GV33+GV35+GV37+GV39 -> 128650.08 | GW4: =GW5+GW33+GW35+GW37+GW39 -> 125716.15 | ... HA4: =HA5+HA33+HA35+HA37+HA39 -> 139302.89 | HB4: 0 | HC4: =HC5+HC33+HC35+HC37+HC39 -> 110173.45 | HD4: =HD5+HD33+HD35+HD37+HD39 -> 121847.11 | HE4: =HE5+HE33+HE35+HE37+HE39 -> 135817.61 | HF4: =HF5+HF33+HF35+HF37+HF39 -> 135627.41 | HG4: =HG5+HG33+HG35+HG37+HG39 -> 137989.71 | HH4: =HH5+HH33+HH35+HH37+HH39 -> 146466.47 | HI4: =HI5+HI33+HI35+HI37+HI39 -> 168354.86 | HJ4: =HJ5+HJ33+HJ35+HJ37+HJ39 -> 164561.77 | ... HN4: =HN5+HN33+HN35+HN37+HN39 -> 182323.74 | HO4: =SUM(HC4:HN4) -> 1750307.9 | HP4: =HP5+HP33+HP35+HP37+HP39 -> 145692.28 | HQ4: =HQ5+HQ33+HQ35+HQ37+HQ39 -> 161104.48 | HR4: =HR5+HR33+HR35+HR37+HR39 -> 179575.04 | HS4: =HS5+HS33+HS35+HS37+HS39 -> 179330.59 | HT4: =HT5+HT33+HT35+HT37+HT39 -> 182470.69 | HU4: =HU5+HU33+HU35+HU37+HU39 -> 193621.87 | HV4: =HV5+HV33+HV35+HV37+HV39 -> 222615.25 | HW4: =HW5+HW33+HW35+HW37+HW39 -> 217601.61 | ... IA4: =IA5+IA33+IA35+IA37+IA39 -> 241070.2 | IB4: =SUM(HP4:IA4) -> 2314273.9 | IC4: =IC5+IC33+IC35+IC37+IC39 -> 192805.84 | ID4: =ID5+ID33+ID35+ID37+ID39 -> 213155.21 | IE4: =IE5+IE33+IE35+IE37+IE39 -> 237565.36 | IF4: =IF5+IF33+IF35+IF37+IF39 -> 237244.64 | IG4: =IG5+IG33+IG35+IG37+IG39 -> 241400.27 | IH4: =IH5+IH33+IH35+IH37+IH39 -> 256053.57 | II4: =II5+II33+II35+II37+II39 -> 294578.31 | IJ4: =IJ5+IJ33+IJ35+IJ37+IJ39 -> 287881.89 | ... IN4: =IN5+IN33+IN35+IN37+IN39 -> 318917.45 | IO4: =SUM(IC4:IN4) -> 3061607.5 | IP4: =IP5+IP33+IP35+IP37+IP39 -> 255258.11 | IQ4: =IQ5+IQ33+IQ35+IQ37+IQ39 -> 282139.82 | IR4: =IR5+IR33+IR35+IR37+IR39 -> 314399.51 | IS4: =IS5+IS33+IS35+IS37+IS39 -> 313972.42 | IT4: =IT5+IT33+IT35+IT37+IT39 -> 319465.66 | IU4: =IU5+IU33+IU35+IU37+IU39 -> 338724.11 | IV4: =IV5+IV33+IV35+IV37+IV39 -> 389965.05 | IW4: =IW5+IW33+IW35+IW37+IW39 -> 380988.74 | ... JA4: =JA5+JA33+JA35+JA37+JA39 -> 422053.52 | JB4: =SUM(IP4:JA4) -> 4051713.8 | JE4: =O4-GB4 -> 848093.51 | JF4: =AB4-GO4 -> 1029160.5 | JG4: =AO4+DM4-HB4 -> 1337307.8 | JH4: =BB4+DZ4-HO4 -> 0 | JI4: =BO4+EM4-IB4 -> 0 | JJ4: =CB4+EZ4-IO4 -> 0 | JK4: =CO4+FM4-JB4 -> 0
B5: Готовая продукция | C5: =C6+C19+C32 -> 51950.811 | D5: =D6+D19+D32 -> 57517.302 | E5: =E6+E19+E32 -> 64043.132 | F5: =F6+F19+F32 -> 63932.04 | G5: =G6+G19+G32 -> 64986.46 | H5: =H6+H19+H32 -> 69003.3 | I5: =I6+I19+I32 -> 79397.065 | J5: =J6+J19+J32 -> 77530.808 | ... N5: =N6+N19+N32 -> 85947.241 | O5: =SUM(C5:N5) -> 825093.51 | P5: =P6+P19+P32 -> 63286.339 | Q5: =Q6+Q19+Q32 -> 70025.496 | R5: =R6+R19+R32 -> 78008.056 | S5: =S6+S19+S32 -> 77882.697 | T5: =T6+T19+T32 -> 79187.031 | U5: =U6+U19+U32 -> 84084.768 | V5: =V6+V19+V32 -> 96713.095 | W5: =W6+W19+W32 -> 94465.264 | ... AA5: =AA6+AA19+AA32 -> 104700.57 | AB5: =SUM(P5:AA5) -> 1005125.5 | AC5: =AC6+AC19+AC32 -> 82602.069 | AD5: =AD6+AD19+AD32 -> 91384.186 | AE5: =AE6+AE19+AE32 -> 101839.43 | AF5: =AF6+AF19+AF32 -> 101686.32 | AG5: =AG6+AG19+AG32 -> 103428.8 | AH5: =AH6+AH19+AH32 -> 109806.61 | AI5: =AI6+AI19+AI32 -> 126233.76 | AJ5: =AJ6+AJ19+AJ32 -> 123362.33 | ... AN5: =AN6+AN19+AN32 -> 136699.1 | AO5: =SUM(AC5:AN5) -> 1312311.4 | AP5: =AP6+AP19+AP32 -> 108527.02 | AQ5: =AQ6+AQ19+AQ32 -> 120049.03 | AR5: =AR6+AR19+AR32 -> 133802.9 | AS5: =AS6+AS19+AS32 -> 133612.7 | AT5: =AT6+AT19+AT32 -> 135931.67 | AU5: =AU6+AU19+AU32 -> 144278.46 | AV5: =AV6+AV19+AV32 -> 165841.89 | AW5: =AW6+AW19+AW32 -> 162113.79 | ... BA5: =BA6+BA19+BA32 -> 179615.8 | BB5: =SUM(AP5:BA5) -> 1724311.7 | BC5: =BC6+BC19+BC32 -> 143979.99 | BD5: =BD6+BD19+BD32 -> 159234.48 | BE5: =BE6+BE19+BE32 -> 177479.74 | BF5: =BF6+BF19+BF32 -> 177235.29 | BG5: =BG6+BG19+BG32 -> 180330.33 | BH5: =BH6+BH19+BH32 -> 191346.33 | BI5: =BI6+BI19+BI32 -> 220001.76 | BJ5: =BJ6+BJ19+BJ32 -> 215055.71 | ... BN5: =BN6+BN19+BN32 -> 238253.94 | BO5: =SUM(BC5:BN5) -> 2287237.8 | BP5: =BP6+BP19+BP32 -> 191025.07 | BQ5: =BQ6+BQ19+BQ32 -> 211210.41 | BR5: =BR6+BR19+BR32 -> 235386.25 | BS5: =BS6+BS19+BS32 -> 235065.53 | BT5: =BT6+BT19+BT32 -> 239174.3 | BU5: =BU6+BU19+BU32 -> 253687.01 | BV5: =BV6+BV19+BV32 -> 291860.28 | BW5: =BW6+BW19+BW32 -> 285234.16 | ... CA5: =CA6+CA19+CA32 -> 315988.54 | CB5: =SUM(BP5:CA5) -> 3033490 | CC5: =CC6+CC19+CC32 -> 253406.11 | CD5: =CD6+CD19+CD32 -> 280117.23 | CE5: =CE6+CE19+CE32 -> 312133.24 | CF5: =CF6+CF19+CF32 -> 311706.14 | CG5: =CG6+CG19+CG32 -> 317150.65 | CH5: =CH6+CH19+CH32 -> 336262.89 | CI5: =CI6+CI19+CI32 -> 387138.29 | CJ5: =CJ6+CJ19+CJ32 -> 378235.09 | ... CN5: =CN6+CN19+CN32 -> 419007.45 | CO5: =SUM(CC5:CN5) -> 4022471.5 | CR5: =O5-'ОПУ БС'!C5 -> 0 | CS5: =AB5-'ОПУ БС'!D5 -> 0 | CT5: =AO5-'ОПУ БС'!E5 -> 0 | CU5: =BB5-'ОПУ БС'!F5 -> 0 | CV5: =BO5-'ОПУ БС'!G5 -> 0 | CW5: =CB5-'ОПУ БС'!H5 -> 0 | CX5: =CO5-'ОПУ БС'!I5 -> 0 | DA5: =DA6+DA19+DA32 -> 0 | DB5: =DB6+DB19+DB32 -> 0 | DC5: =DC6+DC19+DC32 -> 0 | DD5: =DD6+DD19+DD32 -> 0 | DE5: =DE6+DE19+DE32 -> 0 | DF5: =DF6+DF19+DF32 -> 0 | DG5: =DG6+DG19+DG32 -> 0 | DH5: =DH6+DH19+DH32 -> 0 | ... DL5: =DL6+DL19+DL32 -> 0 | DM5: =SUM(DA5:DL5) -> 0 | DN5: =DN6+DN19+DN32 -> 0 | DO5: =DO6+DO19+DO32 -> 0 | DP5: =DP6+DP19+DP32 -> 0 | DQ5: =DQ6+DQ19+DQ32 -> 0 | DR5: =DR6+DR19+DR32 -> 0 | DS5: =DS6+DS19+DS32 -> 0 | DT5: =DT6+DT19+DT32 -> 0 | DU5: =DU6+DU19+DU32 -> 0 | ... DY5: =DY6+DY19+DY32 -> 0 | DZ5: =SUM(DN5:DY5) -> 0 | EA5: =EA6+EA19+EA32 -> 0 | EB5: =EB6+EB19+EB32 -> 0 | EC5: =EC6+EC19+EC32 -> 0 | ED5: =ED6+ED19+ED32 -> 0 | EE5: =EE6+EE19+EE32 -> 0 | EF5: =EF6+EF19+EF32 -> 0 | EG5: =EG6+EG19+EG32 -> 0 | EH5: =EH6+EH19+EH32 -> 0 | ... EL5: =EL6+EL19+EL32 -> 0 | EM5: =SUM(EA5:EL5) -> 0 | EN5: =EN6+EN19+EN32 -> 0 | EO5: =EO6+EO19+EO32 -> 0 | EP5: =EP6+EP19+EP32 -> 0 | EQ5: =EQ6+EQ19+EQ32 -> 0 | ER5: =ER6+ER19+ER32 -> 0 | ES5: =ES6+ES19+ES32 -> 0 | ET5: =ET6+ET19+ET32 -> 0 | EU5: =EU6+EU19+EU32 -> 0 | ... EY5: =EY6+EY19+EY32 -> 0 | EZ5: =SUM(EN5:EY5) -> 0 | FA5: =FA6+FA19+FA32 -> 0 | FB5: =FB6+FB19+FB32 -> 0 | FC5: =FC6+FC19+FC32 -> 0 | FD5: =FD6+FD19+FD32 -> 0 | FE5: =FE6+FE19+FE32 -> 0 | FF5: =FF6+FF19+FF32 -> 0 | FG5: =FG6+FG19+FG32 -> 0 | FH5: =FH6+FH19+FH32 -> 0 | ... FL5: =FL6+FL19+FL32 -> 0 | FM5: =SUM(FA5:FL5) -> 0 | FP5: =FP6+FP19+FP32 -> 51950.811 | FQ5: =FQ6+FQ19+FQ32 -> 57517.302 | FR5: =FR6+FR19+FR32 -> 64043.132 | FS5: =FS6+FS19+FS32 -> 63932.04 | FT5: =FT6+FT19+FT32 -> 64986.46 | FU5: =FU6+FU19+FU32 -> 69003.3 | FV5: =FV6+FV19+FV32 -> 79397.065 | FW5: =FW6+FW19+FW32 -> 77530.808 | ... GA5: =GA6+GA19+GA32 -> 85947.241 | GB5: =SUM(FP5:GA5) -> 825093.51 | GC5: =GC6+GC19+GC32 -> 63286.339 | GD5: =GD6+GD19+GD32 -> 70025.496 | GE5: =GE6+GE19+GE32 -> 78008.056 | GF5: =GF6+GF19+GF32 -> 77882.697 | GG5: =GG6+GG19+GG32 -> 79187.031 | GH5: =GH6+GH19+GH32 -> 84084.768 | GI5: =GI6+GI19+GI32 -> 96713.095 | GJ5: =GJ6+GJ19+GJ32 -> 94465.264 | ... GN5: =GN6+GN19+GN32 -> 104700.57 | GO5: =SUM(GC5:GN5) -> 1005125.5 | GP5: =GP6+GP19+GP32 -> 82602.069 | GQ5: =GQ6+GQ19+GQ32 -> 91384.186 | GR5: =GR6+GR19+GR32 -> 101839.43 | GS5: =GS6+GS19+GS32 -> 101686.32 | GT5: =GT6+GT19+GT32 -> 103428.8 | GU5: =GU6+GU19+GU32 -> 109806.61 | GV5: =GV6+GV19+GV32 -> 126233.76 | GW5: =GW6+GW19+GW32 -> 123362.33 | ... HA5: =HA6+HA19+HA32 -> 136699.1 | HB5: =SUM(GP5:HA5) -> 1312311.4 | HC5: =HC6+HC19+HC32 -> 108527.02 | HD5: =HD6+HD19+HD32 -> 120049.03 | HE5: =HE6+HE19+HE32 -> 133802.9 | HF5: =HF6+HF19+HF32 -> 133612.7 | HG5: =HG6+HG19+HG32 -> 135931.67 | HH5: =HH6+HH19+HH32 -> 144278.46 | HI5: =HI6+HI19+HI32 -> 165841.89 | HJ5: =HJ6+HJ19+HJ32 -> 162113.79 | ... HN5: =HN6+HN19+HN32 -> 179615.8 | HO5: =SUM(HC5:HN5) -> 1724311.7 | HP5: =HP6+HP19+HP32 -> 143979.99 | HQ5: =HQ6+HQ19+HQ32 -> 159234.48 | HR5: =HR6+HR19+HR32 -> 177479.74 | HS5: =HS6+HS19+HS32 -> 177235.29 | HT5: =HT6+HT19+HT32 -> 180330.33 | HU5: =HU6+HU19+HU32 -> 191346.33 | HV5: =HV6+HV19+HV32 -> 220001.76 | HW5: =HW6+HW19+HW32 -> 215055.71 | ... IA5: =IA6+IA19+IA32 -> 238253.94 | IB5: =SUM(HP5:IA5) -> 2287237.8 | IC5: =IC6+IC19+IC32 -> 191025.07 | ID5: =ID6+ID19+ID32 -> 211210.41 | IE5: =IE6+IE19+IE32 -> 235386.25 | IF5: =IF6+IF19+IF32 -> 235065.53 | IG5: =IG6+IG19+IG32 -> 239174.3 | IH5: =IH6+IH19+IH32 -> 253687.01 | II5: =II6+II19+II32 -> 291860.28 | IJ5: =IJ6+IJ19+IJ32 -> 285234.16 | ... IN5: =IN6+IN19+IN32 -> 315988.54 | IO5: =SUM(IC5:IN5) -> 3033490 | IP5: =IP6+IP19+IP32 -> 253406.11 | IQ5: =IQ6+IQ19+IQ32 -> 280117.23 | IR5: =IR6+IR19+IR32 -> 312133.24 | IS5: =IS6+IS19+IS32 -> 311706.14 | IT5: =IT6+IT19+IT32 -> 317150.65 | IU5: =IU6+IU19+IU32 -> 336262.89 | IV5: =IV6+IV19+IV32 -> 387138.29 | IW5: =IW6+IW19+IW32 -> 378235.09 | ... JA5: =JA6+JA19+JA32 -> 419007.45 | JB5: =SUM(IP5:JA5) -> 4022471.5 | JE5: =O5-GB5 -> 0 | JF5: =AB5-GO5 -> 0 | JG5: =AO5+DM5-HB5 -> 0 | JH5: =BB5+DZ5-HO5 -> 0 | JI5: =BO5+EM5-IB5 -> 0 | JJ5: =CB5+EZ5-IO5 -> 0 | JK5: =CO5+FM5-JB5 -> 0
B6: МАГАЗИНЫ | C6: =C7+C11 -> 33993.402 | D6: =D7+D11 -> 37545.724 | E6: =E7+E11 -> 41679.861 | F6: =F7+F11 -> 41597.189 | G6: =G7+G11 -> 42162.159 | H6: =H7+H11 -> 44735.381 | I6: =I7+I11 -> 51936.176 | J6: =J7+J11 -> 50377.323 | ... N6: =N7+N11 -> 55910.2 | O6: =SUM(C6:N6) -> 536737.92 | P6: =P7+P11 -> 39121.168 | Q6: =Q7+Q11 -> 43205.589 | R6: =R7+R11 -> 47966.115 | S6: =S7+S11 -> 47871.956 | T6: =T7+T11 -> 48522.639 | U6: =U7+U11 -> 51479.62 | V6: =V7+V11 -> 59765.906 | W6: =W7+W11 -> 57982.945 | ... AA6: =AA7+AA11 -> 64344.027 | AB6: =SUM(P6:AA6) -> 617702.66 | AC6: =AC7+AC11 -> 48287.575 | AD6: =AD7+AD11 -> 53323.699 | AE6: =AE7+AE11 -> 59203.642 | AF6: =AF7+AF11 -> 59088.743 | AG6: =AG7+AG11 -> 59907.665 | AH6: =AH7+AH11 -> 63529.667 | AI6: =AI7+AI11 -> 73768.969 | AJ6: =AJ7+AJ11 -> 71582.337 | ... AN6: =AN7+AN11 -> 79420.353 | AO6: =SUM(AC6:AN6) -> 762435.39 | AP6: =AP7+AP11 -> 61777.919 | AQ6: =AQ7+AQ11 -> 68219.415 | AR6: =AR7+AR11 -> 75743.116 | AS6: =AS7+AS11 -> 75596.664 | AT6: =AT7+AT11 -> 76662.142 | AU6: =AU7+AU11 -> 81254.419 | AV6: =AV7+AV11 -> 94365.69 | AW6: =AW7+AW11 -> 91595.121 | ... BA6: =BA7+BA11 -> 101608.42 | BB6: =SUM(AP6:BA6) -> 975440.83 | BC6: =BC7+BC11 -> 82108.656 | BD6: =BD7+BD11 -> 90666.058 | BE6: =BE7+BE11 -> 100668.75 | BF6: =BF7+BF11 -> 100475.07 | BG6: =BG7+BG11 -> 101915.96 | BH6: =BH7+BH11 -> 107963.09 | BI6: =BI7+BI11 -> 125406.12 | BJ6: =BJ7+BJ11 -> 121756.76 | ... BN6: =BN7+BN11 -> 135047.13 | BO6: =SUM(BC6:BN6) -> 1296452.5 | BP6: =BP7+BP11 -> 111869.46 | BQ6: =BQ7+BQ11 -> 123521.36 | BR6: =BR7+BR11 -> 137155.18 | BS6: =BS7+BS11 -> 136892.89 | BT6: =BT7+BT11 -> 138890.52 | BU6: =BU7+BU11 -> 147046.9 | BV6: =BV7+BV11 -> 170841.52 | BW6: =BW7+BW11 -> 165912.74 | ... CA6: =CA7+CA11 -> 183995.82 | CB6: =SUM(BP6:CA6) -> 1766359.9 | CC6: =CC7+CC11 -> 154054.25 | CD6: =CD7+CD11 -> 170085.35 | CE6: =CE7+CE11 -> 188871.96 | CF6: =CF7+CF11 -> 188513.75 | CG6: =CG7+CG11 -> 191312.66 | CH6: =CH7+CH11 -> 202447.34 | CI6: =CI7+CI11 -> 235245.21 | CJ6: =CJ7+CJ11 -> 228506.7 | ... CN6: =CN7+CN11 -> 253378.7 | CO6: =SUM(CC6:CN6) -> 2432435.5 | CR6: =O6-'ОПУ БС'!C6 -> 0 | CS6: =AB6-'ОПУ БС'!D6 -> 0 | CT6: =AO6-'ОПУ БС'!E6 -> 0 | CU6: =BB6-'ОПУ БС'!F6 -> 0 | CV6: =BO6-'ОПУ БС'!G6 -> 0 | CW6: =CB6-'ОПУ БС'!H6 -> 0 | CX6: =CO6-'ОПУ БС'!I6 -> 0 | DA6: =DA7+DA11 -> 0 | DB6: =DB7+DB11 -> 0 | DC6: =DC7+DC11 -> 0 | DD6: =DD7+DD11 -> 0 | DE6: =DE7+DE11 -> 0 | DF6: =DF7+DF11 -> 0 | DG6: =DG7+DG11 -> 0 | DH6: =DH7+DH11 -> 0 | ... DL6: =DL7+DL11 -> 0 | DM6: =SUM(DA6:DL6) -> 0 | DN6: =DN7+DN11 -> 0 | DO6: =DO7+DO11 -> 0 | DP6: =DP7+DP11 -> 0 | DQ6: =DQ7+DQ11 -> 0 | DR6: =DR7+DR11 -> 0 | DS6: =DS7+DS11 -> 0 | DT6: =DT7+DT11 -> 0 | DU6: =DU7+DU11 -> 0 | ... DY6: =DY7+DY11 -> 0 | DZ6: =SUM(DN6:DY6) -> 0 | EA6: =EA7+EA11 -> 0 | EB6: =EB7+EB11 -> 0 | EC6: =EC7+EC11 -> 0 | ED6: =ED7+ED11 -> 0 | EE6: =EE7+EE11 -> 0 | EF6: =EF7+EF11 -> 0 | EG6: =EG7+EG11 -> 0 | EH6: =EH7+EH11 -> 0 | ... EL6: =EL7+EL11 -> 0 | EM6: =SUM(EA6:EL6) -> 0 | EN6: =EN7+EN11 -> 0 | EO6: =EO7+EO11 -> 0 | EP6: =EP7+EP11 -> 0 | EQ6: =EQ7+EQ11 -> 0 | ER6: =ER7+ER11 -> 0 | ES6: =ES7+ES11 -> 0 | ET6: =ET7+ET11 -> 0 | EU6: =EU7+EU11 -> 0 | ... EY6: =EY7+EY11 -> 0 | EZ6: =SUM(EN6:EY6) -> 0 | FA6: =FA7+FA11 -> 0 | FB6: =FB7+FB11 -> 0 | FC6: =FC7+FC11 -> 0 | FD6: =FD7+FD11 -> 0 | FE6: =FE7+FE11 -> 0 | FF6: =FF7+FF11 -> 0 | FG6: =FG7+FG11 -> 0 | FH6: =FH7+FH11 -> 0 | ... FL6: =FL7+FL11 -> 0 | FM6: =SUM(FA6:FL6) -> 0 | FP6: =FP7+FP11 -> 33993.402 | FQ6: =FQ7+FQ11 -> 37545.724 | FR6: =FR7+FR11 -> 41679.861 | FS6: =FS7+FS11 -> 41597.189 | FT6: =FT7+FT11 -> 42162.159 | FU6: =FU7+FU11 -> 44735.381 | FV6: =FV7+FV11 -> 51936.176 | FW6: =FW7+FW11 -> 50377.323 | ... GA6: =GA7+GA11 -> 55910.2 | GB6: =SUM(FP6:GA6) -> 536737.92 | GC6: =GC7+GC11 -> 39121.168 | GD6: =GD7+GD11 -> 43205.589 | GE6: =GE7+GE11 -> 47966.115 | GF6: =GF7+GF11 -> 47871.956 | GG6: =GG7+GG11 -> 48522.639 | GH6: =GH7+GH11 -> 51479.62 | GI6: =GI7+GI11 -> 59765.906 | GJ6: =GJ7+GJ11 -> 57982.945 | ... GN6: =GN7+GN11 -> 64344.027 | GO6: =SUM(GC6:GN6) -> 617702.66 | GP6: =GP7+GP11 -> 48287.575 | GQ6: =GQ7+GQ11 -> 53323.699 | GR6: =GR7+GR11 -> 59203.642 | GS6: =GS7+GS11 -> 59088.743 | GT6: =GT7+GT11 -> 59907.665 | GU6: =GU7+GU11 -> 63529.667 | GV6: =GV7+GV11 -> 73768.969 | GW6: =GW7+GW11 -> 71582.337 | ... HA6: =HA7+HA11 -> 79420.353 | HB6: =SUM(GP6:HA6) -> 762435.39 | HC6: =HC7+HC11 -> 61777.919 | HD6: =HD7+HD11 -> 68219.415 | HE6: =HE7+HE11 -> 75743.116 | HF6: =HF7+HF11 -> 75596.664 | HG6: =HG7+HG11 -> 76662.142 | HH6: =HH7+HH11 -> 81254.419 | HI6: =HI7+HI11 -> 94365.69 | HJ6: =HJ7+HJ11 -> 91595.121 | ... HN6: =HN7+HN11 -> 101608.42 | HO6: =SUM(HC6:HN6) -> 975440.83 | HP6: =HP7+HP11 -> 82108.656 | HQ6: =HQ7+HQ11 -> 90666.058 | HR6: =HR7+HR11 -> 100668.75 | HS6: =HS7+HS11 -> 100475.07 | HT6: =HT7+HT11 -> 101915.96 | HU6: =HU7+HU11 -> 107963.09 | HV6: =HV7+HV11 -> 125406.12 | HW6: =HW7+HW11 -> 121756.76 | ... IA6: =IA7+IA11 -> 135047.13 | IB6: =SUM(HP6:IA6) -> 1296452.5 | IC6: =IC7+IC11 -> 111869.46 | ID6: =ID7+ID11 -> 123521.36 | IE6: =IE7+IE11 -> 137155.18 | IF6: =IF7+IF11 -> 136892.89 | IG6: =IG7+IG11 -> 138890.52 | IH6: =IH7+IH11 -> 147046.9 | II6: =II7+II11 -> 170841.52 | IJ6: =IJ7+IJ11 -> 165912.74 | ... IN6: =IN7+IN11 -> 183995.82 | IO6: =SUM(IC6:IN6) -> 1766359.9 | IP6: =IP7+IP11 -> 154054.25 | IQ6: =IQ7+IQ11 -> 170085.35 | IR6: =IR7+IR11 -> 188871.96 | IS6: =IS7+IS11 -> 188513.75 | IT6: =IT7+IT11 -> 191312.66 | IU6: =IU7+IU11 -> 202447.34 | IV6: =IV7+IV11 -> 235245.21 | IW6: =IW7+IW11 -> 228506.7 | ... JA6: =JA7+JA11 -> 253378.7 | JB6: =SUM(IP6:JA6) -> 2432435.5 | JE6: =O6-GB6 -> 0 | JF6: =AB6-GO6 -> 0 | JG6: =AO6+DM6-HB6 -> 0 | JH6: =BB6+DZ6-HO6 -> 0 | JI6: =BO6+EM6-IB6 -> 0 | JJ6: =CB6+EZ6-IO6 -> 0 | JK6: =CO6+FM6-JB6 -> 0
B7: Сухари | C7: =SUM(C8:C10) -> 27314.817 | D7: =SUM(D8:D10) -> 30252.006 | E7: =SUM(E8:E10) -> 33507.382 | F7: =SUM(F8:F10) -> 33424.71 | G7: =SUM(G8:G10) -> 34143.521 | H7: =SUM(H8:H10) -> 36299.954 | I7: =SUM(I8:I10) -> 41691.036 | J7: =SUM(J8:J10) -> 40612.82 | ... N7: =SUM(N8:N10) -> 44925.686 | O7: =SUM(C7:N7) -> 431286.58 | P7: =SUM(P8:P10) -> 31663.982 | Q7: =SUM(Q8:Q10) -> 35061.557 | R7: =SUM(R8:R10) -> 38840.874 | S7: =SUM(S8:S10) -> 38746.715 | T7: =SUM(T8:T10) -> 39579.978 | U7: =SUM(U8:U10) -> 42079.766 | V7: =SUM(V8:V10) -> 48329.236 | W7: =SUM(W8:W10) -> 47079.342 | ... AA7: =SUM(AA8:AA10) -> 52078.918 | AB7: =SUM(P7:AA7) -> 499957.61 | AC7: =SUM(AC8:AC10) -> 39287.131 | AD7: =SUM(AD8:AD10) -> 43494.268 | AE7: =SUM(AE8:AE10) -> 48189.942 | AF7: =SUM(AF8:AF10) -> 48075.042 | AG7: =SUM(AG8:AG10) -> 49108.914 | AH7: =SUM(AH8:AH10) -> 52210.53 | AI7: =SUM(AI8:AI10) -> 59964.569 | AJ7: =SUM(AJ8:AJ10) -> 58413.761 | ... AN7: =SUM(AN8:AN10) -> 64616.992 | AO7: =SUM(AC7:AN7) -> 620323.12 | AP7: =SUM(AP8:AP10) -> 50905.699 | AQ7: =SUM(AQ8:AQ10) -> 56345.806 | AR7: =SUM(AR8:AR10) -> 62438.951 | AS7: =SUM(AS8:AS10) -> 62292.5 | AT7: =SUM(AT8:AT10) -> 63632.123 | AU7: =SUM(AU8:AU10) -> 67650.994 | AV7: =SUM(AV8:AV10) -> 77698.172 | AW7: =SUM(AW8:AW10) -> 75688.736 | ... BA7: =SUM(BA8:BA10) -> 83726.478 | BB7: =SUM(AP7:BA7) -> 803774.19 | BC7: =SUM(BC8:BC10) -> 68439.062 | BD7: =SUM(BD8:BD10) -> 75737.422 | BE7: =SUM(BE8:BE10) -> 83941.479 | BF7: =SUM(BF8:BF10) -> 83747.799 | BG7: =SUM(BG8:BG10) -> 85548.827 | BH7: =SUM(BH8:BH10) -> 90951.911 | BI7: =SUM(BI8:BI10) -> 104459.62 | BJ7: =SUM(BJ8:BJ10) -> 101758.08 | ... BN7: =SUM(BN8:BN10) -> 112564.25 | BO7: =SUM(BC7:BN7) -> 1080616.8 | BP7: =SUM(BP8:BP10) -> 94247.241 | BQ7: =SUM(BQ8:BQ10) -> 104276.05 | BR7: =SUM(BR8:BR10) -> 115591.15 | BS7: =SUM(BS8:BS10) -> 115328.86 | BT7: =SUM(BT8:BT10) -> 117809.05 | BU7: =SUM(BU8:BU10) -> 125249.62 | BV7: =SUM(BV8:BV10) -> 143851.05 | BW7: =SUM(BW8:BW10) -> 140130.77 | ... CA7: =SUM(CA8:CA10) -> 155011.91 | CB7: =SUM(BP7:CA7) -> 1488114.3 | CC7: =SUM(CC8:CC10) -> 130915.55 | CD7: =SUM(CD8:CD10) -> 144815.45 | CE7: =SUM(CE8:CE10) -> 160557.49 | CF7: =SUM(CF8:CF10) -> 160199.29 | CG7: =SUM(CG8:CG10) -> 163644.43 | CH7: =SUM(CH8:CH10) -> 173979.87 | CI7: =SUM(CI8:CI10) -> 199818.47 | CJ7: =SUM(CJ8:CJ10) -> 194650.75 | ... CN7: =SUM(CN8:CN10) -> 215321.62 | CO7: =SUM(CC7:CN7) -> 2067087.6 | CR7: =O7-'ОПУ БС'!C7 -> 0 | CS7: =AB7-'ОПУ БС'!D7 -> 0 | CT7: =AO7-'ОПУ БС'!E7 -> 0 | CU7: =BB7-'ОПУ БС'!F7 -> 0 | CV7: =BO7-'ОПУ БС'!G7 -> 0 | CW7: =CB7-'ОПУ БС'!H7 -> 0 | CX7: =CO7-'ОПУ БС'!I7 -> 0 | DA7: =SUM(DA8:DA10) -> 0 | DB7: =SUM(DB8:DB10) -> 0 | DC7: =SUM(DC8:DC10) -> 0 | DD7: =SUM(DD8:DD10) -> 0 | DE7: =SUM(DE8:DE10) -> 0 | DF7: =SUM(DF8:DF10) -> 0 | DG7: =SUM(DG8:DG10) -> 0 | DH7: =SUM(DH8:DH10) -> 0 | ... DL7: =SUM(DL8:DL10) -> 0 | DM7: =SUM(DA7:DL7) -> 0 | DN7: =SUM(DN8:DN10) -> 0 | DO7: =SUM(DO8:DO10) -> 0 | DP7: =SUM(DP8:DP10) -> 0 | DQ7: =SUM(DQ8:DQ10) -> 0 | DR7: =SUM(DR8:DR10) -> 0 | DS7: =SUM(DS8:DS10) -> 0 | DT7: =SUM(DT8:DT10) -> 0 | DU7: =SUM(DU8:DU10) -> 0 | ... DY7: =SUM(DY8:DY10) -> 0 | DZ7: =SUM(DN7:DY7) -> 0 | EA7: =SUM(EA8:EA10) -> 0 | EB7: =SUM(EB8:EB10) -> 0 | EC7: =SUM(EC8:EC10) -> 0 | ED7: =SUM(ED8:ED10) -> 0 | EE7: =SUM(EE8:EE10) -> 0 | EF7: =SUM(EF8:EF10) -> 0 | EG7: =SUM(EG8:EG10) -> 0 | EH7: =SUM(EH8:EH10) -> 0 | ... EL7: =SUM(EL8:EL10) -> 0 | EM7: =SUM(EA7:EL7) -> 0 | EN7: =SUM(EN8:EN10) -> 0 | EO7: =SUM(EO8:EO10) -> 0 | EP7: =SUM(EP8:EP10) -> 0 | EQ7: =SUM(EQ8:EQ10) -> 0 | ER7: =SUM(ER8:ER10) -> 0 | ES7: =SUM(ES8:ES10) -> 0 | ET7: =SUM(ET8:ET10) -> 0 | EU7: =SUM(EU8:EU10) -> 0 | ... EY7: =SUM(EY8:EY10) -> 0 | EZ7: =SUM(EN7:EY7) -> 0 | FA7: =SUM(FA8:FA10) -> 0 | FB7: =SUM(FB8:FB10) -> 0 | FC7: =SUM(FC8:FC10) -> 0 | FD7: =SUM(FD8:FD10) -> 0 | FE7: =SUM(FE8:FE10) -> 0 | FF7: =SUM(FF8:FF10) -> 0 | FG7: =SUM(FG8:FG10) -> 0 | FH7: =SUM(FH8:FH10) -> 0 | ... FL7: =SUM(FL8:FL10) -> 0 | FM7: =SUM(FA7:FL7) -> 0 | FP7: =SUM(FP8:FP10) -> 27314.817 | FQ7: =SUM(FQ8:FQ10) -> 30252.006 | FR7: =SUM(FR8:FR10) -> 33507.382 | FS7: =SUM(FS8:FS10) -> 33424.71 | FT7: =SUM(FT8:FT10) -> 34143.521 | FU7: =SUM(FU8:FU10) -> 36299.954 | FV7: =SUM(FV8:FV10) -> 41691.036 | FW7: =SUM(FW8:FW10) -> 40612.82 | ... GA7: =SUM(GA8:GA10) -> 44925.686 | GB7: =SUM(FP7:GA7) -> 431286.58 | GC7: =SUM(GC8:GC10) -> 31663.982 | GD7: =SUM(GD8:GD10) -> 35061.557 | GE7: =SUM(GE8:GE10) -> 38840.874 | GF7: =SUM(GF8:GF10) -> 38746.715 | GG7: =SUM(GG8:GG10) -> 39579.978 | GH7: =SUM(GH8:GH10) -> 42079.766 | GI7: =SUM(GI8:GI10) -> 48329.236 | GJ7: =SUM(GJ8:GJ10) -> 47079.342 | ... GN7: =SUM(GN8:GN10) -> 52078.918 | GO7: =SUM(GC7:GN7) -> 499957.61 | GP7: =SUM(GP8:GP10) -> 39287.131 | GQ7: =SUM(GQ8:GQ10) -> 43494.268 | GR7: =SUM(GR8:GR10) -> 48189.942 | GS7: =SUM(GS8:GS10) -> 48075.042 | GT7: =SUM(GT8:GT10) -> 49108.914 | GU7: =SUM(GU8:GU10) -> 52210.53 | GV7: =SUM(GV8:GV10) -> 59964.569 | GW7: =SUM(GW8:GW10) -> 58413.761 | ... HA7: =SUM(HA8:HA10) -> 64616.992 | HB7: =SUM(GP7:HA7) -> 620323.12 | HC7: =SUM(HC8:HC10) -> 50905.699 | HD7: =SUM(HD8:HD10) -> 56345.806 | HE7: =SUM(HE8:HE10) -> 62438.951 | HF7: =SUM(HF8:HF10) -> 62292.5 | HG7: =SUM(HG8:HG10) -> 63632.123 | HH7: =SUM(HH8:HH10) -> 67650.994 | HI7: =SUM(HI8:HI10) -> 77698.172 | HJ7: =SUM(HJ8:HJ10) -> 75688.736 | ... HN7: =SUM(HN8:HN10) -> 83726.478 | HO7: =SUM(HC7:HN7) -> 803774.19 | HP7: =SUM(HP8:HP10) -> 68439.062 | HQ7: =SUM(HQ8:HQ10) -> 75737.422 | HR7: =SUM(HR8:HR10) -> 83941.479 | HS7: =SUM(HS8:HS10) -> 83747.799 | HT7: =SUM(HT8:HT10) -> 85548.827 | HU7: =SUM(HU8:HU10) -> 90951.911 | HV7: =SUM(HV8:HV10) -> 104459.62 | HW7: =SUM(HW8:HW10) -> 101758.08 | ... IA7: =SUM(IA8:IA10) -> 112564.25 | IB7: =SUM(HP7:IA7) -> 1080616.8 | IC7: =SUM(IC8:IC10) -> 94247.241 | ID7: =SUM(ID8:ID10) -> 104276.05 | IE7: =SUM(IE8:IE10) -> 115591.15 | IF7: =SUM(IF8:IF10) -> 115328.86 | IG7: =SUM(IG8:IG10) -> 117809.05 | IH7: =SUM(IH8:IH10) -> 125249.62 | II7: =SUM(II8:II10) -> 143851.05 | IJ7: =SUM(IJ8:IJ10) -> 140130.77 | ... IN7: =SUM(IN8:IN10) -> 155011.91 | IO7: =SUM(IC7:IN7) -> 1488114.3 | IP7: =SUM(IP8:IP10) -> 130915.55 | IQ7: =SUM(IQ8:IQ10) -> 144815.45 | IR7: =SUM(IR8:IR10) -> 160557.49 | IS7: =SUM(IS8:IS10) -> 160199.29 | IT7: =SUM(IT8:IT10) -> 163644.43 | IU7: =SUM(IU8:IU10) -> 173979.87 | IV7: =SUM(IV8:IV10) -> 199818.47 | IW7: =SUM(IW8:IW10) -> 194650.75 | ... JA7: =SUM(JA8:JA10) -> 215321.62 | JB7: =SUM(IP7:JA7) -> 2067087.6 | JE7: =O7-GB7 -> 0 | JF7: =AB7-GO7 -> 0 | JG7: =AO7+DM7-HB7 -> 0 | JH7: =BB7+DZ7-HO7 -> 0 | JI7: =BO7+EM7-IB7 -> 0 | JJ7: =CB7+EZ7-IO7 -> 0 | JK7: =CO7+FM7-JB7 -> 0
B8: Классика | C8: ='ОПУ БС'!$C8/12*'ОПУ БС'!L8 -> 13499.063 | D8: ='ОПУ БС'!$C8/12*'ОПУ БС'!M8 -> 14742.398 | E8: ='ОПУ БС'!$C8/12*'ОПУ БС'!N8 -> 16518.591 | F8: ='ОПУ БС'!$C8/12*'ОПУ БС'!O8 -> 16518.591 | G8: ='ОПУ БС'!$C8/12*'ОПУ БС'!P8 -> 16873.829 | H8: ='ОПУ БС'!$C8/12*'ОПУ БС'!Q8 -> 17939.545 | I8: ='ОПУ БС'!$C8/12*'ОПУ БС'!R8 -> 20603.834 | J8: ='ОПУ БС'!$C8/12*'ОПУ БС'!S8 -> 20070.976 | ... N8: ='ОПУ БС'!$C8/12*'ОПУ БС'!W8 -> 22202.407 | O8: =SUM(C8:N8) -> 213143.11 | P8: ='ОПУ БС'!$D8/12*'ОПУ БС'!L8 -> 15896.657 | Q8: ='ОПУ БС'!$D8/12*'ОПУ БС'!M8 -> 17360.823 | R8: ='ОПУ БС'!$D8/12*'ОПУ БС'!N8 -> 19452.488 | S8: ='ОПУ БС'!$D8/12*'ОПУ БС'!O8 -> 19452.488 | T8: ='ОПУ БС'!$D8/12*'ОПУ БС'!P8 -> 19870.822 | U8: ='ОПУ БС'!$D8/12*'ОПУ БС'!Q8 -> 21125.821 | V8: ='ОПУ БС'!$D8/12*'ОПУ БС'!R8 -> 24263.319 | W8: ='ОПУ БС'!$D8/12*'ОПУ БС'!S8 -> 23635.819 | ... AA8: ='ОПУ БС'!$D8/12*'ОПУ БС'!W8 -> 26145.818 | AB8: =SUM(P8:AA8) -> 250999.85 | AC8: ='ОПУ БС'!$E8/12*'ОПУ БС'!L8 -> 20010.13 | AD8: ='ОПУ БС'!$E8/12*'ОПУ БС'!M8 -> 21853.169 | AE8: ='ОПУ БС'!$E8/12*'ОПУ БС'!N8 -> 24486.08 | AF8: ='ОПУ БС'!$E8/12*'ОПУ БС'!O8 -> 24486.08 | AG8: ='ОПУ БС'!$E8/12*'ОПУ БС'!P8 -> 25012.663 | AH8: ='ОПУ БС'!$E8/12*'ОПУ БС'!Q8 -> 26592.41 | AI8: ='ОПУ БС'!$E8/12*'ОПУ БС'!R8 -> 30541.778 | AJ8: ='ОПУ БС'!$E8/12*'ОПУ БС'!S8 -> 29751.904 | ... AN8: ='ОПУ БС'!$E8/12*'ОПУ БС'!W8 -> 32911.398 | AO8: =SUM(AC8:AN8) -> 315949.42 | AP8: ='ОПУ БС'!$F8/12*'ОПУ БС'!L8 -> 26304.449 | AQ8: ='ОПУ БС'!$F8/12*'ОПУ БС'!M8 -> 28727.228 | AR8: ='ОПУ БС'!$F8/12*'ОПУ БС'!N8 -> 32188.339 | AS8: ='ОПУ БС'!$F8/12*'ОПУ БС'!O8 -> 32188.339 | AT8: ='ОПУ БС'!$F8/12*'ОПУ БС'!P8 -> 32880.562 | AU8: ='ОПУ БС'!$F8/12*'ОПУ БС'!Q8 -> 34957.229 | AV8: ='ОПУ БС'!$F8/12*'ОПУ БС'!R8 -> 40148.896 | AW8: ='ОПУ БС'!$F8/12*'ОПУ БС'!S8 -> 39110.563 | ... BA8: ='ОПУ БС'!$F8/12*'ОПУ БС'!W8 -> 43263.897 | BB8: =SUM(AP8:BA8) -> 415333.41 | BC8: ='ОПУ БС'!$G8/12*'ОПУ БС'!L8 -> 35878.576 | BD8: ='ОПУ БС'!$G8/12*'ОПУ БС'!M8 -> 39183.182 | BE8: ='ОПУ БС'!$G8/12*'ОПУ БС'!N8 -> 43904.047 | BF8: ='ОПУ БС'!$G8/12*'ОПУ БС'!O8 -> 43904.047 | BG8: ='ОПУ БС'!$G8/12*'ОПУ БС'!P8 -> 44848.22 | BH8: ='ОПУ БС'!$G8/12*'ОПУ БС'!Q8 -> 47680.739 | BI8: ='ОПУ БС'!$G8/12*'ОПУ БС'!R8 -> 54762.037 | BJ8: ='ОПУ БС'!$G8/12*'ОПУ БС'!S8 -> 53345.777 | ... BN8: ='ОПУ БС'!$G8/12*'ОПУ БС'!W8 -> 59010.816 | BO8: =SUM(BC8:BN8) -> 566503.83 | BP8: ='ОПУ БС'!$H8/12*'ОПУ БС'!L8 -> 50127.378 | BQ8: ='ОПУ БС'!$H8/12*'ОПУ БС'!M8 -> 54744.374 | BR8: ='ОПУ БС'!$H8/12*'ОПУ БС'!N8 -> 61340.081 | BS8: ='ОПУ БС'!$H8/12*'ОПУ БС'!O8 -> 61340.081 | BT8: ='ОПУ БС'!$H8/12*'ОПУ БС'!P8 -> 62659.223 | BU8: ='ОПУ БС'!$H8/12*'ОПУ БС'!Q8 -> 66616.647 | BV8: ='ОПУ БС'!$H8/12*'ОПУ БС'!R8 -> 76510.209 | BW8: ='ОПУ БС'!$H8/12*'ОПУ БС'!S8 -> 74531.497 | ... CA8: ='ОПУ БС'!$H8/12*'ОПУ БС'!W8 -> 82446.346 | CB8: =SUM(BP8:CA8) -> 791484.92 | CC8: ='ОПУ БС'!$I8/12*'ОПУ БС'!L8 -> 70642.367 | CD8: ='ОПУ БС'!$I8/12*'ОПУ БС'!M8 -> 77148.901 | CE8: ='ОПУ БС'!$I8/12*'ОПУ БС'!N8 -> 86443.949 | CF8: ='ОПУ БС'!$I8/12*'ОПУ БС'!O8 -> 86443.949 | CG8: ='ОПУ БС'!$I8/12*'ОПУ БС'!P8 -> 88302.958 | CH8: ='ОПУ БС'!$I8/12*'ОПУ БС'!Q8 -> 93879.987 | CI8: ='ОПУ БС'!$I8/12*'ОПУ БС'!R8 -> 107822.56 | CJ8: ='ОПУ БС'!$I8/12*'ОПУ БС'!S8 -> 105034.05 | ... CN8: ='ОПУ БС'!$I8/12*'ОПУ БС'!W8 -> 116188.1 | CO8: =SUM(CC8:CN8) -> 1115405.8 | CR8: =O8-'ОПУ БС'!C8 -> 0 | CS8: =AB8-'ОПУ БС'!D8 -> 0 | CT8: =AO8-'ОПУ БС'!E8 -> 0 | CU8: =BB8-'ОПУ БС'!F8 -> 0 | CV8: =BO8-'ОПУ БС'!G8 -> 0 | CW8: =CB8-'ОПУ БС'!H8 -> 0 | CX8: =CO8-'ОПУ БС'!I8 -> 0 | DM8: =SUM(DA8:DL8) -> 0 | DZ8: =SUM(DN8:DY8) -> 0 | EM8: =SUM(EA8:EL8) -> 0 | EZ8: =SUM(EN8:EY8) -> 0 | FM8: =SUM(FA8:FL8) -> 0 | FP8: =C8 -> 13499.063 | FQ8: =D8 -> 14742.398 | FR8: =E8 -> 16518.591 | FS8: =F8 -> 16518.591 | FT8: =G8 -> 16873.829 | FU8: =H8 -> 17939.545 | FV8: =I8 -> 20603.834 | FW8: =J8 -> 20070.976 | ... GA8: =N8 -> 22202.407 | GB8: =SUM(FP8:GA8) -> 213143.11 | GC8: =P8 -> 15896.657 | GD8: =Q8 -> 17360.823 | GE8: =R8 -> 19452.488 | GF8: =S8 -> 19452.488 | GG8: =T8 -> 19870.822 | GH8: =U8 -> 21125.821 | GI8: =V8 -> 24263.319 | GJ8: =W8 -> 23635.819 | ... GN8: =AA8 -> 26145.818 | GO8: =SUM(GC8:GN8) -> 250999.85 | GP8: =AC8+DA8 -> 20010.13 | GQ8: =AD8+DB8 -> 21853.169 | GR8: =AE8+DC8 -> 24486.08 | GS8: =AF8+DD8 -> 24486.08 | GT8: =AG8+DE8 -> 25012.663 | GU8: =AH8+DF8 -> 26592.41 | GV8: =AI8+DG8 -> 30541.778 | GW8: =AJ8+DH8 -> 29751.904 | ... HA8: =AN8+DL8 -> 32911.398 | HB8: =SUM(GP8:HA8) -> 315949.42 | HC8: =AP8+DN8 -> 26304.449 | HD8: =AQ8+DO8 -> 28727.228 | HE8: =AR8+DP8 -> 32188.339 | HF8: =AS8+DQ8 -> 32188.339 | HG8: =AT8+DR8 -> 32880.562 | HH8: =AU8+DS8 -> 34957.229 | HI8: =AV8+DT8 -> 40148.896 | HJ8: =AW8+DU8 -> 39110.563 | ... HN8: =BA8+DY8 -> 43263.897 | HO8: =SUM(HC8:HN8) -> 415333.41 | HP8: =BC8+EA8 -> 35878.576 | HQ8: =BD8+EB8 -> 39183.182 | HR8: =BE8+EC8 -> 43904.047 | HS8: =BF8+ED8 -> 43904.047 | HT8: =BG8+EE8 -> 44848.22 | HU8: =BH8+EF8 -> 47680.739 | HV8: =BI8+EG8 -> 54762.037 | HW8: =BJ8+EH8 -> 53345.777 | ... IA8: =BN8+EL8 -> 59010.816 | IB8: =SUM(HP8:IA8) -> 566503.83 | IC8: =BP8+EN8 -> 50127.378 | ID8: =BQ8+EO8 -> 54744.374 | IE8: =BR8+EP8 -> 61340.081 | IF8: =BS8+EQ8 -> 61340.081 | IG8: =BT8+ER8 -> 62659.223 | IH8: =BU8+ES8 -> 66616.647 | II8: =BV8+ET8 -> 76510.209 | IJ8: =BW8+EU8 -> 74531.497 | ... IN8: =CA8+EY8 -> 82446.346 | IO8: =SUM(IC8:IN8) -> 791484.92 | IP8: =CC8+FA8 -> 70642.367 | IQ8: =CD8+FB8 -> 77148.901 | IR8: =CE8+FC8 -> 86443.949 | IS8: =CF8+FD8 -> 86443.949 | IT8: =CG8+FE8 -> 88302.958 | IU8: =CH8+FF8 -> 93879.987 | IV8: =CI8+FG8 -> 107822.56 | IW8: =CJ8+FH8 -> 105034.05 | ... JA8: =CN8+FL8 -> 116188.1 | JB8: =SUM(IP8:JA8) -> 1115405.8 | JE8: =O8-GB8 -> 0 | JF8: =AB8-GO8 -> 0 | JG8: =AO8+DM8-HB8 -> 0 | JH8: =BB8+DZ8-HO8 -> 0 | JI8: =BO8+EM8-IB8 -> 0 | JJ8: =CB8+EZ8-IO8 -> 0 | JK8: =CO8+FM8-JB8 -> 0
B9: Острые | C9: ='ОПУ БС'!$C9/12*'ОПУ БС'!L9 -> 10674.219 | D9: ='ОПУ БС'!$C9/12*'ОПУ БС'!M9 -> 12078.722 | E9: ='ОПУ БС'!$C9/12*'ОПУ БС'!N9 -> 13061.873 | F9: ='ОПУ БС'!$C9/12*'ОПУ БС'!O9 -> 13061.873 | G9: ='ОПУ БС'!$C9/12*'ОПУ БС'!P9 -> 13342.774 | H9: ='ОПУ БС'!$C9/12*'ОПУ БС'!Q9 -> 14185.475 | I9: ='ОПУ БС'!$C9/12*'ОПУ БС'!R9 -> 16292.229 | J9: ='ОПУ БС'!$C9/12*'ОПУ БС'!S9 -> 15870.878 | ... N9: ='ОПУ БС'!$C9/12*'ОПУ БС'!W9 -> 17556.281 | O9: =SUM(C9:N9) -> 168540.3 | P9: ='ОПУ БС'!$D9/12*'ОПУ БС'!L9 -> 12189.277 | Q9: ='ОПУ БС'!$D9/12*'ОПУ БС'!M9 -> 13793.129 | R9: ='ОПУ БС'!$D9/12*'ОПУ БС'!N9 -> 14915.826 | S9: ='ОПУ БС'!$D9/12*'ОПУ БС'!O9 -> 14915.826 | T9: ='ОПУ БС'!$D9/12*'ОПУ БС'!P9 -> 15236.596 | U9: ='ОПУ БС'!$D9/12*'ОПУ БС'!Q9 -> 16198.908 | V9: ='ОПУ БС'!$D9/12*'ОПУ БС'!R9 -> 18604.686 | W9: ='ОПУ БС'!$D9/12*'ОПУ БС'!S9 -> 18123.53 | ... AA9: ='ОПУ БС'!$D9/12*'ОПУ БС'!W9 -> 20048.153 | AB9: =SUM(P9:AA9) -> 192462.27 | AC9: ='ОПУ БС'!$E9/12*'ОПУ БС'!L9 -> 14910.819 | AD9: ='ОПУ БС'!$E9/12*'ОПУ БС'!M9 -> 16872.769 | AE9: ='ОПУ БС'!$E9/12*'ОПУ БС'!N9 -> 18246.134 | AF9: ='ОПУ БС'!$E9/12*'ОПУ БС'!O9 -> 18246.134 | AG9: ='ОПУ БС'!$E9/12*'ОПУ БС'!P9 -> 18638.524 | AH9: ='ОПУ БС'!$E9/12*'ОПУ БС'!Q9 -> 19815.694 | AI9: ='ОПУ БС'!$E9/12*'ОПУ БС'!R9 -> 22758.619 | AJ9: ='ОПУ БС'!$E9/12*'ОПУ БС'!S9 -> 22170.034 | ... AN9: ='ОПУ БС'!$E9/12*'ОПУ БС'!W9 -> 24524.374 | AO9: =SUM(AC9:AN9) -> 235433.99 | AP9: ='ОПУ БС'!$F9/12*'ОПУ БС'!L9 -> 19036.084 | AQ9: ='ОПУ БС'!$F9/12*'ОПУ БС'!M9 -> 21540.832 | AR9: ='ОПУ БС'!$F9/12*'ОПУ БС'!N9 -> 23294.156 | AS9: ='ОПУ БС'!$F9/12*'ОПУ БС'!O9 -> 23294.156 | AT9: ='ОПУ БС'!$F9/12*'ОПУ БС'!P9 -> 23795.105 | AU9: ='ОПУ БС'!$F9/12*'ОПУ БС'!Q9 -> 25297.954 | AV9: ='ОПУ БС'!$F9/12*'ОПУ БС'!R9 -> 29055.076 | AW9: ='ОПУ БС'!$F9/12*'ОПУ БС'!S9 -> 28303.652 | ... BA9: ='ОПУ БС'!$F9/12*'ОПУ БС'!W9 -> 31309.349 | BB9: =SUM(AP9:BA9) -> 300569.75 | BC9: ='ОПУ БС'!$G9/12*'ОПУ БС'!L9 -> 25200.65 | BD9: ='ОПУ БС'!$G9/12*'ОПУ БС'!M9 -> 28516.525 | BE9: ='ОПУ БС'!$G9/12*'ОПУ БС'!N9 -> 30837.637 | BF9: ='ОПУ БС'!$G9/12*'ОПУ БС'!O9 -> 30837.637 | BG9: ='ОПУ БС'!$G9/12*'ОПУ БС'!P9 -> 31500.812 | BH9: ='ОПУ БС'!$G9/12*'ОПУ БС'!Q9 -> 33490.337 | BI9: ='ОПУ БС'!$G9/12*'ОПУ БС'!R9 -> 38464.149 | BJ9: ='ОПУ БС'!$G9/12*'ОПУ БС'!S9 -> 37469.387 | ... BN9: ='ОПУ БС'!$G9/12*'ОПУ БС'!W9 -> 41448.437 | BO9: =SUM(BC9:BN9) -> 397904.99 | BP9: ='ОПУ БС'!$H9/12*'ОПУ БС'!L9 -> 34152.822 | BQ9: ='ОПУ БС'!$H9/12*'ОПУ БС'!M9 -> 38646.614 | BR9: ='ОПУ БС'!$H9/12*'ОПУ БС'!N9 -> 41792.269 | BS9: ='ОПУ БС'!$H9/12*'ОПУ БС'!O9 -> 41792.269 | BT9: ='ОПУ БС'!$H9/12*'ОПУ БС'!P9 -> 42691.027 | BU9: ='ОПУ БС'!$H9/12*'ОПУ БС'!Q9 -> 45387.303 | BV9: ='ОПУ БС'!$H9/12*'ОПУ БС'!R9 -> 52127.991 | BW9: ='ОПУ БС'!$H9/12*'ОПУ БС'!S9 -> 50779.854 | ... CA9: ='ОПУ БС'!$H9/12*'ОПУ БС'!W9 -> 56172.404 | CB9: =SUM(BP9:CA9) -> 539255.08 | CC9: ='ОПУ БС'!$I9/12*'ОПУ БС'!L9 -> 46661.286 | CD9: ='ОПУ БС'!$I9/12*'ОПУ БС'!M9 -> 52800.929 | CE9: ='ОПУ БС'!$I9/12*'ОПУ БС'!N9 -> 57098.679 | CF9: ='ОПУ БС'!$I9/12*'ОПУ БС'!O9 -> 57098.679 | CG9: ='ОПУ БС'!$I9/12*'ОПУ БС'!P9 -> 58326.608 | CH9: ='ОПУ БС'!$I9/12*'ОПУ БС'!Q9 -> 62010.394 | CI9: ='ОПУ БС'!$I9/12*'ОПУ БС'!R9 -> 71219.858 | CJ9: ='ОПУ БС'!$I9/12*'ОПУ БС'!S9 -> 69377.965 | ... CN9: ='ОПУ БС'!$I9/12*'ОПУ БС'!W9 -> 76745.537 | CO9: =SUM(CC9:CN9) -> 736757.15 | CR9: =O9-'ОПУ БС'!C9 -> 0 | CS9: =AB9-'ОПУ БС'!D9 -> 0 | CT9: =AO9-'ОПУ БС'!E9 -> 0 | CU9: =BB9-'ОПУ БС'!F9 -> 0 | CV9: =BO9-'ОПУ БС'!G9 -> 0 | CW9: =CB9-'ОПУ БС'!H9 -> 0 | CX9: =CO9-'ОПУ БС'!I9 -> 0 | DM9: =SUM(DA9:DL9) -> 0 | DZ9: =SUM(DN9:DY9) -> 0 | EM9: =SUM(EA9:EL9) -> 0 | EZ9: =SUM(EN9:EY9) -> 0 | FM9: =SUM(FA9:FL9) -> 0 | FP9: =C9 -> 10674.219 | FQ9: =D9 -> 12078.722 | FR9: =E9 -> 13061.873 | FS9: =F9 -> 13061.873 | FT9: =G9 -> 13342.774 | FU9: =H9 -> 14185.475 | FV9: =I9 -> 16292.229 | FW9: =J9 -> 15870.878 | ... GA9: =N9 -> 17556.281 | GB9: =SUM(FP9:GA9) -> 168540.3 | GC9: =P9 -> 12189.277 | GD9: =Q9 -> 13793.129 | GE9: =R9 -> 14915.826 | GF9: =S9 -> 14915.826 | GG9: =T9 -> 15236.596 | GH9: =U9 -> 16198.908 | GI9: =V9 -> 18604.686 | GJ9: =W9 -> 18123.53 | ... GN9: =AA9 -> 20048.153 | GO9: =SUM(GC9:GN9) -> 192462.27 | GP9: =AC9+DA9 -> 14910.819 | GQ9: =AD9+DB9 -> 16872.769 | GR9: =AE9+DC9 -> 18246.134 | GS9: =AF9+DD9 -> 18246.134 | GT9: =AG9+DE9 -> 18638.524 | GU9: =AH9+DF9 -> 19815.694 | GV9: =AI9+DG9 -> 22758.619 | GW9: =AJ9+DH9 -> 22170.034 | ... HA9: =AN9+DL9 -> 24524.374 | HB9: =SUM(GP9:HA9) -> 235433.99 | HC9: =AP9+DN9 -> 19036.084 | HD9: =AQ9+DO9 -> 21540.832 | HE9: =AR9+DP9 -> 23294.156 | HF9: =AS9+DQ9 -> 23294.156 | HG9: =AT9+DR9 -> 23795.105 | HH9: =AU9+DS9 -> 25297.954 | HI9: =AV9+DT9 -> 29055.076 | HJ9: =AW9+DU9 -> 28303.652 | ... HN9: =BA9+DY9 -> 31309.349 | HO9: =SUM(HC9:HN9) -> 300569.75 | HP9: =BC9+EA9 -> 25200.65 | HQ9: =BD9+EB9 -> 28516.525 | HR9: =BE9+EC9 -> 30837.637 | HS9: =BF9+ED9 -> 30837.637 | HT9: =BG9+EE9 -> 31500.812 | HU9: =BH9+EF9 -> 33490.337 | HV9: =BI9+EG9 -> 38464.149 | HW9: =BJ9+EH9 -> 37469.387 | ... IA9: =BN9+EL9 -> 41448.437 | IB9: =SUM(HP9:IA9) -> 397904.99 | IC9: =BP9+EN9 -> 34152.822 | ID9: =BQ9+EO9 -> 38646.614 | IE9: =BR9+EP9 -> 41792.269 | IF9: =BS9+EQ9 -> 41792.269 | IG9: =BT9+ER9 -> 42691.027 | IH9: =BU9+ES9 -> 45387.303 | II9: =BV9+ET9 -> 52127.991 | IJ9: =BW9+EU9 -> 50779.854 | ... IN9: =CA9+EY9 -> 56172.404 | IO9: =SUM(IC9:IN9) -> 539255.08 | IP9: =CC9+FA9 -> 46661.286 | IQ9: =CD9+FB9 -> 52800.929 | IR9: =CE9+FC9 -> 57098.679 | IS9: =CF9+FD9 -> 57098.679 | IT9: =CG9+FE9 -> 58326.608 | IU9: =CH9+FF9 -> 62010.394 | IV9: =CI9+FG9 -> 71219.858 | IW9: =CJ9+FH9 -> 69377.965 | ... JA9: =CN9+FL9 -> 76745.537 | JB9: =SUM(IP9:JA9) -> 736757.15 | JE9: =O9-GB9 -> 0 | JF9: =AB9-GO9 -> 0 | JG9: =AO9+DM9-HB9 -> 0 | JH9: =BB9+DZ9-HO9 -> 0 | JI9: =BO9+EM9-IB9 -> 0 | JJ9: =CB9+EZ9-IO9 -> 0 | JK9: =CO9+FM9-JB9 -> 0
B10: ЭкстраХруст | C10: ='ОПУ БС'!$C10/12*'ОПУ БС'!L10 -> 3141.5344 | D10: ='ОПУ БС'!$C10/12*'ОПУ БС'!M10 -> 3430.8862 | E10: ='ОПУ БС'!$C10/12*'ОПУ БС'!N10 -> 3926.9179 | F10: ='ОПУ БС'!$C10/12*'ОПУ БС'!O10 -> 3844.246 | G10: ='ОПУ БС'!$C10/12*'ОПУ БС'!P10 -> 3926.9179 | H10: ='ОПУ БС'!$C10/12*'ОПУ БС'!Q10 -> 4174.9338 | I10: ='ОПУ БС'!$C10/12*'ОПУ БС'!R10 -> 4794.9735 | J10: ='ОПУ БС'!$C10/12*'ОПУ БС'!S10 -> 4670.9656 | ... N10: ='ОПУ БС'!$C10/12*'ОПУ БС'!W10 -> 5166.9973 | O10: =SUM(C10:N10) -> 49603.174 | P10: ='ОПУ БС'!$D10/12*'ОПУ БС'!L10 -> 3578.0478 | Q10: ='ОПУ БС'!$D10/12*'ОПУ БС'!M10 -> 3907.6049 | R10: ='ОПУ БС'!$D10/12*'ОПУ БС'!N10 -> 4472.5598 | S10: ='ОПУ БС'!$D10/12*'ОПУ БС'!O10 -> 4378.4006 | T10: ='ОПУ БС'!$D10/12*'ОПУ БС'!P10 -> 4472.5598 | U10: ='ОПУ БС'!$D10/12*'ОПУ БС'!Q10 -> 4755.0372 | V10: ='ОПУ БС'!$D10/12*'ОПУ БС'!R10 -> 5461.2309 | W10: ='ОПУ БС'!$D10/12*'ОПУ БС'!S10 -> 5319.9922 | ... AA10: ='ОПУ БС'!$D10/12*'ОПУ БС'!W10 -> 5884.9471 | AB10: =SUM(P10:AA10) -> 56495.492 | AC10: ='ОПУ БС'!$E10/12*'ОПУ БС'!L10 -> 4366.1816 | AD10: ='ОПУ БС'!$E10/12*'ОПУ БС'!M10 -> 4768.33 | AE10: ='ОПУ БС'!$E10/12*'ОПУ БС'!N10 -> 5457.7271 | AF10: ='ОПУ БС'!$E10/12*'ОПУ БС'!O10 -> 5342.8275 | AG10: ='ОПУ БС'!$E10/12*'ОПУ БС'!P10 -> 5457.7271 | AH10: ='ОПУ БС'!$E10/12*'ОПУ БС'!Q10 -> 5802.4256 | AI10: ='ОПУ БС'!$E10/12*'ОПУ БС'!R10 -> 6664.172 | AJ10: ='ОПУ БС'!$E10/12*'ОПУ БС'!S10 -> 6491.8227 | ... AN10: ='ОПУ БС'!$E10/12*'ОПУ БС'!W10 -> 7181.2198 | AO10: =SUM(AC10:AN10) -> 68939.71 | AP10: ='ОПУ БС'!$F10/12*'ОПУ БС'!L10 -> 5565.165 | AQ10: ='ОПУ БС'!$F10/12*'ОПУ БС'!M10 -> 6077.746 | AR10: ='ОПУ БС'!$F10/12*'ОПУ БС'!N10 -> 6956.4563 | AS10: ='ОПУ БС'!$F10/12*'ОПУ БС'!O10 -> 6810.0045 | AT10: ='ОПУ БС'!$F10/12*'ОПУ БС'!P10 -> 6956.4563 | AU10: ='ОПУ БС'!$F10/12*'ОПУ БС'!Q10 -> 7395.8114 | AV10: ='ОПУ БС'!$F10/12*'ОПУ БС'!R10 -> 8494.1992 | AW10: ='ОПУ БС'!$F10/12*'ОПУ БС'!S10 -> 8274.5216 | ... BA10: ='ОПУ БС'!$F10/12*'ОПУ БС'!W10 -> 9153.2319 | BB10: =SUM(AP10:BA10) -> 87871.026 | BC10: ='ОПУ БС'!$G10/12*'ОПУ БС'!L10 -> 7359.8363 | BD10: ='ОПУ БС'!$G10/12*'ОПУ БС'!M10 -> 8037.7159 | BE10: ='ОПУ БС'!$G10/12*'ОПУ БС'!N10 -> 9199.7953 | BF10: ='ОПУ БС'!$G10/12*'ОПУ БС'!O10 -> 9006.1154 | BG10: ='ОПУ БС'!$G10/12*'ОПУ БС'!P10 -> 9199.7953 | BH10: ='ОПУ БС'!$G10/12*'ОПУ БС'!Q10 -> 9780.835 | BI10: ='ОПУ БС'!$G10/12*'ОПУ БС'!R10 -> 11233.434 | BJ10: ='ОПУ БС'!$G10/12*'ОПУ БС'!S10 -> 10942.914 | ... BN10: ='ОПУ БС'!$G10/12*'ОПУ БС'!W10 -> 12104.994 | BO10: =SUM(BC10:BN10) -> 116207.94 | BP10: ='ОПУ БС'!$H10/12*'ОПУ БС'!L10 -> 9967.0412 | BQ10: ='ОПУ БС'!$H10/12*'ОПУ БС'!M10 -> 10885.058 | BR10: ='ОПУ БС'!$H10/12*'ОПУ БС'!N10 -> 12458.802 | BS10: ='ОПУ БС'!$H10/12*'ОПУ БС'!O10 -> 12196.511 | BT10: ='ОПУ БС'!$H10/12*'ОПУ БС'!P10 -> 12458.802 | BU10: ='ОПУ БС'!$H10/12*'ОПУ БС'!Q10 -> 13245.673 | BV10: ='ОПУ БС'!$H10/12*'ОПУ БС'!R10 -> 15212.852 | BW10: ='ОПУ БС'!$H10/12*'ОПУ БС'!S10 -> 14819.417 | ... CA10: ='ОПУ БС'!$H10/12*'ОПУ БС'!W10 -> 16393.16 | CB10: =SUM(BP10:CA10) -> 157374.34 | CC10: ='ОПУ БС'!$I10/12*'ОПУ БС'!L10 -> 13611.893 | CD10: ='ОПУ БС'!$I10/12*'ОПУ БС'!M10 -> 14865.62 | CE10: ='ОПУ БС'!$I10/12*'ОПУ БС'!N10 -> 17014.866 | CF10: ='ОПУ БС'!$I10/12*'ОПУ БС'!O10 -> 16656.659 | CG10: ='ОПУ БС'!$I10/12*'ОПУ БС'!P10 -> 17014.866 | CH10: ='ОПУ БС'!$I10/12*'ОПУ БС'!Q10 -> 18089.489 | CI10: ='ОПУ БС'!$I10/12*'ОПУ БС'!R10 -> 20776.047 | CJ10: ='ОПУ БС'!$I10/12*'ОПУ БС'!S10 -> 20238.736 | ... CN10: ='ОПУ БС'!$I10/12*'ОПУ БС'!W10 -> 22387.982 | CO10: =SUM(CC10:CN10) -> 214924.63 | CR10: =O10-'ОПУ БС'!C10 -> 0 | CS10: =AB10-'ОПУ БС'!D10 -> 0 | CT10: =AO10-'ОПУ БС'!E10 -> 0 | CU10: =BB10-'ОПУ БС'!F10 -> 0 | CV10: =BO10-'ОПУ БС'!G10 -> 0 | CW10: =CB10-'ОПУ БС'!H10 -> 0 | CX10: =CO10-'ОПУ БС'!I10 -> 0 | DM10: =SUM(DA10:DL10) -> 0 | DZ10: =SUM(DN10:DY10) -> 0 | EM10: =SUM(EA10:EL10) -> 0 | EZ10: =SUM(EN10:EY10) -> 0 | FM10: =SUM(FA10:FL10) -> 0 | FP10: =C10 -> 3141.5344 | FQ10: =D10 -> 3430.8862 | FR10: =E10 -> 3926.9179 | FS10: =F10 -> 3844.246 | FT10: =G10 -> 3926.9179 | FU10: =H10 -> 4174.9338 | FV10: =I10 -> 4794.9735 | FW10: =J10 -> 4670.9656 | ... GA10: =N10 -> 5166.9973 | GB10: =SUM(FP10:GA10) -> 49603.174 | GC10: =P10 -> 3578.0478 | GD10: =Q10 -> 3907.6049 | GE10: =R10 -> 4472.5598 | GF10: =S10 -> 4378.4006 | GG10: =T10 -> 4472.5598 | GH10: =U10 -> 4755.0372 | GI10: =V10 -> 5461.2309 | GJ10: =W10 -> 5319.9922 | ... GN10: =AA10 -> 5884.9471 | GO10: =SUM(GC10:GN10) -> 56495.492 | GP10: =AC10+DA10 -> 4366.1816 | GQ10: =AD10+DB10 -> 4768.33 | GR10: =AE10+DC10 -> 5457.7271 | GS10: =AF10+DD10 -> 5342.8275 | GT10: =AG10+DE10 -> 5457.7271 | GU10: =AH10+DF10 -> 5802.4256 | GV10: =AI10+DG10 -> 6664.172 | GW10: =AJ10+DH10 -> 6491.8227 | ... HA10: =AN10+DL10 -> 7181.2198 | HB10: =SUM(GP10:HA10) -> 68939.71 | HC10: =AP10+DN10 -> 5565.165 | HD10: =AQ10+DO10 -> 6077.746 | HE10: =AR10+DP10 -> 6956.4563 | HF10: =AS10+DQ10 -> 6810.0045 | HG10: =AT10+DR10 -> 6956.4563 | HH10: =AU10+DS10 -> 7395.8114 | HI10: =AV10+DT10 -> 8494.1992 | HJ10: =AW10+DU10 -> 8274.5216 | ... HN10: =BA10+DY10 -> 9153.2319 | HO10: =SUM(HC10:HN10) -> 87871.026 | HP10: =BC10+EA10 -> 7359.8363 | HQ10: =BD10+EB10 -> 8037.7159 | HR10: =BE10+EC10 -> 9199.7953 | HS10: =BF10+ED10 -> 9006.1154 | HT10: =BG10+EE10 -> 9199.7953 | HU10: =BH10+EF10 -> 9780.835 | HV10: =BI10+EG10 -> 11233.434 | HW10: =BJ10+EH10 -> 10942.914 | ... IA10: =BN10+EL10 -> 12104.994 | IB10: =SUM(HP10:IA10) -> 116207.94 | IC10: =BP10+EN10 -> 9967.0412 | ID10: =BQ10+EO10 -> 10885.058 | IE10: =BR10+EP10 -> 12458.802 | IF10: =BS10+EQ10 -> 12196.511 | IG10: =BT10+ER10 -> 12458.802 | IH10: =BU10+ES10 -> 13245.673 | II10: =BV10+ET10 -> 15212.852 | IJ10: =BW10+EU10 -> 14819.417 | ... IN10: =CA10+EY10 -> 16393.16 | IO10: =SUM(IC10:IN10) -> 157374.34 | IP10: =CC10+FA10 -> 13611.893 | IQ10: =CD10+FB10 -> 14865.62 | IR10: =CE10+FC10 -> 17014.866 | IS10: =CF10+FD10 -> 16656.659 | IT10: =CG10+FE10 -> 17014.866 | IU10: =CH10+FF10 -> 18089.489 | IV10: =CI10+FG10 -> 20776.047 | IW10: =CJ10+FH10 -> 20238.736 | ... JA10: =CN10+FL10 -> 22387.982 | JB10: =SUM(IP10:JA10) -> 214924.63 | JE10: =O10-GB10 -> 0 | JF10: =AB10-GO10 -> 0 | JG10: =AO10+DM10-HB10 -> 0 | JH10: =BB10+DZ10-HO10 -> 0 | JI10: =BO10+EM10-IB10 -> 0 | JJ10: =CB10+EZ10-IO10 -> 0 | JK10: =CO10+FM10-JB10 -> 0
B11: Соусы | C11: =SUM(C12:C18) -> 6678.5849 | D11: =SUM(D12:D18) -> 7293.7177 | E11: =SUM(E12:E18) -> 8172.4789 | F11: =SUM(F12:F18) -> 8172.4789 | G11: =SUM(G12:G18) -> 8018.6375 | H11: =SUM(H12:H18) -> 8435.4271 | I11: =SUM(I12:I18) -> 10245.14 | J11: =SUM(J12:J18) -> 9764.5036 | ... N11: =SUM(N12:N18) -> 10984.515 | O11: =SUM(C11:N11) -> 105451.34 | P11: =SUM(P12:P18) -> 7457.1863 | Q11: =SUM(Q12:Q18) -> 8144.0324 | R11: =SUM(R12:R18) -> 9125.2411 | S11: =SUM(S12:S18) -> 9125.2411 | T11: =SUM(T12:T18) -> 8942.6611 | U11: =SUM(U12:U18) -> 9399.8549 | V11: =SUM(V12:V18) -> 11436.67 | W11: =SUM(W12:W18) -> 10903.603 | ... AA11: =SUM(AA12:AA18) -> 12265.109 | AB11: =SUM(P11:AA11) -> 117745.05 | AC11: =SUM(AC12:AC18) -> 9000.4435 | AD11: =SUM(AD12:AD18) -> 9829.4317 | AE11: =SUM(AE12:AE18) -> 11013.701 | AF11: =SUM(AF12:AF18) -> 11013.701 | AG11: =SUM(AG12:AG18) -> 10798.751 | AH11: =SUM(AH12:AH18) -> 11319.138 | AI11: =SUM(AI12:AI18) -> 13804.4 | AJ11: =SUM(AJ12:AJ18) -> 13168.576 | ... AN11: =SUM(AN12:AN18) -> 14803.361 | AO11: =SUM(AC11:AN11) -> 142112.27 | AP11: =SUM(AP12:AP18) -> 10872.22 | AQ11: =SUM(AQ12:AQ18) -> 11873.609 | AR11: =SUM(AR12:AR18) -> 13304.164 | AS11: =SUM(AS12:AS18) -> 13304.164 | AT11: =SUM(AT12:AT18) -> 13030.019 | AU11: =SUM(AU12:AU18) -> 13603.425 | AV11: =SUM(AV12:AV18) -> 16667.518 | AW11: =SUM(AW12:AW18) -> 15906.385 | ... BA11: =SUM(BA12:BA18) -> 17881.941 | BB11: =SUM(AP11:BA11) -> 171666.64 | BC11: =SUM(BC12:BC18) -> 13669.595 | BD11: =SUM(BD12:BD18) -> 14928.636 | BE11: =SUM(BE12:BE18) -> 16727.267 | BF11: =SUM(BF12:BF18) -> 16727.267 | BG11: =SUM(BG12:BG18) -> 16367.133 | BH11: =SUM(BH12:BH18) -> 17011.18 | BI11: =SUM(BI12:BI18) -> 20946.499 | BJ11: =SUM(BJ12:BJ18) -> 19998.68 | ... BN11: =SUM(BN12:BN18) -> 22482.886 | BO11: =SUM(BC11:BN11) -> 215835.71 | BP11: =SUM(BP12:BP18) -> 17622.217 | BQ11: =SUM(BQ12:BQ18) -> 19245.316 | BR11: =SUM(BR12:BR18) -> 21564.028 | BS11: =SUM(BS12:BS18) -> 21564.028 | BT11: =SUM(BT12:BT18) -> 21081.465 | BU11: =SUM(BU12:BU18) -> 21797.278 | BV11: =SUM(BV12:BV18) -> 26990.47 | BW11: =SUM(BW12:BW18) -> 25781.97 | ... CA11: =SUM(CA12:CA18) -> 28983.909 | CB11: =SUM(BP11:CA11) -> 278245.53 | CC11: =SUM(CC12:CC18) -> 23138.704 | CD11: =SUM(CD12:CD18) -> 25269.9 | CE11: =SUM(CE12:CE18) -> 28314.467 | CF11: =SUM(CF12:CF18) -> 28314.467 | CG11: =SUM(CG12:CG18) -> 27668.228 | CH11: =SUM(CH12:CH18) -> 28467.472 | CI11: =SUM(CI12:CI18) -> 35426.743 | CJ11: =SUM(CJ12:CJ18) -> 33855.956 | ... CN11: =SUM(CN12:CN18) -> 38057.079 | CO11: =SUM(CC11:CN11) -> 365347.95 | CR11: =O11-'ОПУ БС'!C11 -> 0 | CS11: =AB11-'ОПУ БС'!D11 -> 0 | CT11: =AO11-'ОПУ БС'!E11 -> 0 | CU11: =BB11-'ОПУ БС'!F11 -> 0 | CV11: =BO11-'ОПУ БС'!G11 -> 0 | CW11: =CB11-'ОПУ БС'!H11 -> 0 | CX11: =CO11-'ОПУ БС'!I11 -> 0 | DA11: =SUM(DA12:DA18) -> 0 | DB11: =SUM(DB12:DB18) -> 0 | DC11: =SUM(DC12:DC18) -> 0 | DD11: =SUM(DD12:DD18) -> 0 | DE11: =SUM(DE12:DE18) -> 0 | DF11: =SUM(DF12:DF18) -> 0 | DG11: =SUM(DG12:DG18) -> 0 | DH11: =SUM(DH12:DH18) -> 0 | ... DL11: =SUM(DL12:DL18) -> 0 | DM11: =SUM(DA11:DL11) -> 0 | DN11: =SUM(DN12:DN18) -> 0 | DO11: =SUM(DO12:DO18) -> 0 | DP11: =SUM(DP12:DP18) -> 0 | DQ11: =SUM(DQ12:DQ18) -> 0 | DR11: =SUM(DR12:DR18) -> 0 | DS11: =SUM(DS12:DS18) -> 0 | DT11: =SUM(DT12:DT18) -> 0 | DU11: =SUM(DU12:DU18) -> 0 | ... DY11: =SUM(DY12:DY18) -> 0 | DZ11: =SUM(DN11:DY11) -> 0 | EA11: =SUM(EA12:EA18) -> 0 | EB11: =SUM(EB12:EB18) -> 0 | EC11: =SUM(EC12:EC18) -> 0 | ED11: =SUM(ED12:ED18) -> 0 | EE11: =SUM(EE12:EE18) -> 0 | EF11: =SUM(EF12:EF18) -> 0 | EG11: =SUM(EG12:EG18) -> 0 | EH11: =SUM(EH12:EH18) -> 0 | ... EL11: =SUM(EL12:EL18) -> 0 | EM11: =SUM(EA11:EL11) -> 0 | EN11: =SUM(EN12:EN18) -> 0 | EO11: =SUM(EO12:EO18) -> 0 | EP11: =SUM(EP12:EP18) -> 0 | EQ11: =SUM(EQ12:EQ18) -> 0 | ER11: =SUM(ER12:ER18) -> 0 | ES11: =SUM(ES12:ES18) -> 0 | ET11: =SUM(ET12:ET18) -> 0 | EU11: =SUM(EU12:EU18) -> 0 | ... EY11: =SUM(EY12:EY18) -> 0 | EZ11: =SUM(EN11:EY11) -> 0 | FA11: =SUM(FA12:FA18) -> 0 | FB11: =SUM(FB12:FB18) -> 0 | FC11: =SUM(FC12:FC18) -> 0 | FD11: =SUM(FD12:FD18) -> 0 | FE11: =SUM(FE12:FE18) -> 0 | FF11: =SUM(FF12:FF18) -> 0 | FG11: =SUM(FG12:FG18) -> 0 | FH11: =SUM(FH12:FH18) -> 0 | ... FL11: =SUM(FL12:FL18) -> 0 | FM11: =SUM(FA11:FL11) -> 0 | FP11: =SUM(FP12:FP18) -> 6678.5849 | FQ11: =SUM(FQ12:FQ18) -> 7293.7177 | FR11: =SUM(FR12:FR18) -> 8172.4789 | FS11: =SUM(FS12:FS18) -> 8172.4789 | FT11: =SUM(FT12:FT18) -> 8018.6375 | FU11: =SUM(FU12:FU18) -> 8435.4271 | FV11: =SUM(FV12:FV18) -> 10245.14 | FW11: =SUM(FW12:FW18) -> 9764.5036 | ... GA11: =SUM(GA12:GA18) -> 10984.515 | GB11: =SUM(FP11:GA11) -> 105451.34 | GC11: =SUM(GC12:GC18) -> 7457.1863 | GD11: =SUM(GD12:GD18) -> 8144.0324 | GE11: =SUM(GE12:GE18) -> 9125.2411 | GF11: =SUM(GF12:GF18) -> 9125.2411 | GG11: =SUM(GG12:GG18) -> 8942.6611 | GH11: =SUM(GH12:GH18) -> 9399.8549 | GI11: =SUM(GI12:GI18) -> 11436.67 | GJ11: =SUM(GJ12:GJ18) -> 10903.603 | ... GN11: =SUM(GN12:GN18) -> 12265.109 | GO11: =SUM(GC11:GN11) -> 117745.05 | GP11: =SUM(GP12:GP18) -> 9000.4435 | GQ11: =SUM(GQ12:GQ18) -> 9829.4317 | GR11: =SUM(GR12:GR18) -> 11013.701 | GS11: =SUM(GS12:GS18) -> 11013.701 | GT11: =SUM(GT12:GT18) -> 10798.751 | GU11: =SUM(GU12:GU18) -> 11319.138 | GV11: =SUM(GV12:GV18) -> 13804.4 | GW11: =SUM(GW12:GW18) -> 13168.576 | ... HA11: =SUM(HA12:HA18) -> 14803.361 | HB11: =SUM(GP11:HA11) -> 142112.27 | HC11: =SUM(HC12:HC18) -> 10872.22 | HD11: =SUM(HD12:HD18) -> 11873.609 | HE11: =SUM(HE12:HE18) -> 13304.164 | HF11: =SUM(HF12:HF18) -> 13304.164 | HG11: =SUM(HG12:HG18) -> 13030.019 | HH11: =SUM(HH12:HH18) -> 13603.425 | HI11: =SUM(HI12:HI18) -> 16667.518 | HJ11: =SUM(HJ12:HJ18) -> 15906.385 | ... HN11: =SUM(HN12:HN18) -> 17881.941 | HO11: =SUM(HC11:HN11) -> 171666.64 | HP11: =SUM(HP12:HP18) -> 13669.595 | HQ11: =SUM(HQ12:HQ18) -> 14928.636 | HR11: =SUM(HR12:HR18) -> 16727.267 | HS11: =SUM(HS12:HS18) -> 16727.267 | HT11: =SUM(HT12:HT18) -> 16367.133 | HU11: =SUM(HU12:HU18) -> 17011.18 | HV11: =SUM(HV12:HV18) -> 20946.499 | HW11: =SUM(HW12:HW18) -> 19998.68 | ... IA11: =SUM(IA12:IA18) -> 22482.886 | IB11: =SUM(HP11:IA11) -> 215835.71 | IC11: =SUM(IC12:IC18) -> 17622.217 | ID11: =SUM(ID12:ID18) -> 19245.316 | IE11: =SUM(IE12:IE18) -> 21564.028 | IF11: =SUM(IF12:IF18) -> 21564.028 | IG11: =SUM(IG12:IG18) -> 21081.465 | IH11: =SUM(IH12:IH18) -> 21797.278 | II11: =SUM(II12:II18) -> 26990.47 | IJ11: =SUM(IJ12:IJ18) -> 25781.97 | ... IN11: =SUM(IN12:IN18) -> 28983.909 | IO11: =SUM(IC11:IN11) -> 278245.53 | IP11: =SUM(IP12:IP18) -> 23138.704 | IQ11: =SUM(IQ12:IQ18) -> 25269.9 | IR11: =SUM(IR12:IR18) -> 28314.467 | IS11: =SUM(IS12:IS18) -> 28314.467 | IT11: =SUM(IT12:IT18) -> 27668.228 | IU11: =SUM(IU12:IU18) -> 28467.472 | IV11: =SUM(IV12:IV18) -> 35426.743 | IW11: =SUM(IW12:IW18) -> 33855.956 | ... JA11: =SUM(JA12:JA18) -> 38057.079 | JB11: =SUM(IP11:JA11) -> 365347.95 | JE11: =O11-GB11 -> 0 | JF11: =AB11-GO11 -> 0 | JG11: =AO11+DM11-HB11 -> 0 | JH11: =BB11+DZ11-HO11 -> 0 | JI11: =BO11+EM11-IB11 -> 0 | JJ11: =CB11+EZ11-IO11 -> 0 | JK11: =CO11+FM11-JB11 -> 0
B12: Кетчуп | C12: ='ОПУ БС'!$C12/12*'ОПУ БС'!L12 -> 2277.1926 | D12: ='ОПУ БС'!$C12/12*'ОПУ БС'!M12 -> 2486.934 | E12: ='ОПУ БС'!$C12/12*'ОПУ БС'!N12 -> 2786.5646 | F12: ='ОПУ БС'!$C12/12*'ОПУ БС'!O12 -> 2786.5646 | G12: ='ОПУ БС'!$C12/12*'ОПУ БС'!P12 -> 2516.897 | H12: ='ОПУ БС'!$C12/12*'ОПУ БС'!Q12 -> 3026.2691 | I12: ='ОПУ БС'!$C12/12*'ОПУ БС'!R12 -> 3475.715 | J12: ='ОПУ БС'!$C12/12*'ОПУ БС'!S12 -> 3385.8258 | ... N12: ='ОПУ БС'!$C12/12*'ОПУ БС'!W12 -> 3745.3825 | O12: =SUM(C12:N12) -> 35955.672 | P12: ='ОПУ БС'!$D12/12*'ОПУ БС'!L12 -> 2617.3136 | Q12: ='ОПУ БС'!$D12/12*'ОПУ БС'!M12 -> 2858.3819 | R12: ='ОПУ БС'!$D12/12*'ОПУ БС'!N12 -> 3202.7653 | S12: ='ОПУ БС'!$D12/12*'ОПУ БС'!O12 -> 3202.7653 | T12: ='ОПУ БС'!$D12/12*'ОПУ БС'!P12 -> 2892.8203 | U12: ='ОПУ БС'!$D12/12*'ОПУ БС'!Q12 -> 3478.272 | V12: ='ОПУ БС'!$D12/12*'ОПУ БС'!R12 -> 3994.847 | W12: ='ОПУ БС'!$D12/12*'ОПУ БС'!S12 -> 3891.532 | ... AA12: ='ОПУ БС'!$D12/12*'ОПУ БС'!W12 -> 4304.7921 | AB12: =SUM(P12:AA12) -> 41326.004 | AC12: ='ОПУ БС'!$E12/12*'ОПУ БС'!L12 -> 3121.5517 | AD12: ='ОПУ БС'!$E12/12*'ОПУ БС'!M12 -> 3409.0631 | AE12: ='ОПУ БС'!$E12/12*'ОПУ БС'!N12 -> 3819.7936 | AF12: ='ОПУ БС'!$E12/12*'ОПУ БС'!O12 -> 3819.7936 | AG12: ='ОПУ БС'!$E12/12*'ОПУ БС'!P12 -> 3450.1361 | AH12: ='ОПУ БС'!$E12/12*'ОПУ БС'!Q12 -> 4148.378 | AI12: ='ОПУ БС'!$E12/12*'ОПУ БС'!R12 -> 4764.4737 | AJ12: ='ОПУ БС'!$E12/12*'ОПУ БС'!S12 -> 4641.2546 | ... AN12: ='ОПУ БС'!$E12/12*'ОПУ БС'!W12 -> 5134.1312 | AO12: =SUM(AC12:AN12) -> 49287.659 | AP12: ='ОПУ БС'!$F12/12*'ОПУ БС'!L12 -> 3870.8648 | AQ12: ='ОПУ БС'!$F12/12*'ОПУ БС'!M12 -> 4227.3918 | AR12: ='ОПУ БС'!$F12/12*'ОПУ БС'!N12 -> 4736.7161 | AS12: ='ОПУ БС'!$F12/12*'ОПУ БС'!O12 -> 4736.7161 | AT12: ='ОПУ БС'!$F12/12*'ОПУ БС'!P12 -> 4278.3242 | AU12: ='ОПУ БС'!$F12/12*'ОПУ БС'!Q12 -> 5144.1755 | AV12: ='ОПУ БС'!$F12/12*'ОПУ БС'!R12 -> 5908.162 | AW12: ='ОПУ БС'!$F12/12*'ОПУ БС'!S12 -> 5755.3647 | ... BA12: ='ОПУ БС'!$F12/12*'ОПУ БС'!W12 -> 6366.5539 | BB12: =SUM(AP12:BA12) -> 61118.917 | BC12: ='ОПУ БС'!$G12/12*'ОПУ БС'!L12 -> 4973.5834 | BD12: ='ОПУ БС'!$G12/12*'ОПУ БС'!M12 -> 5431.6766 | BE12: ='ОПУ БС'!$G12/12*'ОПУ БС'!N12 -> 6086.0954 | BF12: ='ОПУ БС'!$G12/12*'ОПУ БС'!O12 -> 6086.0954 | BG12: ='ОПУ БС'!$G12/12*'ОПУ БС'!P12 -> 5497.1185 | BH12: ='ОПУ БС'!$G12/12*'ОПУ БС'!Q12 -> 6609.6305 | BI12: ='ОПУ БС'!$G12/12*'ОПУ БС'!R12 -> 7591.2588 | BJ12: ='ОПУ БС'!$G12/12*'ОПУ БС'!S12 -> 7394.9332 | ... BN12: ='ОПУ БС'!$G12/12*'ОПУ БС'!W12 -> 8180.2358 | BO12: =SUM(BC12:BN12) -> 78530.264 | BP12: ='ОПУ БС'!$H12/12*'ОПУ БС'!L12 -> 6538.1114 | BQ12: ='ОПУ БС'!$H12/12*'ОПУ БС'!M12 -> 7140.3059 | BR12: ='ОПУ БС'!$H12/12*'ОПУ БС'!N12 -> 8000.5837 | BS12: ='ОПУ БС'!$H12/12*'ОПУ БС'!O12 -> 8000.5837 | BT12: ='ОПУ БС'!$H12/12*'ОПУ БС'!P12 -> 7226.3337 | BU12: ='ОПУ БС'!$H12/12*'ОПУ БС'!Q12 -> 8688.806 | BV12: ='ОПУ БС'!$H12/12*'ОПУ БС'!R12 -> 9979.2227 | BW12: ='ОПУ БС'!$H12/12*'ОПУ БС'!S12 -> 9721.1394 | ... CA12: ='ОПУ БС'!$H12/12*'ОПУ БС'!W12 -> 10753.473 | CB12: =SUM(BP12:CA12) -> 103233.34 | CC12: ='ОПУ БС'!$I12/12*'ОПУ БС'!L12 -> 8671.9566 | CD12: ='ОПУ БС'!$I12/12*'ОПУ БС'!M12 -> 9470.6895 | CE12: ='ОПУ БС'!$I12/12*'ОПУ БС'!N12 -> 10611.736 | CF12: ='ОПУ БС'!$I12/12*'ОПУ БС'!O12 -> 10611.736 | CG12: ='ОПУ БС'!$I12/12*'ОПУ БС'!P12 -> 9584.7942 | CH12: ='ОПУ БС'!$I12/12*'ОПУ БС'!Q12 -> 11524.574 | CI12: ='ОПУ БС'!$I12/12*'ОПУ БС'!R12 -> 13236.144 | CJ12: ='ОПУ БС'!$I12/12*'ОПУ БС'!S12 -> 12893.83 | ... CN12: ='ОПУ БС'!$I12/12*'ОПУ БС'!W12 -> 14263.087 | CO12: =SUM(CC12:CN12) -> 136925.63 | CR12: =O12-'ОПУ БС'!C12 -> 0 | CS12: =AB12-'ОПУ БС'!D12 -> 0 | CT12: =AO12-'ОПУ БС'!E12 -> 0 | CU12: =BB12-'ОПУ БС'!F12 -> 0 | CV12: =BO12-'ОПУ БС'!G12 -> 0 | CW12: =CB12-'ОПУ БС'!H12 -> 0 | CX12: =CO12-'ОПУ БС'!I12 -> 0 | DM12: =SUM(DA12:DL12) -> 0 | DZ12: =SUM(DN12:DY12) -> 0 | EM12: =SUM(EA12:EL12) -> 0 | EZ12: =SUM(EN12:EY12) -> 0 | FM12: =SUM(FA12:FL12) -> 0 | FP12: =C12 -> 2277.1926 | FQ12: =D12 -> 2486.934 | FR12: =E12 -> 2786.5646 | FS12: =F12 -> 2786.5646 | FT12: =G12 -> 2516.897 | FU12: =H12 -> 3026.2691 | FV12: =I12 -> 3475.715 | FW12: =J12 -> 3385.8258 | ... GA12: =N12 -> 3745.3825 | GB12: =SUM(FP12:GA12) -> 35955.672 | GC12: =P12 -> 2617.3136 | GD12: =Q12 -> 2858.3819 | GE12: =R12 -> 3202.7653 | GF12: =S12 -> 3202.7653 | GG12: =T12 -> 2892.8203 | GH12: =U12 -> 3478.272 | GI12: =V12 -> 3994.847 | GJ12: =W12 -> 3891.532 | ... GN12: =AA12 -> 4304.7921 | GO12: =SUM(GC12:GN12) -> 41326.004 | GP12: =AC12+DA12 -> 3121.5517 | GQ12: =AD12+DB12 -> 3409.0631 | GR12: =AE12+DC12 -> 3819.7936 | GS12: =AF12+DD12 -> 3819.7936 | GT12: =AG12+DE12 -> 3450.1361 | GU12: =AH12+DF12 -> 4148.378 | GV12: =AI12+DG12 -> 4764.4737 | GW12: =AJ12+DH12 -> 4641.2546 | ... HA12: =AN12+DL12 -> 5134.1312 | HB12: =SUM(GP12:HA12) -> 49287.659 | HC12: =AP12+DN12 -> 3870.8648 | HD12: =AQ12+DO12 -> 4227.3918 | HE12: =AR12+DP12 -> 4736.7161 | HF12: =AS12+DQ12 -> 4736.7161 | HG12: =AT12+DR12 -> 4278.3242 | HH12: =AU12+DS12 -> 5144.1755 | HI12: =AV12+DT12 -> 5908.162 | HJ12: =AW12+DU12 -> 5755.3647 | ... HN12: =BA12+DY12 -> 6366.5539 | HO12: =SUM(HC12:HN12) -> 61118.917 | HP12: =BC12+EA12 -> 4973.5834 | HQ12: =BD12+EB12 -> 5431.6766 | HR12: =BE12+EC12 -> 6086.0954 | HS12: =BF12+ED12 -> 6086.0954 | HT12: =BG12+EE12 -> 5497.1185 | HU12: =BH12+EF12 -> 6609.6305 | HV12: =BI12+EG12 -> 7591.2588 | HW12: =BJ12+EH12 -> 7394.9332 | ... IA12: =BN12+EL12 -> 8180.2358 | IB12: =SUM(HP12:IA12) -> 78530.264 | IC12: =BP12+EN12 -> 6538.1114 | ID12: =BQ12+EO12 -> 7140.3059 | IE12: =BR12+EP12 -> 8000.5837 | IF12: =BS12+EQ12 -> 8000.5837 | IG12: =BT12+ER12 -> 7226.3337 | IH12: =BU12+ES12 -> 8688.806 | II12: =BV12+ET12 -> 9979.2227 | IJ12: =BW12+EU12 -> 9721.1394 | ... IN12: =CA12+EY12 -> 10753.473 | IO12: =SUM(IC12:IN12) -> 103233.34 | IP12: =CC12+FA12 -> 8671.9566 | IQ12: =CD12+FB12 -> 9470.6895 | IR12: =CE12+FC12 -> 10611.736 | IS12: =CF12+FD12 -> 10611.736 | IT12: =CG12+FE12 -> 9584.7942 | IU12: =CH12+FF12 -> 11524.574 | IV12: =CI12+FG12 -> 13236.144 | IW12: =CJ12+FH12 -> 12893.83 | ... JA12: =CN12+FL12 -> 14263.087 | JB12: =SUM(IP12:JA12) -> 136925.63 | JE12: =O12-GB12 -> 0 | JF12: =AB12-GO12 -> 0 | JG12: =AO12+DM12-HB12 -> 0 | JH12: =BB12+DZ12-HO12 -> 0 | JI12: =BO12+EM12-IB12 -> 0 | JJ12: =CB12+EZ12-IO12 -> 0 | JK12: =CO12+FM12-JB12 -> 0
B13: Горчица | C13: ='ОПУ БС'!$C13/12*'ОПУ БС'!L13 -> 1194.4504 | D13: ='ОПУ БС'!$C13/12*'ОПУ БС'!M13 -> 1304.4656 | E13: ='ОПУ БС'!$C13/12*'ОПУ БС'!N13 -> 1461.6301 | F13: ='ОПУ БС'!$C13/12*'ОПУ БС'!O13 -> 1461.6301 | G13: ='ОПУ БС'!$C13/12*'ОПУ БС'!P13 -> 1493.063 | H13: ='ОПУ БС'!$C13/12*'ОПУ БС'!Q13 -> 1147.301 | I13: ='ОПУ БС'!$C13/12*'ОПУ БС'!R13 -> 1823.1085 | J13: ='ОПУ БС'!$C13/12*'ОПУ БС'!S13 -> 1775.9592 | ... N13: ='ОПУ БС'!$C13/12*'ОПУ БС'!W13 -> 1964.5566 | O13: =SUM(C13:N13) -> 18859.743 | P13: ='ОПУ БС'!$D13/12*'ОПУ БС'!L13 -> 1385.2444 | Q13: ='ОПУ БС'!$D13/12*'ОПУ БС'!M13 -> 1512.8327 | R13: ='ОПУ БС'!$D13/12*'ОПУ БС'!N13 -> 1695.1017 | S13: ='ОПУ БС'!$D13/12*'ОПУ БС'!O13 -> 1695.1017 | T13: ='ОПУ БС'!$D13/12*'ОПУ БС'!P13 -> 1731.5555 | U13: ='ОПУ БС'!$D13/12*'ОПУ БС'!Q13 -> 1330.5637 | V13: ='ОПУ БС'!$D13/12*'ОПУ БС'!R13 -> 2114.3204 | W13: ='ОПУ БС'!$D13/12*'ОПУ БС'!S13 -> 2059.6397 | ... AA13: ='ОПУ БС'!$D13/12*'ОПУ БС'!W13 -> 2278.3625 | AB13: =SUM(P13:AA13) -> 21872.28 | AC13: ='ОПУ БС'!$E13/12*'ОПУ БС'!L13 -> 1742.5115 | AD13: ='ОПУ БС'!$E13/12*'ОПУ БС'!M13 -> 1903.006 | AE13: ='ОПУ БС'!$E13/12*'ОПУ БС'!N13 -> 2132.2838 | AF13: ='ОПУ БС'!$E13/12*'ОПУ БС'!O13 -> 2132.2838 | AG13: ='ОПУ БС'!$E13/12*'ОПУ БС'!P13 -> 2178.1394 | AH13: ='ОПУ БС'!$E13/12*'ОПУ БС'!Q13 -> 1673.7281 | AI13: ='ОПУ БС'!$E13/12*'ОПУ БС'!R13 -> 2659.6228 | AJ13: ='ОПУ БС'!$E13/12*'ОПУ БС'!S13 -> 2590.8395 | ... AN13: ='ОПУ БС'!$E13/12*'ОПУ БС'!W13 -> 2865.9729 | AO13: =SUM(AC13:AN13) -> 27513.339 | AP13: ='ОПУ БС'!$F13/12*'ОПУ БС'!L13 -> 2294.0704 | AQ13: ='ОПУ БС'!$F13/12*'ОПУ БС'!M13 -> 2505.3663 | AR13: ='ОПУ БС'!$F13/12*'ОПУ БС'!N13 -> 2807.2177 | AS13: ='ОПУ БС'!$F13/12*'ОПУ БС'!O13 -> 2807.2177 | AT13: ='ОПУ БС'!$F13/12*'ОПУ БС'!P13 -> 2867.588 | AU13: ='ОПУ БС'!$F13/12*'ОПУ БС'!Q13 -> 2203.515 | AV13: ='ОПУ БС'!$F13/12*'ОПУ БС'!R13 -> 3501.4758 | AW13: ='ОПУ БС'!$F13/12*'ОПУ БС'!S13 -> 3410.9204 | ... BA13: ='ОПУ БС'!$F13/12*'ОПУ БС'!W13 -> 3773.1421 | BB13: =SUM(AP13:BA13) -> 36222.164 | BC13: ='ОПУ БС'!$G13/12*'ОПУ БС'!L13 -> 3134.9774 | BD13: ='ОПУ БС'!$G13/12*'ОПУ БС'!M13 -> 3423.7253 | BE13: ='ОПУ БС'!$G13/12*'ОПУ БС'!N13 -> 3836.2223 | BF13: ='ОПУ БС'!$G13/12*'ОПУ БС'!O13 -> 3836.2223 | BG13: ='ОПУ БС'!$G13/12*'ОПУ БС'!P13 -> 3918.7217 | BH13: ='ОПУ БС'!$G13/12*'ОПУ БС'!Q13 -> 3011.2283 | BI13: ='ОПУ БС'!$G13/12*'ОПУ БС'!R13 -> 4784.9655 | BJ13: ='ОПУ БС'!$G13/12*'ОПУ БС'!S13 -> 4661.2164 | ... BN13: ='ОПУ БС'!$G13/12*'ОПУ БС'!W13 -> 5156.2128 | BO13: =SUM(BC13:BN13) -> 49499.643 | BP13: ='ОПУ БС'!$H13/12*'ОПУ БС'!L13 -> 4401.8142 | BQ13: ='ОПУ БС'!$H13/12*'ОПУ БС'!M13 -> 4807.2445 | BR13: ='ОПУ БС'!$H13/12*'ОПУ БС'!N13 -> 5386.4305 | BS13: ='ОПУ БС'!$H13/12*'ОПУ БС'!O13 -> 5386.4305 | BT13: ='ОПУ БС'!$H13/12*'ОПУ БС'!P13 -> 5502.2678 | BU13: ='ОПУ БС'!$H13/12*'ОПУ БС'!Q13 -> 4228.0584 | BV13: ='ОПУ БС'!$H13/12*'ОПУ БС'!R13 -> 6718.5585 | BW13: ='ОПУ БС'!$H13/12*'ОПУ БС'!S13 -> 6544.8027 | ... CA13: ='ОПУ БС'!$H13/12*'ОПУ БС'!W13 -> 7239.826 | CB13: =SUM(BP13:CA13) -> 69502.33 | CC13: ='ОПУ БС'!$I13/12*'ОПУ БС'!L13 -> 6195.7587 | CD13: ='ОПУ БС'!$I13/12*'ОПУ БС'!M13 -> 6766.4207 | CE13: ='ОПУ БС'!$I13/12*'ОПУ БС'!N13 -> 7581.6521 | CF13: ='ОПУ БС'!$I13/12*'ОПУ БС'!O13 -> 7581.6521 | CG13: ='ОПУ БС'!$I13/12*'ОПУ БС'!P13 -> 7744.6984 | CH13: ='ОПУ БС'!$I13/12*'ОПУ БС'!Q13 -> 5951.1893 | CI13: ='ОПУ БС'!$I13/12*'ОПУ БС'!R13 -> 9456.6843 | CJ13: ='ОПУ БС'!$I13/12*'ОПУ БС'!S13 -> 9212.1149 | ... CN13: ='ОПУ БС'!$I13/12*'ОПУ БС'!W13 -> 10190.393 | CO13: =SUM(CC13:CN13) -> 97827.769 | CR13: =O13-'ОПУ БС'!C13 -> 0 | CS13: =AB13-'ОПУ БС'!D13 -> 0 | CT13: =AO13-'ОПУ БС'!E13 -> 0 | CU13: =BB13-'ОПУ БС'!F13 -> 0 | CV13: =BO13-'ОПУ БС'!G13 -> 0 | CW13: =CB13-'ОПУ БС'!H13 -> 0 | CX13: =CO13-'ОПУ БС'!I13 -> 0 | DM13: =SUM(DA13:DL13) -> 0 | DZ13: =SUM(DN13:DY13) -> 0 | EM13: =SUM(EA13:EL13) -> 0 | EZ13: =SUM(EN13:EY13) -> 0 | FM13: =SUM(FA13:FL13) -> 0 | FP13: =C13 -> 1194.4504 | FQ13: =D13 -> 1304.4656 | FR13: =E13 -> 1461.6301 | FS13: =F13 -> 1461.6301 | FT13: =G13 -> 1493.063 | FU13: =H13 -> 1147.301 | FV13: =I13 -> 1823.1085 | FW13: =J13 -> 1775.9592 | ... GA13: =N13 -> 1964.5566 | GB13: =SUM(FP13:GA13) -> 18859.743 | GC13: =P13 -> 1385.2444 | GD13: =Q13 -> 1512.8327 | GE13: =R13 -> 1695.1017 | GF13: =S13 -> 1695.1017 | GG13: =T13 -> 1731.5555 | GH13: =U13 -> 1330.5637 | GI13: =V13 -> 2114.3204 | GJ13: =W13 -> 2059.6397 | ... GN13: =AA13 -> 2278.3625 | GO13: =SUM(GC13:GN13) -> 21872.28 | GP13: =AC13+DA13 -> 1742.5115 | GQ13: =AD13+DB13 -> 1903.006 | GR13: =AE13+DC13 -> 2132.2838 | GS13: =AF13+DD13 -> 2132.2838 | GT13: =AG13+DE13 -> 2178.1394 | GU13: =AH13+DF13 -> 1673.7281 | GV13: =AI13+DG13 -> 2659.6228 | GW13: =AJ13+DH13 -> 2590.8395 | ... HA13: =AN13+DL13 -> 2865.9729 | HB13: =SUM(GP13:HA13) -> 27513.339 | HC13: =AP13+DN13 -> 2294.0704 | HD13: =AQ13+DO13 -> 2505.3663 | HE13: =AR13+DP13 -> 2807.2177 | HF13: =AS13+DQ13 -> 2807.2177 | HG13: =AT13+DR13 -> 2867.588 | HH13: =AU13+DS13 -> 2203.515 | HI13: =AV13+DT13 -> 3501.4758 | HJ13: =AW13+DU13 -> 3410.9204 | ... HN13: =BA13+DY13 -> 3773.1421 | HO13: =SUM(HC13:HN13) -> 36222.164 | HP13: =BC13+EA13 -> 3134.9774 | HQ13: =BD13+EB13 -> 3423.7253 | HR13: =BE13+EC13 -> 3836.2223 | HS13: =BF13+ED13 -> 3836.2223 | HT13: =BG13+EE13 -> 3918.7217 | HU13: =BH13+EF13 -> 3011.2283 | HV13: =BI13+EG13 -> 4784.9655 | HW13: =BJ13+EH13 -> 4661.2164 | ... IA13: =BN13+EL13 -> 5156.2128 | IB13: =SUM(HP13:IA13) -> 49499.643 | IC13: =BP13+EN13 -> 4401.8142 | ID13: =BQ13+EO13 -> 4807.2445 | IE13: =BR13+EP13 -> 5386.4305 | IF13: =BS13+EQ13 -> 5386.4305 | IG13: =BT13+ER13 -> 5502.2678 | IH13: =BU13+ES13 -> 4228.0584 | II13: =BV13+ET13 -> 6718.5585 | IJ13: =BW13+EU13 -> 6544.8027 | ... IN13: =CA13+EY13 -> 7239.826 | IO13: =SUM(IC13:IN13) -> 69502.33 | IP13: =CC13+FA13 -> 6195.7587 | IQ13: =CD13+FB13 -> 6766.4207 | IR13: =CE13+FC13 -> 7581.6521 | IS13: =CF13+FD13 -> 7581.6521 | IT13: =CG13+FE13 -> 7744.6984 | IU13: =CH13+FF13 -> 5951.1893 | IV13: =CI13+FG13 -> 9456.6843 | IW13: =CJ13+FH13 -> 9212.1149 | ... JA13: =CN13+FL13 -> 10190.393 | JB13: =SUM(IP13:JA13) -> 97827.769 | JE13: =O13-GB13 -> 0 | JF13: =AB13-GO13 -> 0 | JG13: =AO13+DM13-HB13 -> 0 | JH13: =BB13+DZ13-HO13 -> 0 | JI13: =BO13+EM13-IB13 -> 0 | JJ13: =CB13+EZ13-IO13 -> 0 | JK13: =CO13+FM13-JB13 -> 0
B14: Сырный | C14: ='ОПУ БС'!$C14/12*'ОПУ БС'!L14 -> 1957.3922 | D14: ='ОПУ БС'!$C14/12*'ОПУ БС'!M14 -> 2137.6783 | E14: ='ОПУ БС'!$C14/12*'ОПУ БС'!N14 -> 2395.2299 | F14: ='ОПУ БС'!$C14/12*'ОПУ БС'!O14 -> 2395.2299 | G14: ='ОПУ БС'!$C14/12*'ОПУ БС'!P14 -> 2446.7402 | H14: ='ОПУ БС'!$C14/12*'ОПУ БС'!Q14 -> 2601.2712 | I14: ='ОПУ БС'!$C14/12*'ОПУ БС'!R14 -> 3039.1089 | J14: ='ОПУ БС'!$C14/12*'ОПУ БС'!S14 -> 2910.3331 | ... N14: ='ОПУ БС'!$C14/12*'ОПУ БС'!W14 -> 3219.395 | O14: =SUM(C14:N14) -> 30906.192 | P14: ='ОПУ БС'!$D14/12*'ОПУ БС'!L14 -> 2076.6532 | Q14: ='ОПУ БС'!$D14/12*'ОПУ БС'!M14 -> 2267.9239 | R14: ='ОПУ БС'!$D14/12*'ОПУ БС'!N14 -> 2541.1677 | S14: ='ОПУ БС'!$D14/12*'ОПУ БС'!O14 -> 2541.1677 | T14: ='ОПУ БС'!$D14/12*'ОПУ БС'!P14 -> 2595.8165 | U14: ='ОПУ БС'!$D14/12*'ОПУ БС'!Q14 -> 2759.7628 | V14: ='ОПУ БС'!$D14/12*'ОПУ БС'!R14 -> 3224.2773 | W14: ='ОПУ БС'!$D14/12*'ОПУ БС'!S14 -> 3087.6554 | ... AA14: ='ОПУ БС'!$D14/12*'ОПУ БС'!W14 -> 3415.548 | AB14: =SUM(P14:AA14) -> 32789.261 | AC14: ='ОПУ БС'!$E14/12*'ОПУ БС'!L14 -> 2541.4723 | AD14: ='ОПУ БС'!$E14/12*'ОПУ БС'!M14 -> 2775.5553 | AE14: ='ОПУ БС'!$E14/12*'ОПУ БС'!N14 -> 3109.9595 | AF14: ='ОПУ БС'!$E14/12*'ОПУ БС'!O14 -> 3109.9595 | AG14: ='ОПУ БС'!$E14/12*'ОПУ БС'!P14 -> 3176.8404 | AH14: ='ОПУ БС'!$E14/12*'ОПУ БС'!Q14 -> 3377.4829 | AI14: ='ОПУ БС'!$E14/12*'ОПУ БС'!R14 -> 3945.9702 | AJ14: ='ОПУ БС'!$E14/12*'ОПУ БС'!S14 -> 3778.768 | ... AN14: ='ОПУ БС'!$E14/12*'ОПУ БС'!W14 -> 4180.0531 | AO14: =SUM(AC14:AN14) -> 40128.51 | AP14: ='ОПУ БС'!$F14/12*'ОПУ БС'!L14 -> 2776.9134 | AQ14: ='ОПУ БС'!$F14/12*'ОПУ БС'!M14 -> 3032.6817 | AR14: ='ОПУ БС'!$F14/12*'ОПУ БС'!N14 -> 3398.065 | AS14: ='ОПУ БС'!$F14/12*'ОПУ БС'!O14 -> 3398.065 | AT14: ='ОПУ БС'!$F14/12*'ОПУ БС'!P14 -> 3471.1417 | AU14: ='ОПУ БС'!$F14/12*'ОПУ БС'!Q14 -> 3690.3717 | AV14: ='ОПУ БС'!$F14/12*'ОПУ БС'!R14 -> 4311.5234 | AW14: ='ОПУ БС'!$F14/12*'ОПУ БС'!S14 -> 4128.8317 | ... BA14: ='ОПУ БС'!$F14/12*'ОПУ БС'!W14 -> 4567.2917 | BB14: =SUM(AP14:BA14) -> 43846 | BC14: ='ОПУ БС'!$G14/12*'ОПУ БС'!L14 -> 3130.4564 | BD14: ='ОПУ БС'!$G14/12*'ОПУ БС'!M14 -> 3418.788 | BE14: ='ОПУ БС'!$G14/12*'ОПУ БС'!N14 -> 3830.6901 | BF14: ='ОПУ БС'!$G14/12*'ОПУ БС'!O14 -> 3830.6901 | BG14: ='ОПУ БС'!$G14/12*'ОПУ БС'!P14 -> 3913.0706 | BH14: ='ОПУ БС'!$G14/12*'ОПУ БС'!Q14 -> 4160.2119 | BI14: ='ОПУ БС'!$G14/12*'ОПУ БС'!R14 -> 4860.4455 | BJ14: ='ОПУ БС'!$G14/12*'ОПУ БС'!S14 -> 4654.4944 | ... BN14: ='ОПУ БС'!$G14/12*'ОПУ БС'!W14 -> 5148.777 | BO14: =SUM(BC14:BN14) -> 49428.26 | BP14: ='ОПУ БС'!$H14/12*'ОПУ БС'!L14 -> 3549.2669 | BQ14: ='ОПУ БС'!$H14/12*'ОПУ БС'!M14 -> 3876.173 | BR14: ='ОПУ БС'!$H14/12*'ОПУ БС'!N14 -> 4343.1818 | BS14: ='ОПУ БС'!$H14/12*'ОПУ БС'!O14 -> 4343.1818 | BT14: ='ОПУ БС'!$H14/12*'ОПУ БС'!P14 -> 4436.5836 | BU14: ='ОПУ БС'!$H14/12*'ОПУ БС'!Q14 -> 4716.7889 | BV14: ='ОПУ БС'!$H14/12*'ОПУ БС'!R14 -> 5510.7038 | BW14: ='ОПУ БС'!$H14/12*'ОПУ БС'!S14 -> 5277.1994 | ... CA14: ='ОПУ БС'!$H14/12*'ОПУ БС'!W14 -> 5837.61 | CB14: =SUM(BP14:CA14) -> 56041.056 | CC14: ='ОПУ БС'!$I14/12*'ОПУ БС'!L14 -> 4171.4272 | CD14: ='ОПУ БС'!$I14/12*'ОПУ БС'!M14 -> 4555.6376 | CE14: ='ОПУ БС'!$I14/12*'ОПУ БС'!N14 -> 5104.5096 | CF14: ='ОПУ БС'!$I14/12*'ОПУ БС'!O14 -> 5104.5096 | CG14: ='ОПУ БС'!$I14/12*'ОПУ БС'!P14 -> 5214.284 | CH14: ='ОПУ БС'!$I14/12*'ОПУ БС'!Q14 -> 5543.6072 | CI14: ='ОПУ БС'!$I14/12*'ОПУ БС'!R14 -> 6476.6896 | CJ14: ='ОПУ БС'!$I14/12*'ОПУ БС'!S14 -> 6202.2536 | ... CN14: ='ОПУ БС'!$I14/12*'ОПУ БС'!W14 -> 6860.9 | CO14: =SUM(CC14:CN14) -> 65864.64 | CR14: =O14-'ОПУ БС'!C14 -> 0 | CS14: =AB14-'ОПУ БС'!D14 -> 0 | CT14: =AO14-'ОПУ БС'!E14 -> 0 | CU14: =BB14-'ОПУ БС'!F14 -> 0 | CV14: =BO14-'ОПУ БС'!G14 -> 0 | CW14: =CB14-'ОПУ БС'!H14 -> 0 | CX14: =CO14-'ОПУ БС'!I14 -> 0 | DM14: =SUM(DA14:DL14) -> 0 | DZ14: =SUM(DN14:DY14) -> 0 | EM14: =SUM(EA14:EL14) -> 0 | EZ14: =SUM(EN14:EY14) -> 0 | FM14: =SUM(FA14:FL14) -> 0 | FP14: =C14 -> 1957.3922 | FQ14: =D14 -> 2137.6783 | FR14: =E14 -> 2395.2299 | FS14: =F14 -> 2395.2299 | FT14: =G14 -> 2446.7402 | FU14: =H14 -> 2601.2712 | FV14: =I14 -> 3039.1089 | FW14: =J14 -> 2910.3331 | ... GA14: =N14 -> 3219.395 | GB14: =SUM(FP14:GA14) -> 30906.192 | GC14: =P14 -> 2076.6532 | GD14: =Q14 -> 2267.9239 | GE14: =R14 -> 2541.1677 | GF14: =S14 -> 2541.1677 | GG14: =T14 -> 2595.8165 | GH14: =U14 -> 2759.7628 | GI14: =V14 -> 3224.2773 | GJ14: =W14 -> 3087.6554 | ... GN14: =AA14 -> 3415.548 | GO14: =SUM(GC14:GN14) -> 32789.261 | GP14: =AC14+DA14 -> 2541.4723 | GQ14: =AD14+DB14 -> 2775.5553 | GR14: =AE14+DC14 -> 3109.9595 | GS14: =AF14+DD14 -> 3109.9595 | GT14: =AG14+DE14 -> 3176.8404 | GU14: =AH14+DF14 -> 3377.4829 | GV14: =AI14+DG14 -> 3945.9702 | GW14: =AJ14+DH14 -> 3778.768 | ... HA14: =AN14+DL14 -> 4180.0531 | HB14: =SUM(GP14:HA14) -> 40128.51 | HC14: =AP14+DN14 -> 2776.9134 | HD14: =AQ14+DO14 -> 3032.6817 | HE14: =AR14+DP14 -> 3398.065 | HF14: =AS14+DQ14 -> 3398.065 | HG14: =AT14+DR14 -> 3471.1417 | HH14: =AU14+DS14 -> 3690.3717 | HI14: =AV14+DT14 -> 4311.5234 | HJ14: =AW14+DU14 -> 4128.8317 | ... HN14: =BA14+DY14 -> 4567.2917 | HO14: =SUM(HC14:HN14) -> 43846 | HP14: =BC14+EA14 -> 3130.4564 | HQ14: =BD14+EB14 -> 3418.788 | HR14: =BE14+EC14 -> 3830.6901 | HS14: =BF14+ED14 -> 3830.6901 | HT14: =BG14+EE14 -> 3913.0706 | HU14: =BH14+EF14 -> 4160.2119 | HV14: =BI14+EG14 -> 4860.4455 | HW14: =BJ14+EH14 -> 4654.4944 | ... IA14: =BN14+EL14 -> 5148.777 | IB14: =SUM(HP14:IA14) -> 49428.26 | IC14: =BP14+EN14 -> 3549.2669 | ID14: =BQ14+EO14 -> 3876.173 | IE14: =BR14+EP14 -> 4343.1818 | IF14: =BS14+EQ14 -> 4343.1818 | IG14: =BT14+ER14 -> 4436.5836 | IH14: =BU14+ES14 -> 4716.7889 | II14: =BV14+ET14 -> 5510.7038 | IJ14: =BW14+EU14 -> 5277.1994 | ... IN14: =CA14+EY14 -> 5837.61 | IO14: =SUM(IC14:IN14) -> 56041.056 | IP14: =CC14+FA14 -> 4171.4272 | IQ14: =CD14+FB14 -> 4555.6376 | IR14: =CE14+FC14 -> 5104.5096 | IS14: =CF14+FD14 -> 5104.5096 | IT14: =CG14+FE14 -> 5214.284 | IU14: =CH14+FF14 -> 5543.6072 | IV14: =CI14+FG14 -> 6476.6896 | IW14: =CJ14+FH14 -> 6202.2536 | ... JA14: =CN14+FL14 -> 6860.9 | JB14: =SUM(IP14:JA14) -> 65864.64 | JE14: =O14-GB14 -> 0 | JF14: =AB14-GO14 -> 0 | JG14: =AO14+DM14-HB14 -> 0 | JH14: =BB14+DZ14-HO14 -> 0 | JI14: =BO14+EM14-IB14 -> 0 | JJ14: =CB14+EZ14-IO14 -> 0 | JK14: =CO14+FM14-JB14 -> 0
B15: Кисло-сладкий | C15: ='ОПУ БС'!$C15/12*'ОПУ БС'!L15 -> 524.07575 | D15: ='ОПУ БС'!$C15/12*'ОПУ БС'!M15 -> 572.34588 | E15: ='ОПУ БС'!$C15/12*'ОПУ БС'!N15 -> 641.30321 | F15: ='ОПУ БС'!$C15/12*'ОПУ БС'!O15 -> 641.30321 | G15: ='ОПУ БС'!$C15/12*'ОПУ БС'!P15 -> 655.09468 | H15: ='ОПУ БС'!$C15/12*'ОПУ БС'!Q15 -> 696.46908 | I15: ='ОПУ БС'!$C15/12*'ОПУ БС'!R15 -> 799.90509 | J15: ='ОПУ БС'!$C15/12*'ОПУ БС'!S15 -> 613.72028 | ... N15: ='ОПУ БС'!$C15/12*'ОПУ БС'!W15 -> 861.96669 | O15: =SUM(C15:N15) -> 8274.8802 | P15: ='ОПУ БС'!$D15/12*'ОПУ БС'!L15 -> 582.8414 | Q15: ='ОПУ БС'!$D15/12*'ОПУ БС'!M15 -> 636.52416 | R15: ='ОПУ БС'!$D15/12*'ОПУ БС'!N15 -> 713.21382 | S15: ='ОПУ БС'!$D15/12*'ОПУ БС'!O15 -> 713.21382 | T15: ='ОПУ БС'!$D15/12*'ОПУ БС'!P15 -> 728.55175 | U15: ='ОПУ БС'!$D15/12*'ОПУ БС'!Q15 -> 774.56554 | V15: ='ОПУ БС'!$D15/12*'ОПУ БС'!R15 -> 889.60003 | W15: ='ОПУ БС'!$D15/12*'ОПУ БС'!S15 -> 682.53795 | ... AA15: ='ОПУ БС'!$D15/12*'ОПУ БС'!W15 -> 958.62072 | AB15: =SUM(P15:AA15) -> 9202.7589 | AC15: ='ОПУ БС'!$E15/12*'ОПУ БС'!L15 -> 676.59667 | AD15: ='ОПУ БС'!$E15/12*'ОПУ БС'!M15 -> 738.91478 | AE15: ='ОПУ БС'!$E15/12*'ОПУ БС'!N15 -> 827.94066 | AF15: ='ОПУ БС'!$E15/12*'ОПУ БС'!O15 -> 827.94066 | AG15: ='ОПУ БС'!$E15/12*'ОПУ БС'!P15 -> 845.74583 | AH15: ='ОПУ БС'!$E15/12*'ОПУ БС'!Q15 -> 899.16136 | AI15: ='ОПУ БС'!$E15/12*'ОПУ БС'!R15 -> 1032.7002 | AJ15: ='ОПУ БС'!$E15/12*'ОПУ БС'!S15 -> 792.33031 | ... AN15: ='ОПУ БС'!$E15/12*'ОПУ БС'!W15 -> 1112.8235 | AO15: =SUM(AC15:AN15) -> 10683.105 | AP15: ='ОПУ БС'!$F15/12*'ОПУ БС'!L15 -> 819.81972 | AQ15: ='ОПУ БС'!$F15/12*'ОПУ БС'!M15 -> 895.32943 | AR15: ='ОПУ БС'!$F15/12*'ОПУ БС'!N15 -> 1003.2004 | AS15: ='ОПУ БС'!$F15/12*'ОПУ БС'!O15 -> 1003.2004 | AT15: ='ОПУ БС'!$F15/12*'ОПУ БС'!P15 -> 1024.7746 | AU15: ='ОПУ БС'!$F15/12*'ОПУ БС'!Q15 -> 1089.4973 | AV15: ='ОПУ БС'!$F15/12*'ОПУ БС'!R15 -> 1251.3038 | AW15: ='ОПУ БС'!$F15/12*'ОПУ БС'!S15 -> 960.05204 | ... BA15: ='ОПУ БС'!$F15/12*'ОПУ БС'!W15 -> 1348.3877 | BB15: =SUM(AP15:BA15) -> 12944.522 | BC15: ='ОПУ БС'!$G15/12*'ОПУ БС'!L15 -> 1031.8538 | BD15: ='ОПУ БС'!$G15/12*'ОПУ БС'!M15 -> 1126.8929 | BE15: ='ОПУ БС'!$G15/12*'ОПУ БС'!N15 -> 1262.6631 | BF15: ='ОПУ БС'!$G15/12*'ОПУ БС'!O15 -> 1262.6631 | BG15: ='ОПУ БС'!$G15/12*'ОПУ БС'!P15 -> 1289.8172 | BH15: ='ОПУ БС'!$G15/12*'ОПУ БС'!Q15 -> 1371.2793 | BI15: ='ОПУ БС'!$G15/12*'ОПУ БС'!R15 -> 1574.9347 | BJ15: ='ОПУ БС'!$G15/12*'ОПУ БС'!S15 -> 1208.3551 | ... BN15: ='ОПУ БС'!$G15/12*'ОПУ БС'!W15 -> 1697.1279 | BO15: =SUM(BC15:BN15) -> 16292.428 | BP15: ='ОПУ БС'!$H15/12*'ОПУ БС'!L15 -> 1328.3666 | BQ15: ='ОПУ БС'!$H15/12*'ОПУ БС'!M15 -> 1450.7161 | BR15: ='ОПУ БС'!$H15/12*'ОПУ БС'!N15 -> 1625.5012 | BS15: ='ОПУ БС'!$H15/12*'ОПУ БС'!O15 -> 1625.5012 | BT15: ='ОПУ БС'!$H15/12*'ОПУ БС'!P15 -> 1660.4582 | BU15: ='ОПУ БС'!$H15/12*'ОПУ БС'!Q15 -> 1765.3292 | BV15: ='ОПУ БС'!$H15/12*'ОПУ БС'!R15 -> 2027.5069 | BW15: ='ОПУ БС'!$H15/12*'ОПУ БС'!S15 -> 1555.5872 | ... CA15: ='ОПУ БС'!$H15/12*'ОПУ БС'!W15 -> 2184.8134 | CB15: =SUM(BP15:CA15) -> 20974.209 | CC15: ='ОПУ БС'!$I15/12*'ОПУ БС'!L15 -> 1734.2037 | CD15: ='ОПУ БС'!$I15/12*'ОПУ БС'!M15 -> 1893.933 | CE15: ='ОПУ БС'!$I15/12*'ОПУ БС'!N15 -> 2122.1177 | CF15: ='ОПУ БС'!$I15/12*'ОПУ БС'!O15 -> 2122.1177 | CG15: ='ОПУ БС'!$I15/12*'ОПУ БС'!P15 -> 2167.7546 | CH15: ='ОПУ БС'!$I15/12*'ОПУ БС'!Q15 -> 2304.6655 | CI15: ='ОПУ БС'!$I15/12*'ОПУ БС'!R15 -> 2646.9425 | CJ15: ='ОПУ БС'!$I15/12*'ОПУ БС'!S15 -> 2030.8438 | ... CN15: ='ОПУ БС'!$I15/12*'ОПУ БС'!W15 -> 2852.3087 | CO15: =SUM(CC15:CN15) -> 27382.164 | CR15: =O15-'ОПУ БС'!C15 -> 0 | CS15: =AB15-'ОПУ БС'!D15 -> 0 | CT15: =AO15-'ОПУ БС'!E15 -> 0 | CU15: =BB15-'ОПУ БС'!F15 -> 0 | CV15: =BO15-'ОПУ БС'!G15 -> 0 | CW15: =CB15-'ОПУ БС'!H15 -> 0 | CX15: =CO15-'ОПУ БС'!I15 -> 0 | DM15: =SUM(DA15:DL15) -> 0 | DZ15: =SUM(DN15:DY15) -> 0 | EM15: =SUM(EA15:EL15) -> 0 | EZ15: =SUM(EN15:EY15) -> 0 | FM15: =SUM(FA15:FL15) -> 0 | FP15: =C15 -> 524.07575 | FQ15: =D15 -> 572.34588 | FR15: =E15 -> 641.30321 | FS15: =F15 -> 641.30321 | FT15: =G15 -> 655.09468 | FU15: =H15 -> 696.46908 | FV15: =I15 -> 799.90509 | FW15: =J15 -> 613.72028 | ... GA15: =N15 -> 861.96669 | GB15: =SUM(FP15:GA15) -> 8274.8802 | GC15: =P15 -> 582.8414 | GD15: =Q15 -> 636.52416 | GE15: =R15 -> 713.21382 | GF15: =S15 -> 713.21382 | GG15: =T15 -> 728.55175 | GH15: =U15 -> 774.56554 | GI15: =V15 -> 889.60003 | GJ15: =W15 -> 682.53795 | ... GN15: =AA15 -> 958.62072 | GO15: =SUM(GC15:GN15) -> 9202.7589 | GP15: =AC15+DA15 -> 676.59667 | GQ15: =AD15+DB15 -> 738.91478 | GR15: =AE15+DC15 -> 827.94066 | GS15: =AF15+DD15 -> 827.94066 | GT15: =AG15+DE15 -> 845.74583 | GU15: =AH15+DF15 -> 899.16136 | GV15: =AI15+DG15 -> 1032.7002 | GW15: =AJ15+DH15 -> 792.33031 | ... HA15: =AN15+DL15 -> 1112.8235 | HB15: =SUM(GP15:HA15) -> 10683.105 | HC15: =AP15+DN15 -> 819.81972 | HD15: =AQ15+DO15 -> 895.32943 | HE15: =AR15+DP15 -> 1003.2004 | HF15: =AS15+DQ15 -> 1003.2004 | HG15: =AT15+DR15 -> 1024.7746 | HH15: =AU15+DS15 -> 1089.4973 | HI15: =AV15+DT15 -> 1251.3038 | HJ15: =AW15+DU15 -> 960.05204 | ... HN15: =BA15+DY15 -> 1348.3877 | HO15: =SUM(HC15:HN15) -> 12944.522 | HP15: =BC15+EA15 -> 1031.8538 | HQ15: =BD15+EB15 -> 1126.8929 | HR15: =BE15+EC15 -> 1262.6631 | HS15: =BF15+ED15 -> 1262.6631 | HT15: =BG15+EE15 -> 1289.8172 | HU15: =BH15+EF15 -> 1371.2793 | HV15: =BI15+EG15 -> 1574.9347 | HW15: =BJ15+EH15 -> 1208.3551 | ... IA15: =BN15+EL15 -> 1697.1279 | IB15: =SUM(HP15:IA15) -> 16292.428 | IC15: =BP15+EN15 -> 1328.3666 | ID15: =BQ15+EO15 -> 1450.7161 | IE15: =BR15+EP15 -> 1625.5012 | IF15: =BS15+EQ15 -> 1625.5012 | IG15: =BT15+ER15 -> 1660.4582 | IH15: =BU15+ES15 -> 1765.3292 | II15: =BV15+ET15 -> 2027.5069 | IJ15: =BW15+EU15 -> 1555.5872 | ... IN15: =CA15+EY15 -> 2184.8134 | IO15: =SUM(IC15:IN15) -> 20974.209 | IP15: =CC15+FA15 -> 1734.2037 | IQ15: =CD15+FB15 -> 1893.933 | IR15: =CE15+FC15 -> 2122.1177 | IS15: =CF15+FD15 -> 2122.1177 | IT15: =CG15+FE15 -> 2167.7546 | IU15: =CH15+FF15 -> 2304.6655 | IV15: =CI15+FG15 -> 2646.9425 | IW15: =CJ15+FH15 -> 2030.8438 | ... JA15: =CN15+FL15 -> 2852.3087 | JB15: =SUM(IP15:JA15) -> 27382.164 | JE15: =O15-GB15 -> 0 | JF15: =AB15-GO15 -> 0 | JG15: =AO15+DM15-HB15 -> 0 | JH15: =BB15+DZ15-HO15 -> 0 | JI15: =BO15+EM15-IB15 -> 0 | JJ15: =CB15+EZ15-IO15 -> 0 | JK15: =CO15+FM15-JB15 -> 0
B16: Чесночный | C16: ='ОПУ БС'!$C16/12*'ОПУ БС'!L16 -> 320.91645 | D16: ='ОПУ БС'!$C16/12*'ОПУ БС'!M16 -> 350.47454 | E16: ='ОПУ БС'!$C16/12*'ОПУ БС'!N16 -> 392.70039 | F16: ='ОПУ БС'!$C16/12*'ОПУ БС'!O16 -> 392.70039 | G16: ='ОПУ БС'!$C16/12*'ОПУ БС'!P16 -> 401.14556 | H16: ='ОПУ БС'!$C16/12*'ОПУ БС'!Q16 -> 426.48107 | I16: ='ОПУ БС'!$C16/12*'ОПУ БС'!R16 -> 489.81985 | J16: ='ОПУ БС'!$C16/12*'ОПУ БС'!S16 -> 477.15209 | ... N16: ='ОПУ БС'!$C16/12*'ОПУ БС'!W16 -> 527.82311 | O16: =SUM(C16:N16) -> 5067.1018 | P16: ='ОПУ БС'!$D16/12*'ОПУ БС'!L16 -> 353.85791 | Q16: ='ОПУ БС'!$D16/12*'ОПУ БС'!M16 -> 386.45009 | R16: ='ОПУ БС'!$D16/12*'ОПУ БС'!N16 -> 433.01034 | S16: ='ОПУ БС'!$D16/12*'ОПУ БС'!O16 -> 433.01034 | T16: ='ОПУ БС'!$D16/12*'ОПУ БС'!P16 -> 442.32239 | U16: ='ОПУ БС'!$D16/12*'ОПУ БС'!Q16 -> 470.25854 | V16: ='ОПУ БС'!$D16/12*'ОПУ БС'!R16 -> 540.09892 | W16: ='ОПУ БС'!$D16/12*'ОПУ БС'!S16 -> 526.13084 | ... AA16: ='ОПУ БС'!$D16/12*'ОПУ БС'!W16 -> 582.00314 | AB16: =SUM(P16:AA16) -> 5587.2302 | AC16: ='ОПУ БС'!$E16/12*'ОПУ БС'!L16 -> 414.27228 | AD16: ='ОПУ БС'!$E16/12*'ОПУ БС'!M16 -> 452.42893 | AE16: ='ОПУ БС'!$E16/12*'ОПУ БС'!N16 -> 506.93844 | AF16: ='ОПУ БС'!$E16/12*'ОПУ БС'!O16 -> 506.93844 | AG16: ='ОПУ БС'!$E16/12*'ОПУ БС'!P16 -> 517.84035 | AH16: ='ОПУ БС'!$E16/12*'ОПУ БС'!Q16 -> 550.54605 | AI16: ='ОПУ БС'!$E16/12*'ОПУ БС'!R16 -> 632.31032 | AJ16: ='ОПУ БС'!$E16/12*'ОПУ БС'!S16 -> 615.95746 | ... AN16: ='ОПУ БС'!$E16/12*'ОПУ БС'!W16 -> 681.36888 | AO16: =SUM(AC16:AN16) -> 6541.1412 | AP16: ='ОПУ БС'!$F16/12*'ОПУ БС'!L16 -> 508.25661 | AQ16: ='ОПУ БС'!$F16/12*'ОПУ БС'!M16 -> 555.06972 | AR16: ='ОПУ БС'!$F16/12*'ОПУ БС'!N16 -> 621.94559 | AS16: ='ОПУ БС'!$F16/12*'ОПУ БС'!O16 -> 621.94559 | AT16: ='ОПУ БС'!$F16/12*'ОПУ БС'!P16 -> 635.32076 | AU16: ='ОПУ БС'!$F16/12*'ОПУ БС'!Q16 -> 675.44628 | AV16: ='ОПУ БС'!$F16/12*'ОПУ БС'!R16 -> 775.76009 | AW16: ='ОПУ БС'!$F16/12*'ОПУ БС'!S16 -> 755.69733 | ... BA16: ='ОПУ БС'!$F16/12*'ОПУ БС'!W16 -> 835.94837 | BB16: =SUM(AP16:BA16) -> 8025.1043 | BC16: ='ОПУ БС'!$G16/12*'ОПУ БС'!L16 -> 649.20484 | BD16: ='ОПУ БС'!$G16/12*'ОПУ БС'!M16 -> 709.00002 | BE16: ='ОПУ БС'!$G16/12*'ОПУ БС'!N16 -> 794.42171 | BF16: ='ОПУ БС'!$G16/12*'ОПУ БС'!O16 -> 794.42171 | BG16: ='ОПУ БС'!$G16/12*'ОПУ БС'!P16 -> 811.50605 | BH16: ='ОПУ БС'!$G16/12*'ОПУ БС'!Q16 -> 862.75906 | BI16: ='ОПУ БС'!$G16/12*'ОПУ БС'!R16 -> 990.8916 | BJ16: ='ОПУ БС'!$G16/12*'ОПУ БС'!S16 -> 965.26509 | ... BN16: ='ОПУ БС'!$G16/12*'ОПУ БС'!W16 -> 1067.7711 | BO16: =SUM(BC16:BN16) -> 10250.603 | BP16: ='ОПУ БС'!$H16/12*'ОПУ БС'!L16 -> 849.24081 | BQ16: ='ОПУ БС'!$H16/12*'ОПУ БС'!M16 -> 927.46036 | BR16: ='ОПУ БС'!$H16/12*'ОПУ БС'!N16 -> 1039.2026 | BS16: ='ОПУ БС'!$H16/12*'ОПУ БС'!O16 -> 1039.2026 | BT16: ='ОПУ БС'!$H16/12*'ОПУ БС'!P16 -> 1061.551 | BU16: ='ОПУ БС'!$H16/12*'ОПУ БС'!Q16 -> 1128.5963 | BV16: ='ОПУ БС'!$H16/12*'ОПУ БС'!R16 -> 1296.2097 | BW16: ='ОПУ БС'!$H16/12*'ОПУ БС'!S16 -> 1262.687 | ... CA16: ='ОПУ БС'!$H16/12*'ОПУ БС'!W16 -> 1396.7777 | CB16: =SUM(BP16:CA16) -> 13409.065 | CC16: ='ОПУ БС'!$I16/12*'ОПУ БС'!L16 -> 1126.5889 | CD16: ='ОПУ БС'!$I16/12*'ОПУ БС'!M16 -> 1230.3537 | CE16: ='ОПУ БС'!$I16/12*'ОПУ БС'!N16 -> 1378.5891 | CF16: ='ОПУ БС'!$I16/12*'ОПУ БС'!O16 -> 1378.5891 | CG16: ='ОПУ БС'!$I16/12*'ОПУ БС'!P16 -> 1408.2362 | CH16: ='ОПУ БС'!$I16/12*'ОПУ БС'!Q16 -> 1497.1774 | CI16: ='ОПУ БС'!$I16/12*'ОПУ БС'!R16 -> 1719.5305 | CJ16: ='ОПУ БС'!$I16/12*'ОПУ БС'!S16 -> 1675.0599 | ... CN16: ='ОПУ БС'!$I16/12*'ОПУ БС'!W16 -> 1852.9423 | CO16: =SUM(CC16:CN16) -> 17788.246 | CR16: =O16-'ОПУ БС'!C16 -> 0 | CS16: =AB16-'ОПУ БС'!D16 -> 0 | CT16: =AO16-'ОПУ БС'!E16 -> 0 | CU16: =BB16-'ОПУ БС'!F16 -> 0 | CV16: =BO16-'ОПУ БС'!G16 -> 0 | CW16: =CB16-'ОПУ БС'!H16 -> 0 | CX16: =CO16-'ОПУ БС'!I16 -> 0 | DM16: =SUM(DA16:DL16) -> 0 | DZ16: =SUM(DN16:DY16) -> 0 | EM16: =SUM(EA16:EL16) -> 0 | EZ16: =SUM(EN16:EY16) -> 0 | FM16: =SUM(FA16:FL16) -> 0 | FP16: =C16 -> 320.91645 | FQ16: =D16 -> 350.47454 | FR16: =E16 -> 392.70039 | FS16: =F16 -> 392.70039 | FT16: =G16 -> 401.14556 | FU16: =H16 -> 426.48107 | FV16: =I16 -> 489.81985 | FW16: =J16 -> 477.15209 | ... GA16: =N16 -> 527.82311 | GB16: =SUM(FP16:GA16) -> 5067.1018 | GC16: =P16 -> 353.85791 | GD16: =Q16 -> 386.45009 | GE16: =R16 -> 433.01034 | GF16: =S16 -> 433.01034 | GG16: =T16 -> 442.32239 | GH16: =U16 -> 470.25854 | GI16: =V16 -> 540.09892 | GJ16: =W16 -> 526.13084 | ... GN16: =AA16 -> 582.00314 | GO16: =SUM(GC16:GN16) -> 5587.2302 | GP16: =AC16+DA16 -> 414.27228 | GQ16: =AD16+DB16 -> 452.42893 | GR16: =AE16+DC16 -> 506.93844 | GS16: =AF16+DD16 -> 506.93844 | GT16: =AG16+DE16 -> 517.84035 | GU16: =AH16+DF16 -> 550.54605 | GV16: =AI16+DG16 -> 632.31032 | GW16: =AJ16+DH16 -> 615.95746 | ... HA16: =AN16+DL16 -> 681.36888 | HB16: =SUM(GP16:HA16) -> 6541.1412 | HC16: =AP16+DN16 -> 508.25661 | HD16: =AQ16+DO16 -> 555.06972 | HE16: =AR16+DP16 -> 621.94559 | HF16: =AS16+DQ16 -> 621.94559 | HG16: =AT16+DR16 -> 635.32076 | HH16: =AU16+DS16 -> 675.44628 | HI16: =AV16+DT16 -> 775.76009 | HJ16: =AW16+DU16 -> 755.69733 | ... HN16: =BA16+DY16 -> 835.94837 | HO16: =SUM(HC16:HN16) -> 8025.1043 | HP16: =BC16+EA16 -> 649.20484 | HQ16: =BD16+EB16 -> 709.00002 | HR16: =BE16+EC16 -> 794.42171 | HS16: =BF16+ED16 -> 794.42171 | HT16: =BG16+EE16 -> 811.50605 | HU16: =BH16+EF16 -> 862.75906 | HV16: =BI16+EG16 -> 990.8916 | HW16: =BJ16+EH16 -> 965.26509 | ... IA16: =BN16+EL16 -> 1067.7711 | IB16: =SUM(HP16:IA16) -> 10250.603 | IC16: =BP16+EN16 -> 849.24081 | ID16: =BQ16+EO16 -> 927.46036 | IE16: =BR16+EP16 -> 1039.2026 | IF16: =BS16+EQ16 -> 1039.2026 | IG16: =BT16+ER16 -> 1061.551 | IH16: =BU16+ES16 -> 1128.5963 | II16: =BV16+ET16 -> 1296.2097 | IJ16: =BW16+EU16 -> 1262.687 | ... IN16: =CA16+EY16 -> 1396.7777 | IO16: =SUM(IC16:IN16) -> 13409.065 | IP16: =CC16+FA16 -> 1126.5889 | IQ16: =CD16+FB16 -> 1230.3537 | IR16: =CE16+FC16 -> 1378.5891 | IS16: =CF16+FD16 -> 1378.5891 | IT16: =CG16+FE16 -> 1408.2362 | IU16: =CH16+FF16 -> 1497.1774 | IV16: =CI16+FG16 -> 1719.5305 | IW16: =CJ16+FH16 -> 1675.0599 | ... JA16: =CN16+FL16 -> 1852.9423 | JB16: =SUM(IP16:JA16) -> 17788.246 | JE16: =O16-GB16 -> 0 | JF16: =AB16-GO16 -> 0 | JG16: =AO16+DM16-HB16 -> 0 | JH16: =BB16+DZ16-HO16 -> 0 | JI16: =BO16+EM16-IB16 -> 0 | JJ16: =CB16+EZ16-IO16 -> 0 | JK16: =CO16+FM16-JB16 -> 0
B17: Коктейльный | C17: ='ОПУ БС'!$C17/12*'ОПУ БС'!L17 -> 363.40475 | D17: ='ОПУ БС'!$C17/12*'ОПУ БС'!M17 -> 396.87624 | E17: ='ОПУ БС'!$C17/12*'ОПУ БС'!N17 -> 444.69265 | F17: ='ОПУ БС'!$C17/12*'ОПУ БС'!O17 -> 444.69265 | G17: ='ОПУ БС'!$C17/12*'ОПУ БС'!P17 -> 454.25594 | H17: ='ОПУ БС'!$C17/12*'ОПУ БС'!Q17 -> 482.94578 | I17: ='ОПУ БС'!$C17/12*'ОПУ БС'!R17 -> 554.67041 | J17: ='ОПУ БС'!$C17/12*'ОПУ БС'!S17 -> 540.32548 | ... N17: ='ОПУ БС'!$C17/12*'ОПУ БС'!W17 -> 597.70518 | O17: =SUM(C17:N17) -> 5737.9697 | P17: ='ОПУ БС'!$D17/12*'ОПУ БС'!L17 -> 398.88314 | Q17: ='ОПУ БС'!$D17/12*'ОПУ БС'!M17 -> 435.62237 | R17: ='ОПУ БС'!$D17/12*'ОПУ БС'!N17 -> 488.107 | S17: ='ОПУ БС'!$D17/12*'ОПУ БС'!O17 -> 488.107 | T17: ='ОПУ БС'!$D17/12*'ОПУ БС'!P17 -> 498.60392 | U17: ='ОПУ БС'!$D17/12*'ОПУ БС'!Q17 -> 530.0947 | V17: ='ОПУ БС'!$D17/12*'ОПУ БС'!R17 -> 608.82163 | W17: ='ОПУ БС'!$D17/12*'ОПУ БС'!S17 -> 593.07624 | ... AA17: ='ОПУ БС'!$D17/12*'ОПУ БС'!W17 -> 656.05779 | AB17: =SUM(P17:AA17) -> 6298.1548 | AC17: ='ОПУ БС'!$E17/12*'ОПУ БС'!L17 -> 460.68883 | AD17: ='ОПУ БС'!$E17/12*'ОПУ БС'!M17 -> 503.12069 | AE17: ='ОПУ БС'!$E17/12*'ОПУ БС'!N17 -> 563.73764 | AF17: ='ОПУ БС'!$E17/12*'ОПУ БС'!O17 -> 563.73764 | AG17: ='ОПУ БС'!$E17/12*'ОПУ БС'!P17 -> 575.86103 | AH17: ='ОПУ БС'!$E17/12*'ОПУ БС'!Q17 -> 612.2312 | AI17: ='ОПУ БС'!$E17/12*'ОПУ БС'!R17 -> 703.15663 | AJ17: ='ОПУ БС'!$E17/12*'ОПУ БС'!S17 -> 684.97154 | ... AN17: ='ОПУ БС'!$E17/12*'ОПУ БС'!W17 -> 757.71188 | AO17: =SUM(AC17:AN17) -> 7274.0341 | AP17: ='ОПУ БС'!$F17/12*'ОПУ БС'!L17 -> 556.72852 | AQ17: ='ОПУ БС'!$F17/12*'ОПУ БС'!M17 -> 608.00614 | AR17: ='ОПУ БС'!$F17/12*'ОПУ БС'!N17 -> 681.2599 | AS17: ='ОПУ БС'!$F17/12*'ОПУ БС'!O17 -> 681.2599 | AT17: ='ОПУ БС'!$F17/12*'ОПУ БС'!P17 -> 695.91065 | AU17: ='ОПУ БС'!$F17/12*'ОПУ БС'!Q17 -> 739.8629 | AV17: ='ОПУ БС'!$F17/12*'ОПУ БС'!R17 -> 849.74353 | AW17: ='ОПУ БС'!$F17/12*'ОПУ БС'!S17 -> 827.7674 | ... BA17: ='ОПУ БС'!$F17/12*'ОПУ БС'!W17 -> 915.67191 | BB17: =SUM(AP17:BA17) -> 8790.4503 | BC17: ='ОПУ БС'!$G17/12*'ОПУ БС'!L17 -> 700.06776 | BD17: ='ОПУ БС'!$G17/12*'ОПУ БС'!M17 -> 764.54769 | BE17: ='ОПУ БС'!$G17/12*'ОПУ БС'!N17 -> 856.66187 | BF17: ='ОПУ БС'!$G17/12*'ОПУ БС'!O17 -> 856.66187 | BG17: ='ОПУ БС'!$G17/12*'ОПУ БС'!P17 -> 875.08471 | BH17: ='ОПУ БС'!$G17/12*'ОПУ БС'!Q17 -> 930.35321 | BI17: ='ОПУ БС'!$G17/12*'ОПУ БС'!R17 -> 1068.5245 | BJ17: ='ОПУ БС'!$G17/12*'ОПУ БС'!S17 -> 1040.8902 | ... BN17: ='ОПУ БС'!$G17/12*'ОПУ БС'!W17 -> 1151.4272 | BO17: =SUM(BC17:BN17) -> 11053.702 | BP17: ='ОПУ БС'!$H17/12*'ОПУ БС'!L17 -> 901.47171 | BQ17: ='ОПУ БС'!$H17/12*'ОПУ БС'!M17 -> 984.502 | BR17: ='ОПУ БС'!$H17/12*'ОПУ БС'!N17 -> 1103.1167 | BS17: ='ОПУ БС'!$H17/12*'ОПУ БС'!O17 -> 1103.1167 | BT17: ='ОПУ БС'!$H17/12*'ОПУ БС'!P17 -> 1126.8396 | BU17: ='ОПУ БС'!$H17/12*'ОПУ БС'!Q17 -> 1198.0085 | BV17: ='ОПУ БС'!$H17/12*'ОПУ БС'!R17 -> 1375.9305 | BW17: ='ОПУ БС'!$H17/12*'ОПУ БС'!S17 -> 1340.3461 | ... CA17: ='ОПУ БС'!$H17/12*'ОПУ БС'!W17 -> 1482.6837 | CB17: =SUM(BP17:CA17) -> 14233.764 | CC17: ='ОПУ БС'!$I17/12*'ОПУ БС'!L17 -> 1177.6249 | CD17: ='ОПУ БС'!$I17/12*'ОПУ БС'!M17 -> 1286.0904 | CE17: ='ОПУ БС'!$I17/12*'ОПУ БС'!N17 -> 1441.041 | CF17: ='ОПУ БС'!$I17/12*'ОПУ БС'!O17 -> 1441.041 | CG17: ='ОПУ БС'!$I17/12*'ОПУ БС'!P17 -> 1472.0312 | CH17: ='ОПУ БС'!$I17/12*'ОПУ БС'!Q17 -> 1565.0015 | CI17: ='ОПУ БС'!$I17/12*'ОПУ БС'!R17 -> 1797.4275 | CJ17: ='ОПУ БС'!$I17/12*'ОПУ БС'!S17 -> 1750.9423 | ... CN17: ='ОПУ БС'!$I17/12*'ОПУ БС'!W17 -> 1936.8831 | CO17: =SUM(CC17:CN17) -> 18594.078 | CR17: =O17-'ОПУ БС'!C17 -> 0 | CS17: =AB17-'ОПУ БС'!D17 -> 0 | CT17: =AO17-'ОПУ БС'!E17 -> 0 | CU17: =BB17-'ОПУ БС'!F17 -> 0 | CV17: =BO17-'ОПУ БС'!G17 -> 0 | CW17: =CB17-'ОПУ БС'!H17 -> 0 | CX17: =CO17-'ОПУ БС'!I17 -> 0 | DM17: =SUM(DA17:DL17) -> 0 | DZ17: =SUM(DN17:DY17) -> 0 | EM17: =SUM(EA17:EL17) -> 0 | EZ17: =SUM(EN17:EY17) -> 0 | FM17: =SUM(FA17:FL17) -> 0 | FP17: =C17 -> 363.40475 | FQ17: =D17 -> 396.87624 | FR17: =E17 -> 444.69265 | FS17: =F17 -> 444.69265 | FT17: =G17 -> 454.25594 | FU17: =H17 -> 482.94578 | FV17: =I17 -> 554.67041 | FW17: =J17 -> 540.32548 | ... GA17: =N17 -> 597.70518 | GB17: =SUM(FP17:GA17) -> 5737.9697 | GC17: =P17 -> 398.88314 | GD17: =Q17 -> 435.62237 | GE17: =R17 -> 488.107 | GF17: =S17 -> 488.107 | GG17: =T17 -> 498.60392 | GH17: =U17 -> 530.0947 | GI17: =V17 -> 608.82163 | GJ17: =W17 -> 593.07624 | ... GN17: =AA17 -> 656.05779 | GO17: =SUM(GC17:GN17) -> 6298.1548 | GP17: =AC17+DA17 -> 460.68883 | GQ17: =AD17+DB17 -> 503.12069 | GR17: =AE17+DC17 -> 563.73764 | GS17: =AF17+DD17 -> 563.73764 | GT17: =AG17+DE17 -> 575.86103 | GU17: =AH17+DF17 -> 612.2312 | GV17: =AI17+DG17 -> 703.15663 | GW17: =AJ17+DH17 -> 684.97154 | ... HA17: =AN17+DL17 -> 757.71188 | HB17: =SUM(GP17:HA17) -> 7274.0341 | HC17: =AP17+DN17 -> 556.72852 | HD17: =AQ17+DO17 -> 608.00614 | HE17: =AR17+DP17 -> 681.2599 | HF17: =AS17+DQ17 -> 681.2599 | HG17: =AT17+DR17 -> 695.91065 | HH17: =AU17+DS17 -> 739.8629 | HI17: =AV17+DT17 -> 849.74353 | HJ17: =AW17+DU17 -> 827.7674 | ... HN17: =BA17+DY17 -> 915.67191 | HO17: =SUM(HC17:HN17) -> 8790.4503 | HP17: =BC17+EA17 -> 700.06776 | HQ17: =BD17+EB17 -> 764.54769 | HR17: =BE17+EC17 -> 856.66187 | HS17: =BF17+ED17 -> 856.66187 | HT17: =BG17+EE17 -> 875.08471 | HU17: =BH17+EF17 -> 930.35321 | HV17: =BI17+EG17 -> 1068.5245 | HW17: =BJ17+EH17 -> 1040.8902 | ... IA17: =BN17+EL17 -> 1151.4272 | IB17: =SUM(HP17:IA17) -> 11053.702 | IC17: =BP17+EN17 -> 901.47171 | ID17: =BQ17+EO17 -> 984.502 | IE17: =BR17+EP17 -> 1103.1167 | IF17: =BS17+EQ17 -> 1103.1167 | IG17: =BT17+ER17 -> 1126.8396 | IH17: =BU17+ES17 -> 1198.0085 | II17: =BV17+ET17 -> 1375.9305 | IJ17: =BW17+EU17 -> 1340.3461 | ... IN17: =CA17+EY17 -> 1482.6837 | IO17: =SUM(IC17:IN17) -> 14233.764 | IP17: =CC17+FA17 -> 1177.6249 | IQ17: =CD17+FB17 -> 1286.0904 | IR17: =CE17+FC17 -> 1441.041 | IS17: =CF17+FD17 -> 1441.041 | IT17: =CG17+FE17 -> 1472.0312 | IU17: =CH17+FF17 -> 1565.0015 | IV17: =CI17+FG17 -> 1797.4275 | IW17: =CJ17+FH17 -> 1750.9423 | ... JA17: =CN17+FL17 -> 1936.8831 | JB17: =SUM(IP17:JA17) -> 18594.078 | JE17: =O17-GB17 -> 0 | JF17: =AB17-GO17 -> 0 | JG17: =AO17+DM17-HB17 -> 0 | JH17: =BB17+DZ17-HO17 -> 0 | JI17: =BO17+EM17-IB17 -> 0 | JJ17: =CB17+EZ17-IO17 -> 0 | JK17: =CO17+FM17-JB17 -> 0
B18: Медовая горчица | C18: ='ОПУ БС'!$C18/12*'ОПУ БС'!L18 -> 41.152816 | D18: ='ОПУ БС'!$C18/12*'ОПУ БС'!M18 -> 44.943207 | E18: ='ОПУ БС'!$C18/12*'ОПУ БС'!N18 -> 50.358052 | F18: ='ОПУ БС'!$C18/12*'ОПУ БС'!O18 -> 50.358052 | G18: ='ОПУ БС'!$C18/12*'ОПУ БС'!P18 -> 51.44102 | H18: ='ОПУ БС'!$C18/12*'ОПУ БС'!Q18 -> 54.689927 | I18: ='ОПУ БС'!$C18/12*'ОПУ БС'!R18 -> 62.812193 | J18: ='ОПУ БС'!$C18/12*'ОПУ БС'!S18 -> 61.18774 | ... N18: ='ОПУ БС'!$C18/12*'ОПУ БС'!W18 -> 67.685553 | O18: =SUM(C18:N18) -> 649.78131 | P18: ='ОПУ БС'!$D18/12*'ОПУ БС'!L18 -> 42.392642 | Q18: ='ОПУ БС'!$D18/12*'ОПУ БС'!M18 -> 46.297227 | R18: ='ОПУ БС'!$D18/12*'ОПУ БС'!N18 -> 51.875206 | S18: ='ОПУ БС'!$D18/12*'ОПУ БС'!O18 -> 51.875206 | T18: ='ОПУ БС'!$D18/12*'ОПУ БС'!P18 -> 52.990802 | U18: ='ОПУ БС'!$D18/12*'ОПУ БС'!Q18 -> 56.33759 | V18: ='ОПУ БС'!$D18/12*'ОПУ БС'!R18 -> 64.704559 | W18: ='ОПУ БС'!$D18/12*'ОПУ БС'!S18 -> 63.031165 | ... AA18: ='ОПУ БС'!$D18/12*'ОПУ БС'!W18 -> 69.72474 | AB18: =SUM(P18:AA18) -> 669.3575 | AC18: ='ОПУ БС'!$E18/12*'ОПУ БС'!L18 -> 43.350203 | AD18: ='ОПУ БС'!$E18/12*'ОПУ БС'!M18 -> 47.342984 | AE18: ='ОПУ БС'!$E18/12*'ОПУ БС'!N18 -> 53.046958 | AF18: ='ОПУ БС'!$E18/12*'ОПУ БС'!O18 -> 53.046958 | AG18: ='ОПУ БС'!$E18/12*'ОПУ БС'!P18 -> 54.187753 | AH18: ='ОПУ БС'!$E18/12*'ОПУ БС'!Q18 -> 57.610138 | AI18: ='ОПУ БС'!$E18/12*'ОПУ БС'!R18 -> 66.166099 | AJ18: ='ОПУ БС'!$E18/12*'ОПУ БС'!S18 -> 64.454906 | ... AN18: ='ОПУ БС'!$E18/12*'ОПУ БС'!W18 -> 71.299675 | AO18: =SUM(AC18:AN18) -> 684.47688 | AP18: ='ОПУ БС'!$F18/12*'ОПУ БС'!L18 -> 45.567034 | AQ18: ='ОПУ БС'!$F18/12*'ОПУ БС'!M18 -> 49.763998 | AR18: ='ОПУ БС'!$F18/12*'ОПУ БС'!N18 -> 55.75966 | AS18: ='ОПУ БС'!$F18/12*'ОПУ БС'!O18 -> 55.75966 | AT18: ='ОПУ БС'!$F18/12*'ОПУ БС'!P18 -> 56.958793 | AU18: ='ОПУ БС'!$F18/12*'ОПУ БС'!Q18 -> 60.55619 | AV18: ='ОПУ БС'!$F18/12*'ОПУ БС'!R18 -> 69.549684 | AW18: ='ОПУ БС'!$F18/12*'ОПУ БС'!S18 -> 67.750985 | ... BA18: ='ОПУ БС'!$F18/12*'ОПУ БС'!W18 -> 74.94578 | BB18: =SUM(AP18:BA18) -> 719.47949 | BC18: ='ОПУ БС'!$G18/12*'ОПУ БС'!L18 -> 49.451147 | BD18: ='ОПУ БС'!$G18/12*'ОПУ БС'!M18 -> 54.005857 | BE18: ='ОПУ БС'!$G18/12*'ОПУ БС'!N18 -> 60.512587 | BF18: ='ОПУ БС'!$G18/12*'ОПУ БС'!O18 -> 60.512587 | BG18: ='ОПУ БС'!$G18/12*'ОПУ БС'!P18 -> 61.813933 | BH18: ='ОПУ БС'!$G18/12*'ОПУ БС'!Q18 -> 65.717971 | BI18: ='ОПУ БС'!$G18/12*'ОПУ БС'!R18 -> 75.478066 | BJ18: ='ОПУ БС'!$G18/12*'ОПУ БС'!S18 -> 73.526047 | ... BN18: ='ОПУ БС'!$G18/12*'ОПУ БС'!W18 -> 81.334123 | BO18: =SUM(BC18:BN18) -> 780.80758 | BP18: ='ОПУ БС'!$H18/12*'ОПУ БС'!L18 -> 53.945223 | BQ18: ='ОПУ БС'!$H18/12*'ОПУ БС'!M18 -> 58.913862 | BR18: ='ОПУ БС'!$H18/12*'ОПУ БС'!N18 -> 66.011918 | BS18: ='ОПУ БС'!$H18/12*'ОПУ БС'!O18 -> 66.011918 | BT18: ='ОПУ БС'!$H18/12*'ОПУ БС'!P18 -> 67.431529 | BU18: ='ОПУ БС'!$H18/12*'ОПУ БС'!Q18 -> 71.690362 | BV18: ='ОПУ БС'!$H18/12*'ОПУ БС'!R18 -> 82.337446 | BW18: ='ОПУ БС'!$H18/12*'ОПУ БС'!S18 -> 80.208029 | ... CA18: ='ОПУ БС'!$H18/12*'ОПУ БС'!W18 -> 88.725696 | CB18: =SUM(BP18:CA18) -> 851.76668 | CC18: ='ОПУ БС'!$I18/12*'ОПУ БС'!L18 -> 61.143674 | CD18: ='ОПУ БС'!$I18/12*'ОПУ БС'!M18 -> 66.775329 | CE18: ='ОПУ БС'!$I18/12*'ОПУ БС'!N18 -> 74.820549 | CF18: ='ОПУ БС'!$I18/12*'ОПУ БС'!O18 -> 74.820549 | CG18: ='ОПУ БС'!$I18/12*'ОПУ БС'!P18 -> 76.429593 | CH18: ='ОПУ БС'!$I18/12*'ОПУ БС'!Q18 -> 81.256725 | CI18: ='ОПУ БС'!$I18/12*'ОПУ БС'!R18 -> 93.324556 | CJ18: ='ОПУ БС'!$I18/12*'ОПУ БС'!S18 -> 90.91099 | ... CN18: ='ОПУ БС'!$I18/12*'ОПУ БС'!W18 -> 100.56525 | CO18: =SUM(CC18:CN18) -> 965.42644 | CR18: =O18-'ОПУ БС'!C18 -> 0 | CS18: =AB18-'ОПУ БС'!D18 -> 0 | CT18: =AO18-'ОПУ БС'!E18 -> 0 | CU18: =BB18-'ОПУ БС'!F18 -> 0 | CV18: =BO18-'ОПУ БС'!G18 -> 0 | CW18: =CB18-'ОПУ БС'!H18 -> 0 | CX18: =CO18-'ОПУ БС'!I18 -> 0 | DM18: =SUM(DA18:DL18) -> 0 | DZ18: =SUM(DN18:DY18) -> 0 | EM18: =SUM(EA18:EL18) -> 0 | EZ18: =SUM(EN18:EY18) -> 0 | FM18: =SUM(FA18:FL18) -> 0 | FP18: =C18 -> 41.152816 | FQ18: =D18 -> 44.943207 | FR18: =E18 -> 50.358052 | FS18: =F18 -> 50.358052 | FT18: =G18 -> 51.44102 | FU18: =H18 -> 54.689927 | FV18: =I18 -> 62.812193 | FW18: =J18 -> 61.18774 | ... GA18: =N18 -> 67.685553 | GB18: =SUM(FP18:GA18) -> 649.78131 | GC18: =P18 -> 42.392642 | GD18: =Q18 -> 46.297227 | GE18: =R18 -> 51.875206 | GF18: =S18 -> 51.875206 | GG18: =T18 -> 52.990802 | GH18: =U18 -> 56.33759 | GI18: =V18 -> 64.704559 | GJ18: =W18 -> 63.031165 | ... GN18: =AA18 -> 69.72474 | GO18: =SUM(GC18:GN18) -> 669.3575 | GP18: =AC18+DA18 -> 43.350203 | GQ18: =AD18+DB18 -> 47.342984 | GR18: =AE18+DC18 -> 53.046958 | GS18: =AF18+DD18 -> 53.046958 | GT18: =AG18+DE18 -> 54.187753 | GU18: =AH18+DF18 -> 57.610138 | GV18: =AI18+DG18 -> 66.166099 | GW18: =AJ18+DH18 -> 64.454906 | ... HA18: =AN18+DL18 -> 71.299675 | HB18: =SUM(GP18:HA18) -> 684.47688 | HC18: =AP18+DN18 -> 45.567034 | HD18: =AQ18+DO18 -> 49.763998 | HE18: =AR18+DP18 -> 55.75966 | HF18: =AS18+DQ18 -> 55.75966 | HG18: =AT18+DR18 -> 56.958793 | HH18: =AU18+DS18 -> 60.55619 | HI18: =AV18+DT18 -> 69.549684 | HJ18: =AW18+DU18 -> 67.750985 | ... HN18: =BA18+DY18 -> 74.94578 | HO18: =SUM(HC18:HN18) -> 719.47949 | HP18: =BC18+EA18 -> 49.451147 | HQ18: =BD18+EB18 -> 54.005857 | HR18: =BE18+EC18 -> 60.512587 | HS18: =BF18+ED18 -> 60.512587 | HT18: =BG18+EE18 -> 61.813933 | HU18: =BH18+EF18 -> 65.717971 | HV18: =BI18+EG18 -> 75.478066 | HW18: =BJ18+EH18 -> 73.526047 | ... IA18: =BN18+EL18 -> 81.334123 | IB18: =SUM(HP18:IA18) -> 780.80758 | IC18: =BP18+EN18 -> 53.945223 | ID18: =BQ18+EO18 -> 58.913862 | IE18: =BR18+EP18 -> 66.011918 | IF18: =BS18+EQ18 -> 66.011918 | IG18: =BT18+ER18 -> 67.431529 | IH18: =BU18+ES18 -> 71.690362 | II18: =BV18+ET18 -> 82.337446 | IJ18: =BW18+EU18 -> 80.208029 | ... IN18: =CA18+EY18 -> 88.725696 | IO18: =SUM(IC18:IN18) -> 851.76668 | IP18: =CC18+FA18 -> 61.143674 | IQ18: =CD18+FB18 -> 66.775329 | IR18: =CE18+FC18 -> 74.820549 | IS18: =CF18+FD18 -> 74.820549 | IT18: =CG18+FE18 -> 76.429593 | IU18: =CH18+FF18 -> 81.256725 | IV18: =CI18+FG18 -> 93.324556 | IW18: =CJ18+FH18 -> 90.91099 | ... JA18: =CN18+FL18 -> 100.56525 | JB18: =SUM(IP18:JA18) -> 965.42644 | JE18: =O18-GB18 -> 0 | JF18: =AB18-GO18 -> 0 | JG18: =AO18+DM18-HB18 -> 0 | JH18: =BB18+DZ18-HO18 -> 0 | JI18: =BO18+EM18-IB18 -> 0 | JJ18: =CB18+EZ18-IO18 -> 0 | JK18: =CO18+FM18-JB18 -> 0
B19: РЕСТОРАНЫ | C19: =C20+C24 -> 17957.409 | D19: =D20+D24 -> 19971.579 | E19: =E20+E24 -> 22363.271 | F19: =F20+F24 -> 22334.851 | G19: =G20+G24 -> 22824.301 | H19: =H20+H24 -> 24267.919 | I19: =I20+I24 -> 27460.889 | J19: =J20+J24 -> 27153.485 | ... N19: =N20+N24 -> 30037.041 | O19: =SUM(C19:N19) -> 288355.59 | P19: =P20+P24 -> 24165.17 | Q19: =Q20+Q24 -> 26819.906 | R19: =R20+R24 -> 30041.941 | S19: =S20+S24 -> 30010.741 | T19: =T20+T24 -> 30664.392 | U19: =U20+U24 -> 32605.148 | V19: =V20+V24 -> 36947.19 | W19: =W20+W24 -> 36482.319 | ... AA19: =AA20+AA24 -> 40356.548 | AB19: =SUM(P19:AA19) -> 387422.86 | AC19: =AC20+AC24 -> 34314.494 | AD19: =AD20+AD24 -> 38060.486 | AE19: =AE20+AE24 -> 42635.791 | AF19: =AF20+AF24 -> 42597.576 | AG19: =AG20+AG24 -> 43521.137 | AH19: =AH20+AH24 -> 46276.94 | AI19: =AI20+AI24 -> 52464.793 | AJ19: =AJ20+AJ24 -> 51779.989 | ... AN19: =AN20+AN24 -> 57278.749 | AO19: =SUM(AC19:AN19) -> 549875.99 | AP19: =AP20+AP24 -> 46749.097 | AQ19: =AQ20+AQ24 -> 51829.619 | AR19: =AR20+AR24 -> 58059.78 | AS19: =AS20+AS24 -> 58016.041 | AT19: =AT20+AT24 -> 59269.526 | AU19: =AU20+AU24 -> 63024.037 | AV19: =AV20+AV24 -> 71476.201 | AW19: =AW20+AW24 -> 70518.669 | ... BA19: =BA20+BA24 -> 78007.378 | BB19: =SUM(AP19:BA19) -> 748870.82 | BC19: =BC20+BC24 -> 61871.332 | BD19: =BD20+BD24 -> 68568.422 | BE19: =BE20+BE24 -> 76810.993 | BF19: =BF20+BF24 -> 76760.227 | BG19: =BG20+BG24 -> 78414.369 | BH19: =BH20+BH24 -> 83383.235 | BI19: =BI20+BI24 -> 94595.645 | BJ19: =BJ20+BJ24 -> 93298.953 | ... BN19: =BN20+BN24 -> 103206.81 | BO19: =SUM(BC19:BN19) -> 990785.34 | BP19: =BP20+BP24 -> 79155.608 | BQ19: =BQ20+BQ24 -> 87689.047 | BR19: =BR20+BR24 -> 98231.074 | BS19: =BS20+BS24 -> 98172.636 | BT19: =BT20+BT24 -> 100283.78 | BU19: =BU20+BU24 -> 106640.11 | BV19: =BV20+BV24 -> 121018.75 | BW19: =BW20+BW24 -> 119321.42 | ... CA19: =CA20+CA24 -> 131992.72 | CB19: =SUM(BP19:CA19) -> 1267130.1 | CC19: =CC20+CC24 -> 99351.855 | CD19: =CD20+CD24 -> 110031.88 | CE19: =CE20+CE24 -> 123261.28 | CF19: =CF20+CF24 -> 123192.39 | CG19: =CG20+CG24 -> 125837.99 | CH19: =CH20+CH24 -> 133815.55 | CI19: =CI20+CI24 -> 151893.09 | CJ19: =CJ20+CJ24 -> 149728.39 | ... CN19: =CN20+CN24 -> 165628.75 | CO19: =SUM(CC19:CN19) -> 1590036 | CR19: =O19-'ОПУ БС'!C19 -> 0 | CS19: =AB19-'ОПУ БС'!D19 -> 0 | CT19: =AO19-'ОПУ БС'!E19 -> 0 | CU19: =BB19-'ОПУ БС'!F19 -> 0 | CV19: =BO19-'ОПУ БС'!G19 -> 0 | CW19: =CB19-'ОПУ БС'!H19 -> 0 | CX19: =CO19-'ОПУ БС'!I19 -> 0 | DA19: =DA20+DA24 -> 0 | DB19: =DB20+DB24 -> 0 | DC19: =DC20+DC24 -> 0 | DD19: =DD20+DD24 -> 0 | DE19: =DE20+DE24 -> 0 | DF19: =DF20+DF24 -> 0 | DG19: =DG20+DG24 -> 0 | DH19: =DH20+DH24 -> 0 | ... DL19: =DL20+DL24 -> 0 | DM19: =SUM(DA19:DL19) -> 0 | DN19: =DN20+DN24 -> 0 | DO19: =DO20+DO24 -> 0 | DP19: =DP20+DP24 -> 0 | DQ19: =DQ20+DQ24 -> 0 | DR19: =DR20+DR24 -> 0 | DS19: =DS20+DS24 -> 0 | DT19: =DT20+DT24 -> 0 | DU19: =DU20+DU24 -> 0 | ... DY19: =DY20+DY24 -> 0 | DZ19: =SUM(DN19:DY19) -> 0 | EA19: =EA20+EA24 -> 0 | EB19: =EB20+EB24 -> 0 | EC19: =EC20+EC24 -> 0 | ED19: =ED20+ED24 -> 0 | EE19: =EE20+EE24 -> 0 | EF19: =EF20+EF24 -> 0 | EG19: =EG20+EG24 -> 0 | EH19: =EH20+EH24 -> 0 | ... EL19: =EL20+EL24 -> 0 | EM19: =SUM(EA19:EL19) -> 0 | EN19: =EN20+EN24 -> 0 | EO19: =EO20+EO24 -> 0 | EP19: =EP20+EP24 -> 0 | EQ19: =EQ20+EQ24 -> 0 | ER19: =ER20+ER24 -> 0 | ES19: =ES20+ES24 -> 0 | ET19: =ET20+ET24 -> 0 | EU19: =EU20+EU24 -> 0 | ... EY19: =EY20+EY24 -> 0 | EZ19: =SUM(EN19:EY19) -> 0 | FA19: =FA20+FA24 -> 0 | FB19: =FB20+FB24 -> 0 | FC19: =FC20+FC24 -> 0 | FD19: =FD20+FD24 -> 0 | FE19: =FE20+FE24 -> 0 | FF19: =FF20+FF24 -> 0 | FG19: =FG20+FG24 -> 0 | FH19: =FH20+FH24 -> 0 | ... FL19: =FL20+FL24 -> 0 | FM19: =SUM(FA19:FL19) -> 0 | FP19: =FP20+FP24 -> 17957.409 | FQ19: =FQ20+FQ24 -> 19971.579 | FR19: =FR20+FR24 -> 22363.271 | FS19: =FS20+FS24 -> 22334.851 | FT19: =FT20+FT24 -> 22824.301 | FU19: =FU20+FU24 -> 24267.919 | FV19: =FV20+FV24 -> 27460.889 | FW19: =FW20+FW24 -> 27153.485 | ... GA19: =GA20+GA24 -> 30037.041 | GB19: =SUM(FP19:GA19) -> 288355.59 | GC19: =GC20+GC24 -> 24165.17 | GD19: =GD20+GD24 -> 26819.906 | GE19: =GE20+GE24 -> 30041.941 | GF19: =GF20+GF24 -> 30010.741 | GG19: =GG20+GG24 -> 30664.392 | GH19: =GH20+GH24 -> 32605.148 | GI19: =GI20+GI24 -> 36947.19 | GJ19: =GJ20+GJ24 -> 36482.319 | ... GN19: =GN20+GN24 -> 40356.548 | GO19: =SUM(GC19:GN19) -> 387422.86 | GP19: =GP20+GP24 -> 34314.494 | GQ19: =GQ20+GQ24 -> 38060.486 | GR19: =GR20+GR24 -> 42635.791 | GS19: =GS20+GS24 -> 42597.576 | GT19: =GT20+GT24 -> 43521.137 | GU19: =GU20+GU24 -> 46276.94 | GV19: =GV20+GV24 -> 52464.793 | GW19: =GW20+GW24 -> 51779.989 | ... HA19: =HA20+HA24 -> 57278.749 | HB19: =SUM(GP19:HA19) -> 549875.99 | HC19: =HC20+HC24 -> 46749.097 | HD19: =HD20+HD24 -> 51829.619 | HE19: =HE20+HE24 -> 58059.78 | HF19: =HF20+HF24 -> 58016.041 | HG19: =HG20+HG24 -> 59269.526 | HH19: =HH20+HH24 -> 63024.037 | HI19: =HI20+HI24 -> 71476.201 | HJ19: =HJ20+HJ24 -> 70518.669 | ... HN19: =HN20+HN24 -> 78007.378 | HO19: =SUM(HC19:HN19) -> 748870.82 | HP19: =HP20+HP24 -> 61871.332 | HQ19: =HQ20+HQ24 -> 68568.422 | HR19: =HR20+HR24 -> 76810.993 | HS19: =HS20+HS24 -> 76760.227 | HT19: =HT20+HT24 -> 78414.369 | HU19: =HU20+HU24 -> 83383.235 | HV19: =HV20+HV24 -> 94595.645 | HW19: =HW20+HW24 -> 93298.953 | ... IA19: =IA20+IA24 -> 103206.81 | IB19: =SUM(HP19:IA19) -> 990785.34 | IC19: =IC20+IC24 -> 79155.608 | ID19: =ID20+ID24 -> 87689.047 | IE19: =IE20+IE24 -> 98231.074 | IF19: =IF20+IF24 -> 98172.636 | IG19: =IG20+IG24 -> 100283.78 | IH19: =IH20+IH24 -> 106640.11 | II19: =II20+II24 -> 121018.75 | IJ19: =IJ20+IJ24 -> 119321.42 | ... IN19: =IN20+IN24 -> 131992.72 | IO19: =SUM(IC19:IN19) -> 1267130.1 | IP19: =IP20+IP24 -> 99351.855 | IQ19: =IQ20+IQ24 -> 110031.88 | IR19: =IR20+IR24 -> 123261.28 | IS19: =IS20+IS24 -> 123192.39 | IT19: =IT20+IT24 -> 125837.99 | IU19: =IU20+IU24 -> 133815.55 | IV19: =IV20+IV24 -> 151893.09 | IW19: =IW20+IW24 -> 149728.39 | ... JA19: =JA20+JA24 -> 165628.75 | JB19: =SUM(IP19:JA19) -> 1590036 | JE19: =O19-GB19 -> 0 | JF19: =AB19-GO19 -> 0 | JG19: =AO19+DM19-HB19 -> 0 | JH19: =BB19+DZ19-HO19 -> 0 | JI19: =BO19+EM19-IB19 -> 0 | JJ19: =CB19+EZ19-IO19 -> 0 | JK19: =CO19+FM19-JB19 -> 0
B20: Сухари | C20: =SUM(C21:C23) -> 15330.89 | D20: =SUM(D21:D23) -> 16742.946 | E20: =SUM(E21:E23) -> 18760.168 | F20: =SUM(F21:F23) -> 18760.168 | G20: =SUM(G21:G23) -> 19163.613 | H20: =SUM(H21:H23) -> 20373.946 | I20: =SUM(I21:I23) -> 23399.78 | J20: =SUM(J21:J23) -> 22794.613 | ... N20: =SUM(N21:N23) -> 25215.28 | O20: =SUM(C20:N20) -> 242066.69 | P20: =SUM(P21:P23) -> 21152.328 | Q20: =SUM(Q21:Q23) -> 23100.569 | R20: =SUM(R21:R23) -> 25883.77 | S20: =SUM(S21:S23) -> 25883.77 | T20: =SUM(T21:T23) -> 26440.41 | U20: =SUM(U21:U23) -> 28110.331 | V20: =SUM(V21:V23) -> 32285.133 | W20: =SUM(W21:W23) -> 31450.172 | ... AA20: =SUM(AA21:AA23) -> 34790.014 | AB20: =SUM(P20:AA20) -> 333984.13 | AC20: =SUM(AC21:AC23) -> 30325.375 | AD20: =SUM(AD21:AD23) -> 33118.501 | AE20: =SUM(AE21:AE23) -> 37108.682 | AF20: =SUM(AF21:AF23) -> 37108.682 | AG20: =SUM(AG21:AG23) -> 37906.718 | AH20: =SUM(AH21:AH23) -> 40300.827 | AI20: =SUM(AI21:AI23) -> 46286.098 | AJ20: =SUM(AJ21:AJ23) -> 45089.044 | ... AN20: =SUM(AN21:AN23) -> 49877.261 | AO20: =SUM(AC20:AN20) -> 478821.7 | AP20: =SUM(AP21:AP23) -> 41668.464 | AQ20: =SUM(AQ21:AQ23) -> 45506.349 | AR20: =SUM(AR21:AR23) -> 50989.042 | AS20: =SUM(AS21:AS23) -> 50989.042 | AT20: =SUM(AT21:AT23) -> 52085.58 | AU20: =SUM(AU21:AU23) -> 55375.196 | AV20: =SUM(AV21:AV23) -> 63599.235 | AW20: =SUM(AW21:AW23) -> 61954.427 | ... BA20: =SUM(BA21:BA23) -> 68533.658 | BB20: =SUM(AP20:BA20) -> 657923.12 | BC20: =SUM(BC21:BC23) -> 55462.879 | BD20: =SUM(BD21:BD23) -> 60571.302 | BE20: =SUM(BE21:BE23) -> 67869.049 | BF20: =SUM(BF21:BF23) -> 67869.049 | BG20: =SUM(BG21:BG23) -> 69328.598 | BH20: =SUM(BH21:BH23) -> 73707.246 | BI20: =SUM(BI21:BI23) -> 84653.867 | BJ20: =SUM(BJ21:BJ23) -> 82464.543 | ... BN20: =SUM(BN21:BN23) -> 91221.84 | BO20: =SUM(BC20:BN20) -> 875729.66 | BP20: =SUM(BP21:BP23) -> 71273.858 | BQ20: =SUM(BQ21:BQ23) -> 77838.556 | BR20: =SUM(BR21:BR23) -> 87216.695 | BS20: =SUM(BS21:BS23) -> 87216.695 | BT20: =SUM(BT21:BT23) -> 89092.323 | BU20: =SUM(BU21:BU23) -> 94719.206 | BV20: =SUM(BV21:BV23) -> 108786.41 | BW20: =SUM(BW21:BW23) -> 105972.97 | ... CA20: =SUM(CA21:CA23) -> 117226.74 | CB20: =SUM(BP20:CA20) -> 1125376.7 | CC20: =SUM(CC21:CC23) -> 89688.924 | CD20: =SUM(CD21:CD23) -> 97949.746 | CE20: =SUM(CE21:CE23) -> 109750.92 | CF20: =SUM(CF21:CF23) -> 109750.92 | CG20: =SUM(CG21:CG23) -> 112111.16 | CH20: =SUM(CH21:CH23) -> 119191.86 | CI20: =SUM(CI21:CI23) -> 136893.62 | CJ20: =SUM(CJ21:CJ23) -> 133353.27 | ... CN20: =SUM(CN21:CN23) -> 147514.68 | CO20: =SUM(CC20:CN20) -> 1416140.9 | CR20: =O20-'ОПУ БС'!C20 -> 0 | CS20: =AB20-'ОПУ БС'!D20 -> 0 | CT20: =AO20-'ОПУ БС'!E20 -> 0 | CU20: =BB20-'ОПУ БС'!F20 -> 0 | CV20: =BO20-'ОПУ БС'!G20 -> 0 | CW20: =CB20-'ОПУ БС'!H20 -> 0 | CX20: =CO20-'ОПУ БС'!I20 -> 0 | DA20: =SUM(DA21:DA23) -> 0 | DB20: =SUM(DB21:DB23) -> 0 | DC20: =SUM(DC21:DC23) -> 0 | DD20: =SUM(DD21:DD23) -> 0 | DE20: =SUM(DE21:DE23) -> 0 | DF20: =SUM(DF21:DF23) -> 0 | DG20: =SUM(DG21:DG23) -> 0 | DH20: =SUM(DH21:DH23) -> 0 | ... DL20: =SUM(DL21:DL23) -> 0 | DM20: =SUM(DA20:DL20) -> 0 | DN20: =SUM(DN21:DN23) -> 0 | DO20: =SUM(DO21:DO23) -> 0 | DP20: =SUM(DP21:DP23) -> 0 | DQ20: =SUM(DQ21:DQ23) -> 0 | DR20: =SUM(DR21:DR23) -> 0 | DS20: =SUM(DS21:DS23) -> 0 | DT20: =SUM(DT21:DT23) -> 0 | DU20: =SUM(DU21:DU23) -> 0 | ... DY20: =SUM(DY21:DY23) -> 0 | DZ20: =SUM(DN20:DY20) -> 0 | EA20: =SUM(EA21:EA23) -> 0 | EB20: =SUM(EB21:EB23) -> 0 | EC20: =SUM(EC21:EC23) -> 0 | ED20: =SUM(ED21:ED23) -> 0 | EE20: =SUM(EE21:EE23) -> 0 | EF20: =SUM(EF21:EF23) -> 0 | EG20: =SUM(EG21:EG23) -> 0 | EH20: =SUM(EH21:EH23) -> 0 | ... EL20: =SUM(EL21:EL23) -> 0 | EM20: =SUM(EA20:EL20) -> 0 | EN20: =SUM(EN21:EN23) -> 0 | EO20: =SUM(EO21:EO23) -> 0 | EP20: =SUM(EP21:EP23) -> 0 | EQ20: =SUM(EQ21:EQ23) -> 0 | ER20: =SUM(ER21:ER23) -> 0 | ES20: =SUM(ES21:ES23) -> 0 | ET20: =SUM(ET21:ET23) -> 0 | EU20: =SUM(EU21:EU23) -> 0 | ... EY20: =SUM(EY21:EY23) -> 0 | EZ20: =SUM(EN20:EY20) -> 0 | FA20: =SUM(FA21:FA23) -> 0 | FB20: =SUM(FB21:FB23) -> 0 | FC20: =SUM(FC21:FC23) -> 0 | FD20: =SUM(FD21:FD23) -> 0 | FE20: =SUM(FE21:FE23) -> 0 | FF20: =SUM(FF21:FF23) -> 0 | FG20: =SUM(FG21:FG23) -> 0 | FH20: =SUM(FH21:FH23) -> 0 | ... FL20: =SUM(FL21:FL23) -> 0 | FM20: =SUM(FA20:FL20) -> 0 | FP20: =SUM(FP21:FP23) -> 15330.89 | FQ20: =SUM(FQ21:FQ23) -> 16742.946 | FR20: =SUM(FR21:FR23) -> 18760.168 | FS20: =SUM(FS21:FS23) -> 18760.168 | FT20: =SUM(FT21:FT23) -> 19163.613 | FU20: =SUM(FU21:FU23) -> 20373.946 | FV20: =SUM(FV21:FV23) -> 23399.78 | FW20: =SUM(FW21:FW23) -> 22794.613 | ... GA20: =SUM(GA21:GA23) -> 25215.28 | GB20: =SUM(FP20:GA20) -> 242066.69 | GC20: =SUM(GC21:GC23) -> 21152.328 | GD20: =SUM(GD21:GD23) -> 23100.569 | GE20: =SUM(GE21:GE23) -> 25883.77 | GF20: =SUM(GF21:GF23) -> 25883.77 | GG20: =SUM(GG21:GG23) -> 26440.41 | GH20: =SUM(GH21:GH23) -> 28110.331 | GI20: =SUM(GI21:GI23) -> 32285.133 | GJ20: =SUM(GJ21:GJ23) -> 31450.172 | ... GN20: =SUM(GN21:GN23) -> 34790.014 | GO20: =SUM(GC20:GN20) -> 333984.13 | GP20: =SUM(GP21:GP23) -> 30325.375 | GQ20: =SUM(GQ21:GQ23) -> 33118.501 | GR20: =SUM(GR21:GR23) -> 37108.682 | GS20: =SUM(GS21:GS23) -> 37108.682 | GT20: =SUM(GT21:GT23) -> 37906.718 | GU20: =SUM(GU21:GU23) -> 40300.827 | GV20: =SUM(GV21:GV23) -> 46286.098 | GW20: =SUM(GW21:GW23) -> 45089.044 | ... HA20: =SUM(HA21:HA23) -> 49877.261 | HB20: =SUM(GP20:HA20) -> 478821.7 | HC20: =SUM(HC21:HC23) -> 41668.464 | HD20: =SUM(HD21:HD23) -> 45506.349 | HE20: =SUM(HE21:HE23) -> 50989.042 | HF20: =SUM(HF21:HF23) -> 50989.042 | HG20: =SUM(HG21:HG23) -> 52085.58 | HH20: =SUM(HH21:HH23) -> 55375.196 | HI20: =SUM(HI21:HI23) -> 63599.235 | HJ20: =SUM(HJ21:HJ23) -> 61954.427 | ... HN20: =SUM(HN21:HN23) -> 68533.658 | HO20: =SUM(HC20:HN20) -> 657923.12 | HP20: =SUM(HP21:HP23) -> 55462.879 | HQ20: =SUM(HQ21:HQ23) -> 60571.302 | HR20: =SUM(HR21:HR23) -> 67869.049 | HS20: =SUM(HS21:HS23) -> 67869.049 | HT20: =SUM(HT21:HT23) -> 69328.598 | HU20: =SUM(HU21:HU23) -> 73707.246 | HV20: =SUM(HV21:HV23) -> 84653.867 | HW20: =SUM(HW21:HW23) -> 82464.543 | ... IA20: =SUM(IA21:IA23) -> 91221.84 | IB20: =SUM(HP20:IA20) -> 875729.66 | IC20: =SUM(IC21:IC23) -> 71273.858 | ID20: =SUM(ID21:ID23) -> 77838.556 | IE20: =SUM(IE21:IE23) -> 87216.695 | IF20: =SUM(IF21:IF23) -> 87216.695 | IG20: =SUM(IG21:IG23) -> 89092.323 | IH20: =SUM(IH21:IH23) -> 94719.206 | II20: =SUM(II21:II23) -> 108786.41 | IJ20: =SUM(IJ21:IJ23) -> 105972.97 | ... IN20: =SUM(IN21:IN23) -> 117226.74 | IO20: =SUM(IC20:IN20) -> 1125376.7 | IP20: =SUM(IP21:IP23) -> 89688.924 | IQ20: =SUM(IQ21:IQ23) -> 97949.746 | IR20: =SUM(IR21:IR23) -> 109750.92 | IS20: =SUM(IS21:IS23) -> 109750.92 | IT20: =SUM(IT21:IT23) -> 112111.16 | IU20: =SUM(IU21:IU23) -> 119191.86 | IV20: =SUM(IV21:IV23) -> 136893.62 | IW20: =SUM(IW21:IW23) -> 133353.27 | ... JA20: =SUM(JA21:JA23) -> 147514.68 | JB20: =SUM(IP20:JA20) -> 1416140.9 | JE20: =O20-GB20 -> 0 | JF20: =AB20-GO20 -> 0 | JG20: =AO20+DM20-HB20 -> 0 | JH20: =BB20+DZ20-HO20 -> 0 | JI20: =BO20+EM20-IB20 -> 0 | JJ20: =CB20+EZ20-IO20 -> 0 | JK20: =CO20+FM20-JB20 -> 0
B21: Классика | C21: ='ОПУ БС'!$C21/12*'ОПУ БС'!L21 -> 7234.8528 | D21: ='ОПУ БС'!$C21/12*'ОПУ БС'!M21 -> 7901.2208 | E21: ='ОПУ БС'!$C21/12*'ОПУ БС'!N21 -> 8853.1751 | F21: ='ОПУ БС'!$C21/12*'ОПУ БС'!O21 -> 8853.1751 | G21: ='ОПУ БС'!$C21/12*'ОПУ БС'!P21 -> 9043.566 | H21: ='ОПУ БС'!$C21/12*'ОПУ БС'!Q21 -> 9614.7386 | I21: ='ОПУ БС'!$C21/12*'ОПУ БС'!R21 -> 11042.67 | J21: ='ОПУ БС'!$C21/12*'ОПУ БС'!S21 -> 10757.084 | ... N21: ='ОПУ БС'!$C21/12*'ОПУ БС'!W21 -> 11899.429 | O21: =SUM(C21:N21) -> 114234.52 | P21: ='ОПУ БС'!$D21/12*'ОПУ БС'!L21 -> 10055.66 | Q21: ='ОПУ БС'!$D21/12*'ОПУ БС'!M21 -> 10981.839 | R21: ='ОПУ БС'!$D21/12*'ОПУ БС'!N21 -> 12304.953 | S21: ='ОПУ БС'!$D21/12*'ОПУ БС'!O21 -> 12304.953 | T21: ='ОПУ БС'!$D21/12*'ОПУ БС'!P21 -> 12569.575 | U21: ='ОПУ БС'!$D21/12*'ОПУ БС'!Q21 -> 13363.443 | V21: ='ОПУ БС'!$D21/12*'ОПУ БС'!R21 -> 15348.113 | W21: ='ОПУ БС'!$D21/12*'ОПУ БС'!S21 -> 14951.179 | ... AA21: ='ОПУ БС'!$D21/12*'ОПУ БС'!W21 -> 16538.915 | AB21: =SUM(P21:AA21) -> 158773.58 | AC21: ='ОПУ БС'!$E21/12*'ОПУ БС'!L21 -> 14879.95 | AD21: ='ОПУ БС'!$E21/12*'ОПУ БС'!M21 -> 16250.471 | AE21: ='ОПУ БС'!$E21/12*'ОПУ БС'!N21 -> 18208.359 | AF21: ='ОПУ БС'!$E21/12*'ОПУ БС'!O21 -> 18208.359 | AG21: ='ОПУ БС'!$E21/12*'ОПУ БС'!P21 -> 18599.937 | AH21: ='ОПУ БС'!$E21/12*'ОПУ БС'!Q21 -> 19774.67 | AI21: ='ОПУ БС'!$E21/12*'ОПУ БС'!R21 -> 22711.502 | AJ21: ='ОПУ БС'!$E21/12*'ОПУ БС'!S21 -> 22124.136 | ... AN21: ='ОПУ БС'!$E21/12*'ОПУ БС'!W21 -> 24473.601 | AO21: =SUM(AC21:AN21) -> 234946.57 | AP21: ='ОПУ БС'!$F21/12*'ОПУ БС'!L21 -> 21014.75 | AQ21: ='ОПУ БС'!$F21/12*'ОПУ БС'!M21 -> 22950.319 | AR21: ='ОПУ БС'!$F21/12*'ОПУ БС'!N21 -> 25715.417 | AS21: ='ОПУ БС'!$F21/12*'ОПУ БС'!O21 -> 25715.417 | AT21: ='ОПУ БС'!$F21/12*'ОПУ БС'!P21 -> 26268.437 | AU21: ='ОПУ БС'!$F21/12*'ОПУ БС'!Q21 -> 27927.496 | AV21: ='ОПУ БС'!$F21/12*'ОПУ БС'!R21 -> 32075.144 | AW21: ='ОПУ БС'!$F21/12*'ОПУ БС'!S21 -> 31245.615 | ... BA21: ='ОПУ БС'!$F21/12*'ОПУ БС'!W21 -> 34563.733 | BB21: =SUM(AP21:BA21) -> 331811.84 | BC21: ='ОПУ БС'!$G21/12*'ОПУ БС'!L21 -> 28631.742 | BD21: ='ОПУ БС'!$G21/12*'ОПУ БС'!M21 -> 31268.876 | BE21: ='ОПУ БС'!$G21/12*'ОПУ БС'!N21 -> 35036.21 | BF21: ='ОПУ БС'!$G21/12*'ОПУ БС'!O21 -> 35036.21 | BG21: ='ОПУ БС'!$G21/12*'ОПУ БС'!P21 -> 35789.677 | BH21: ='ОПУ БС'!$G21/12*'ОПУ БС'!Q21 -> 38050.078 | BI21: ='ОПУ БС'!$G21/12*'ОПУ БС'!R21 -> 43701.08 | BJ21: ='ОПУ БС'!$G21/12*'ОПУ БС'!S21 -> 42570.879 | ... BN21: ='ОПУ БС'!$G21/12*'ОПУ БС'!W21 -> 47091.681 | BO21: =SUM(BC21:BN21) -> 452080.13 | BP21: ='ОПУ БС'!$H21/12*'ОПУ БС'!L21 -> 37550.749 | BQ21: ='ОПУ БС'!$H21/12*'ОПУ БС'!M21 -> 41009.37 | BR21: ='ОПУ БС'!$H21/12*'ОПУ БС'!N21 -> 45950.258 | BS21: ='ОПУ БС'!$H21/12*'ОПУ БС'!O21 -> 45950.258 | BT21: ='ОПУ БС'!$H21/12*'ОПУ БС'!P21 -> 46938.436 | BU21: ='ОПУ БС'!$H21/12*'ОПУ БС'!Q21 -> 49902.969 | BV21: ='ОПУ БС'!$H21/12*'ОПУ БС'!R21 -> 57314.301 | BW21: ='ОПУ БС'!$H21/12*'ОПУ БС'!S21 -> 55832.034 | ... CA21: ='ОПУ БС'!$H21/12*'ОПУ БС'!W21 -> 61761.1 | CB21: =SUM(BP21:CA21) -> 592906.56 | CC21: ='ОПУ БС'!$I21/12*'ОПУ БС'!L21 -> 48134.327 | CD21: ='ОПУ БС'!$I21/12*'ОПУ БС'!M21 -> 52567.752 | CE21: ='ОПУ БС'!$I21/12*'ОПУ БС'!N21 -> 58901.216 | CF21: ='ОПУ БС'!$I21/12*'ОПУ БС'!O21 -> 58901.216 | CG21: ='ОПУ БС'!$I21/12*'ОПУ БС'!P21 -> 60167.909 | CH21: ='ОПУ БС'!$I21/12*'ОПУ БС'!Q21 -> 63967.988 | CI21: ='ОПУ БС'!$I21/12*'ОПУ БС'!R21 -> 73468.184 | CJ21: ='ОПУ БС'!$I21/12*'ОПУ БС'!S21 -> 71568.145 | ... CN21: ='ОПУ БС'!$I21/12*'ОПУ БС'!W21 -> 79168.302 | CO21: =SUM(CC21:CN21) -> 760015.7 | CR21: =O21-'ОПУ БС'!C21 -> 0 | CS21: =AB21-'ОПУ БС'!D21 -> 0 | CT21: =AO21-'ОПУ БС'!E21 -> 0 | CU21: =BB21-'ОПУ БС'!F21 -> 0 | CV21: =BO21-'ОПУ БС'!G21 -> 0 | CW21: =CB21-'ОПУ БС'!H21 -> 0 | CX21: =CO21-'ОПУ БС'!I21 -> 0 | DM21: =SUM(DA21:DL21) -> 0 | DZ21: =SUM(DN21:DY21) -> 0 | EM21: =SUM(EA21:EL21) -> 0 | EZ21: =SUM(EN21:EY21) -> 0 | FM21: =SUM(FA21:FL21) -> 0 | FP21: =C21 -> 7234.8528 | FQ21: =D21 -> 7901.2208 | FR21: =E21 -> 8853.1751 | FS21: =F21 -> 8853.1751 | FT21: =G21 -> 9043.566 | FU21: =H21 -> 9614.7386 | FV21: =I21 -> 11042.67 | FW21: =J21 -> 10757.084 | ... GA21: =N21 -> 11899.429 | GB21: =SUM(FP21:GA21) -> 114234.52 | GC21: =P21 -> 10055.66 | GD21: =Q21 -> 10981.839 | GE21: =R21 -> 12304.953 | GF21: =S21 -> 12304.953 | GG21: =T21 -> 12569.575 | GH21: =U21 -> 13363.443 | GI21: =V21 -> 15348.113 | GJ21: =W21 -> 14951.179 | ... GN21: =AA21 -> 16538.915 | GO21: =SUM(GC21:GN21) -> 158773.58 | GP21: =AC21+DA21 -> 14879.95 | GQ21: =AD21+DB21 -> 16250.471 | GR21: =AE21+DC21 -> 18208.359 | GS21: =AF21+DD21 -> 18208.359 | GT21: =AG21+DE21 -> 18599.937 | GU21: =AH21+DF21 -> 19774.67 | GV21: =AI21+DG21 -> 22711.502 | GW21: =AJ21+DH21 -> 22124.136 | ... HA21: =AN21+DL21 -> 24473.601 | HB21: =SUM(GP21:HA21) -> 234946.57 | HC21: =AP21+DN21 -> 21014.75 | HD21: =AQ21+DO21 -> 22950.319 | HE21: =AR21+DP21 -> 25715.417 | HF21: =AS21+DQ21 -> 25715.417 | HG21: =AT21+DR21 -> 26268.437 | HH21: =AU21+DS21 -> 27927.496 | HI21: =AV21+DT21 -> 32075.144 | HJ21: =AW21+DU21 -> 31245.615 | ... HN21: =BA21+DY21 -> 34563.733 | HO21: =SUM(HC21:HN21) -> 331811.84 | HP21: =BC21+EA21 -> 28631.742 | HQ21: =BD21+EB21 -> 31268.876 | HR21: =BE21+EC21 -> 35036.21 | HS21: =BF21+ED21 -> 35036.21 | HT21: =BG21+EE21 -> 35789.677 | HU21: =BH21+EF21 -> 38050.078 | HV21: =BI21+EG21 -> 43701.08 | HW21: =BJ21+EH21 -> 42570.879 | ... IA21: =BN21+EL21 -> 47091.681 | IB21: =SUM(HP21:IA21) -> 452080.13 | IC21: =BP21+EN21 -> 37550.749 | ID21: =BQ21+EO21 -> 41009.37 | IE21: =BR21+EP21 -> 45950.258 | IF21: =BS21+EQ21 -> 45950.258 | IG21: =BT21+ER21 -> 46938.436 | IH21: =BU21+ES21 -> 49902.969 | II21: =BV21+ET21 -> 57314.301 | IJ21: =BW21+EU21 -> 55832.034 | ... IN21: =CA21+EY21 -> 61761.1 | IO21: =SUM(IC21:IN21) -> 592906.56 | IP21: =CC21+FA21 -> 48134.327 | IQ21: =CD21+FB21 -> 52567.752 | IR21: =CE21+FC21 -> 58901.216 | IS21: =CF21+FD21 -> 58901.216 | IT21: =CG21+FE21 -> 60167.909 | IU21: =CH21+FF21 -> 63967.988 | IV21: =CI21+FG21 -> 73468.184 | IW21: =CJ21+FH21 -> 71568.145 | ... JA21: =CN21+FL21 -> 79168.302 | JB21: =SUM(IP21:JA21) -> 760015.7 | JE21: =O21-GB21 -> 0 | JF21: =AB21-GO21 -> 0 | JG21: =AO21+DM21-HB21 -> 0 | JH21: =BB21+DZ21-HO21 -> 0 | JI21: =BO21+EM21-IB21 -> 0 | JJ21: =CB21+EZ21-IO21 -> 0 | JK21: =CO21+FM21-JB21 -> 0
B22: Острые | C22: ='ОПУ БС'!$C22/12*'ОПУ БС'!L22 -> 6300.997 | D22: ='ОПУ БС'!$C22/12*'ОПУ БС'!M22 -> 6881.352 | E22: ='ОПУ БС'!$C22/12*'ОПУ БС'!N22 -> 7710.4305 | F22: ='ОПУ БС'!$C22/12*'ОПУ БС'!O22 -> 7710.4305 | G22: ='ОПУ БС'!$C22/12*'ОПУ БС'!P22 -> 7876.2463 | H22: ='ОПУ БС'!$C22/12*'ОПУ БС'!Q22 -> 8373.6934 | I22: ='ОПУ БС'!$C22/12*'ОПУ БС'!R22 -> 9617.3112 | J22: ='ОПУ БС'!$C22/12*'ОПУ БС'!S22 -> 9368.5877 | ... N22: ='ОПУ БС'!$C22/12*'ОПУ БС'!W22 -> 10363.482 | O22: =SUM(C22:N22) -> 99489.426 | P22: ='ОПУ БС'!$D22/12*'ОПУ БС'!L22 -> 8359.8749 | Q22: ='ОПУ БС'!$D22/12*'ОПУ БС'!M22 -> 9129.8634 | R22: ='ОПУ БС'!$D22/12*'ОПУ БС'!N22 -> 10229.847 | S22: ='ОПУ БС'!$D22/12*'ОПУ БС'!O22 -> 10229.847 | T22: ='ОПУ БС'!$D22/12*'ОПУ БС'!P22 -> 10449.844 | U22: ='ОПУ БС'!$D22/12*'ОПУ БС'!Q22 -> 11109.834 | V22: ='ОПУ БС'!$D22/12*'ОПУ БС'!R22 -> 12759.809 | W22: ='ОПУ БС'!$D22/12*'ОПУ БС'!S22 -> 12429.814 | ... AA22: ='ОПУ БС'!$D22/12*'ОПУ БС'!W22 -> 13749.794 | AB22: =SUM(P22:AA22) -> 131998.03 | AC22: ='ОПУ БС'!$E22/12*'ОПУ БС'!L22 -> 11257.727 | AD22: ='ОПУ БС'!$E22/12*'ОПУ БС'!M22 -> 12294.623 | AE22: ='ОПУ БС'!$E22/12*'ОПУ БС'!N22 -> 13775.903 | AF22: ='ОПУ БС'!$E22/12*'ОПУ БС'!O22 -> 13775.903 | AG22: ='ОПУ БС'!$E22/12*'ОПУ БС'!P22 -> 14072.159 | AH22: ='ОПУ БС'!$E22/12*'ОПУ БС'!Q22 -> 14960.927 | AI22: ='ОПУ БС'!$E22/12*'ОПУ БС'!R22 -> 17182.847 | AJ22: ='ОПУ БС'!$E22/12*'ОПУ БС'!S22 -> 16738.463 | ... AN22: ='ОПУ БС'!$E22/12*'ОПУ БС'!W22 -> 18515.999 | AO22: =SUM(AC22:AN22) -> 177753.59 | AP22: ='ОПУ БС'!$F22/12*'ОПУ БС'!L22 -> 14611.533 | AQ22: ='ОПУ БС'!$F22/12*'ОПУ БС'!M22 -> 15957.332 | AR22: ='ОПУ БС'!$F22/12*'ОПУ БС'!N22 -> 17879.902 | AS22: ='ОПУ БС'!$F22/12*'ОПУ БС'!O22 -> 17879.902 | AT22: ='ОПУ БС'!$F22/12*'ОПУ БС'!P22 -> 18264.416 | AU22: ='ОПУ БС'!$F22/12*'ОПУ БС'!Q22 -> 19417.958 | AV22: ='ОПУ БС'!$F22/12*'ОПУ БС'!R22 -> 22301.813 | AW22: ='ОПУ БС'!$F22/12*'ОПУ БС'!S22 -> 21725.042 | ... BA22: ='ОПУ БС'!$F22/12*'ОПУ БС'!W22 -> 24032.126 | BB22: =SUM(AP22:BA22) -> 230708.41 | BC22: ='ОПУ БС'!$G22/12*'ОПУ БС'!L22 -> 18504.917 | BD22: ='ОПУ БС'!$G22/12*'ОПУ БС'!M22 -> 20209.317 | BE22: ='ОПУ БС'!$G22/12*'ОПУ БС'!N22 -> 22644.174 | BF22: ='ОПУ БС'!$G22/12*'ОПУ БС'!O22 -> 22644.174 | BG22: ='ОПУ БС'!$G22/12*'ОПУ БС'!P22 -> 23131.146 | BH22: ='ОПУ БС'!$G22/12*'ОПУ БС'!Q22 -> 24592.06 | BI22: ='ОПУ БС'!$G22/12*'ОПУ БС'!R22 -> 28244.346 | BJ22: ='ОПУ БС'!$G22/12*'ОПУ БС'!S22 -> 27513.889 | ... BN22: ='ОПУ БС'!$G22/12*'ОПУ БС'!W22 -> 30435.718 | BO22: =SUM(BC22:BN22) -> 292182.89 | BP22: ='ОПУ БС'!$H22/12*'ОПУ БС'!L22 -> 22737.108 | BQ22: ='ОПУ БС'!$H22/12*'ОПУ БС'!M22 -> 24831.316 | BR22: ='ОПУ БС'!$H22/12*'ОПУ БС'!N22 -> 27823.041 | BS22: ='ОПУ БС'!$H22/12*'ОПУ БС'!O22 -> 27823.041 | BT22: ='ОПУ БС'!$H22/12*'ОПУ БС'!P22 -> 28421.386 | BU22: ='ОПУ БС'!$H22/12*'ОПУ БС'!Q22 -> 30216.42 | BV22: ='ОПУ БС'!$H22/12*'ОПУ БС'!R22 -> 34704.008 | BW22: ='ОПУ БС'!$H22/12*'ОПУ БС'!S22 -> 33806.49 | ... CA22: ='ОПУ БС'!$H22/12*'ОПУ БС'!W22 -> 37396.56 | CB22: =SUM(BP22:CA22) -> 359006.98 | CC22: ='ОПУ БС'!$I22/12*'ОПУ БС'!L22 -> 27615.792 | CD22: ='ОПУ БС'!$I22/12*'ОПУ БС'!M22 -> 30159.352 | CE22: ='ОПУ БС'!$I22/12*'ОПУ БС'!N22 -> 33793.009 | CF22: ='ОПУ БС'!$I22/12*'ОПУ БС'!O22 -> 33793.009 | CG22: ='ОПУ БС'!$I22/12*'ОПУ БС'!P22 -> 34519.74 | CH22: ='ОПУ БС'!$I22/12*'ОПУ БС'!Q22 -> 36699.935 | CI22: ='ОПУ БС'!$I22/12*'ОПУ БС'!R22 -> 42150.42 | CJ22: ='ОПУ БС'!$I22/12*'ОПУ БС'!S22 -> 41060.323 | ... CN22: ='ОПУ БС'!$I22/12*'ОПУ БС'!W22 -> 45420.711 | CO22: =SUM(CC22:CN22) -> 436038.83 | CR22: =O22-'ОПУ БС'!C22 -> 0 | CS22: =AB22-'ОПУ БС'!D22 -> 0 | CT22: =AO22-'ОПУ БС'!E22 -> 0 | CU22: =BB22-'ОПУ БС'!F22 -> 0 | CV22: =BO22-'ОПУ БС'!G22 -> 0 | CW22: =CB22-'ОПУ БС'!H22 -> 0 | CX22: =CO22-'ОПУ БС'!I22 -> 0 | DM22: =SUM(DA22:DL22) -> 0 | DZ22: =SUM(DN22:DY22) -> 0 | EM22: =SUM(EA22:EL22) -> 0 | EZ22: =SUM(EN22:EY22) -> 0 | FM22: =SUM(FA22:FL22) -> 0 | FP22: =C22 -> 6300.997 | FQ22: =D22 -> 6881.352 | FR22: =E22 -> 7710.4305 | FS22: =F22 -> 7710.4305 | FT22: =G22 -> 7876.2463 | FU22: =H22 -> 8373.6934 | FV22: =I22 -> 9617.3112 | FW22: =J22 -> 9368.5877 | ... GA22: =N22 -> 10363.482 | GB22: =SUM(FP22:GA22) -> 99489.426 | GC22: =P22 -> 8359.8749 | GD22: =Q22 -> 9129.8634 | GE22: =R22 -> 10229.847 | GF22: =S22 -> 10229.847 | GG22: =T22 -> 10449.844 | GH22: =U22 -> 11109.834 | GI22: =V22 -> 12759.809 | GJ22: =W22 -> 12429.814 | ... GN22: =AA22 -> 13749.794 | GO22: =SUM(GC22:GN22) -> 131998.03 | GP22: =AC22+DA22 -> 11257.727 | GQ22: =AD22+DB22 -> 12294.623 | GR22: =AE22+DC22 -> 13775.903 | GS22: =AF22+DD22 -> 13775.903 | GT22: =AG22+DE22 -> 14072.159 | GU22: =AH22+DF22 -> 14960.927 | GV22: =AI22+DG22 -> 17182.847 | GW22: =AJ22+DH22 -> 16738.463 | ... HA22: =AN22+DL22 -> 18515.999 | HB22: =SUM(GP22:HA22) -> 177753.59 | HC22: =AP22+DN22 -> 14611.533 | HD22: =AQ22+DO22 -> 15957.332 | HE22: =AR22+DP22 -> 17879.902 | HF22: =AS22+DQ22 -> 17879.902 | HG22: =AT22+DR22 -> 18264.416 | HH22: =AU22+DS22 -> 19417.958 | HI22: =AV22+DT22 -> 22301.813 | HJ22: =AW22+DU22 -> 21725.042 | ... HN22: =BA22+DY22 -> 24032.126 | HO22: =SUM(HC22:HN22) -> 230708.41 | HP22: =BC22+EA22 -> 18504.917 | HQ22: =BD22+EB22 -> 20209.317 | HR22: =BE22+EC22 -> 22644.174 | HS22: =BF22+ED22 -> 22644.174 | HT22: =BG22+EE22 -> 23131.146 | HU22: =BH22+EF22 -> 24592.06 | HV22: =BI22+EG22 -> 28244.346 | HW22: =BJ22+EH22 -> 27513.889 | ... IA22: =BN22+EL22 -> 30435.718 | IB22: =SUM(HP22:IA22) -> 292182.89 | IC22: =BP22+EN22 -> 22737.108 | ID22: =BQ22+EO22 -> 24831.316 | IE22: =BR22+EP22 -> 27823.041 | IF22: =BS22+EQ22 -> 27823.041 | IG22: =BT22+ER22 -> 28421.386 | IH22: =BU22+ES22 -> 30216.42 | II22: =BV22+ET22 -> 34704.008 | IJ22: =BW22+EU22 -> 33806.49 | ... IN22: =CA22+EY22 -> 37396.56 | IO22: =SUM(IC22:IN22) -> 359006.98 | IP22: =CC22+FA22 -> 27615.792 | IQ22: =CD22+FB22 -> 30159.352 | IR22: =CE22+FC22 -> 33793.009 | IS22: =CF22+FD22 -> 33793.009 | IT22: =CG22+FE22 -> 34519.74 | IU22: =CH22+FF22 -> 36699.935 | IV22: =CI22+FG22 -> 42150.42 | IW22: =CJ22+FH22 -> 41060.323 | ... JA22: =CN22+FL22 -> 45420.711 | JB22: =SUM(IP22:JA22) -> 436038.83 | JE22: =O22-GB22 -> 0 | JF22: =AB22-GO22 -> 0 | JG22: =AO22+DM22-HB22 -> 0 | JH22: =BB22+DZ22-HO22 -> 0 | JI22: =BO22+EM22-IB22 -> 0 | JJ22: =CB22+EZ22-IO22 -> 0 | JK22: =CO22+FM22-JB22 -> 0
B23: ЭкстраХруст | C23: ='ОПУ БС'!$C23/12*'ОПУ БС'!L23 -> 1795.0405 | D23: ='ОПУ БС'!$C23/12*'ОПУ БС'!M23 -> 1960.3731 | E23: ='ОПУ БС'!$C23/12*'ОПУ БС'!N23 -> 2196.5627 | F23: ='ОПУ БС'!$C23/12*'ОПУ БС'!O23 -> 2196.5627 | G23: ='ОПУ БС'!$C23/12*'ОПУ БС'!P23 -> 2243.8006 | H23: ='ОПУ БС'!$C23/12*'ОПУ БС'!Q23 -> 2385.5143 | I23: ='ОПУ БС'!$C23/12*'ОПУ БС'!R23 -> 2739.7986 | J23: ='ОПУ БС'!$C23/12*'ОПУ БС'!S23 -> 2668.9417 | ... N23: ='ОПУ БС'!$C23/12*'ОПУ БС'!W23 -> 2952.3692 | O23: =SUM(C23:N23) -> 28342.744 | P23: ='ОПУ БС'!$D23/12*'ОПУ БС'!L23 -> 2736.7931 | Q23: ='ОПУ БС'!$D23/12*'ОПУ БС'!M23 -> 2988.8662 | R23: ='ОПУ БС'!$D23/12*'ОПУ БС'!N23 -> 3348.9706 | S23: ='ОПУ БС'!$D23/12*'ОПУ БС'!O23 -> 3348.9706 | T23: ='ОПУ БС'!$D23/12*'ОПУ БС'!P23 -> 3420.9914 | U23: ='ОПУ БС'!$D23/12*'ОПУ БС'!Q23 -> 3637.054 | V23: ='ОПУ БС'!$D23/12*'ОПУ БС'!R23 -> 4177.2106 | W23: ='ОПУ БС'!$D23/12*'ОПУ БС'!S23 -> 4069.1793 | ... AA23: ='ОПУ БС'!$D23/12*'ОПУ БС'!W23 -> 4501.3045 | AB23: =SUM(P23:AA23) -> 43212.523 | AC23: ='ОПУ БС'!$E23/12*'ОПУ БС'!L23 -> 4187.6979 | AD23: ='ОПУ БС'!$E23/12*'ОПУ БС'!M23 -> 4573.4069 | AE23: ='ОПУ БС'!$E23/12*'ОПУ БС'!N23 -> 5124.4198 | AF23: ='ОПУ БС'!$E23/12*'ОПУ БС'!O23 -> 5124.4198 | AG23: ='ОПУ БС'!$E23/12*'ОПУ БС'!P23 -> 5234.6224 | AH23: ='ОПУ БС'!$E23/12*'ОПУ БС'!Q23 -> 5565.2301 | AI23: ='ОПУ БС'!$E23/12*'ОПУ БС'!R23 -> 6391.7494 | AJ23: ='ОПУ БС'!$E23/12*'ОПУ БС'!S23 -> 6226.4456 | ... AN23: ='ОПУ БС'!$E23/12*'ОПУ БС'!W23 -> 6887.661 | AO23: =SUM(AC23:AN23) -> 66121.546 | AP23: ='ОПУ БС'!$F23/12*'ОПУ БС'!L23 -> 6042.1819 | AQ23: ='ОПУ БС'!$F23/12*'ОПУ БС'!M23 -> 6598.6986 | AR23: ='ОПУ БС'!$F23/12*'ОПУ БС'!N23 -> 7393.7226 | AS23: ='ОПУ БС'!$F23/12*'ОПУ БС'!O23 -> 7393.7226 | AT23: ='ОПУ БС'!$F23/12*'ОПУ БС'!P23 -> 7552.7273 | AU23: ='ОПУ БС'!$F23/12*'ОПУ БС'!Q23 -> 8029.7417 | AV23: ='ОПУ БС'!$F23/12*'ОПУ БС'!R23 -> 9222.2776 | AW23: ='ОПУ БС'!$F23/12*'ОПУ БС'!S23 -> 8983.7704 | ... BA23: ='ОПУ БС'!$F23/12*'ОПУ БС'!W23 -> 9937.7991 | BB23: =SUM(AP23:BA23) -> 95402.872 | BC23: ='ОПУ БС'!$G23/12*'ОПУ БС'!L23 -> 8326.2202 | BD23: ='ОПУ БС'!$G23/12*'ОПУ БС'!M23 -> 9093.1089 | BE23: ='ОПУ БС'!$G23/12*'ОПУ БС'!N23 -> 10188.664 | BF23: ='ОПУ БС'!$G23/12*'ОПУ БС'!O23 -> 10188.664 | BG23: ='ОПУ БС'!$G23/12*'ОПУ БС'!P23 -> 10407.775 | BH23: ='ОПУ БС'!$G23/12*'ОПУ БС'!Q23 -> 11065.108 | BI23: ='ОПУ БС'!$G23/12*'ОПУ БС'!R23 -> 12708.441 | BJ23: ='ОПУ БС'!$G23/12*'ОПУ БС'!S23 -> 12379.775 | ... BN23: ='ОПУ БС'!$G23/12*'ОПУ БС'!W23 -> 13694.441 | BO23: =SUM(BC23:BN23) -> 131466.64 | BP23: ='ОПУ БС'!$H23/12*'ОПУ БС'!L23 -> 10986.001 | BQ23: ='ОПУ БС'!$H23/12*'ОПУ БС'!M23 -> 11997.869 | BR23: ='ОПУ БС'!$H23/12*'ОПУ БС'!N23 -> 13443.396 | BS23: ='ОПУ БС'!$H23/12*'ОПУ БС'!O23 -> 13443.396 | BT23: ='ОПУ БС'!$H23/12*'ОПУ БС'!P23 -> 13732.501 | BU23: ='ОПУ БС'!$H23/12*'ОПУ БС'!Q23 -> 14599.817 | BV23: ='ОПУ БС'!$H23/12*'ОПУ БС'!R23 -> 16768.107 | BW23: ='ОПУ БС'!$H23/12*'ОПУ БС'!S23 -> 16334.449 | ... CA23: ='ОПУ БС'!$H23/12*'ОПУ БС'!W23 -> 18069.08 | CB23: =SUM(BP23:CA23) -> 173463.17 | CC23: ='ОПУ БС'!$I23/12*'ОПУ БС'!L23 -> 13938.804 | CD23: ='ОПУ БС'!$I23/12*'ОПУ БС'!M23 -> 15222.642 | CE23: ='ОПУ БС'!$I23/12*'ОПУ БС'!N23 -> 17056.695 | CF23: ='ОПУ БС'!$I23/12*'ОПУ БС'!O23 -> 17056.695 | CG23: ='ОПУ БС'!$I23/12*'ОПУ БС'!P23 -> 17423.506 | CH23: ='ОПУ БС'!$I23/12*'ОПУ БС'!Q23 -> 18523.938 | CI23: ='ОПУ БС'!$I23/12*'ОПУ БС'!R23 -> 21275.017 | CJ23: ='ОПУ БС'!$I23/12*'ОПУ БС'!S23 -> 20724.801 | ... CN23: ='ОПУ БС'!$I23/12*'ОПУ БС'!W23 -> 22925.665 | CO23: =SUM(CC23:CN23) -> 220086.39 | CR23: =O23-'ОПУ БС'!C23 -> 0 | CS23: =AB23-'ОПУ БС'!D23 -> 0 | CT23: =AO23-'ОПУ БС'!E23 -> 0 | CU23: =BB23-'ОПУ БС'!F23 -> 0 | CV23: =BO23-'ОПУ БС'!G23 -> 0 | CW23: =CB23-'ОПУ БС'!H23 -> 0 | CX23: =CO23-'ОПУ БС'!I23 -> 0 | DM23: =SUM(DA23:DL23) -> 0 | DZ23: =SUM(DN23:DY23) -> 0 | EM23: =SUM(EA23:EL23) -> 0 | EZ23: =SUM(EN23:EY23) -> 0 | FM23: =SUM(FA23:FL23) -> 0 | FP23: =C23 -> 1795.0405 | FQ23: =D23 -> 1960.3731 | FR23: =E23 -> 2196.5627 | FS23: =F23 -> 2196.5627 | FT23: =G23 -> 2243.8006 | FU23: =H23 -> 2385.5143 | FV23: =I23 -> 2739.7986 | FW23: =J23 -> 2668.9417 | ... GA23: =N23 -> 2952.3692 | GB23: =SUM(FP23:GA23) -> 28342.744 | GC23: =P23 -> 2736.7931 | GD23: =Q23 -> 2988.8662 | GE23: =R23 -> 3348.9706 | GF23: =S23 -> 3348.9706 | GG23: =T23 -> 3420.9914 | GH23: =U23 -> 3637.054 | GI23: =V23 -> 4177.2106 | GJ23: =W23 -> 4069.1793 | ... GN23: =AA23 -> 4501.3045 | GO23: =SUM(GC23:GN23) -> 43212.523 | GP23: =AC23+DA23 -> 4187.6979 | GQ23: =AD23+DB23 -> 4573.4069 | GR23: =AE23+DC23 -> 5124.4198 | GS23: =AF23+DD23 -> 5124.4198 | GT23: =AG23+DE23 -> 5234.6224 | GU23: =AH23+DF23 -> 5565.2301 | GV23: =AI23+DG23 -> 6391.7494 | GW23: =AJ23+DH23 -> 6226.4456 | ... HA23: =AN23+DL23 -> 6887.661 | HB23: =SUM(GP23:HA23) -> 66121.546 | HC23: =AP23+DN23 -> 6042.1819 | HD23: =AQ23+DO23 -> 6598.6986 | HE23: =AR23+DP23 -> 7393.7226 | HF23: =AS23+DQ23 -> 7393.7226 | HG23: =AT23+DR23 -> 7552.7273 | HH23: =AU23+DS23 -> 8029.7417 | HI23: =AV23+DT23 -> 9222.2776 | HJ23: =AW23+DU23 -> 8983.7704 | ... HN23: =BA23+DY23 -> 9937.7991 | HO23: =SUM(HC23:HN23) -> 95402.872 | HP23: =BC23+EA23 -> 8326.2202 | HQ23: =BD23+EB23 -> 9093.1089 | HR23: =BE23+EC23 -> 10188.664 | HS23: =BF23+ED23 -> 10188.664 | HT23: =BG23+EE23 -> 10407.775 | HU23: =BH23+EF23 -> 11065.108 | HV23: =BI23+EG23 -> 12708.441 | HW23: =BJ23+EH23 -> 12379.775 | ... IA23: =BN23+EL23 -> 13694.441 | IB23: =SUM(HP23:IA23) -> 131466.64 | IC23: =BP23+EN23 -> 10986.001 | ID23: =BQ23+EO23 -> 11997.869 | IE23: =BR23+EP23 -> 13443.396 | IF23: =BS23+EQ23 -> 13443.396 | IG23: =BT23+ER23 -> 13732.501 | IH23: =BU23+ES23 -> 14599.817 | II23: =BV23+ET23 -> 16768.107 | IJ23: =BW23+EU23 -> 16334.449 | ... IN23: =CA23+EY23 -> 18069.08 | IO23: =SUM(IC23:IN23) -> 173463.17 | IP23: =CC23+FA23 -> 13938.804 | IQ23: =CD23+FB23 -> 15222.642 | IR23: =CE23+FC23 -> 17056.695 | IS23: =CF23+FD23 -> 17056.695 | IT23: =CG23+FE23 -> 17423.506 | IU23: =CH23+FF23 -> 18523.938 | IV23: =CI23+FG23 -> 21275.017 | IW23: =CJ23+FH23 -> 20724.801 | ... JA23: =CN23+FL23 -> 22925.665 | JB23: =SUM(IP23:JA23) -> 220086.39 | JE23: =O23-GB23 -> 0 | JF23: =AB23-GO23 -> 0 | JG23: =AO23+DM23-HB23 -> 0 | JH23: =BB23+DZ23-HO23 -> 0 | JI23: =BO23+EM23-IB23 -> 0 | JJ23: =CB23+EZ23-IO23 -> 0 | JK23: =CO23+FM23-JB23 -> 0
B24: Соусы | C24: =SUM(C25:C31) -> 2626.5188 | D24: =SUM(D25:D31) -> 3228.6326 | E24: =SUM(E25:E31) -> 3603.1025 | F24: =SUM(F25:F31) -> 3574.6828 | G24: =SUM(G25:G31) -> 3660.6886 | H24: =SUM(H25:H31) -> 3893.9723 | I24: =SUM(I25:I31) -> 4061.1094 | J24: =SUM(J25:J31) -> 4358.8718 | ... N24: =SUM(N25:N31) -> 4821.7608 | O24: =SUM(C24:N24) -> 46288.904 | P24: =SUM(P25:P31) -> 3012.842 | Q24: =SUM(Q25:Q31) -> 3719.3373 | R24: =SUM(R25:R31) -> 4158.1713 | S24: =SUM(S25:S31) -> 4126.9712 | T24: =SUM(T25:T31) -> 4223.9818 | U24: =SUM(U25:U31) -> 4494.8167 | V24: =SUM(V25:V31) -> 4662.0571 | W24: =SUM(W25:W31) -> 5032.1469 | ... AA24: =SUM(AA25:AA31) -> 5566.5342 | AB24: =SUM(P24:AA24) -> 53438.728 | AC24: =SUM(AC25:AC31) -> 3989.1198 | AD24: =SUM(AD25:AD31) -> 4941.9849 | AE24: =SUM(AE25:AE31) -> 5527.1086 | AF24: =SUM(AF25:AF31) -> 5488.8935 | AG24: =SUM(AG25:AG31) -> 5614.4185 | AH24: =SUM(AH25:AH31) -> 5976.1136 | AI24: =SUM(AI25:AI31) -> 6178.6948 | AJ24: =SUM(AJ25:AJ31) -> 6690.9457 | ... AN24: =SUM(AN25:AN31) -> 7401.4886 | AO24: =SUM(AC24:AN24) -> 71054.291 | AP24: =SUM(AP25:AP31) -> 5080.6327 | AQ24: =SUM(AQ25:AQ31) -> 6323.2695 | AR24: =SUM(AR25:AR31) -> 7070.7382 | AS24: =SUM(AS25:AS31) -> 7026.9989 | AT24: =SUM(AT25:AT31) -> 7183.9459 | AU24: =SUM(AU25:AU31) -> 7648.8416 | AV24: =SUM(AV25:AV31) -> 7876.966 | AW24: =SUM(AW25:AW31) -> 8564.2423 | ... BA24: =SUM(BA25:BA31) -> 9473.7193 | BB24: =SUM(AP24:BA24) -> 90947.706 | BC24: =SUM(BC25:BC31) -> 6408.4534 | BD24: =SUM(BD25:BD31) -> 7997.1209 | BE24: =SUM(BE25:BE31) -> 8941.9445 | BF24: =SUM(BF25:BF31) -> 8891.178 | BG24: =SUM(BG25:BG31) -> 9085.7711 | BH24: =SUM(BH25:BH31) -> 9675.9886 | BI24: =SUM(BI25:BI31) -> 9941.7779 | BJ24: =SUM(BJ25:BJ31) -> 10834.41 | ... BN24: =SUM(BN25:BN31) -> 11984.967 | BO24: =SUM(BC24:BN24) -> 115055.68 | BP24: =SUM(BP25:BP31) -> 7881.75 | BQ24: =SUM(BQ25:BQ31) -> 9850.4915 | BR24: =SUM(BR25:BR31) -> 11014.38 | BS24: =SUM(BS25:BS31) -> 10955.942 | BT24: =SUM(BT25:BT31) -> 11191.462 | BU24: =SUM(BU25:BU31) -> 11920.905 | BV24: =SUM(BV25:BV31) -> 12232.338 | BW24: =SUM(BW25:BW31) -> 13348.445 | ... CA24: =SUM(CA25:CA31) -> 14765.979 | CB24: =SUM(BP24:CA24) -> 141753.4 | CC24: =SUM(CC25:CC31) -> 9662.931 | CD24: =SUM(CD25:CD31) -> 12082.131 | CE24: =SUM(CE25:CE31) -> 13510.356 | CF24: =SUM(CF25:CF31) -> 13441.47 | CG24: =SUM(CG25:CG31) -> 13726.837 | CH24: =SUM(CH25:CH31) -> 14623.688 | CI24: =SUM(CI25:CI31) -> 14999.465 | CJ24: =SUM(CJ25:CJ31) -> 16375.123 | ... CN24: =SUM(CN25:CN31) -> 18114.074 | CO24: =SUM(CC24:CN24) -> 173895.11 | CR24: =O24-'ОПУ БС'!C24 -> 0 | CS24: =AB24-'ОПУ БС'!D24 -> 0 | CT24: =AO24-'ОПУ БС'!E24 -> 0 | CU24: =BB24-'ОПУ БС'!F24 -> 0 | CV24: =BO24-'ОПУ БС'!G24 -> 0 | CW24: =CB24-'ОПУ БС'!H24 -> 0 | CX24: =CO24-'ОПУ БС'!I24 -> 0 | DA24: =SUM(DA25:DA31) -> 0 | DB24: =SUM(DB25:DB31) -> 0 | DC24: =SUM(DC25:DC31) -> 0 | DD24: =SUM(DD25:DD31) -> 0 | DE24: =SUM(DE25:DE31) -> 0 | DF24: =SUM(DF25:DF31) -> 0 | DG24: =SUM(DG25:DG31) -> 0 | DH24: =SUM(DH25:DH31) -> 0 | ... DL24: =SUM(DL25:DL31) -> 0 | DM24: =SUM(DA24:DL24) -> 0 | DN24: =SUM(DN25:DN31) -> 0 | DO24: =SUM(DO25:DO31) -> 0 | DP24: =SUM(DP25:DP31) -> 0 | DQ24: =SUM(DQ25:DQ31) -> 0 | DR24: =SUM(DR25:DR31) -> 0 | DS24: =SUM(DS25:DS31) -> 0 | DT24: =SUM(DT25:DT31) -> 0 | DU24: =SUM(DU25:DU31) -> 0 | ... DY24: =SUM(DY25:DY31) -> 0 | DZ24: =SUM(DN24:DY24) -> 0 | EA24: =SUM(EA25:EA31) -> 0 | EB24: =SUM(EB25:EB31) -> 0 | EC24: =SUM(EC25:EC31) -> 0 | ED24: =SUM(ED25:ED31) -> 0 | EE24: =SUM(EE25:EE31) -> 0 | EF24: =SUM(EF25:EF31) -> 0 | EG24: =SUM(EG25:EG31) -> 0 | EH24: =SUM(EH25:EH31) -> 0 | ... EL24: =SUM(EL25:EL31) -> 0 | EM24: =SUM(EA24:EL24) -> 0 | EN24: =SUM(EN25:EN31) -> 0 | EO24: =SUM(EO25:EO31) -> 0 | EP24: =SUM(EP25:EP31) -> 0 | EQ24: =SUM(EQ25:EQ31) -> 0 | ER24: =SUM(ER25:ER31) -> 0 | ES24: =SUM(ES25:ES31) -> 0 | ET24: =SUM(ET25:ET31) -> 0 | EU24: =SUM(EU25:EU31) -> 0 | ... EY24: =SUM(EY25:EY31) -> 0 | EZ24: =SUM(EN24:EY24) -> 0 | FA24: =SUM(FA25:FA31) -> 0 | FB24: =SUM(FB25:FB31) -> 0 | FC24: =SUM(FC25:FC31) -> 0 | FD24: =SUM(FD25:FD31) -> 0 | FE24: =SUM(FE25:FE31) -> 0 | FF24: =SUM(FF25:FF31) -> 0 | FG24: =SUM(FG25:FG31) -> 0 | FH24: =SUM(FH25:FH31) -> 0 | ... FL24: =SUM(FL25:FL31) -> 0 | FM24: =SUM(FA24:FL24) -> 0 | FP24: =SUM(FP25:FP31) -> 2626.5188 | FQ24: =SUM(FQ25:FQ31) -> 3228.6326 | FR24: =SUM(FR25:FR31) -> 3603.1025 | FS24: =SUM(FS25:FS31) -> 3574.6828 | FT24: =SUM(FT25:FT31) -> 3660.6886 | FU24: =SUM(FU25:FU31) -> 3893.9723 | FV24: =SUM(FV25:FV31) -> 4061.1094 | FW24: =SUM(FW25:FW31) -> 4358.8718 | ... GA24: =SUM(GA25:GA31) -> 4821.7608 | GB24: =SUM(FP24:GA24) -> 46288.904 | GC24: =SUM(GC25:GC31) -> 3012.842 | GD24: =SUM(GD25:GD31) -> 3719.3373 | GE24: =SUM(GE25:GE31) -> 4158.1713 | GF24: =SUM(GF25:GF31) -> 4126.9712 | GG24: =SUM(GG25:GG31) -> 4223.9818 | GH24: =SUM(GH25:GH31) -> 4494.8167 | GI24: =SUM(GI25:GI31) -> 4662.0571 | GJ24: =SUM(GJ25:GJ31) -> 5032.1469 | ... GN24: =SUM(GN25:GN31) -> 5566.5342 | GO24: =SUM(GC24:GN24) -> 53438.728 | GP24: =SUM(GP25:GP31) -> 3989.1198 | GQ24: =SUM(GQ25:GQ31) -> 4941.9849 | GR24: =SUM(GR25:GR31) -> 5527.1086 | GS24: =SUM(GS25:GS31) -> 5488.8935 | GT24: =SUM(GT25:GT31) -> 5614.4185 | GU24: =SUM(GU25:GU31) -> 5976.1136 | GV24: =SUM(GV25:GV31) -> 6178.6948 | GW24: =SUM(GW25:GW31) -> 6690.9457 | ... HA24: =SUM(HA25:HA31) -> 7401.4886 | HB24: =SUM(GP24:HA24) -> 71054.291 | HC24: =SUM(HC25:HC31) -> 5080.6327 | HD24: =SUM(HD25:HD31) -> 6323.2695 | HE24: =SUM(HE25:HE31) -> 7070.7382 | HF24: =SUM(HF25:HF31) -> 7026.9989 | HG24: =SUM(HG25:HG31) -> 7183.9459 | HH24: =SUM(HH25:HH31) -> 7648.8416 | HI24: =SUM(HI25:HI31) -> 7876.966 | HJ24: =SUM(HJ25:HJ31) -> 8564.2423 | ... HN24: =SUM(HN25:HN31) -> 9473.7193 | HO24: =SUM(HC24:HN24) -> 90947.706 | HP24: =SUM(HP25:HP31) -> 6408.4534 | HQ24: =SUM(HQ25:HQ31) -> 7997.1209 | HR24: =SUM(HR25:HR31) -> 8941.9445 | HS24: =SUM(HS25:HS31) -> 8891.178 | HT24: =SUM(HT25:HT31) -> 9085.7711 | HU24: =SUM(HU25:HU31) -> 9675.9886 | HV24: =SUM(HV25:HV31) -> 9941.7779 | HW24: =SUM(HW25:HW31) -> 10834.41 | ... IA24: =SUM(IA25:IA31) -> 11984.967 | IB24: =SUM(HP24:IA24) -> 115055.68 | IC24: =SUM(IC25:IC31) -> 7881.75 | ID24: =SUM(ID25:ID31) -> 9850.4915 | IE24: =SUM(IE25:IE31) -> 11014.38 | IF24: =SUM(IF25:IF31) -> 10955.942 | IG24: =SUM(IG25:IG31) -> 11191.462 | IH24: =SUM(IH25:IH31) -> 11920.905 | II24: =SUM(II25:II31) -> 12232.338 | IJ24: =SUM(IJ25:IJ31) -> 13348.445 | ... IN24: =SUM(IN25:IN31) -> 14765.979 | IO24: =SUM(IC24:IN24) -> 141753.4 | IP24: =SUM(IP25:IP31) -> 9662.931 | IQ24: =SUM(IQ25:IQ31) -> 12082.131 | IR24: =SUM(IR25:IR31) -> 13510.356 | IS24: =SUM(IS25:IS31) -> 13441.47 | IT24: =SUM(IT25:IT31) -> 13726.837 | IU24: =SUM(IU25:IU31) -> 14623.688 | IV24: =SUM(IV25:IV31) -> 14999.465 | IW24: =SUM(IW25:IW31) -> 16375.123 | ... JA24: =SUM(JA25:JA31) -> 18114.074 | JB24: =SUM(IP24:JA24) -> 173895.11 | JE24: =O24-GB24 -> 0 | JF24: =AB24-GO24 -> 0 | JG24: =AO24+DM24-HB24 -> 0 | JH24: =BB24+DZ24-HO24 -> 0 | JI24: =BO24+EM24-IB24 -> 0 | JJ24: =CB24+EZ24-IO24 -> 0 | JK24: =CO24+FM24-JB24 -> 0
B25: Кетчуп | C25: ='ОПУ БС'!$C25/12*'ОПУ БС'!L25 -> 915.33519 | D25: ='ОПУ БС'!$C25/12*'ОПУ БС'!M25 -> 1332.8565 | E25: ='ОПУ БС'!$C25/12*'ОПУ БС'!N25 -> 1493.4416 | F25: ='ОПУ БС'!$C25/12*'ОПУ БС'!O25 -> 1493.4416 | G25: ='ОПУ БС'!$C25/12*'ОПУ БС'!P25 -> 1525.5586 | H25: ='ОПУ БС'!$C25/12*'ОПУ БС'!Q25 -> 1621.9097 | I25: ='ОПУ БС'!$C25/12*'ОПУ БС'!R25 -> 1461.3246 | J25: ='ОПУ БС'!$C25/12*'ОПУ БС'!S25 -> 1814.6119 | ... N25: ='ОПУ БС'!$C25/12*'ОПУ БС'!W25 -> 2007.314 | O25: =SUM(C25:N25) -> 19270.215 | P25: ='ОПУ БС'!$D25/12*'ОПУ БС'!L25 -> 1114.8322 | Q25: ='ОПУ БС'!$D25/12*'ОПУ БС'!M25 -> 1623.3522 | R25: ='ОПУ БС'!$D25/12*'ОПУ БС'!N25 -> 1818.9368 | S25: ='ОПУ БС'!$D25/12*'ОПУ БС'!O25 -> 1818.9368 | T25: ='ОПУ БС'!$D25/12*'ОПУ БС'!P25 -> 1858.0537 | U25: ='ОПУ БС'!$D25/12*'ОПУ БС'!Q25 -> 1975.4045 | V25: ='ОПУ БС'!$D25/12*'ОПУ БС'!R25 -> 1779.8199 | W25: ='ОПУ БС'!$D25/12*'ОПУ БС'!S25 -> 2210.106 | ... AA25: ='ОПУ БС'!$D25/12*'ОПУ БС'!W25 -> 2444.8075 | AB25: =SUM(P25:AA25) -> 23470.152 | AC25: ='ОПУ БС'!$E25/12*'ОПУ БС'!L25 -> 1532.9557 | AD25: ='ОПУ БС'!$E25/12*'ОПУ БС'!M25 -> 2232.1986 | AE25: ='ОПУ БС'!$E25/12*'ОПУ БС'!N25 -> 2501.1382 | AF25: ='ОПУ БС'!$E25/12*'ОПУ БС'!O25 -> 2501.1382 | AG25: ='ОПУ БС'!$E25/12*'ОПУ БС'!P25 -> 2554.9262 | AH25: ='ОПУ БС'!$E25/12*'ОПУ БС'!Q25 -> 2716.2899 | AI25: ='ОПУ БС'!$E25/12*'ОПУ БС'!R25 -> 2447.3503 | AJ25: ='ОПУ БС'!$E25/12*'ОПУ БС'!S25 -> 3039.0174 | ... AN25: ='ОПУ БС'!$E25/12*'ОПУ БС'!W25 -> 3361.7449 | AO25: =SUM(AC25:AN25) -> 32272.751 | AP25: ='ОПУ БС'!$F25/12*'ОПУ БС'!L25 -> 2038.1661 | AQ25: ='ОПУ БС'!$F25/12*'ОПУ БС'!M25 -> 2967.8558 | AR25: ='ОПУ БС'!$F25/12*'ОПУ БС'!N25 -> 3325.4288 | AS25: ='ОПУ БС'!$F25/12*'ОПУ БС'!O25 -> 3325.4288 | AT25: ='ОПУ БС'!$F25/12*'ОПУ БС'!P25 -> 3396.9434 | AU25: ='ОПУ БС'!$F25/12*'ОПУ БС'!Q25 -> 3611.4872 | AV25: ='ОПУ БС'!$F25/12*'ОПУ БС'!R25 -> 3253.9142 | AW25: ='ОПУ БС'!$F25/12*'ОПУ БС'!S25 -> 4040.5748 | ... BA25: ='ОПУ БС'!$F25/12*'ОПУ БС'!W25 -> 4469.6624 | BB25: =SUM(AP25:BA25) -> 42908.759 | BC25: ='ОПУ БС'!$G25/12*'ОПУ БС'!L25 -> 2635.2198 | BD25: ='ОПУ БС'!$G25/12*'ОПУ БС'!M25 -> 3837.2499 | BE25: ='ОПУ БС'!$G25/12*'ОПУ БС'!N25 -> 4299.5692 | BF25: ='ОПУ БС'!$G25/12*'ОПУ БС'!O25 -> 4299.5692 | BG25: ='ОПУ БС'!$G25/12*'ОПУ БС'!P25 -> 4392.033 | BH25: ='ОПУ БС'!$G25/12*'ОПУ БС'!Q25 -> 4669.4246 | BI25: ='ОПУ БС'!$G25/12*'ОПУ БС'!R25 -> 4207.1053 | BJ25: ='ОПУ БС'!$G25/12*'ОПУ БС'!S25 -> 5224.2077 | ... BN25: ='ОПУ БС'!$G25/12*'ОПУ БС'!W25 -> 5778.9908 | BO25: =SUM(BC25:BN25) -> 55478.312 | BP25: ='ОПУ БС'!$H25/12*'ОПУ БС'!L25 -> 3287.8962 | BQ25: ='ОПУ БС'!$H25/12*'ОПУ БС'!M25 -> 4787.6383 | BR25: ='ОПУ БС'!$H25/12*'ОПУ БС'!N25 -> 5364.4622 | BS25: ='ОПУ БС'!$H25/12*'ОПУ БС'!O25 -> 5364.4622 | BT25: ='ОПУ БС'!$H25/12*'ОПУ БС'!P25 -> 5479.827 | BU25: ='ОПУ БС'!$H25/12*'ОПУ БС'!Q25 -> 5825.9213 | BV25: ='ОПУ БС'!$H25/12*'ОПУ БС'!R25 -> 5249.0974 | BW25: ='ОПУ БС'!$H25/12*'ОПУ БС'!S25 -> 6518.11 | ... CA25: ='ОПУ БС'!$H25/12*'ОПУ БС'!W25 -> 7210.2987 | CB25: =SUM(BP25:CA25) -> 69218.867 | CC25: ='ОПУ БС'!$I25/12*'ОПУ БС'!L25 -> 4051.2775 | CD25: ='ОПУ БС'!$I25/12*'ОПУ БС'!M25 -> 5899.2287 | CE25: ='ОПУ БС'!$I25/12*'ОПУ БС'!N25 -> 6609.9792 | CF25: ='ОПУ БС'!$I25/12*'ОПУ БС'!O25 -> 6609.9792 | CG25: ='ОПУ БС'!$I25/12*'ОПУ БС'!P25 -> 6752.1292 | CH25: ='ОПУ БС'!$I25/12*'ОПУ БС'!Q25 -> 7178.5795 | CI25: ='ОПУ БС'!$I25/12*'ОПУ БС'!R25 -> 6467.8291 | CJ25: ='ОПУ БС'!$I25/12*'ОПУ БС'!S25 -> 8031.4801 | ... CN25: ='ОПУ БС'!$I25/12*'ОПУ БС'!W25 -> 8884.3806 | CO25: =SUM(CC25:CN25) -> 85290.054 | CR25: =O25-'ОПУ БС'!C25 -> 0 | CS25: =AB25-'ОПУ БС'!D25 -> 0 | CT25: =AO25-'ОПУ БС'!E25 -> 0 | CU25: =BB25-'ОПУ БС'!F25 -> 0 | CV25: =BO25-'ОПУ БС'!G25 -> 0 | CW25: =CB25-'ОПУ БС'!H25 -> 0 | CX25: =CO25-'ОПУ БС'!I25 -> 0 | DM25: =SUM(DA25:DL25) -> 0 | DZ25: =SUM(DN25:DY25) -> 0 | EM25: =SUM(EA25:EL25) -> 0 | EZ25: =SUM(EN25:EY25) -> 0 | FM25: =SUM(FA25:FL25) -> 0 | FP25: =C25 -> 915.33519 | FQ25: =D25 -> 1332.8565 | FR25: =E25 -> 1493.4416 | FS25: =F25 -> 1493.4416 | FT25: =G25 -> 1525.5586 | FU25: =H25 -> 1621.9097 | FV25: =I25 -> 1461.3246 | FW25: =J25 -> 1814.6119 | ... GA25: =N25 -> 2007.314 | GB25: =SUM(FP25:GA25) -> 19270.215 | GC25: =P25 -> 1114.8322 | GD25: =Q25 -> 1623.3522 | GE25: =R25 -> 1818.9368 | GF25: =S25 -> 1818.9368 | GG25: =T25 -> 1858.0537 | GH25: =U25 -> 1975.4045 | GI25: =V25 -> 1779.8199 | GJ25: =W25 -> 2210.106 | ... GN25: =AA25 -> 2444.8075 | GO25: =SUM(GC25:GN25) -> 23470.152 | GP25: =AC25+DA25 -> 1532.9557 | GQ25: =AD25+DB25 -> 2232.1986 | GR25: =AE25+DC25 -> 2501.1382 | GS25: =AF25+DD25 -> 2501.1382 | GT25: =AG25+DE25 -> 2554.9262 | GU25: =AH25+DF25 -> 2716.2899 | GV25: =AI25+DG25 -> 2447.3503 | GW25: =AJ25+DH25 -> 3039.0174 | ... HA25: =AN25+DL25 -> 3361.7449 | HB25: =SUM(GP25:HA25) -> 32272.751 | HC25: =AP25+DN25 -> 2038.1661 | HD25: =AQ25+DO25 -> 2967.8558 | HE25: =AR25+DP25 -> 3325.4288 | HF25: =AS25+DQ25 -> 3325.4288 | HG25: =AT25+DR25 -> 3396.9434 | HH25: =AU25+DS25 -> 3611.4872 | HI25: =AV25+DT25 -> 3253.9142 | HJ25: =AW25+DU25 -> 4040.5748 | ... HN25: =BA25+DY25 -> 4469.6624 | HO25: =SUM(HC25:HN25) -> 42908.759 | HP25: =BC25+EA25 -> 2635.2198 | HQ25: =BD25+EB25 -> 3837.2499 | HR25: =BE25+EC25 -> 4299.5692 | HS25: =BF25+ED25 -> 4299.5692 | HT25: =BG25+EE25 -> 4392.033 | HU25: =BH25+EF25 -> 4669.4246 | HV25: =BI25+EG25 -> 4207.1053 | HW25: =BJ25+EH25 -> 5224.2077 | ... IA25: =BN25+EL25 -> 5778.9908 | IB25: =SUM(HP25:IA25) -> 55478.312 | IC25: =BP25+EN25 -> 3287.8962 | ID25: =BQ25+EO25 -> 4787.6383 | IE25: =BR25+EP25 -> 5364.4622 | IF25: =BS25+EQ25 -> 5364.4622 | IG25: =BT25+ER25 -> 5479.827 | IH25: =BU25+ES25 -> 5825.9213 | II25: =BV25+ET25 -> 5249.0974 | IJ25: =BW25+EU25 -> 6518.11 | ... IN25: =CA25+EY25 -> 7210.2987 | IO25: =SUM(IC25:IN25) -> 69218.867 | IP25: =CC25+FA25 -> 4051.2775 | IQ25: =CD25+FB25 -> 5899.2287 | IR25: =CE25+FC25 -> 6609.9792 | IS25: =CF25+FD25 -> 6609.9792 | IT25: =CG25+FE25 -> 6752.1292 | IU25: =CH25+FF25 -> 7178.5795 | IV25: =CI25+FG25 -> 6467.8291 | IW25: =CJ25+FH25 -> 8031.4801 | ... JA25: =CN25+FL25 -> 8884.3806 | JB25: =SUM(IP25:JA25) -> 85290.054 | JE25: =O25-GB25 -> 0 | JF25: =AB25-GO25 -> 0 | JG25: =AO25+DM25-HB25 -> 0 | JH25: =BB25+DZ25-HO25 -> 0 | JI25: =BO25+EM25-IB25 -> 0 | JJ25: =CB25+EZ25-IO25 -> 0 | JK25: =CO25+FM25-JB25 -> 0
B26: Горчица | C26: ='ОПУ БС'!$C26/12*'ОПУ БС'!L26 -> 512.68557 | D26: ='ОПУ БС'!$C26/12*'ОПУ БС'!M26 -> 586.89006 | E26: ='ОПУ БС'!$C26/12*'ОПУ БС'!N26 -> 627.36524 | F26: ='ОПУ БС'!$C26/12*'ОПУ БС'!O26 -> 627.36524 | G26: ='ОПУ БС'!$C26/12*'ОПУ БС'!P26 -> 640.85697 | H26: ='ОПУ БС'!$C26/12*'ОПУ БС'!Q26 -> 681.33214 | I26: ='ОПУ БС'!$C26/12*'ОПУ БС'!R26 -> 782.52009 | J26: ='ОПУ БС'!$C26/12*'ОПУ БС'!S26 -> 762.2825 | ... N26: ='ОПУ БС'!$C26/12*'ОПУ БС'!W26 -> 843.23285 | O26: =SUM(C26:N26) -> 8095.0354 | P26: ='ОПУ БС'!$D26/12*'ОПУ БС'!L26 -> 440.01254 | Q26: ='ОПУ БС'!$D26/12*'ОПУ БС'!M26 -> 503.69856 | R26: ='ОПУ БС'!$D26/12*'ОПУ БС'!N26 -> 538.43639 | S26: ='ОПУ БС'!$D26/12*'ОПУ БС'!O26 -> 538.43639 | T26: ='ОПУ БС'!$D26/12*'ОПУ БС'!P26 -> 550.01567 | U26: ='ОПУ БС'!$D26/12*'ОПУ БС'!Q26 -> 584.7535 | V26: ='ОПУ БС'!$D26/12*'ОПУ БС'!R26 -> 671.59808 | W26: ='ОПУ БС'!$D26/12*'ОПУ БС'!S26 -> 654.22917 | ... AA26: ='ОПУ БС'!$D26/12*'ОПУ БС'!W26 -> 723.70483 | AB26: =SUM(P26:AA26) -> 6947.5664 | AC26: ='ОПУ БС'!$E26/12*'ОПУ БС'!L26 -> 520.53301 | AD26: ='ОПУ БС'!$E26/12*'ОПУ БС'!M26 -> 595.87332 | AE26: ='ОПУ БС'!$E26/12*'ОПУ БС'!N26 -> 636.96803 | AF26: ='ОПУ БС'!$E26/12*'ОПУ БС'!O26 -> 636.96803 | AG26: ='ОПУ БС'!$E26/12*'ОПУ БС'!P26 -> 650.66627 | AH26: ='ОПУ БС'!$E26/12*'ОПУ БС'!Q26 -> 691.76098 | AI26: ='ОПУ БС'!$E26/12*'ОПУ БС'!R26 -> 794.49776 | AJ26: ='ОПУ БС'!$E26/12*'ОПУ БС'!S26 -> 773.9504 | ... AN26: ='ОПУ БС'!$E26/12*'ОПУ БС'!W26 -> 856.13983 | AO26: =SUM(AC26:AN26) -> 8218.9423 | AP26: ='ОПУ БС'!$F26/12*'ОПУ БС'!L26 -> 621.677 | AQ26: ='ОПУ БС'!$F26/12*'ОПУ БС'!M26 -> 711.65657 | AR26: ='ОПУ БС'!$F26/12*'ОПУ БС'!N26 -> 760.73633 | AS26: ='ОПУ БС'!$F26/12*'ОПУ БС'!O26 -> 760.73633 | AT26: ='ОПУ БС'!$F26/12*'ОПУ БС'!P26 -> 777.09625 | AU26: ='ОПУ БС'!$F26/12*'ОПУ БС'!Q26 -> 826.17602 | AV26: ='ОПУ БС'!$F26/12*'ОПУ БС'!R26 -> 948.87543 | AW26: ='ОПУ БС'!$F26/12*'ОПУ БС'!S26 -> 924.33554 | ... BA26: ='ОПУ БС'!$F26/12*'ОПУ БС'!W26 -> 1022.4951 | BB26: =SUM(AP26:BA26) -> 9815.9527 | BC26: ='ОПУ БС'!$G26/12*'ОПУ БС'!L26 -> 742.95302 | BD26: ='ОПУ БС'!$G26/12*'ОПУ БС'!M26 -> 850.4857 | BE26: ='ОПУ БС'!$G26/12*'ОПУ БС'!N26 -> 909.13988 | BF26: ='ОПУ БС'!$G26/12*'ОПУ БС'!O26 -> 909.13988 | BG26: ='ОПУ БС'!$G26/12*'ОПУ БС'!P26 -> 928.69128 | BH26: ='ОПУ БС'!$G26/12*'ОПУ БС'!Q26 -> 987.34546 | BI26: ='ОПУ БС'!$G26/12*'ОПУ БС'!R26 -> 1133.9809 | BJ26: ='ОПУ БС'!$G26/12*'ОПУ БС'!S26 -> 1104.6538 | ... BN26: ='ОПУ БС'!$G26/12*'ОПУ БС'!W26 -> 1221.9622 | BO26: =SUM(BC26:BN26) -> 11730.837 | BP26: ='ОПУ БС'!$H26/12*'ОПУ БС'!L26 -> 871.74349 | BQ26: ='ОПУ БС'!$H26/12*'ОПУ БС'!M26 -> 997.91689 | BR26: ='ОПУ БС'!$H26/12*'ОПУ БС'!N26 -> 1066.7387 | BS26: ='ОПУ БС'!$H26/12*'ОПУ БС'!O26 -> 1066.7387 | BT26: ='ОПУ БС'!$H26/12*'ОПУ БС'!P26 -> 1089.6794 | BU26: ='ОПУ БС'!$H26/12*'ОПУ БС'!Q26 -> 1158.5012 | BV26: ='ОПУ БС'!$H26/12*'ОПУ БС'!R26 -> 1330.5559 | BW26: ='ОПУ БС'!$H26/12*'ОПУ БС'!S26 -> 1296.1449 | ... CA26: ='ОПУ БС'!$H26/12*'ОПУ БС'!W26 -> 1433.7886 | CB26: =SUM(BP26:CA26) -> 13764.371 | CC26: ='ОПУ БС'!$I26/12*'ОПУ БС'!L26 -> 1033.3386 | CD26: ='ОПУ БС'!$I26/12*'ОПУ БС'!M26 -> 1182.9007 | CE26: ='ОПУ БС'!$I26/12*'ОПУ БС'!N26 -> 1264.4801 | CF26: ='ОПУ БС'!$I26/12*'ОПУ БС'!O26 -> 1264.4801 | CG26: ='ОПУ БС'!$I26/12*'ОПУ БС'!P26 -> 1291.6732 | CH26: ='ОПУ БС'!$I26/12*'ОПУ БС'!Q26 -> 1373.2526 | CI26: ='ОПУ БС'!$I26/12*'ОПУ БС'!R26 -> 1577.201 | CJ26: ='ОПУ БС'!$I26/12*'ОПУ БС'!S26 -> 1536.4113 | ... CN26: ='ОПУ БС'!$I26/12*'ОПУ БС'!W26 -> 1699.57 | CO26: =SUM(CC26:CN26) -> 16315.872 | CR26: =O26-'ОПУ БС'!C26 -> 0 | CS26: =AB26-'ОПУ БС'!D26 -> 0 | CT26: =AO26-'ОПУ БС'!E26 -> 0 | CU26: =BB26-'ОПУ БС'!F26 -> 0 | CV26: =BO26-'ОПУ БС'!G26 -> 0 | CW26: =CB26-'ОПУ БС'!H26 -> 0 | CX26: =CO26-'ОПУ БС'!I26 -> 0 | DM26: =SUM(DA26:DL26) -> 0 | DZ26: =SUM(DN26:DY26) -> 0 | EM26: =SUM(EA26:EL26) -> 0 | EZ26: =SUM(EN26:EY26) -> 0 | FM26: =SUM(FA26:FL26) -> 0 | FP26: =C26 -> 512.68557 | FQ26: =D26 -> 586.89006 | FR26: =E26 -> 627.36524 | FS26: =F26 -> 627.36524 | FT26: =G26 -> 640.85697 | FU26: =H26 -> 681.33214 | FV26: =I26 -> 782.52009 | FW26: =J26 -> 762.2825 | ... GA26: =N26 -> 843.23285 | GB26: =SUM(FP26:GA26) -> 8095.0354 | GC26: =P26 -> 440.01254 | GD26: =Q26 -> 503.69856 | GE26: =R26 -> 538.43639 | GF26: =S26 -> 538.43639 | GG26: =T26 -> 550.01567 | GH26: =U26 -> 584.7535 | GI26: =V26 -> 671.59808 | GJ26: =W26 -> 654.22917 | ... GN26: =AA26 -> 723.70483 | GO26: =SUM(GC26:GN26) -> 6947.5664 | GP26: =AC26+DA26 -> 520.53301 | GQ26: =AD26+DB26 -> 595.87332 | GR26: =AE26+DC26 -> 636.96803 | GS26: =AF26+DD26 -> 636.96803 | GT26: =AG26+DE26 -> 650.66627 | GU26: =AH26+DF26 -> 691.76098 | GV26: =AI26+DG26 -> 794.49776 | GW26: =AJ26+DH26 -> 773.9504 | ... HA26: =AN26+DL26 -> 856.13983 | HB26: =SUM(GP26:HA26) -> 8218.9423 | HC26: =AP26+DN26 -> 621.677 | HD26: =AQ26+DO26 -> 711.65657 | HE26: =AR26+DP26 -> 760.73633 | HF26: =AS26+DQ26 -> 760.73633 | HG26: =AT26+DR26 -> 777.09625 | HH26: =AU26+DS26 -> 826.17602 | HI26: =AV26+DT26 -> 948.87543 | HJ26: =AW26+DU26 -> 924.33554 | ... HN26: =BA26+DY26 -> 1022.4951 | HO26: =SUM(HC26:HN26) -> 9815.9527 | HP26: =BC26+EA26 -> 742.95302 | HQ26: =BD26+EB26 -> 850.4857 | HR26: =BE26+EC26 -> 909.13988 | HS26: =BF26+ED26 -> 909.13988 | HT26: =BG26+EE26 -> 928.69128 | HU26: =BH26+EF26 -> 987.34546 | HV26: =BI26+EG26 -> 1133.9809 | HW26: =BJ26+EH26 -> 1104.6538 | ... IA26: =BN26+EL26 -> 1221.9622 | IB26: =SUM(HP26:IA26) -> 11730.837 | IC26: =BP26+EN26 -> 871.74349 | ID26: =BQ26+EO26 -> 997.91689 | IE26: =BR26+EP26 -> 1066.7387 | IF26: =BS26+EQ26 -> 1066.7387 | IG26: =BT26+ER26 -> 1089.6794 | IH26: =BU26+ES26 -> 1158.5012 | II26: =BV26+ET26 -> 1330.5559 | IJ26: =BW26+EU26 -> 1296.1449 | ... IN26: =CA26+EY26 -> 1433.7886 | IO26: =SUM(IC26:IN26) -> 13764.371 | IP26: =CC26+FA26 -> 1033.3386 | IQ26: =CD26+FB26 -> 1182.9007 | IR26: =CE26+FC26 -> 1264.4801 | IS26: =CF26+FD26 -> 1264.4801 | IT26: =CG26+FE26 -> 1291.6732 | IU26: =CH26+FF26 -> 1373.2526 | IV26: =CI26+FG26 -> 1577.201 | IW26: =CJ26+FH26 -> 1536.4113 | ... JA26: =CN26+FL26 -> 1699.57 | JB26: =SUM(IP26:JA26) -> 16315.872 | JE26: =O26-GB26 -> 0 | JF26: =AB26-GO26 -> 0 | JG26: =AO26+DM26-HB26 -> 0 | JH26: =BB26+DZ26-HO26 -> 0 | JI26: =BO26+EM26-IB26 -> 0 | JJ26: =CB26+EZ26-IO26 -> 0 | JK26: =CO26+FM26-JB26 -> 0
B27: Сырный | C27: ='ОПУ БС'!$C27/12*'ОПУ БС'!L27 -> 597.07502 | D27: ='ОПУ БС'!$C27/12*'ОПУ БС'!M27 -> 652.06877 | E27: ='ОПУ БС'!$C27/12*'ОПУ БС'!N27 -> 746.34378 | F27: ='ОПУ БС'!$C27/12*'ОПУ БС'!O27 -> 730.63128 | G27: ='ОПУ БС'!$C27/12*'ОПУ БС'!P27 -> 746.34378 | H27: ='ОПУ БС'!$C27/12*'ОПУ БС'!Q27 -> 793.48128 | I27: ='ОПУ БС'!$C27/12*'ОПУ БС'!R27 -> 911.32503 | J27: ='ОПУ БС'!$C27/12*'ОПУ БС'!S27 -> 887.75628 | ... N27: ='ОПУ БС'!$C27/12*'ОПУ БС'!W27 -> 982.03128 | O27: =SUM(C27:N27) -> 9427.5003 | P27: ='ОПУ БС'!$D27/12*'ОПУ БС'!L27 -> 633.45392 | Q27: ='ОПУ БС'!$D27/12*'ОПУ БС'!M27 -> 691.79836 | R27: ='ОПУ БС'!$D27/12*'ОПУ БС'!N27 -> 791.8174 | S27: ='ОПУ БС'!$D27/12*'ОПУ БС'!O27 -> 775.14756 | T27: ='ОПУ БС'!$D27/12*'ОПУ БС'!P27 -> 791.8174 | U27: ='ОПУ БС'!$D27/12*'ОПУ БС'!Q27 -> 841.82692 | V27: ='ОПУ БС'!$D27/12*'ОПУ БС'!R27 -> 966.85072 | W27: ='ОПУ БС'!$D27/12*'ОПУ БС'!S27 -> 941.84596 | ... AA27: ='ОПУ БС'!$D27/12*'ОПУ БС'!W27 -> 1041.865 | AB27: =SUM(P27:AA27) -> 10001.904 | AC27: ='ОПУ БС'!$E27/12*'ОПУ БС'!L27 -> 775.24047 | AD27: ='ОПУ БС'!$E27/12*'ОПУ БС'!M27 -> 846.6442 | AE27: ='ОПУ БС'!$E27/12*'ОПУ БС'!N27 -> 969.05059 | AF27: ='ОПУ БС'!$E27/12*'ОПУ БС'!O27 -> 948.64952 | AG27: ='ОПУ БС'!$E27/12*'ОПУ БС'!P27 -> 969.05059 | AH27: ='ОПУ БС'!$E27/12*'ОПУ БС'!Q27 -> 1030.2538 | AI27: ='ОПУ БС'!$E27/12*'ОПУ БС'!R27 -> 1183.2618 | AJ27: ='ОПУ БС'!$E27/12*'ОПУ БС'!S27 -> 1152.6602 | ... AN27: ='ОПУ БС'!$E27/12*'ОПУ БС'!W27 -> 1275.0666 | AO27: =SUM(AC27:AN27) -> 12240.639 | AP27: ='ОПУ БС'!$F27/12*'ОПУ БС'!L27 -> 847.05846 | AQ27: ='ОПУ БС'!$F27/12*'ОПУ БС'!M27 -> 925.07701 | AR27: ='ОПУ БС'!$F27/12*'ОПУ БС'!N27 -> 1058.8231 | AS27: ='ОПУ БС'!$F27/12*'ОПУ БС'!O27 -> 1036.5321 | AT27: ='ОПУ БС'!$F27/12*'ОПУ БС'!P27 -> 1058.8231 | AU27: ='ОПУ БС'!$F27/12*'ОПУ БС'!Q27 -> 1125.6961 | AV27: ='ОПУ БС'!$F27/12*'ОПУ БС'!R27 -> 1292.8787 | AW27: ='ОПУ БС'!$F27/12*'ОПУ БС'!S27 -> 1259.4422 | ... BA27: ='ОПУ БС'!$F27/12*'ОПУ БС'!W27 -> 1393.1883 | BB27: =SUM(AP27:BA27) -> 13374.607 | BC27: ='ОПУ БС'!$G27/12*'ОПУ БС'!L27 -> 954.90182 | BD27: ='ОПУ БС'!$G27/12*'ОПУ БС'!M27 -> 1042.8533 | BE27: ='ОПУ БС'!$G27/12*'ОПУ БС'!N27 -> 1193.6273 | BF27: ='ОПУ БС'!$G27/12*'ОПУ БС'!O27 -> 1168.4983 | BG27: ='ОПУ БС'!$G27/12*'ОПУ БС'!P27 -> 1193.6273 | BH27: ='ОПУ БС'!$G27/12*'ОПУ БС'!Q27 -> 1269.0143 | BI27: ='ОПУ БС'!$G27/12*'ОПУ БС'!R27 -> 1457.4817 | BJ27: ='ОПУ БС'!$G27/12*'ОПУ БС'!S27 -> 1419.7882 | ... BN27: ='ОПУ БС'!$G27/12*'ОПУ БС'!W27 -> 1570.5622 | BO27: =SUM(BC27:BN27) -> 15077.397 | BP27: ='ОПУ БС'!$H27/12*'ОПУ БС'!L27 -> 1082.6541 | BQ27: ='ОПУ БС'!$H27/12*'ОПУ БС'!M27 -> 1182.3722 | BR27: ='ОПУ БС'!$H27/12*'ОПУ БС'!N27 -> 1353.3176 | BS27: ='ОПУ БС'!$H27/12*'ОПУ БС'!O27 -> 1324.8267 | BT27: ='ОПУ БС'!$H27/12*'ОПУ БС'!P27 -> 1353.3176 | BU27: ='ОПУ БС'!$H27/12*'ОПУ БС'!Q27 -> 1438.7903 | BV27: ='ОПУ БС'!$H27/12*'ОПУ БС'!R27 -> 1652.472 | BW27: ='ОПУ БС'!$H27/12*'ОПУ БС'!S27 -> 1609.7357 | ... CA27: ='ОПУ БС'!$H27/12*'ОПУ БС'!W27 -> 1780.681 | CB27: =SUM(BP27:CA27) -> 17094.538 | CC27: ='ОПУ БС'!$I27/12*'ОПУ БС'!L27 -> 1272.4354 | CD27: ='ОПУ БС'!$I27/12*'ОПУ БС'!M27 -> 1389.6333 | CE27: ='ОПУ БС'!$I27/12*'ОПУ БС'!N27 -> 1590.5442 | CF27: ='ОПУ БС'!$I27/12*'ОПУ БС'!O27 -> 1557.0591 | CG27: ='ОПУ БС'!$I27/12*'ОПУ БС'!P27 -> 1590.5442 | CH27: ='ОПУ БС'!$I27/12*'ОПУ БС'!Q27 -> 1690.9996 | CI27: ='ОПУ БС'!$I27/12*'ОПУ БС'!R27 -> 1942.1382 | CJ27: ='ОПУ БС'!$I27/12*'ОПУ БС'!S27 -> 1891.9105 | ... CN27: ='ОПУ БС'!$I27/12*'ОПУ БС'!W27 -> 2092.8213 | CO27: =SUM(CC27:CN27) -> 20091.085 | CR27: =O27-'ОПУ БС'!C27 -> 0 | CS27: =AB27-'ОПУ БС'!D27 -> 0 | CT27: =AO27-'ОПУ БС'!E27 -> 0 | CU27: =BB27-'ОПУ БС'!F27 -> 0 | CV27: =BO27-'ОПУ БС'!G27 -> 0 | CW27: =CB27-'ОПУ БС'!H27 -> 0 | CX27: =CO27-'ОПУ БС'!I27 -> 0 | DM27: =SUM(DA27:DL27) -> 0 | DZ27: =SUM(DN27:DY27) -> 0 | EM27: =SUM(EA27:EL27) -> 0 | EZ27: =SUM(EN27:EY27) -> 0 | FM27: =SUM(FA27:FL27) -> 0 | FP27: =C27 -> 597.07502 | FQ27: =D27 -> 652.06877 | FR27: =E27 -> 746.34378 | FS27: =F27 -> 730.63128 | FT27: =G27 -> 746.34378 | FU27: =H27 -> 793.48128 | FV27: =I27 -> 911.32503 | FW27: =J27 -> 887.75628 | ... GA27: =N27 -> 982.03128 | GB27: =SUM(FP27:GA27) -> 9427.5003 | GC27: =P27 -> 633.45392 | GD27: =Q27 -> 691.79836 | GE27: =R27 -> 791.8174 | GF27: =S27 -> 775.14756 | GG27: =T27 -> 791.8174 | GH27: =U27 -> 841.82692 | GI27: =V27 -> 966.85072 | GJ27: =W27 -> 941.84596 | ... GN27: =AA27 -> 1041.865 | GO27: =SUM(GC27:GN27) -> 10001.904 | GP27: =AC27+DA27 -> 775.24047 | GQ27: =AD27+DB27 -> 846.6442 | GR27: =AE27+DC27 -> 969.05059 | GS27: =AF27+DD27 -> 948.64952 | GT27: =AG27+DE27 -> 969.05059 | GU27: =AH27+DF27 -> 1030.2538 | GV27: =AI27+DG27 -> 1183.2618 | GW27: =AJ27+DH27 -> 1152.6602 | ... HA27: =AN27+DL27 -> 1275.0666 | HB27: =SUM(GP27:HA27) -> 12240.639 | HC27: =AP27+DN27 -> 847.05846 | HD27: =AQ27+DO27 -> 925.07701 | HE27: =AR27+DP27 -> 1058.8231 | HF27: =AS27+DQ27 -> 1036.5321 | HG27: =AT27+DR27 -> 1058.8231 | HH27: =AU27+DS27 -> 1125.6961 | HI27: =AV27+DT27 -> 1292.8787 | HJ27: =AW27+DU27 -> 1259.4422 | ... HN27: =BA27+DY27 -> 1393.1883 | HO27: =SUM(HC27:HN27) -> 13374.607 | HP27: =BC27+EA27 -> 954.90182 | HQ27: =BD27+EB27 -> 1042.8533 | HR27: =BE27+EC27 -> 1193.6273 | HS27: =BF27+ED27 -> 1168.4983 | HT27: =BG27+EE27 -> 1193.6273 | HU27: =BH27+EF27 -> 1269.0143 | HV27: =BI27+EG27 -> 1457.4817 | HW27: =BJ27+EH27 -> 1419.7882 | ... IA27: =BN27+EL27 -> 1570.5622 | IB27: =SUM(HP27:IA27) -> 15077.397 | IC27: =BP27+EN27 -> 1082.6541 | ID27: =BQ27+EO27 -> 1182.3722 | IE27: =BR27+EP27 -> 1353.3176 | IF27: =BS27+EQ27 -> 1324.8267 | IG27: =BT27+ER27 -> 1353.3176 | IH27: =BU27+ES27 -> 1438.7903 | II27: =BV27+ET27 -> 1652.472 | IJ27: =BW27+EU27 -> 1609.7357 | ... IN27: =CA27+EY27 -> 1780.681 | IO27: =SUM(IC27:IN27) -> 17094.538 | IP27: =CC27+FA27 -> 1272.4354 | IQ27: =CD27+FB27 -> 1389.6333 | IR27: =CE27+FC27 -> 1590.5442 | IS27: =CF27+FD27 -> 1557.0591 | IT27: =CG27+FE27 -> 1590.5442 | IU27: =CH27+FF27 -> 1690.9996 | IV27: =CI27+FG27 -> 1942.1382 | IW27: =CJ27+FH27 -> 1891.9105 | ... JA27: =CN27+FL27 -> 2092.8213 | JB27: =SUM(IP27:JA27) -> 20091.085 | JE27: =O27-GB27 -> 0 | JF27: =AB27-GO27 -> 0 | JG27: =AO27+DM27-HB27 -> 0 | JH27: =BB27+DZ27-HO27 -> 0 | JI27: =BO27+EM27-IB27 -> 0 | JJ27: =CB27+EZ27-IO27 -> 0 | JK27: =CO27+FM27-JB27 -> 0
B28: Кисло-сладкий | C28: ='ОПУ БС'!$C28/12*'ОПУ БС'!L28 -> 241.43755 | D28: ='ОПУ БС'!$C28/12*'ОПУ БС'!M28 -> 263.67522 | E28: ='ОПУ БС'!$C28/12*'ОПУ БС'!N28 -> 295.44332 | F28: ='ОПУ БС'!$C28/12*'ОПУ БС'!O28 -> 282.73608 | G28: ='ОПУ БС'!$C28/12*'ОПУ БС'!P28 -> 301.79694 | H28: ='ОПУ БС'!$C28/12*'ОПУ БС'!Q28 -> 320.8578 | I28: ='ОПУ БС'!$C28/12*'ОПУ БС'!R28 -> 368.50994 | J28: ='ОПУ БС'!$C28/12*'ОПУ БС'!S28 -> 358.97952 | ... N28: ='ОПУ БС'!$C28/12*'ОПУ БС'!W28 -> 397.10123 | O28: =SUM(C28:N28) -> 3812.1718 | P28: ='ОПУ БС'!$D28/12*'ОПУ БС'!L28 -> 276.07493 | Q28: ='ОПУ БС'!$D28/12*'ОПУ БС'!M28 -> 301.50289 | R28: ='ОПУ БС'!$D28/12*'ОПУ БС'!N28 -> 337.82854 | S28: ='ОПУ БС'!$D28/12*'ОПУ БС'!O28 -> 323.29828 | T28: ='ОПУ БС'!$D28/12*'ОПУ БС'!P28 -> 345.09367 | U28: ='ОПУ БС'!$D28/12*'ОПУ БС'!Q28 -> 366.88906 | V28: ='ОПУ БС'!$D28/12*'ОПУ БС'!R28 -> 421.37753 | W28: ='ОПУ БС'!$D28/12*'ОПУ БС'!S28 -> 410.47984 | ... AA28: ='ОПУ БС'!$D28/12*'ОПУ БС'!W28 -> 454.07062 | AB28: =SUM(P28:AA28) -> 4359.0779 | AC28: ='ОПУ БС'!$E28/12*'ОПУ БС'!L28 -> 338.4671 | AD28: ='ОПУ БС'!$E28/12*'ОПУ БС'!M28 -> 369.64171 | AE28: ='ОПУ БС'!$E28/12*'ОПУ БС'!N28 -> 414.17685 | AF28: ='ОПУ БС'!$E28/12*'ОПУ БС'!O28 -> 396.36279 | AG28: ='ОПУ БС'!$E28/12*'ОПУ БС'!P28 -> 423.08388 | AH28: ='ОПУ БС'!$E28/12*'ОПУ БС'!Q28 -> 449.80497 | AI28: ='ОПУ БС'!$E28/12*'ОПУ БС'!R28 -> 516.60768 | AJ28: ='ОПУ БС'!$E28/12*'ОПУ БС'!S28 -> 503.24714 | ... AN28: ='ОПУ БС'!$E28/12*'ОПУ БС'!W28 -> 556.68932 | AO28: =SUM(AC28:AN28) -> 5344.2174 | AP28: ='ОПУ БС'!$F28/12*'ОПУ БС'!L28 -> 407.51687 | AQ28: ='ОПУ БС'!$F28/12*'ОПУ БС'!M28 -> 445.05132 | AR28: ='ОПУ БС'!$F28/12*'ОПУ БС'!N28 -> 498.67196 | AS28: ='ОПУ БС'!$F28/12*'ОПУ БС'!O28 -> 477.22371 | AT28: ='ОПУ БС'!$F28/12*'ОПУ БС'!P28 -> 509.39609 | AU28: ='ОПУ БС'!$F28/12*'ОПУ БС'!Q28 -> 541.56848 | AV28: ='ОПУ БС'!$F28/12*'ОПУ БС'!R28 -> 621.99944 | AW28: ='ОПУ БС'!$F28/12*'ОПУ БС'!S28 -> 605.91325 | ... BA28: ='ОПУ БС'!$F28/12*'ОПУ БС'!W28 -> 670.25802 | BB28: =SUM(AP28:BA28) -> 6434.4769 | BC28: ='ОПУ БС'!$G28/12*'ОПУ БС'!L28 -> 487.11275 | BD28: ='ОПУ БС'!$G28/12*'ОПУ БС'!M28 -> 531.97839 | BE28: ='ОПУ БС'!$G28/12*'ОПУ БС'!N28 -> 596.07217 | BF28: ='ОПУ БС'!$G28/12*'ОПУ БС'!O28 -> 570.43466 | BG28: ='ОПУ БС'!$G28/12*'ОПУ БС'!P28 -> 608.89093 | BH28: ='ОПУ БС'!$G28/12*'ОПУ БС'!Q28 -> 647.3472 | BI28: ='ОПУ БС'!$G28/12*'ОПУ БС'!R28 -> 743.48787 | BJ28: ='ОПУ БС'!$G28/12*'ОПУ БС'!S28 -> 724.25974 | ... BN28: ='ОПУ БС'!$G28/12*'ОПУ БС'!W28 -> 801.17228 | BO28: =SUM(BC28:BN28) -> 7691.2539 | BP28: ='ОПУ БС'!$H28/12*'ОПУ БС'!L28 -> 568.99239 | BQ28: ='ОПУ БС'!$H28/12*'ОПУ БС'!M28 -> 621.39959 | BR28: ='ОПУ БС'!$H28/12*'ОПУ БС'!N28 -> 696.26701 | BS28: ='ОПУ БС'!$H28/12*'ОПУ БС'!O28 -> 666.32004 | BT28: ='ОПУ БС'!$H28/12*'ОПУ БС'!P28 -> 711.24049 | BU28: ='ОПУ БС'!$H28/12*'ОПУ БС'!Q28 -> 756.16094 | BV28: ='ОПУ БС'!$H28/12*'ОПУ БС'!R28 -> 868.46207 | BW28: ='ОПУ БС'!$H28/12*'ОПУ БС'!S28 -> 846.00185 | ... CA28: ='ОПУ БС'!$H28/12*'ОПУ БС'!W28 -> 935.84275 | CB28: =SUM(BP28:CA28) -> 8984.0904 | CC28: ='ОПУ БС'!$I28/12*'ОПУ БС'!L28 -> 672.62023 | CD28: ='ОПУ БС'!$I28/12*'ОПУ БС'!M28 -> 734.57209 | CE28: ='ОПУ БС'!$I28/12*'ОПУ БС'!N28 -> 823.07475 | CF28: ='ОПУ БС'!$I28/12*'ОПУ БС'!O28 -> 787.67369 | CG28: ='ОПУ БС'!$I28/12*'ОПУ БС'!P28 -> 840.77529 | CH28: ='ОПУ БС'!$I28/12*'ОПУ БС'!Q28 -> 893.87688 | CI28: ='ОПУ БС'!$I28/12*'ОПУ БС'!R28 -> 1026.6309 | CJ28: ='ОПУ БС'!$I28/12*'ОПУ БС'!S28 -> 1000.0801 | ... CN28: ='ОПУ БС'!$I28/12*'ОПУ БС'!W28 -> 1106.2833 | CO28: =SUM(CC28:CN28) -> 10620.319 | CR28: =O28-'ОПУ БС'!C28 -> 0 | CS28: =AB28-'ОПУ БС'!D28 -> 0 | CT28: =AO28-'ОПУ БС'!E28 -> 0 | CU28: =BB28-'ОПУ БС'!F28 -> 0 | CV28: =BO28-'ОПУ БС'!G28 -> 0 | CW28: =CB28-'ОПУ БС'!H28 -> 0 | CX28: =CO28-'ОПУ БС'!I28 -> 0 | DM28: =SUM(DA28:DL28) -> 0 | DZ28: =SUM(DN28:DY28) -> 0 | EM28: =SUM(EA28:EL28) -> 0 | EZ28: =SUM(EN28:EY28) -> 0 | FM28: =SUM(FA28:FL28) -> 0 | FP28: =C28 -> 241.43755 | FQ28: =D28 -> 263.67522 | FR28: =E28 -> 295.44332 | FS28: =F28 -> 282.73608 | FT28: =G28 -> 301.79694 | FU28: =H28 -> 320.8578 | FV28: =I28 -> 368.50994 | FW28: =J28 -> 358.97952 | ... GA28: =N28 -> 397.10123 | GB28: =SUM(FP28:GA28) -> 3812.1718 | GC28: =P28 -> 276.07493 | GD28: =Q28 -> 301.50289 | GE28: =R28 -> 337.82854 | GF28: =S28 -> 323.29828 | GG28: =T28 -> 345.09367 | GH28: =U28 -> 366.88906 | GI28: =V28 -> 421.37753 | GJ28: =W28 -> 410.47984 | ... GN28: =AA28 -> 454.07062 | GO28: =SUM(GC28:GN28) -> 4359.0779 | GP28: =AC28+DA28 -> 338.4671 | GQ28: =AD28+DB28 -> 369.64171 | GR28: =AE28+DC28 -> 414.17685 | GS28: =AF28+DD28 -> 396.36279 | GT28: =AG28+DE28 -> 423.08388 | GU28: =AH28+DF28 -> 449.80497 | GV28: =AI28+DG28 -> 516.60768 | GW28: =AJ28+DH28 -> 503.24714 | ... HA28: =AN28+DL28 -> 556.68932 | HB28: =SUM(GP28:HA28) -> 5344.2174 | HC28: =AP28+DN28 -> 407.51687 | HD28: =AQ28+DO28 -> 445.05132 | HE28: =AR28+DP28 -> 498.67196 | HF28: =AS28+DQ28 -> 477.22371 | HG28: =AT28+DR28 -> 509.39609 | HH28: =AU28+DS28 -> 541.56848 | HI28: =AV28+DT28 -> 621.99944 | HJ28: =AW28+DU28 -> 605.91325 | ... HN28: =BA28+DY28 -> 670.25802 | HO28: =SUM(HC28:HN28) -> 6434.4769 | HP28: =BC28+EA28 -> 487.11275 | HQ28: =BD28+EB28 -> 531.97839 | HR28: =BE28+EC28 -> 596.07217 | HS28: =BF28+ED28 -> 570.43466 | HT28: =BG28+EE28 -> 608.89093 | HU28: =BH28+EF28 -> 647.3472 | HV28: =BI28+EG28 -> 743.48787 | HW28: =BJ28+EH28 -> 724.25974 | ... IA28: =BN28+EL28 -> 801.17228 | IB28: =SUM(HP28:IA28) -> 7691.2539 | IC28: =BP28+EN28 -> 568.99239 | ID28: =BQ28+EO28 -> 621.39959 | IE28: =BR28+EP28 -> 696.26701 | IF28: =BS28+EQ28 -> 666.32004 | IG28: =BT28+ER28 -> 711.24049 | IH28: =BU28+ES28 -> 756.16094 | II28: =BV28+ET28 -> 868.46207 | IJ28: =BW28+EU28 -> 846.00185 | ... IN28: =CA28+EY28 -> 935.84275 | IO28: =SUM(IC28:IN28) -> 8984.0904 | IP28: =CC28+FA28 -> 672.62023 | IQ28: =CD28+FB28 -> 734.57209 | IR28: =CE28+FC28 -> 823.07475 | IS28: =CF28+FD28 -> 787.67369 | IT28: =CG28+FE28 -> 840.77529 | IU28: =CH28+FF28 -> 893.87688 | IV28: =CI28+FG28 -> 1026.6309 | IW28: =CJ28+FH28 -> 1000.0801 | ... JA28: =CN28+FL28 -> 1106.2833 | JB28: =SUM(IP28:JA28) -> 10620.319 | JE28: =O28-GB28 -> 0 | JF28: =AB28-GO28 -> 0 | JG28: =AO28+DM28-HB28 -> 0 | JH28: =BB28+DZ28-HO28 -> 0 | JI28: =BO28+EM28-IB28 -> 0 | JJ28: =CB28+EZ28-IO28 -> 0 | JK28: =CO28+FM28-JB28 -> 0
B29: Чесночный | C29: ='ОПУ БС'!$C29/12*'ОПУ БС'!L29 -> 146.28533 | D29: ='ОПУ БС'!$C29/12*'ОПУ БС'!M29 -> 159.75898 | E29: ='ОПУ БС'!$C29/12*'ОПУ БС'!N29 -> 179.00705 | F29: ='ОПУ БС'!$C29/12*'ОПУ БС'!O29 -> 179.00705 | G29: ='ОПУ БС'!$C29/12*'ОПУ БС'!P29 -> 179.00705 | H29: ='ОПУ БС'!$C29/12*'ОПУ БС'!Q29 -> 194.4055 | I29: ='ОПУ БС'!$C29/12*'ОПУ БС'!R29 -> 223.27761 | J29: ='ОПУ БС'!$C29/12*'ОПУ БС'!S29 -> 217.50318 | ... N29: ='ОПУ БС'!$C29/12*'ОПУ БС'!W29 -> 240.60087 | O29: =SUM(C29:N29) -> 2309.7683 | P29: ='ОПУ БС'!$D29/12*'ОПУ БС'!L29 -> 250.1971 | Q29: ='ОПУ БС'!$D29/12*'ОПУ БС'!M29 -> 273.24157 | R29: ='ОПУ БС'!$D29/12*'ОПУ БС'!N29 -> 306.16225 | S29: ='ОПУ БС'!$D29/12*'ОПУ БС'!O29 -> 306.16225 | T29: ='ОПУ БС'!$D29/12*'ОПУ БС'!P29 -> 306.16225 | U29: ='ОПУ БС'!$D29/12*'ОПУ БС'!Q29 -> 332.49878 | V29: ='ОПУ БС'!$D29/12*'ОПУ БС'!R29 -> 381.87979 | W29: ='ОПУ БС'!$D29/12*'ОПУ БС'!S29 -> 372.00359 | ... AA29: ='ОПУ БС'!$D29/12*'ОПУ БС'!W29 -> 411.5084 | AB29: =SUM(P29:AA29) -> 3950.4806 | AC29: ='ОПУ БС'!$E29/12*'ОПУ БС'!L29 -> 407.08805 | AD29: ='ОПУ БС'!$E29/12*'ОПУ БС'!M29 -> 444.58301 | AE29: ='ОПУ БС'!$E29/12*'ОПУ БС'!N29 -> 498.14722 | AF29: ='ОПУ БС'!$E29/12*'ОПУ БС'!O29 -> 498.14722 | AG29: ='ОПУ БС'!$E29/12*'ОПУ БС'!P29 -> 498.14722 | AH29: ='ОПУ БС'!$E29/12*'ОПУ БС'!Q29 -> 540.9986 | AI29: ='ОПУ БС'!$E29/12*'ОПУ БС'!R29 -> 621.34492 | AJ29: ='ОПУ БС'!$E29/12*'ОПУ БС'!S29 -> 605.27566 | ... AN29: ='ОПУ БС'!$E29/12*'ОПУ БС'!W29 -> 669.55272 | AO29: =SUM(AC29:AN29) -> 6427.7061 | AP29: ='ОПУ БС'!$F29/12*'ОПУ БС'!L29 -> 611.07026 | AQ29: ='ОПУ БС'!$F29/12*'ОПУ БС'!M29 -> 667.35305 | AR29: ='ОПУ БС'!$F29/12*'ОПУ БС'!N29 -> 747.75703 | AS29: ='ОПУ БС'!$F29/12*'ОПУ БС'!O29 -> 747.75703 | AT29: ='ОПУ БС'!$F29/12*'ОПУ БС'!P29 -> 747.75703 | AU29: ='ОПУ БС'!$F29/12*'ОПУ БС'!Q29 -> 812.08021 | AV29: ='ОПУ БС'!$F29/12*'ОПУ БС'!R29 -> 932.68618 | AW29: ='ОПУ БС'!$F29/12*'ОПУ БС'!S29 -> 908.56499 | ... BA29: ='ОПУ БС'!$F29/12*'ОПУ БС'!W29 -> 1005.0498 | BB29: =SUM(AP29:BA29) -> 9648.4778 | BC29: ='ОПУ БС'!$G29/12*'ОПУ БС'!L29 -> 866.54719 | BD29: ='ОПУ БС'!$G29/12*'ОПУ БС'!M29 -> 946.36075 | BE29: ='ОПУ БС'!$G29/12*'ОПУ БС'!N29 -> 1060.3801 | BF29: ='ОПУ БС'!$G29/12*'ОПУ БС'!O29 -> 1060.3801 | BG29: ='ОПУ БС'!$G29/12*'ОПУ БС'!P29 -> 1060.3801 | BH29: ='ОПУ БС'!$G29/12*'ОПУ БС'!Q29 -> 1151.5956 | BI29: ='ОПУ БС'!$G29/12*'ОПУ БС'!R29 -> 1322.6247 | BJ29: ='ОПУ БС'!$G29/12*'ОПУ БС'!S29 -> 1288.4189 | ... BN29: ='ОПУ БС'!$G29/12*'ОПУ БС'!W29 -> 1425.2421 | BO29: =SUM(BC29:BN29) -> 13682.324 | BP29: ='ОПУ БС'!$H29/12*'ОПУ БС'!L29 -> 1165.9126 | BQ29: ='ОПУ БС'!$H29/12*'ОПУ БС'!M29 -> 1273.2992 | BR29: ='ОПУ БС'!$H29/12*'ОПУ БС'!N29 -> 1426.7088 | BS29: ='ОПУ БС'!$H29/12*'ОПУ БС'!O29 -> 1426.7088 | BT29: ='ОПУ БС'!$H29/12*'ОПУ БС'!P29 -> 1426.7088 | BU29: ='ОПУ БС'!$H29/12*'ОПУ БС'!Q29 -> 1549.4364 | BV29: ='ОПУ БС'!$H29/12*'ОПУ БС'!R29 -> 1779.5507 | BW29: ='ОПУ БС'!$H29/12*'ОПУ БС'!S29 -> 1733.5279 | ... CA29: ='ОПУ БС'!$H29/12*'ОПУ БС'!W29 -> 1917.6193 | CB29: =SUM(BP29:CA29) -> 18409.146 | CC29: ='ОПУ БС'!$I29/12*'ОПУ БС'!L29 -> 1514.6504 | CD29: ='ОПУ БС'!$I29/12*'ОПУ БС'!M29 -> 1654.1577 | CE29: ='ОПУ БС'!$I29/12*'ОПУ БС'!N29 -> 1853.4538 | CF29: ='ОПУ БС'!$I29/12*'ОПУ БС'!O29 -> 1853.4538 | CG29: ='ОПУ БС'!$I29/12*'ОПУ БС'!P29 -> 1853.4538 | CH29: ='ОПУ БС'!$I29/12*'ОПУ БС'!Q29 -> 2012.8907 | CI29: ='ОПУ БС'!$I29/12*'ОПУ БС'!R29 -> 2311.8349 | CJ29: ='ОПУ БС'!$I29/12*'ОПУ БС'!S29 -> 2252.0461 | ... CN29: ='ОПУ БС'!$I29/12*'ОПУ БС'!W29 -> 2491.2014 | CO29: =SUM(CC29:CN29) -> 23915.533 | CR29: =O29-'ОПУ БС'!C29 -> 0 | CS29: =AB29-'ОПУ БС'!D29 -> 0 | CT29: =AO29-'ОПУ БС'!E29 -> 0 | CU29: =BB29-'ОПУ БС'!F29 -> 0 | CV29: =BO29-'ОПУ БС'!G29 -> 0 | CW29: =CB29-'ОПУ БС'!H29 -> 0 | CX29: =CO29-'ОПУ БС'!I29 -> 0 | DM29: =SUM(DA29:DL29) -> 0 | DZ29: =SUM(DN29:DY29) -> 0 | EM29: =SUM(EA29:EL29) -> 0 | EZ29: =SUM(EN29:EY29) -> 0 | FM29: =SUM(FA29:FL29) -> 0 | FP29: =C29 -> 146.28533 | FQ29: =D29 -> 159.75898 | FR29: =E29 -> 179.00705 | FS29: =F29 -> 179.00705 | FT29: =G29 -> 179.00705 | FU29: =H29 -> 194.4055 | FV29: =I29 -> 223.27761 | FW29: =J29 -> 217.50318 | ... GA29: =N29 -> 240.60087 | GB29: =SUM(FP29:GA29) -> 2309.7683 | GC29: =P29 -> 250.1971 | GD29: =Q29 -> 273.24157 | GE29: =R29 -> 306.16225 | GF29: =S29 -> 306.16225 | GG29: =T29 -> 306.16225 | GH29: =U29 -> 332.49878 | GI29: =V29 -> 381.87979 | GJ29: =W29 -> 372.00359 | ... GN29: =AA29 -> 411.5084 | GO29: =SUM(GC29:GN29) -> 3950.4806 | GP29: =AC29+DA29 -> 407.08805 | GQ29: =AD29+DB29 -> 444.58301 | GR29: =AE29+DC29 -> 498.14722 | GS29: =AF29+DD29 -> 498.14722 | GT29: =AG29+DE29 -> 498.14722 | GU29: =AH29+DF29 -> 540.9986 | GV29: =AI29+DG29 -> 621.34492 | GW29: =AJ29+DH29 -> 605.27566 | ... HA29: =AN29+DL29 -> 669.55272 | HB29: =SUM(GP29:HA29) -> 6427.7061 | HC29: =AP29+DN29 -> 611.07026 | HD29: =AQ29+DO29 -> 667.35305 | HE29: =AR29+DP29 -> 747.75703 | HF29: =AS29+DQ29 -> 747.75703 | HG29: =AT29+DR29 -> 747.75703 | HH29: =AU29+DS29 -> 812.08021 | HI29: =AV29+DT29 -> 932.68618 | HJ29: =AW29+DU29 -> 908.56499 | ... HN29: =BA29+DY29 -> 1005.0498 | HO29: =SUM(HC29:HN29) -> 9648.4778 | HP29: =BC29+EA29 -> 866.54719 | HQ29: =BD29+EB29 -> 946.36075 | HR29: =BE29+EC29 -> 1060.3801 | HS29: =BF29+ED29 -> 1060.3801 | HT29: =BG29+EE29 -> 1060.3801 | HU29: =BH29+EF29 -> 1151.5956 | HV29: =BI29+EG29 -> 1322.6247 | HW29: =BJ29+EH29 -> 1288.4189 | ... IA29: =BN29+EL29 -> 1425.2421 | IB29: =SUM(HP29:IA29) -> 13682.324 | IC29: =BP29+EN29 -> 1165.9126 | ID29: =BQ29+EO29 -> 1273.2992 | IE29: =BR29+EP29 -> 1426.7088 | IF29: =BS29+EQ29 -> 1426.7088 | IG29: =BT29+ER29 -> 1426.7088 | IH29: =BU29+ES29 -> 1549.4364 | II29: =BV29+ET29 -> 1779.5507 | IJ29: =BW29+EU29 -> 1733.5279 | ... IN29: =CA29+EY29 -> 1917.6193 | IO29: =SUM(IC29:IN29) -> 18409.146 | IP29: =CC29+FA29 -> 1514.6504 | IQ29: =CD29+FB29 -> 1654.1577 | IR29: =CE29+FC29 -> 1853.4538 | IS29: =CF29+FD29 -> 1853.4538 | IT29: =CG29+FE29 -> 1853.4538 | IU29: =CH29+FF29 -> 2012.8907 | IV29: =CI29+FG29 -> 2311.8349 | IW29: =CJ29+FH29 -> 2252.0461 | ... JA29: =CN29+FL29 -> 2491.2014 | JB29: =SUM(IP29:JA29) -> 23915.533 | JE29: =O29-GB29 -> 0 | JF29: =AB29-GO29 -> 0 | JG29: =AO29+DM29-HB29 -> 0 | JH29: =BB29+DZ29-HO29 -> 0 | JI29: =BO29+EM29-IB29 -> 0 | JJ29: =CB29+EZ29-IO29 -> 0 | JK29: =CO29+FM29-JB29 -> 0
