Workbook

Sheet Последовательность расчётов
B2: Последовательность расчётов
B3: [1] | C3: На листе «План-Факт» рассчитайте отклонения фактических показателей от плановых в абсолютных и относительных значениях.
B4: [2] | C4: Проанализируйте, какие выводы можно сделать на данном этапе.
B5: [3] | C5: На листе «Свод факта» рассчитайте отклонения фактических показателей от плановых.
B6: [4] | C6: Проанализируйте, какие выводы можно сделать на данном этапе.
B7: [5] | C7: Сделайте свод данных на листах «Выгрузка персонал», «Выгрузка оборудование» и «Выгрузка лицензии» и сравните получившиеся результаты с данными на листе «Свод факта».
B8: [6] | C8: Добавьте недостающие данные из выгрузок на лист «Свод факта».
B9: [7] | C9: Сделайте выводы на листе «Свод факта» и «План-факт», добавьте предложения по доработке бюджетной модели для минимизации отклонений в будущем.
B10: [8] | C10: В отдельном pptx-файле сформируйте для руководства Kihi презентацию по результатам работы новых направлений. Дополнитеные таблицы / расчёты для презентации по необходимости формируйте на листе «Для презентации».

Sheet Для презентации
B2: Community | D2: Education | Q2: Подсказку? | U2: Да
B3: План | C3: Факт | D3: План | E3: Факт
A4: Расходы на персонал | B4: =Расчеты!O63 -> 6048 | C4: ='Свод факта'!O94 -> 6296 | D4: =Расчеты!O69 -> 11892 | E4: ='Свод факта'!O100 -> 13385.2 | Q4: Нет | R4: =IF(Q4="Нет", " ", "На первом слайде обычно показывают общую картину - заберите таблицу с результатами анализа с листа План-факт.") | U4: Нет
Q5: Нет
Q6: Нет | R6: =IF(Q6="Нет", " ", "Сделайте выводы и дайте рекомендации.")
B7: Education | Q7: Нет | R7: =IF(Q7="Нет", " ", "Подумайте, что может сделать подразделение маркетинга на основании отчета?")
B8: План | C8: Факт | Q8: Нет | R8: =IF(Q8="Нет", " ", "Подумайте, что могут сделать подразделения поддержки Community и Education на основании отчета?")
A9: Расходы на лицензии | B9: =Расчеты!O184 -> 960 | C9: ='Свод факта'!O247 -> 1704.2816 | Q9: Нет | R9: =IF(Q9="Нет", " ", "Подумайте, что может сделать подразделение, отвечающее за контент направления Education?")
Q10: Нет | R10: =IF(Q10="Нет", " ", "Если все вышеозвученные подразделения внесут свой вклад, нужно ли будет что-то ещё делать подразделению финансов?")
A11: Расходы на оборудование | Q11: Нет | R11: =IF(Q11="Нет", " ", "Не перегружайте презентацию ненужной для менеджмента информацией. Выводы о необходимости доработки бюджетной модели лучше оставить внутри подразделения финансов.")
B14: Итого новые проекты | E14: Community | H14: Education
A15: Тыс. Руб. | B15: Факт | C15: План | D15: Δ (±) | E15: Факт | F15: План | G15: Δ (±) | H15: Факт | I15: План | J15: Δ (±)
A16: Валовая прибыль | B16: -7878 | C16: -7012 | D16: -866 | E16: -7094 | F16: -6057 | G16: -1037 | H16: -784 | I16: -955 | J16: 171
A17: Операционные расходы | B17: 8663 | C17: 8974 | D17: -311 | E17: 3600 | F17: 3745 | G17: -145 | H17: 3600 | I17: 3802 | J17: -202
A18: Операционная прибыль | B18: -16541 | C18: -15987 | D18: -554 | E18: -10694 | F18: -9802 | G18: -892 | H18: -4384 | I18: -4757 | J18: 373
A19: Чистая прибыль | B19: -16541 | C19: -15987 | D19: -554 | E19: -10694 | F19: -9802 | G19: -892 | H19: -4384 | I19: -4757 | J19: 373

Sheet Факт-->

Sheet План-Факт
B2: Таблица 1. Отчёт о прибылях и убытках, тыс. руб. | R2: Подсказку? | V2: Да
C3: Итого новые проекты | H3: Community | M3: Education | V3: Нет
C4: Факт | D4: План | E4: Δ | F4: Δ, % | H4: Факт | I4: План | J4: Δ | K4: Δ, % | M4: Факт | N4: План | O4: Δ | P4: Δ, % | R4: Нет | S4: =IF(R4="Нет", " ", "Δ = Факт - План. Δ, % = (Факт - План) / План * 100% ")
B5: Выручка | C5: =H5+M5 -> 21796.6 | D5: =Бюджет!C5 -> 20487.56 | E5: =C5-D5 -> 1309.04 | F5: =(C5-D5)/D5*100% -> 0.06389438 | H5: ='Свод факта'!O10 -> 4057.4333 | I5: =Бюджет!F5 -> 4840.5369 | J5: =H5-I5 -> -783.10353 | K5: =(H5-I5)/I5*100% -> -0.1617803 | M5: ='Свод факта'!O16 -> 17739.167 | N5: =Бюджет!I5 -> 15647.023 | O5: =M5-N5 -> 2092.1435 | P5: =(M5-N5)/N5*100% -> 0.13370872
B6: Себестоимость | C6: =H6+M6 -> 29674.634 | D6: =Бюджет!C6 -> 27500 | E6: =C6-D6 -> 2174.6338 | F6: =(C6-D6)/D6*100% -> 0.079077592 | H6: ='Свод факта'!O88+'Свод факта'!O94+'Свод факта'!O235+'Свод факта'!O242 -> 11151.819 | I6: =Бюджет!F6 -> 10898 | J6: =H6-I6 -> 253.81885 | K6: =(H6-I6)/I6*100% -> 0.023290406 | M6: ='Свод факта'!O89+'Свод факта'!O100+'Свод факта'!O236+'Свод факта'!O247 -> 18522.815 | N6: =Бюджет!I6 -> 16602 | O6: =M6-N6 -> 1920.8149 | P6: =(M6-N6)/N6*100% -> 0.1156978
B7: Валовая прибыль | C7: =C5-C6 -> -7878.0338 | D7: =Бюджет!C7 -> -7012.44 | E7: =C7-D7 -> -865.59383 | F7: =(C7-D7)/D7*100% -> 0.1234369 | H7: =H5-H6 -> -7094.3855 | I7: =Бюджет!F7 -> -6057.4631 | J7: =H7-I7 -> -1036.9224 | K7: =(H7-I7)/I7*100% -> 0.17118096 | M7: =M5-M6 -> -783.64827 | N7: =Бюджет!I7 -> -954.97681 | O7: =M7-N7 -> 171.32855 | P7: =(M7-N7)/N7*100% -> -0.17940598
B8: Валовая прибыль, % | C8: =C7/C5 -> -0.36143407 | D8: =Бюджет!C8 -> -0.34227795 | E8: =C8-D8 -> -0.019156122 | F8: =C8-D8 -> -0.019156122 | H8: =H7/H5 -> -1.748491 | I8: =Бюджет!F8 -> -1.2514032 | K8: =H8-I8 -> -0.4970878 | M8: =M7/M5 -> -0.04417616 | N8: =Бюджет!I8 -> -0.061032492 | P8: =M8-N8 -> 0.016856332
B9: Операционные расходы | C9: =SUM(C10:C14) -> 8663.0022 | D9: =Бюджет!C9 -> 8974.13 | E9: =C9-D9 -> -311.12782 | F9: =(C9-D9)/D9*100% -> -0.034669413 | H9: =SUM(H10:H14) -> 3600 | I9: =Бюджет!F9 -> 3744.98 | J9: =H9-I9 -> -144.98 | K9: =(H9-I9)/I9*100% -> -0.038713157 | M9: =SUM(M10:M14) -> 3600 | N9: =Бюджет!I9 -> 3802.02 | O9: =M9-N9 -> -202.02 | P9: =(M9-N9)/N9*100% -> -0.053134912
B10: Расходы на персонал | C10: ='Свод факта'!O105 -> 697.6 | D10: =Бюджет!C10 -> 648 | E10: =C10-D10 -> 49.6 | F10: =(C10-D10)/D10*100% -> 0.07654321 | H10: 0 | I10: =Бюджет!F10 -> 0 | J10: =H10-I10 -> 0 | K10: 0 | M10: 0 | N10: =Бюджет!I10 -> 0 | O10: =M10-N10 -> 0 | P10: 0
B11: Аренда | C11: ='Свод факта'!O222 -> 675 | D11: =Бюджет!C11 -> 675 | E11: =C11-D11 -> 0 | F11: 0 | H11: 0 | I11: =Бюджет!F11 -> 0 | J11: =H11-I11 -> 0 | K11: 0 | M11: 0 | N11: =Бюджет!I11 -> 0 | O11: =M11-N11 -> 0 | P11: 0
B12: Реклама и маркетинг | C12: =H12+M12 -> 7200 | D12: =Бюджет!C12 -> 7200 | E12: =C12-D12 -> 0 | F12: 0 | H12: ='Свод факта'!O229 -> 3600 | I12: =Бюджет!F12 -> 3600 | J12: =H12-I12 -> 0 | K12: 0 | M12: ='Свод факта'!O230 -> 3600 | N12: =Бюджет!I12 -> 3600 | O12: =M12-N12 -> 0 | P12: 0
B13: Оборудование, лицензии и ПО | C13: =H13+M13+'Свод факта'!O237+'Свод факта'!O252 -> 90.40218 | D13: =Бюджет!C13 -> 90 | E13: =C13-D13 -> 0.40218 | F13: 0 | H13: 0 | I13: =Бюджет!F13 -> 0 | J13: =H13-I13 -> 0 | K13: 0 | M13: 0 | N13: =Бюджет!I13 -> 0 | O13: =M13-N13 -> 0 | P13: 0
B14: Прочие и непредвиденные расходы | C14: 0 | D14: =Бюджет!C14 -> 361.13 | E14: =C14-D14 -> -361.13 | F14: =(C14-D14)/D14*100% -> -1 | H14: 0 | I14: =Бюджет!F14 -> 144.98 | J14: =H14-I14 -> -144.98 | K14: =(H14-I14)/I14*100% -> -1 | M14: 0 | N14: =Бюджет!I14 -> 202.02 | O14: =M14-N14 -> -202.02 | P14: =(M14-N14)/N14*100% -> -1
B15: Операционная прибыль | C15: =C7-C9 -> -16541.036 | D15: =Бюджет!C15 -> -15986.57 | E15: =C15-D15 -> -554.46601 | F15: =(C15-D15)/D15*100% -> 0.034683238 | H15: =H7-H9 -> -10694.386 | I15: =Бюджет!F15 -> -9802.4431 | J15: =H15-I15 -> -891.94238 | K15: =(H15-I15)/I15*100% -> 0.090991844 | M15: =M7-M9 -> -4383.6483 | N15: =Бюджет!I15 -> -4756.9968 | O15: =M15-N15 -> 373.34855 | P15: =(M15-N15)/N15*100% -> -0.078484086
B16: Операционная прибыль, % | C16: =C15/C5 -> -0.75888148 | D16: =Бюджет!C16 -> -0.78030619 | F16: =C16-D16 -> 0.021424716 | H16: =H15/H5 -> -2.6357514 | I16: =Бюджет!F16 -> -2.0250735 | K16: =H16-I16 -> -0.61067784 | M16: =M15/M5 -> -0.24711692 | N16: =Бюджет!I16 -> -0.30401929 | P16: =M16-N16 -> 0.056902364
B17: Налог на прибыль | C17: =IF(C15>0, C15*25%, 0) -> 0 | D17: =Бюджет!C17 -> 0 | E17: =C17-D17 -> 0 | F17: 0 | H17: 0 | I17: =Бюджет!F17 -> 0 | J17: =H17-I17 -> 0 | K17: 0 | M17: 0 | N17: =Бюджет!I17 -> 0 | O17: 0 | P17: 0
B18: Чистая прибыль | C18: =C15-C17 -> -16541.036 | D18: =Бюджет!C18 -> -15986.57 | E18: =C18-D18 -> -554.46601 | F18: =(C18-D18)/D18*100% -> 0.034683238 | H18: =H15-H17 -> -10694.386 | I18: =Бюджет!F18 -> -9802.4431 | J18: =H18-I18 -> -891.94238 | K18: =(H18-I18)/I18*100% -> 0.090991844 | M18: =M15-M17 -> -4383.6483 | N18: =Бюджет!I18 -> -4756.9968 | O18: =M18-N18 -> 373.34855 | P18: =(M18-N18)/N18*100% -> -0.078484086
B19: Чистая прибыль, % | C19: =C18/C5 -> -0.75888148 | D19: =Бюджет!C19 -> -0.78030619 | F19: =C19-D19 -> 0.021424716 | H19: =H18/H5 -> -2.6357514 | I19: =Бюджет!F19 -> -2.0250735 | K19: =H19-I19 -> -0.61067784 | M19: =M18/M5 -> -0.24711692 | N19: =Бюджет!I19 -> -0.30401929 | P19: =M19-N19 -> 0.056902364
B21: Выводы | R21: Да | S21: =IF(R21="Нет", " ", "Для формирование полных выводов проведите детальный анализ отклонений на листе Свод факта.") -> Для формирование полных выводов проведите детальный анализ отклонений на листе Свод факта.
B22: План по чистой прибыли по новым направлениям в целом за 2026 год не выполнен, убытки выше плановых (в абсолютном отклонении -554, в относиельном на 3%) | R22: Да | S22: =IF(R22="Нет", " ", "Проверьте, выполнен ли план по чистой прибыли в по новым направлениям в целом за 2026 год? Сделайте вывод.") -> Проверьте, выполнен ли план по чистой прибыли в по новым направлениям в целом за 2026 год? Сделайте вывод.
B23: По направлению Education план перевыполнен - убыток меньше плана в относительном отклонении на 8% | R23: Да | S23: =IF(R23="Нет", " ", "Проверьте, выполнен ли план по чистой прибыли Community и Education за 2026 год? Сделайте вывод.") -> Проверьте, выполнен ли план по чистой прибыли Community и Education за 2026 год? Сделайте вывод.
B24: По направлению Community недовыполнение, убытки выше плановых в относительном отклонении на 9% | R24: Да | S24: =IF(R24="Нет", " ", "Выполнен ли план по количеству привлечённых пользователей? Сделай вывод о выполнении/невыполнении плана.") -> Выполнен ли план по количеству привлечённых пользователей? Сделай вывод о выполнении/невыполнении плана.
B25: Community: план по привлечению пользователей не выполнен по всем категориям. Наибольший разрыв — в «Подписке на месяц» и «Пакете на 3 месяца». Основная причина — более медленный рост фактического числа пользователей по сравнению с амбициозным планом. | R25: Да | S25: =IF(R25="Нет", " ", "Были ли учтены выбывающие клиенты в бюджетной модели? Сделай вывод.") -> Были ли учтены выбывающие клиенты в бюджетной модели? Сделай вывод.
B26: Education: план перевыполнен в большинстве категорий, кроме «Фритрек». Успех в привлечении пользователей с различными моделями оплаты. | R26: Да | S26: =IF(R26="Нет", " ", "Соответствует ли фактический уровень продаж плановому? Сделай вывод.") -> Соответствует ли фактический уровень продаж плановому? Сделай вывод.
B27: Выбывающие клиенты, вероятно, не были учтены в полной мере. План строился на предположении стабильного или растущего числа клиентов, без поправки на отток | R27: Да | S27: =IF(R27="Нет", " ", "Были ли учтены в плане компенсации по питанию в расходах на персонал? Сделай вывод.") -> Были ли учтены в плане компенсации по питанию в расходах на персонал? Сделай вывод.
B28: Фактический уровень продаж не соотвествует плановому, по табл Уровень Проникновения Продаж сделаны расчеты для наглядности | R28: Да | S28: =IF(R28="Нет", " ", "Было ли учтено в плане влияние курса доллара на стоимость лицензий? Сделай вывод.") -> Было ли учтено в плане влияние курса доллара на стоимость лицензий? Сделай вывод.
B29: В плане не была учтена такая статья расходов как компенсация по питанию, обязательно включить этот пункт в бюджетирование с учётом среднего чека и числа сотрудников | R29: Да | S29: =IF(R29="Нет", " ", "Оправдались ли ожидания по количеству сотрудников? Сделай вывод.") -> Оправдались ли ожидания по количеству сотрудников? Сделай вывод.
B30: Изменение курса доллара не было учтено при планировании при оплате за лицензии, что повлияло существенное повышение цены для новых кураторов | R30: Да | S30: =IF(R30="Нет", " ", "Был ли учтён при планировании период закупки оборудования по мере роста штата? Сделай вывод.") -> Был ли учтён при планировании период закупки оборудования по мере роста штата? Сделай вывод.
B31: Несогласованность темпов роста штата и закупок, когда новые сотрудники приходят, а необходимое оборудование (компьютеры, лицензии ПО, периферия) не готово, учтёно при планировании не было | R31: Да | S31: =IF(R31="Нет", " ", "Какие рекомендации на основе полученных выводов можно дать руководству компании?") -> Какие рекомендации на основе полученных выводов можно дать руководству компании?
B32: Рекомендации руководству улучшить синхронизацию отделов, организовать регулярные встречи (например, раз в неделю) между HR, IT-отделом и отделом закупок для согласования планов по росту штата и закупке оборудования | R32: Да | S32: =IF(R32="Нет", " ", "Из полученных выводов, как думаете, что нужно сделать для минимизации отклонений пана от факта в будущем?") -> Из полученных выводов, как думаете, что нужно сделать для минимизации отклонений пана от факта в будущем?
B33: Для каждой вакансии зафиксировать сроки закупки оборудования (например: ПК — за 3 недели до выхода сотрудника, лицензии ПО — за 1 неделю);
B34: Внедрить сценарное планирование, проводить регулярный анализ отклонений
B35: Для минимизации отклонений плана от факта нужно улучшить систему прогнозирования,
B36: Внедрить систему еженедельного/ежемесячного план-фактного анализа,
B37: Улучшить координацию между отделами, систему мотивации
B38: Анализировать причины отклонений, после каждого отчётного периода проводить 'разбор полётов'
B39: Учесть факторы риска и неопределённости

Sheet Свод факта
B2: Таблица 2. Количество дней в периоде, шт. | AP2: Выводы | AR2: Подсказку?
C3: янв.26 | D3: фев.26 | E3: мар.26 | F3: апр.26 | G3: 46143 | H3: июн.26 | I3: июл.26 | J3: авг.26 | K3: сент.26 | L3: окт.26 | M3: ноя.26 | N3: дек.26 | O3: 2026 | P3: янв.26 | Q3: фев.26 | R3: мар.26 | S3: апр.26 | T3: 46143 | U3: июн.26 | V3: июл.26 | W3: авг.26 | X3: сент.26 | Y3: окт.26 | Z3: ноя.26 | AA3: дек.26 | AB3: 2026
B4: всего | C4: 31 | D4: 28 | E4: 31 | F4: 30 | G4: 31 | H4: 30 | I4: 31 | J4: 31 | K4: 30 | L4: 31 | M4: 30 | N4: 31 | O4: =SUM(C4:N4) -> 365 | P4: 31 | Q4: 28 | R4: 31 | S4: 30 | T4: 31 | U4: 30 | V4: 31 | W4: 31 | X4: 30 | Y4: 31 | Z4: 30 | AA4: 31 | AB4: =SUM(P4:AA4) -> 365
B5: рабочих | C5: 15 | D5: 19 | E5: 21 | F5: 22 | G5: 19 | H5: 21 | I5: 23 | J5: 21 | K5: 22 | L5: 22 | M5: 20 | N5: 22 | O5: =SUM(C5:N5) -> 247 | P5: 15 | Q5: 19 | R5: 21 | S5: 22 | T5: 19 | U5: 21 | V5: 23 | W5: 21 | X5: 22 | Y5: 22 | Z5: 20 | AA5: 22 | AB5: =SUM(P5:AA5) -> 247
B7: Таблица 3. Выручка, тыс. руб. | I7: факт | P7: Δ (факт - план) | AR7: Нет | AS7: =IF(AR7="Нет", " ", "Δ факт/план = Факт - План. Плановые данные находятся на предпоследнем листе Расчёты")
C8: янв.26 | D8: фев.26 | E8: мар.26 | F8: апр.26 | G8: 46143 | H8: июн.26 | I8: июл.26 | J8: авг.26 | K8: сент.26 | L8: окт.26 | M8: ноя.26 | N8: дек.26 | O8: 2026 | P8: янв.26 | Q8: фев.26 | R8: мар.26 | S8: апр.26 | T8: 46143 | U8: июн.26 | V8: июл.26 | W8: авг.26 | X8: сент.26 | Y8: окт.26 | Z8: ноя.26 | AA8: дек.26 | AB8: 2026 | AR8: Нет | AS8: =IF(AR8="Нет", " ", "Для дальнейшего анализа рассчитайте план-факт отклонения по драйверам данного показателя.")
B10: Community | C10: =SUM(C11:C15) -> 0 | D10: =SUM(D11:D15) -> 70.516667 | E10: =SUM(E11:E15) -> 125.53333 | F10: =SUM(F11:F15) -> 183.53333 | G10: =SUM(G11:G15) -> 241.15 | H10: =SUM(H11:H15) -> 298.86667 | I10: =SUM(I11:I15) -> 361.25 | J10: =SUM(J11:J15) -> 427.53333 | ... N10: =SUM(N11:N15) -> 683.21667 | O10: =SUM(C10:N10) -> 4057.4333 | P10: =SUM(P11:P15) -> 0 | Q10: =SUM(Q11:Q15) -> 2.1833333 | R10: =SUM(R11:R15) -> -12.295 | S10: =SUM(S11:S15) -> -24.971415 | T10: =SUM(T11:T15) -> -39.232662 | U10: =SUM(U11:U15) -> -54.615834 | V10: =SUM(V11:V15) -> -68.805313 | W10: =SUM(W11:W15) -> -82.732766 | ... AA10: =SUM(AA11:AA15) -> -149.67825 | AB10: =SUM(P10:AA10) -> -783.10353
B11: Первый месяц | C11: 0 | D11: 0 | E11: 0 | F11: 0 | G11: 0 | H11: 0 | I11: 0 | J11: 0 | K11: 0 | L11: 0 | M11: 0 | N11: 0 | O11: =SUM(C11:N11) -> 0 | P11: =C11-Расчеты!C10 -> 0 | Q11: =D11-Расчеты!D10 -> 0 | R11: =E11-Расчеты!E10 -> 0 | S11: =F11-Расчеты!F10 -> 0 | T11: =G11-Расчеты!G10 -> 0 | U11: =H11-Расчеты!H10 -> 0 | V11: =I11-Расчеты!I10 -> 0 | W11: =J11-Расчеты!J10 -> 0 | ... AA11: =N11-Расчеты!N10 -> 0 | AB11: =SUM(P11:AA11) -> 0
B12: Подписка на месяц | C12: 0 | D12: 30.6 | E12: 54.9 | F12: 80.1 | G12: 105.9 | H12: 130.8 | I12: 158.1 | J12: 187.2 | K12: 216.9 | L12: 243.3 | M12: 270.9 | N12: 299.4 | O12: =SUM(C12:N12) -> 1778.1 | P12: =C12-Расчеты!C11 -> 0 | Q12: =D12-Расчеты!D11 -> 0.6 | R12: =E12-Расчеты!E11 -> -5.61 | S12: =F12-Расчеты!F11 -> -11.43867 | T12: =G12-Расчеты!G11 -> -17.194827 | U12: =H12-Расчеты!H11 -> -24.387439 | V12: =I12-Расчеты!I11 -> -30.704772 | W12: =J12-Расчеты!J11 -> -36.819263 | ... AA12: =N12-Расчеты!N11 -> -66.261182 | AB12: =SUM(P12:AA12) -> -347.01374
B13: Пакет на 3 месяца | C13: 0 | D13: 21.533333 | E13: 39.1 | F13: 56.666667 | G13: 74.8 | H13: 92.366667 | I13: 112.48333 | J13: 132.6 | K13: 153.56667 | L13: 171.98333 | M13: 192.38333 | N13: 212.21667 | O13: =SUM(C13:N13) -> 1259.7 | P13: =C13-Расчеты!C12 -> 0 | Q13: =D13-Расчеты!D12 -> 0.28333333 | R13: =E13-Расчеты!E12 -> -3.76125 | S13: =F13-Расчеты!F12 -> -8.1732246 | T13: =G13-Расчеты!G12 -> -12.392169 | U13: =H13-Расчеты!H12 -> -17.55777 | V13: =I13-Расчеты!I12 -> -21.25338 | W13: =J13-Расчеты!J12 -> -26.080311 | ... AA13: =N13-Расчеты!N12 -> -46.793338 | AB13: =SUM(P13:AA13) -> -245.5889
B14: Пакет на 6 месяцев | C14: 0 | D14: 14.133333 | E14: 24.533333 | F14: 36.266667 | G14: 47.2 | H14: 59.2 | I14: 70.666667 | J14: 83.733333 | K14: 96.8 | L14: 107.73333 | M14: 120.26667 | N14: 133.6 | O14: =SUM(C14:N14) -> 794.13333 | P14: =C14-Расчеты!C13 -> 0 | Q14: =D14-Расчеты!D13 -> 0.8 | R14: =E14-Расчеты!E13 -> -2.36 | S14: =F14-Расчеты!F13 -> -4.4171867 | T14: =G14-Расчеты!G13 -> -7.5088122 | U14: =H14-Расчеты!H13 -> -9.7721953 | V14: =I14-Расчеты!I13 -> -13.246565 | W14: =J14-Расчеты!J13 -> -15.830784 | ... AA14: =N14-Расчеты!N13 -> -28.916081 | AB14: =SUM(P14:AA14) -> -150.36166
B15: Пакет на 12 месяцев | C15: 0 | D15: 4.25 | E15: 7 | F15: 10.5 | G15: 13.25 | H15: 16.5 | I15: 20 | J15: 24 | K15: 27.5 | L15: 30.75 | M15: 33.75 | N15: 38 | O15: =SUM(C15:N15) -> 225.5 | P15: =C15-Расчеты!C14 -> 0 | Q15: =D15-Расчеты!D14 -> 0.5 | R15: =E15-Расчеты!E14 -> -0.56375 | S15: =F15-Расчеты!F14 -> -0.94233375 | T15: =G15-Расчеты!G14 -> -2.1368534 | U15: =H15-Расчеты!H14 -> -2.8984299 | V15: =I15-Расчеты!I14 -> -3.6005964 | W15: =J15-Расчеты!J14 -> -4.0024079 | ... AA15: =N15-Расчеты!N14 -> -7.7076478 | AB15: =SUM(P15:AA15) -> -40.139218
B16: Education | C16: =SUM(C17:C21) -> 246.83333 | D16: =SUM(D17:D21) -> 436.33333 | E16: =SUM(E17:E21) -> 674.5 | F16: =SUM(F17:F21) -> 912.66667 | G16: =SUM(G17:G21) -> 1093.3333 | H16: =SUM(H17:H21) -> 1294.5 | I16: =SUM(I17:I21) -> 1496.5 | J16: =SUM(J17:J21) -> 1771.1667 | ... N16: =SUM(N17:N21) -> 2846.1667 | O16: =SUM(C16:N16) -> 17739.167 | P16: =SUM(P17:P21) -> 63.166667 | Q16: =SUM(Q17:Q21) -> 65.326667 | R16: =SUM(R17:R21) -> 112.40653 | S16: =SUM(S17:S21) -> 155.66466 | T16: =SUM(T17:T21) -> 137.52462 | U16: =SUM(U17:U21) -> 129.82496 | V16: =SUM(V17:V21) -> 112.39 | W16: =SUM(W17:W21) -> 156.5183 | ... AA16: =SUM(AA17:AA21) -> 344.5698 | AB16: =SUM(P16:AA16) -> 2092.1435
B17: Фритрек | C17: 0 | D17: 0 | E17: 0 | F17: 0 | G17: 0 | H17: 0 | I17: 0 | J17: 0 | K17: 0 | L17: 0 | M17: 0 | N17: 0 | O17: =SUM(C17:N17) -> 0 | P17: =C17-Расчеты!C16 -> 0 | Q17: =D17-Расчеты!D16 -> 0 | R17: =E17-Расчеты!E16 -> 0 | S17: =F17-Расчеты!F16 -> 0 | T17: =G17-Расчеты!G16 -> 0 | U17: =H17-Расчеты!H16 -> 0 | V17: =I17-Расчеты!I16 -> 0 | W17: =J17-Расчеты!J16 -> 0 | ... AA17: =N17-Расчеты!N16 -> 0 | AB17: =SUM(P17:AA17) -> 0
B18: Полная оплата курса | C18: 25 | D18: 41.666667 | E18: 58.333333 | F18: 75 | G18: 83.333333 | H18: 100 | I18: 108.33333 | J18: 133.33333 | K18: 141.66667 | L18: 166.66667 | M18: 191.66667 | N18: 200 | O18: =SUM(C18:N18) -> 1325 | P18: =C18-Расчеты!C17 -> 15 | Q18: =D18-Расчеты!D17 -> 21.466667 | R18: =E18-Расчеты!E17 -> 27.729333 | S18: =F18-Расчеты!F17 -> 33.78392 | T18: =G18-Расчеты!G17 -> 31.292932 | U18: =H18-Расчеты!H17 -> 36.587566 | V18: =I18-Расчеты!I17 -> 32.973442 | W18: =J18-Расчеты!J17 -> 45.421444 | ... AA18: =N18-Расчеты!N17 -> 63.796904 | AB18: =SUM(P18:AA18) -> 473.07496
B19: Оплата курса 2 траншами | C19: 45.833333 | D19: 91.666667 | E19: 146.66667 | F19: 201.66667 | G19: 247.5 | H19: 275 | I19: 311.66667 | J19: 375.83333 | K19: 467.5 | L19: 531.66667 | M19: 577.5 | N19: 641.66667 | O19: =SUM(C19:N19) -> 3914.1667 | P19: =C19-Расчеты!C18 -> 9.1666667 | Q19: =D19-Расчеты!D18 -> 17.6 | R19: =E19-Расчеты!E18 -> 34.452 | S19: =F19-Расчеты!F18 -> 50.54104 | T19: =G19-Расчеты!G18 -> 56.685194 | U19: =H19-Расчеты!H18 -> 42.487742 | V19: =I19-Расчеты!I18 -> 35.347066 | W19: =J19-Расчеты!J18 -> 53.489739 | ... AA19: =N19-Расчеты!N18 -> 142.25531 | AB19: =SUM(P19:AA19) -> 790.44153
B20: Оплата курса 3 траншами | C20: 76 | D20: 133 | E20: 199.5 | F20: 266 | G20: 332.5 | H20: 389.5 | I20: 446.5 | J20: 532 | K20: 608 | L20: 703 | M20: 769.5 | N20: 864.5 | O20: =SUM(C20:N20) -> 5320 | P20: =C20-Расчеты!C19 -> 19 | Q20: =D20-Расчеты!D19 -> 17.86 | R20: =E20-Расчеты!E19 -> 25.0572 | S20: =F20-Расчеты!F19 -> 31.068344 | T20: =G20-Расчеты!G19 -> 35.869711 | U20: =H20-Расчеты!H19 -> 28.049127 | V20: =I20-Расчеты!I19 -> 16.948621 | W20: =J20-Расчеты!J19 -> 30.90223 | ... AA20: =N20-Расчеты!N19 -> 88.142352 | AB20: =SUM(P20:AA20) -> 464.02729
B21: Оплата курса помесячно | C21: 100 | D21: 170 | E21: 270 | F21: 370 | G21: 430 | H21: 530 | I21: 630 | J21: 730 | K21: 840 | L21: 950 | M21: 1020 | N21: 1140 | O21: =SUM(C21:N21) -> 7180 | P21: =C21-Расчеты!C20 -> 20 | Q21: =D21-Расчеты!D20 -> 8.4 | R21: =E21-Расчеты!E20 -> 25.168 | S21: =F21-Расчеты!F20 -> 40.27136 | T21: =G21-Расчеты!G20 -> 13.676787 | U21: =H21-Расчеты!H20 -> 22.700529 | V21: =I21-Расчеты!I20 -> 27.120872 | W21: =J21-Расчеты!J20 -> 26.704885 | ... AA21: =N21-Расчеты!N20 -> 50.37523 | AB21: =SUM(P21:AA21) -> 364.5997
B23: Таблица 3.1. Количество пользователей, чел. | I23: факт | P23: Δ (факт - план) | AP23: Допущение о 100% лояльности неверно. Это подтверждается данными из таблицы 3.1.2 («Количество продлений») и колонками с отклонениями (факт – план). Для минимизации отклонений в будующем можно разделить прогноз на новые клиенты и продления, анализируя их отдельно.Стимулирование бонусы за продление, отдельные предложения. Провести анализ причин оттока по сегментам (опросы, анализ поведения) | AR23: Нет | AS23: =IF(AR23="Нет", " ", "Ниже добавлены таблицы с дополнительными вводными, сформированными на основании фактических данных по оплатам. Проанализируйте их и сделайте выводы. При необходимости справа от таблиц, на пустом пространстве, сделайте дополнительные расчёты.")
C24: янв.26 | D24: фев.26 | E24: мар.26 | F24: апр.26 | G24: 46143 | H24: июн.26 | I24: июл.26 | J24: авг.26 | K24: сент.26 | L24: окт.26 | M24: ноя.26 | N24: дек.26 | O24: 2026 | P24: янв.26 | Q24: фев.26 | R24: мар.26 | S24: апр.26 | T24: 46143 | U24: июн.26 | V24: июл.26 | W24: авг.26 | X24: сент.26 | Y24: окт.26 | Z24: ноя.26 | AA24: дек.26 | AB24: 2026 | AR24: Нет | AS24: =IF(AR24="Нет", " ", "Было ли верно допущение о 100%-ой лояльности при выстраивании бюджетной модели? Сделайте вывод, что нужно сделать для минимизации отклонений в будущем?")
B26: Community
B27: Первый месяц | C27: 504 | D27: 507 | E27: 509 | F27: 514 | G27: 515 | H27: 525 | I27: 543 | J27: 567 | K27: 551 | L27: 561 | M27: 570 | N27: 580 | P27: =C27-Расчеты!C26 -> 4 | Q27: =D27-Расчеты!D26 -> -1.5 | R27: =E27-Расчеты!E26 -> -8.1445 | S27: =F27-Расчеты!F26 -> -11.935956 | T27: =G27-Расчеты!G26 -> -19.876868 | U27: =H27-Расчеты!H26 -> -35.288868 | V27: =I27-Расчеты!I26 -> -43.908192 | W27: =J27-Расчеты!J26 -> -47.7922 | ... AA27: =N27-Расчеты!N26 -> -21.866937 | AB27: =AA27 -> -21.866937
B28: Подписка на месяц | C28: 0 | D28: 102 | E28: 183 | F28: 267 | G28: 353 | H28: 436 | I28: 527 | J28: 624 | K28: 723 | L28: 811 | M28: 903 | N28: 998 | P28: =C28-Расчеты!C27 -> 0 | Q28: =D28-Расчеты!D27 -> 2 | R28: =E28-Расчеты!E27 -> -18.7 | S28: =F28-Расчеты!F27 -> -38.1289 | T28: =G28-Расчеты!G27 -> -57.316091 | U28: =H28-Расчеты!H27 -> -81.291465 | V28: =I28-Расчеты!I27 -> -102.34924 | W28: =J28-Расчеты!J27 -> -122.73088 | ... AA28: =N28-Расчеты!N27 -> -220.87061 | AB28: =AA28 -> -220.87061
B29: Пакет на 3 месяца | C29: 0 | D29: 76 | E29: 138 | F29: 200 | G29: 264 | H29: 326 | I29: 397 | J29: 468 | K29: 542 | L29: 607 | M29: 679 | N29: 749 | P29: =C29-Расчеты!C28 -> 0 | Q29: =D29-Расчеты!D28 -> 1 | R29: =E29-Расчеты!E28 -> -13.275 | S29: =F29-Расчеты!F28 -> -28.846675 | T29: =G29-Расчеты!G28 -> -43.737068 | U29: =H29-Расчеты!H28 -> -61.968599 | V29: =I29-Расчеты!I28 -> -75.011929 | W29: =J29-Расчеты!J28 -> -92.048158 | ... AA29: =N29-Расчеты!N28 -> -165.15296 | AB29: =AA29 -> -165.15296
B30: Пакет на 6 месяцев | C30: 0 | D30: 53 | E30: 92 | F30: 136 | G30: 177 | H30: 222 | I30: 265 | J30: 314 | K30: 363 | L30: 404 | M30: 451 | N30: 501 | P30: =C30-Расчеты!C29 -> 0 | Q30: =D30-Расчеты!D29 -> 3 | R30: =E30-Расчеты!E29 -> -8.85 | S30: =F30-Расчеты!F29 -> -16.56445 | T30: =G30-Расчеты!G29 -> -28.158046 | U30: =H30-Расчеты!H29 -> -36.645732 | V30: =I30-Расчеты!I29 -> -49.674619 | W30: =J30-Расчеты!J29 -> -59.365438 | ... AA30: =N30-Расчеты!N29 -> -108.4353 | AB30: =AA30 -> -108.4353
B31: Пакет на 12 месяцев | C31: 0 | D31: 17 | E31: 28 | F31: 42 | G31: 53 | H31: 66 | I31: 80 | J31: 96 | K31: 110 | L31: 123 | M31: 135 | N31: 152 | P31: =C31-Расчеты!C30 -> 0 | Q31: =D31-Расчеты!D30 -> 2 | R31: =E31-Расчеты!E30 -> -2.255 | S31: =F31-Расчеты!F30 -> -3.769335 | T31: =G31-Расчеты!G30 -> -8.5474137 | U31: =H31-Расчеты!H30 -> -11.59372 | V31: =I31-Расчеты!I30 -> -14.402386 | W31: =J31-Расчеты!J30 -> -16.009632 | ... AA31: =N31-Расчеты!N30 -> -30.830591 | AB31: =AA31 -> -30.830591
B32: Education
B33: Фритрек | C33: 97 | D33: 100 | E33: 103 | F33: 105 | G33: 106 | H33: 113 | I33: 115 | J33: 117 | K33: 111 | L33: 113 | M33: 104 | N33: 81 | P33: =C33-Расчеты!C32 -> 57 | Q33: =D33-Расчеты!D32 -> 59.2 | R33: =E33-Расчеты!E32 -> 61.384 | S33: =F33-Расчеты!F32 -> 62.55168 | T33: =G33-Расчеты!G32 -> 62.702714 | U33: =H33-Расчеты!H32 -> 67.511871 | V33: =I33-Расчеты!I32 -> 67.210172 | W33: =J33-Расчеты!J32 -> 66.792006 | ... AA33: =N33-Расчеты!N32 -> 31.265028 | AB33: =AA33 -> 31.265028
B34: Полная оплата курса | C34: 3 | D34: 5 | E34: 7 | F34: 9 | G34: 10 | H34: 12 | I34: 13 | J34: 16 | K34: 17 | L34: 20 | M34: 23 | N34: 24 | P34: =C34-Расчеты!C33 -> 1.8 | Q34: =D34-Расчеты!D33 -> 2.576 | R34: =E34-Расчеты!E33 -> 3.32752 | S34: =F34-Расчеты!F33 -> 4.0540704 | T34: =G34-Расчеты!G33 -> 3.7551518 | U34: =H34-Расчеты!H33 -> 4.3905079 | V34: =I34-Расчеты!I33 -> 3.9568131 | W34: =J34-Расчеты!J33 -> 5.4505733 | ... AA34: =N34-Расчеты!N33 -> 7.6556285 | AB34: =AA34 -> 7.6556285
B35: Оплата курса 2 траншами | C35: 5 | D35: 10 | E35: 16 | F35: 22 | G35: 27 | H35: 30 | I35: 34 | J35: 41 | K35: 51 | L35: 58 | M35: 63 | N35: 70 | P35: =C35-Расчеты!C34 -> 1 | Q35: =D35-Расчеты!D34 -> 1.92 | R35: =E35-Расчеты!E34 -> 3.7584 | S35: =F35-Расчеты!F34 -> 5.513568 | T35: =G35-Расчеты!G34 -> 6.1838394 | U35: =H35-Расчеты!H34 -> 4.6350265 | V35: =I35-Расчеты!I34 -> 3.8560436 | W35: =J35-Расчеты!J34 -> 5.8352442 | ... AA35: =N35-Расчеты!N34 -> 15.518762 | AB35: =AA35 -> 15.518762
B36: Оплата курса 3 траншами | C36: 8 | D36: 14 | E36: 21 | F36: 28 | G36: 35 | H36: 41 | I36: 47 | J36: 56 | K36: 64 | L36: 74 | M36: 81 | N36: 91 | P36: =C36-Расчеты!C35 -> 2 | Q36: =D36-Расчеты!D35 -> 1.88 | R36: =E36-Расчеты!E35 -> 2.6376 | S36: =F36-Расчеты!F35 -> 3.270352 | T36: =G36-Расчеты!G35 -> 3.775759 | U36: =H36-Расчеты!H35 -> 2.9525397 | V36: =I36-Расчеты!I35 -> 1.7840654 | W36: =J36-Расчеты!J35 -> 3.2528664 | ... AA36: =N36-Расчеты!N35 -> 9.2781423 | AB36: =AA36 -> 9.2781423
B37: Оплата курса помесячно | C37: 10 | D37: 17 | E37: 27 | F37: 37 | G37: 43 | H37: 53 | I37: 63 | J37: 73 | K37: 84 | L37: 95 | M37: 102 | N37: 114 | P37: =C37-Расчеты!C36 -> 2 | Q37: =D37-Расчеты!D36 -> 0.84 | R37: =E37-Расчеты!E36 -> 2.5168 | S37: =F37-Расчеты!F36 -> 4.027136 | T37: =G37-Расчеты!G36 -> 1.3676787 | U37: =H37-Расчеты!H36 -> 2.2700529 | V37: =I37-Расчеты!I36 -> 2.7120872 | W37: =J37-Расчеты!J36 -> 2.6704885 | ... AA37: =N37-Расчеты!N36 -> 5.037523 | AB37: =AA37 -> 5.037523
B39: Таблица 3.1.1. Количество новых пользователей, чел. | I39: факт | P39: Δ (факт - план) | AC39: уровень проникновения продаж факт | AP39: Уровень продаж проникновения для всех типов подписок Community демонстрирует стабильный и невысокий рост. Анализ кол-ва продлений показывает кумулятивный рост, но с явными отклонениями от плановых показателей. Рекомендация например включить Бонусы за продление (скидка 10–15% при оплате следующего периода). Система накопительных баллов (например, за активность, отзывы). 'Уровень проникновения продаж для всех типов подписок Education стабильно низкий, самый высокий рост показывает при помесячной форме оплаты.Эксклюзивный контент для продливших подписку. По продлению отклонения от плана: меньше, чем в Community. Сезонные колебания: незначительные, отток минимален (особенно в сравнении с Community). По ежемесячному приросту по Education Фритрек показывает спад сезонности ноябрь-декабрь. Для повышения точности планирования нужно учитывать в плане прогноза как сезонность, внедрить метрики удержания: LTV (жизненный цикл клиента); CAC (стоимость привлечения). Автоматизировать мониторинг отклонений (еженедельные отчёты по Δ = факт – план). Учитывать внешние факторы (конкуренция, экономические условия) при корректировке планов. | AR39: Нет | AS39: =IF(AR39="Нет", " ", "Сделайте расчёт фактического уровня проникновения продаж по новым клиентам как Количество платных клиентов / Количество бесплатных * 100%. Сравните с плановым уровнем.")
C40: янв.26 | D40: фев.26 | E40: мар.26 | F40: апр.26 | G40: 46143 | H40: июн.26 | I40: июл.26 | J40: авг.26 | K40: сент.26 | L40: окт.26 | M40: ноя.26 | N40: дек.26 | O40: 2026 | P40: янв.26 | Q40: фев.26 | R40: мар.26 | S40: апр.26 | T40: 46143 | U40: июн.26 | V40: июл.26 | W40: авг.26 | X40: сент.26 | Y40: окт.26 | Z40: ноя.26 | AA40: дек.26 | AB40: 2026 | AC40: янв.26 | AD40: фев.26 | AE40: мар.26 | AF40: апр.26 | AG40: 46143 | AH40: июн.26 | AI40: июл.26 | AJ40: авг.26 | AK40: сент.26 | AL40: окт.26 | AM40: ноя.26 | AN40: дек.26 | AR40: Нет | AS40: =IF(AR40="Нет", " ", "Проверьте, как соотносится уровень проникновения продаж и количество продлений у Community? Сделайте вывод, что можно рекомендовать для изменения ситуации?")
B42: Community | AC42: Community | AR42: Нет | AS42: =IF(AR42="Нет", " ", "Проверьте, как соотносится уровень проникновения продаж и количество продлений у Education? Сделайте вывод, что можно рекомендовать для изменения ситуации?")
B43: Первый месяц | C43: 504 | D43: 507 | E43: 509 | F43: 514 | G43: 515 | H43: 525 | I43: 543 | J43: 567 | K43: 551 | L43: 561 | M43: 570 | N43: 580 | AC43: 0 | AD43: 0 | AE43: 0 | AF43: 0 | AG43: 0 | AH43: 0 | AI43: 0 | AJ43: 0 | AK43: 0 | AL43: 0 | AM43: 0 | AN43: 0 | AR43: Нет | AS43: =IF(AR43="Нет", " ", "Рассчитайте ежемесячный темп прироста новых клиентов на бесплатных продуктах как Количество клиентов в текущем месяце / Количествоклиентов в предыдущем месяце - 1. Сравните с планом по сезонности.")
B44: Подписка на месяц | C44: 0 | D44: 102 | E44: 103 | F44: 105 | G44: 108 | H44: 107 | I44: 113 | J44: 120 | K44: 125 | L44: 115 | M44: 115 | N44: 117 | AC44: 0 | AD44: =D44/C43 -> 0.20238095 | AE44: =E44/D43 -> 0.20315582 | AF44: =F44/E43 -> 0.20628684 | AG44: =G44/F43 -> 0.21011673 | AH44: =H44/G43 -> 0.20776699 | AI44: =I44/H43 -> 0.2152381 | AJ44: =J44/I43 -> 0.22099448 | AK44: =K44/J43 -> 0.22045855 | ... AN44: =N44/M43 -> 0.20526316 | AR44: Нет | AS44: =IF(AR44="Нет", " ", "Сделайте вывод по предыдущему расчёту, что можно изменить в модели для повышения точности планирования?")
B45: Пакет на 3 месяца | C45: 0 | D45: 76 | E45: 78 | F45: 78 | G45: 80 | H45: 79 | I45: 86 | J45: 90 | K45: 93 | L45: 85 | M45: 88 | N45: 88 | AC45: 0 | AD45: =D45/C43 -> 0.15079365 | AE45: =E45/D43 -> 0.15384615 | AF45: =F45/E43 -> 0.15324165 | AG45: =G45/F43 -> 0.15564202 | AH45: =H45/G43 -> 0.15339806 | AI45: =I45/H43 -> 0.16380952 | AJ45: =J45/I43 -> 0.16574586 | AK45: =K45/J43 -> 0.16402116 | ... AN45: =N45/M43 -> 0.15438596
B46: Пакет на 6 месяцев | C46: 0 | D46: 53 | E46: 52 | F46: 55 | G46: 54 | H46: 57 | I46: 58 | J46: 62 | K46: 64 | L46: 56 | M46: 57 | N46: 60 | AC46: 0 | AD46: =D46/C43 -> 0.10515873 | AE46: =E46/D43 -> 0.1025641 | AF46: =F46/E43 -> 0.10805501 | AG46: =G46/F43 -> 0.10505837 | AH46: =H46/G43 -> 0.11067961 | AI46: =I46/H43 -> 0.11047619 | AJ46: =J46/I43 -> 0.11418048 | AK46: =K46/J43 -> 0.11287478 | ... AN46: =N46/M43 -> 0.10526316
B47: Пакет на 12 месяцев | C47: 0 | D47: 17 | E47: 16 | F47: 17 | G47: 16 | H47: 16 | I47: 17 | J47: 20 | K47: 20 | L47: 18 | M47: 16 | N47: 19 | AC47: 0 | AD47: =D47/C43 -> 0.033730159 | AE47: =E47/D43 -> 0.031558185 | AF47: =F47/E43 -> 0.033398821 | AG47: =G47/F43 -> 0.031128405 | AH47: =H47/G43 -> 0.031067961 | AI47: =I47/H43 -> 0.032380952 | AJ47: =J47/I43 -> 0.036832413 | AK47: =K47/J43 -> 0.035273369 | ... AN47: =N47/M43 -> 0.033333333
B48: Education | AC48: Education
B49: Фритрек | C49: 97 | D49: 100 | E49: 103 | F49: 105 | G49: 106 | H49: 113 | I49: 115 | J49: 117 | K49: 111 | L49: 113 | M49: 104 | N49: 81 | AC49: 0 | AD49: 0 | AE49: 0 | AF49: 0 | AG49: 0 | AH49: 0 | AI49: 0 | AJ49: 0 | AK49: 0 | AL49: 0 | AM49: 0 | AN49: 0
B50: Полная оплата курса | C50: 3 | D50: 3 | E50: 3 | F50: 3 | G50: 3 | H50: 3 | I50: 3 | J50: 3 | K50: 3 | L50: 3 | M50: 3 | N50: 3 | AC50: =C50 -> 3 | AD50: =D50/C49 -> 0.030927835 | AE50: =E50/D49 -> 0.03 | AF50: =F50/E49 -> 0.029126214 | AG50: =G50/F49 -> 0.028571429 | AH50: =H50/G49 -> 0.028301887 | AI50: =I50/H49 -> 0.026548673 | AJ50: =J50/I49 -> 0.026086957 | AK50: =K50/J49 -> 0.025641026 | ... AN50: =N50/M49 -> 0.028846154
B51: Оплата курса 2 траншами | C51: 5 | D51: 6 | E51: 7 | F51: 7 | G51: 7 | H51: 7 | I51: 7 | J51: 7 | K51: 10 | L51: 7 | M51: 7 | N51: 7 | AC51: =C51 -> 5 | AD51: =D51/C49 -> 0.06185567 | AE51: =E51/D49 -> 0.07 | AF51: =F51/E49 -> 0.067961165 | AG51: =G51/F49 -> 0.066666667 | AH51: =H51/G49 -> 0.066037736 | AI51: =I51/H49 -> 0.061946903 | AJ51: =J51/I49 -> 0.060869565 | AK51: =K51/J49 -> 0.085470085 | ... AN51: =N51/M49 -> 0.067307692
B52: Оплата курса 3 траншами | C52: 8 | D52: 8 | E52: 8 | F52: 8 | G52: 9 | H52: 9 | I52: 9 | J52: 9 | K52: 9 | L52: 10 | M52: 10 | N52: 11 | AC52: =C52 -> 8 | AD52: =D52/C49 -> 0.082474227 | AE52: =E52/D49 -> 0.08 | AF52: =F52/E49 -> 0.077669903 | AG52: =G52/F49 -> 0.085714286 | AH52: =H52/G49 -> 0.08490566 | AI52: =I52/H49 -> 0.079646018 | AJ52: =J52/I49 -> 0.07826087 | AK52: =K52/J49 -> 0.076923077 | ... AN52: =N52/M49 -> 0.10576923
B53: Оплата курса помесячно | C53: 10 | D53: 10 | E53: 10 | F53: 11 | G53: 11 | H53: 11 | I53: 12 | J53: 12 | K53: 12 | L53: 12 | M53: 13 | N53: 13 | AC53: =C53 -> 10 | AD53: =D53/C49 -> 0.10309278 | AE53: =E53/D49 -> 0.1 | AF53: =F53/E49 -> 0.10679612 | AG53: =G53/F49 -> 0.1047619 | AH53: =H53/G49 -> 0.10377358 | AI53: =I53/H49 -> 0.10619469 | AJ53: =J53/I49 -> 0.10434783 | AK53: =K53/J49 -> 0.1025641 | ... AN53: =N53/M49 -> 0.125
B55: Таблица 3.1.2. Количество продлений, чел. | I55: факт | P55: Δ (факт - план) | AC55: ежемесячный прирост
C56: янв.26 | D56: фев.26 | E56: мар.26 | F56: апр.26 | G56: 46143 | H56: июн.26 | I56: июл.26 | J56: авг.26 | K56: сент.26 | L56: окт.26 | M56: ноя.26 | N56: дек.26 | O56: 2026 | P56: янв.26 | Q56: фев.26 | R56: мар.26 | S56: апр.26 | T56: 46143 | U56: июн.26 | V56: июл.26 | W56: авг.26 | X56: сент.26 | Y56: окт.26 | Z56: ноя.26 | AA56: дек.26 | AB56: 2026 | AC56: янв.26 | AD56: фев.26 | AE56: мар.26 | AF56: апр.26 | AG56: 46143 | AH56: июн.26 | AI56: июл.26 | AJ56: авг.26 | AK56: сент.26 | AL56: окт.26 | AM56: ноя.26 | AN56: дек.26
B58: Community | AC58: Community Первый месяц
B59: Подписка на месяц | C59: 0 | D59: 0 | E59: 80 | F59: 162 | G59: 245 | H59: 329 | I59: 414 | J59: 504 | K59: 598 | L59: 696 | M59: 788 | N59: 881 | AC59: 0 | AD59: =D43/C43-1 -> 0.005952381 | AE59: =E43/D43-1 -> 0.0039447732 | AF59: =F43/E43-1 -> 0.0098231827 | AG59: =G43/F43-1 -> 0.0019455253 | AH59: =H43/G43-1 -> 0.019417476 | AI59: =I43/H43-1 -> 0.034285714 | AJ59: =J43/I43-1 -> 0.044198895 | AK59: =K43/J43-1 -> -0.028218695 | ... AN59: =N43/M43-1 -> 0.01754386
B60: Пакет на 3 месяца | C60: 0 | D60: 0 | E60: 60 | F60: 122 | G60: 184 | H60: 247 | I60: 311 | J60: 378 | K60: 449 | L60: 522 | M60: 591 | N60: 661
B61: Пакет на 6 месяцев | C61: 0 | D61: 0 | E61: 40 | F61: 81 | G61: 123 | H61: 165 | I61: 207 | J61: 252 | K61: 299 | L61: 348 | M61: 394 | N61: 441
B62: Пакет на 12 месяцев | C62: 0 | D62: 0 | E62: 12 | F62: 25 | G62: 37 | H62: 50 | I62: 63 | J62: 76 | K62: 90 | L62: 105 | M62: 119 | N62: 133
B63: Education | AC63: Education Фритрек
B64: Полная оплата курса | C64: 0 | D64: 2 | E64: 4 | F64: 6 | G64: 7 | H64: 9 | I64: 10 | J64: 13 | K64: 14 | L64: 17 | M64: 20 | N64: 21 | AC64: 0 | AD64: =D49/C49-1 -> 0.030927835 | AE64: =E49/D49-1 -> 0.03 | AF64: =F49/E49-1 -> 0.019417476 | AG64: =G49/F49-1 -> 0.0095238095 | AH64: =H49/G49-1 -> 0.066037736 | AI64: =I49/H49-1 -> 0.017699115 | AJ64: =J49/I49-1 -> 0.017391304 | AK64: =K49/J49-1 -> -0.051282051 | ... AN64: =N49/M49-1 -> -0.22115385
B65: Оплата курса 2 траншами | C65: 0 | D65: 4 | E65: 9 | F65: 15 | G65: 20 | H65: 23 | I65: 27 | J65: 34 | K65: 41 | L65: 51 | M65: 56 | N65: 63
B66: Оплата курса 3 траншами | C66: 0 | D66: 6 | E66: 13 | F66: 20 | G66: 26 | H66: 32 | I66: 38 | J66: 47 | K66: 55 | L66: 64 | M66: 71 | N66: 80
B67: Оплата курса помесячно | C67: 0 | D67: 7 | E67: 17 | F67: 26 | G67: 32 | H67: 42 | I67: 51 | J67: 61 | K67: 72 | L67: 83 | M67: 89 | N67: 101
B69: Таблица 3.2. Стоимость подписки в мес., руб. | I69: факт | P69: Δ (факт - план)
C70: янв.26 | D70: фев.26 | E70: мар.26 | F70: апр.26 | G70: 46143 | H70: июн.26 | I70: июл.26 | J70: авг.26 | K70: сент.26 | L70: окт.26 | M70: ноя.26 | N70: дек.26 | O70: 2026 | P70: янв.26 | Q70: фев.26 | R70: мар.26 | S70: апр.26 | T70: 46143 | U70: июн.26 | V70: июл.26 | W70: авг.26 | X70: сент.26 | Y70: окт.26 | Z70: ноя.26 | AA70: дек.26 | AB70: 2026
B72: Community
B73: Первый месяц | C73: 0 | D73: 0 | E73: 0 | F73: 0 | G73: 0 | H73: 0 | I73: 0 | J73: 0 | K73: 0 | L73: 0 | M73: 0 | N73: 0 | P73: =C73-Расчеты!C42 -> 0 | Q73: =D73-Расчеты!D42 -> 0 | R73: =E73-Расчеты!E42 -> 0 | S73: =F73-Расчеты!F42 -> 0 | T73: =G73-Расчеты!G42 -> 0 | U73: =H73-Расчеты!H42 -> 0 | V73: =I73-Расчеты!I42 -> 0 | W73: =J73-Расчеты!J42 -> 0 | ... AA73: =N73-Расчеты!N42 -> 0 | AB73: =SUM(P73:AA73) -> 0
B74: Подписка на месяц | C74: 300 | D74: 300 | E74: 300 | F74: 300 | G74: 300 | H74: 300 | I74: 300 | J74: 300 | K74: 300 | L74: 300 | M74: 300 | N74: 300 | P74: =C74-Расчеты!C43 -> 0 | Q74: =D74-Расчеты!D43 -> 0 | R74: =E74-Расчеты!E43 -> 0 | S74: =F74-Расчеты!F43 -> 0 | T74: =G74-Расчеты!G43 -> 0 | U74: =H74-Расчеты!H43 -> 0 | V74: =I74-Расчеты!I43 -> 0 | W74: =J74-Расчеты!J43 -> 0 | ... AA74: =N74-Расчеты!N43 -> 0 | AB74: =SUM(P74:AA74) -> 0
B75: Пакет на 3 месяца | C75: 283.33333 | D75: 283.33333 | E75: 283.33333 | F75: 283.33333 | G75: 283.33333 | H75: 283.33333 | I75: 283.33333 | J75: 283.33333 | K75: 283.33333 | L75: 283.33333 | M75: 283.33333 | N75: 283.33333 | P75: =C75-Расчеты!C44 -> 0 | Q75: =D75-Расчеты!D44 -> 0 | R75: =E75-Расчеты!E44 -> 0 | S75: =F75-Расчеты!F44 -> 0 | T75: =G75-Расчеты!G44 -> 0 | U75: =H75-Расчеты!H44 -> 0 | V75: =I75-Расчеты!I44 -> 0 | W75: =J75-Расчеты!J44 -> 0 | ... AA75: =N75-Расчеты!N44 -> 0 | AB75: =SUM(P75:AA75) -> 0
B76: Пакет на 6 месяцев | C76: 266.66667 | D76: 266.66667 | E76: 266.66667 | F76: 266.66667 | G76: 266.66667 | H76: 266.66667 | I76: 266.66667 | J76: 266.66667 | K76: 266.66667 | L76: 266.66667 | M76: 266.66667 | N76: 266.66667 | P76: =C76-Расчеты!C45 -> 0 | Q76: =D76-Расчеты!D45 -> 0 | R76: =E76-Расчеты!E45 -> 0 | S76: =F76-Расчеты!F45 -> 0 | T76: =G76-Расчеты!G45 -> 0 | U76: =H76-Расчеты!H45 -> 0 | V76: =I76-Расчеты!I45 -> 0 | W76: =J76-Расчеты!J45 -> 0 | ... AA76: =N76-Расчеты!N45 -> 0 | AB76: =SUM(P76:AA76) -> 0
B77: Пакет на 12 месяцев | C77: 250 | D77: 250 | E77: 250 | F77: 250 | G77: 250 | H77: 250 | I77: 250 | J77: 250 | K77: 250 | L77: 250 | M77: 250 | N77: 250 | P77: =C77-Расчеты!C46 -> 0 | Q77: =D77-Расчеты!D46 -> 0 | R77: =E77-Расчеты!E46 -> 0 | S77: =F77-Расчеты!F46 -> 0 | T77: =G77-Расчеты!G46 -> 0 | U77: =H77-Расчеты!H46 -> 0 | V77: =I77-Расчеты!I46 -> 0 | W77: =J77-Расчеты!J46 -> 0 | ... AA77: =N77-Расчеты!N46 -> 0 | AB77: =SUM(P77:AA77) -> 0
B78: Education
B79: Фритрек | C79: 0 | D79: 0 | E79: 0 | F79: 0 | G79: 0 | H79: 0 | I79: 0 | J79: 0 | K79: 0 | L79: 0 | M79: 0 | N79: 0 | P79: =C79-Расчеты!C48 -> 0 | Q79: =D79-Расчеты!D48 -> 0 | R79: =E79-Расчеты!E48 -> 0 | S79: =F79-Расчеты!F48 -> 0 | T79: =G79-Расчеты!G48 -> 0 | U79: =H79-Расчеты!H48 -> 0 | V79: =I79-Расчеты!I48 -> 0 | W79: =J79-Расчеты!J48 -> 0 | ... AA79: =N79-Расчеты!N48 -> 0 | AB79: =SUM(P79:AA79) -> 0
B80: Полная оплата курса | C80: 8333.3333 | D80: 8333.3333 | E80: 8333.3333 | F80: 8333.3333 | G80: 8333.3333 | H80: 8333.3333 | I80: 8333.3333 | J80: 8333.3333 | K80: 8333.3333 | L80: 8333.3333 | M80: 8333.3333 | N80: 8333.3333 | P80: =C80-Расчеты!C49 -> 0 | Q80: =D80-Расчеты!D49 -> 0 | R80: =E80-Расчеты!E49 -> 0 | S80: =F80-Расчеты!F49 -> 0 | T80: =G80-Расчеты!G49 -> 0 | U80: =H80-Расчеты!H49 -> 0 | V80: =I80-Расчеты!I49 -> 0 | W80: =J80-Расчеты!J49 -> 0 | ... AA80: =N80-Расчеты!N49 -> 0 | AB80: =SUM(P80:AA80) -> 0
B81: Оплата курса 2 траншами | C81: 9166.6667 | D81: 9166.6667 | E81: 9166.6667 | F81: 9166.6667 | G81: 9166.6667 | H81: 9166.6667 | I81: 9166.6667 | J81: 9166.6667 | K81: 9166.6667 | L81: 9166.6667 | M81: 9166.6667 | N81: 9166.6667 | P81: =C81-Расчеты!C50 -> 0 | Q81: =D81-Расчеты!D50 -> 0 | R81: =E81-Расчеты!E50 -> 0 | S81: =F81-Расчеты!F50 -> 0 | T81: =G81-Расчеты!G50 -> 0 | U81: =H81-Расчеты!H50 -> 0 | V81: =I81-Расчеты!I50 -> 0 | W81: =J81-Расчеты!J50 -> 0 | ... AA81: =N81-Расчеты!N50 -> 0 | AB81: =SUM(P81:AA81) -> 0
B82: Оплата курса 3 траншами | C82: 9500 | D82: 9500 | E82: 9500 | F82: 9500 | G82: 9500 | H82: 9500 | I82: 9500 | J82: 9500 | K82: 9500 | L82: 9500 | M82: 9500 | N82: 9500 | P82: =C82-Расчеты!C51 -> 0 | Q82: =D82-Расчеты!D51 -> 0 | R82: =E82-Расчеты!E51 -> 0 | S82: =F82-Расчеты!F51 -> 0 | T82: =G82-Расчеты!G51 -> 0 | U82: =H82-Расчеты!H51 -> 0 | V82: =I82-Расчеты!I51 -> 0 | W82: =J82-Расчеты!J51 -> 0 | ... AA82: =N82-Расчеты!N51 -> 0 | AB82: =SUM(P82:AA82) -> 0
B83: Оплата курса помесячно | C83: 10000 | D83: 10000 | E83: 10000 | F83: 10000 | G83: 10000 | H83: 10000 | I83: 10000 | J83: 10000 | K83: 10000 | L83: 10000 | M83: 10000 | N83: 10000 | P83: =C83-Расчеты!C52 -> 0 | Q83: =D83-Расчеты!D52 -> 0 | R83: =E83-Расчеты!E52 -> 0 | S83: =F83-Расчеты!F52 -> 0 | T83: =G83-Расчеты!G52 -> 0 | U83: =H83-Расчеты!H52 -> 0 | V83: =I83-Расчеты!I52 -> 0 | W83: =J83-Расчеты!J52 -> 0 | ... AA83: =N83-Расчеты!N52 -> 0 | AB83: =SUM(P83:AA83) -> 0
B85: Таблица 4. Расходы на аутсорс-разработку под ключ, тыс. руб. | K85: факт | P85: Δ (факт - план)
C86: янв.26 | D86: фев.26 | E86: мар.26 | F86: апр.26 | G86: 46143 | H86: июн.26 | I86: июл.26 | J86: авг.26 | K86: сент.26 | L86: окт.26 | M86: ноя.26 | N86: дек.26 | O86: 2026 | P86: янв.26 | Q86: фев.26 | R86: мар.26 | S86: апр.26 | T86: 46143 | U86: июн.26 | V86: июл.26 | W86: авг.26 | X86: сент.26 | Y86: окт.26 | Z86: ноя.26 | AA86: дек.26 | AB86: 2026
B88: Community | C88: 333.33333 | D88: 333.33333 | E88: 333.33333 | F88: 333.33333 | G88: 333.33333 | H88: 333.33333 | I88: 333.33333 | J88: 333.33333 | K88: 333.33333 | L88: 333.33333 | M88: 333.33333 | N88: 333.33333 | O88: =SUM(C88:N88) -> 4000 | P88: =C88-Расчеты!C57 -> 0 | Q88: =D88-Расчеты!D57 -> 0 | R88: =E88-Расчеты!E57 -> 0 | S88: =F88-Расчеты!F57 -> 0 | T88: =G88-Расчеты!G57 -> 0 | U88: =H88-Расчеты!H57 -> 0 | V88: =I88-Расчеты!I57 -> 0 | W88: =J88-Расчеты!J57 -> 0 | ... AA88: =N88-Расчеты!N57 -> 0 | AB88: =SUM(P88:AA88) -> 0
B89: Education | C89: 250 | D89: 250 | E89: 250 | F89: 250 | G89: 250 | H89: 250 | I89: 250 | J89: 250 | K89: 250 | L89: 250 | M89: 250 | N89: 250 | O89: =SUM(C89:N89) -> 3000 | P89: =C89-Расчеты!C58 -> 0 | Q89: =D89-Расчеты!D58 -> 0 | R89: =E89-Расчеты!E58 -> 0 | S89: =F89-Расчеты!F58 -> 0 | T89: =G89-Расчеты!G58 -> 0 | U89: =H89-Расчеты!H58 -> 0 | V89: =I89-Расчеты!I58 -> 0 | W89: =J89-Расчеты!J58 -> 0 | ... AA89: =N89-Расчеты!N58 -> 0 | AB89: =SUM(P89:AA89) -> 0
B91: Таблица 5. Расходы на поддерживающий персонал, тыс. руб. | K91: факт | P91: Δ (факт - план) | AP91: Из выгрузки не попали компенсация питания, добавил табл. 5.5. Отколнения в таб.5 это ровно не запланированная компенсация на питание и количество кураторов конечно | AR91: Нет | AS91: =IF(AR91="Нет", " ", "Для выявления причин отклонений по данному показателю, проанализируйте его драйверы.")
C92: янв.26 | D92: фев.26 | E92: мар.26 | F92: апр.26 | G92: 46143 | H92: июн.26 | I92: июл.26 | J92: авг.26 | K92: сент.26 | L92: окт.26 | M92: ноя.26 | N92: дек.26 | O92: 2026 | P92: янв.26 | Q92: фев.26 | R92: мар.26 | S92: апр.26 | T92: 46143 | U92: июн.26 | V92: июл.26 | W92: авг.26 | X92: сент.26 | Y92: окт.26 | Z92: ноя.26 | AA92: дек.26 | AB92: 2026 | AR92: Нет | AS92: =IF(AR92="Нет", " ", "Текущих драйверов недостаточно для выявления причин отклонений, требуется анализ дополнительных данных. Проанализируйте данные на листе Выгрузка персонал. Добавьте недостающие данные на лист Свод факта.")
B94: Community | C94: =SUM(C95:C99) -> 521 | D94: =SUM(D95:D99) -> 524 | E94: =SUM(E95:E99) -> 524 | F94: =SUM(F95:F99) -> 525 | G94: =SUM(G95:G99) -> 524 | H94: =SUM(H95:H99) -> 523 | I94: =SUM(I95:I99) -> 527 | J94: =SUM(J95:J99) -> 526 | ... N94: =SUM(N95:N99) -> 525 | O94: =SUM(C94:N94) -> 6296 | P94: =SUM(P95:P99) -> 17 | Q94: =SUM(Q95:Q99) -> 20 | R94: =SUM(R95:R99) -> 20 | S94: =SUM(S95:S99) -> 21 | T94: =SUM(T95:T99) -> 20 | U94: =SUM(U95:U99) -> 19 | V94: =SUM(V95:V99) -> 23 | W94: =SUM(W95:W99) -> 22 | ... AA94: =SUM(AA95:AA99) -> 21 | AB94: =SUM(P94:AA94) -> 248 | AR94: Нет | AS94: =IF(AR94="Нет", " ", "Проверьте, все ли данные из выгрузки попали в модель бюджета?")
B95: Producr Owner | C95: 135.4 | D95: 136 | E95: 136 | F95: 136.2 | G95: 136 | H95: 135.8 | I95: 136.6 | J95: 136.4 | K95: 136.2 | L95: 136.6 | M95: 136.2 | N95: 136.2 | O95: =SUM(C95:N95) -> 1633.6 | P95: =C95-Расчеты!C64 -> 3.4 | Q95: =D95-Расчеты!D64 -> 4 | R95: =E95-Расчеты!E64 -> 4 | S95: =F95-Расчеты!F64 -> 4.2 | T95: =G95-Расчеты!G64 -> 4 | U95: =H95-Расчеты!H64 -> 3.8 | V95: =I95-Расчеты!I64 -> 4.6 | W95: =J95-Расчеты!J64 -> 4.4 | ... AA95: =N95-Расчеты!N64 -> 4.2 | AB95: =SUM(P95:AA95) -> 49.6
B96: Модератор | C96: 83.4 | D96: 84 | E96: 84 | F96: 84.2 | G96: 84 | H96: 83.8 | I96: 84.6 | J96: 84.4 | K96: 84.2 | L96: 84.6 | M96: 84.2 | N96: 84.2 | O96: =SUM(C96:N96) -> 1009.6 | P96: =C96-Расчеты!C65 -> 3.4 | Q96: =D96-Расчеты!D65 -> 4 | R96: =E96-Расчеты!E65 -> 4 | S96: =F96-Расчеты!F65 -> 4.2 | T96: =G96-Расчеты!G65 -> 4 | U96: =H96-Расчеты!H65 -> 3.8 | V96: =I96-Расчеты!I65 -> 4.6 | W96: =J96-Расчеты!J65 -> 4.4 | ... AA96: =N96-Расчеты!N65 -> 4.2 | AB96: =SUM(P96:AA96) -> 49.6
B97: Инженер тех. поддержки | C97: 83.4 | D97: 84 | E97: 84 | F97: 84.2 | G97: 84 | H97: 83.8 | I97: 84.6 | J97: 84.4 | K97: 84.2 | L97: 84.6 | M97: 84.2 | N97: 84.2 | O97: =SUM(C97:N97) -> 1009.6 | P97: =C97-Расчеты!C66 -> 3.4 | Q97: =D97-Расчеты!D66 -> 4 | R97: =E97-Расчеты!E66 -> 4 | S97: =F97-Расчеты!F66 -> 4.2 | T97: =G97-Расчеты!G66 -> 4 | U97: =H97-Расчеты!H66 -> 3.8 | V97: =I97-Расчеты!I66 -> 4.6 | W97: =J97-Расчеты!J66 -> 4.4 | ... AA97: =N97-Расчеты!N66 -> 4.2 | AB97: =SUM(P97:AA97) -> 49.6
B98: Контент-мейкер | C98: 109.4 | D98: 110 | E98: 110 | F98: 110.2 | G98: 110 | H98: 109.8 | I98: 110.6 | J98: 110.4 | K98: 110.2 | L98: 110.6 | M98: 110.2 | N98: 110.2 | O98: =SUM(C98:N98) -> 1321.6 | P98: =C98-Расчеты!C67 -> 3.4 | Q98: =D98-Расчеты!D67 -> 4 | R98: =E98-Расчеты!E67 -> 4 | S98: =F98-Расчеты!F67 -> 4.2 | T98: =G98-Расчеты!G67 -> 4 | U98: =H98-Расчеты!H67 -> 3.8 | V98: =I98-Расчеты!I67 -> 4.6 | W98: =J98-Расчеты!J67 -> 4.4 | ... AA98: =N98-Расчеты!N67 -> 4.2 | AB98: =SUM(P98:AA98) -> 49.6
B99: SMM | C99: 109.4 | D99: 110 | E99: 110 | F99: 110.2 | G99: 110 | H99: 109.8 | I99: 110.6 | J99: 110.4 | K99: 110.2 | L99: 110.6 | M99: 110.2 | N99: 110.2 | O99: =SUM(C99:N99) -> 1321.6 | P99: =C99-Расчеты!C68 -> 3.4 | Q99: =D99-Расчеты!D68 -> 4 | R99: =E99-Расчеты!E68 -> 4 | S99: =F99-Расчеты!F68 -> 4.2 | T99: =G99-Расчеты!G68 -> 4 | U99: =H99-Расчеты!H68 -> 3.8 | V99: =I99-Расчеты!I68 -> 4.6 | W99: =J99-Расчеты!J68 -> 4.4 | ... AA99: =N99-Расчеты!N68 -> 4.2 | AB99: =SUM(P99:AA99) -> 49.6
B100: Education | C100: =SUM(C101:C104) -> 476.6 | D100: =SUM(D101:D104) -> 615 | E100: =SUM(E101:E104) -> 751 | F100: =SUM(F101:F104) -> 888.4 | G100: =SUM(G101:G104) -> 887 | H100: =SUM(H101:H104) -> 1021.4 | I100: =SUM(I101:I104) -> 1164.4 | J100: =SUM(J101:J104) -> 1299 | ... N100: =SUM(N101:N104) -> 1705.6 | O100: =SUM(C100:N100) -> 13385.2 | P100: =SUM(P101:P104) -> 13.6 | Q100: =SUM(Q101:Q104) -> 20 | R100: =SUM(R101:R104) -> 156 | S100: =SUM(S101:S104) -> 161.4 | T100: =SUM(T101:T104) -> 28 | U100: =SUM(U101:U104) -> 30.4 | V100: =SUM(V101:V104) -> 173.4 | W100: =SUM(W101:W104) -> 176 | ... AA100: =SUM(AA101:AA104) -> 186.6 | AB100: =SUM(P100:AA100) -> 1493.2
B101: Producr Owner | C101: 135.4 | D101: 136 | E101: 136 | F101: 136.2 | G101: 136 | H101: 135.8 | I101: 136.6 | J101: 136.4 | K101: 136.2 | L101: 136.6 | M101: 136.2 | N101: 136.2 | O101: =SUM(C101:N101) -> 1633.6 | P101: =C101-Расчеты!C70 -> 3.4 | Q101: =D101-Расчеты!D70 -> 4 | R101: =E101-Расчеты!E70 -> 4 | S101: =F101-Расчеты!F70 -> 4.2 | T101: =G101-Расчеты!G70 -> 4 | U101: =H101-Расчеты!H70 -> 3.8 | V101: =I101-Расчеты!I70 -> 4.6 | W101: =J101-Расчеты!J70 -> 4.4 | ... AA101: =N101-Расчеты!N70 -> 4.2 | AB101: =SUM(P101:AA101) -> 49.6
B102: Куратор | C102: 135.4 | D102: 272 | E102: 408 | F102: 544.8 | G102: 544 | H102: 679 | I102: 819.6 | J102: 954.8 | K102: 1089.6 | L102: 1229.4 | M102: 1225.8 | N102: 1362 | O102: =SUM(C102:N102) -> 9264.4 | P102: =C102-Расчеты!C71 -> 3.4 | Q102: =D102-Расчеты!D71 -> 8 | R102: =E102-Расчеты!E71 -> 144 | S102: =F102-Расчеты!F71 -> 148.8 | T102: =G102-Расчеты!G71 -> 16 | U102: =H102-Расчеты!H71 -> 19 | V102: =I102-Расчеты!I71 -> 159.6 | W102: =J102-Расчеты!J71 -> 162.8 | ... AA102: =N102-Расчеты!N71 -> 174 | AB102: =SUM(P102:AA102) -> 1344.4
B103: Инженер тех. поддержки | C103: 96.4 | D103: 97 | E103: 97 | F103: 97.2 | G103: 97 | H103: 96.8 | I103: 97.6 | J103: 97.4 | K103: 97.2 | L103: 97.6 | M103: 97.2 | N103: 97.2 | O103: =SUM(C103:N103) -> 1165.6 | P103: =C103-Расчеты!C72 -> 3.4 | Q103: =D103-Расчеты!D72 -> 4 | R103: =E103-Расчеты!E72 -> 4 | S103: =F103-Расчеты!F72 -> 4.2 | T103: =G103-Расчеты!G72 -> 4 | U103: =H103-Расчеты!H72 -> 3.8 | V103: =I103-Расчеты!I72 -> 4.6 | W103: =J103-Расчеты!J72 -> 4.4 | ... AA103: =N103-Расчеты!N72 -> 4.2 | AB103: =SUM(P103:AA103) -> 49.6
B104: SMM | C104: 109.4 | D104: 110 | E104: 110 | F104: 110.2 | G104: 110 | H104: 109.8 | I104: 110.6 | J104: 110.4 | K104: 110.2 | L104: 110.6 | M104: 110.2 | N104: 110.2 | O104: =SUM(C104:N104) -> 1321.6 | P104: =C104-Расчеты!C73 -> 3.4 | Q104: =D104-Расчеты!D73 -> 4 | R104: =E104-Расчеты!E73 -> 4 | S104: =F104-Расчеты!F73 -> 4.2 | T104: =G104-Расчеты!G73 -> 4 | U104: =H104-Расчеты!H73 -> 3.8 | V104: =I104-Расчеты!I73 -> 4.6 | W104: =J104-Расчеты!J73 -> 4.4 | ... AA104: =N104-Расчеты!N73 -> 4.2 | AB104: =SUM(P104:AA104) -> 49.6
B105: Бухгалтер | C105: 57.4 | D105: 58 | E105: 58 | F105: 58.2 | G105: 58 | H105: 57.8 | I105: 58.6 | J105: 58.4 | K105: 58.2 | L105: 58.6 | M105: 58.2 | N105: 58.2 | O105: =SUM(C105:N105) -> 697.6 | P105: =C105-Расчеты!C74 -> 3.4 | Q105: =D105-Расчеты!D74 -> 4 | R105: =E105-Расчеты!E74 -> 4 | S105: =F105-Расчеты!F74 -> 4.2 | T105: =G105-Расчеты!G74 -> 4 | U105: =H105-Расчеты!H74 -> 3.8 | V105: =I105-Расчеты!I74 -> 4.6 | W105: =J105-Расчеты!J74 -> 4.4 | ... AA105: =N105-Расчеты!N74 -> 4.2 | AB105: =SUM(P105:AA105) -> 49.6
B107: Таблица 5.1. Заработная плата с учётом количества штатных единиц, тыс. руб. | K107: факт | P107: Δ (факт - план) | AR107: Нет | AS107: =IF(AR107="Нет", " ", "Для выявления причин отклонений по данному показателю, проанализируйте его драйверы.")
C108: янв.26 | D108: фев.26 | E108: мар.26 | F108: апр.26 | G108: 46143 | H108: июн.26 | I108: июл.26 | J108: авг.26 | K108: сент.26 | L108: окт.26 | M108: ноя.26 | N108: дек.26 | O108: 2026 | P108: янв.26 | Q108: фев.26 | R108: мар.26 | S108: апр.26 | T108: 46143 | U108: июн.26 | V108: июл.26 | W108: авг.26 | X108: сент.26 | Y108: окт.26 | Z108: ноя.26 | AA108: дек.26 | AB108: 2026
B110: Community | C110: =SUM(C111:C115) -> 380 | D110: =SUM(D111:D115) -> 380 | E110: =SUM(E111:E115) -> 380 | F110: =SUM(F111:F115) -> 380 | G110: =SUM(G111:G115) -> 380 | H110: =SUM(H111:H115) -> 380 | I110: =SUM(I111:I115) -> 380 | J110: =SUM(J111:J115) -> 380 | ... N110: =SUM(N111:N115) -> 380 | O110: =SUM(C110:N110) -> 4560 | P110: =SUM(P111:P115) -> -124 | Q110: =SUM(Q111:Q115) -> -124 | R110: =SUM(R111:R115) -> -124 | S110: =SUM(S111:S115) -> -124 | T110: =SUM(T111:T115) -> -124 | U110: =SUM(U111:U115) -> -124 | V110: =SUM(V111:V115) -> -124 | W110: =SUM(W111:W115) -> -124 | ... AA110: =SUM(AA111:AA115) -> -124 | AB110: =SUM(P110:AA110) -> -1488
B111: Producr Owner | C111: 100 | D111: 100 | E111: 100 | F111: 100 | G111: 100 | H111: 100 | I111: 100 | J111: 100 | K111: 100 | L111: 100 | M111: 100 | N111: 100 | O111: =SUM(C111:N111) -> 1200 | P111: =C111-Расчеты!C64 -> -32 | Q111: =D111-Расчеты!D64 -> -32 | R111: =E111-Расчеты!E64 -> -32 | S111: =F111-Расчеты!F64 -> -32 | T111: =G111-Расчеты!G64 -> -32 | U111: =H111-Расчеты!H64 -> -32 | V111: =I111-Расчеты!I64 -> -32 | W111: =J111-Расчеты!J64 -> -32 | ... AA111: =N111-Расчеты!N64 -> -32 | AB111: =SUM(P111:AA111) -> -384
B112: Модератор | C112: 60 | D112: 60 | E112: 60 | F112: 60 | G112: 60 | H112: 60 | I112: 60 | J112: 60 | K112: 60 | L112: 60 | M112: 60 | N112: 60 | O112: =SUM(C112:N112) -> 720 | P112: =C112-Расчеты!C65 -> -20 | Q112: =D112-Расчеты!D65 -> -20 | R112: =E112-Расчеты!E65 -> -20 | S112: =F112-Расчеты!F65 -> -20 | T112: =G112-Расчеты!G65 -> -20 | U112: =H112-Расчеты!H65 -> -20 | V112: =I112-Расчеты!I65 -> -20 | W112: =J112-Расчеты!J65 -> -20 | ... AA112: =N112-Расчеты!N65 -> -20 | AB112: =SUM(P112:AA112) -> -240
B113: Инженер тех. поддержки | C113: 60 | D113: 60 | E113: 60 | F113: 60 | G113: 60 | H113: 60 | I113: 60 | J113: 60 | K113: 60 | L113: 60 | M113: 60 | N113: 60 | O113: =SUM(C113:N113) -> 720 | P113: =C113-Расчеты!C66 -> -20 | Q113: =D113-Расчеты!D66 -> -20 | R113: =E113-Расчеты!E66 -> -20 | S113: =F113-Расчеты!F66 -> -20 | T113: =G113-Расчеты!G66 -> -20 | U113: =H113-Расчеты!H66 -> -20 | V113: =I113-Расчеты!I66 -> -20 | W113: =J113-Расчеты!J66 -> -20 | ... AA113: =N113-Расчеты!N66 -> -20 | AB113: =SUM(P113:AA113) -> -240
B114: Контент-мейкер | C114: 80 | D114: 80 | E114: 80 | F114: 80 | G114: 80 | H114: 80 | I114: 80 | J114: 80 | K114: 80 | L114: 80 | M114: 80 | N114: 80 | O114: =SUM(C114:N114) -> 960 | P114: =C114-Расчеты!C67 -> -26 | Q114: =D114-Расчеты!D67 -> -26 | R114: =E114-Расчеты!E67 -> -26 | S114: =F114-Расчеты!F67 -> -26 | T114: =G114-Расчеты!G67 -> -26 | U114: =H114-Расчеты!H67 -> -26 | V114: =I114-Расчеты!I67 -> -26 | W114: =J114-Расчеты!J67 -> -26 | ... AA114: =N114-Расчеты!N67 -> -26 | AB114: =SUM(P114:AA114) -> -312
B115: SMM | C115: 80 | D115: 80 | E115: 80 | F115: 80 | G115: 80 | H115: 80 | I115: 80 | J115: 80 | K115: 80 | L115: 80 | M115: 80 | N115: 80 | O115: =SUM(C115:N115) -> 960 | P115: =C115-Расчеты!C68 -> -26 | Q115: =D115-Расчеты!D68 -> -26 | R115: =E115-Расчеты!E68 -> -26 | S115: =F115-Расчеты!F68 -> -26 | T115: =G115-Расчеты!G68 -> -26 | U115: =H115-Расчеты!H68 -> -26 | V115: =I115-Расчеты!I68 -> -26 | W115: =J115-Расчеты!J68 -> -26 | ... AA115: =N115-Расчеты!N68 -> -26 | AB115: =SUM(P115:AA115) -> -312
B116: Education | C116: =SUM(C117:C120) -> 350 | D116: =SUM(D117:D120) -> 450 | E116: =SUM(E117:E120) -> 550 | F116: =SUM(F117:F120) -> 650 | G116: =SUM(G117:G120) -> 650 | H116: =SUM(H117:H120) -> 750 | I116: =SUM(I117:I120) -> 850 | J116: =SUM(J117:J120) -> 950 | ... N116: =SUM(N117:N120) -> 1250 | O116: =SUM(C116:N116) -> 9800 | P116: =SUM(P117:P120) -> -113 | Q116: =SUM(Q117:Q120) -> -145 | R116: =SUM(R117:R120) -> -45 | S116: =SUM(S117:S120) -> -77 | T116: =SUM(T117:T120) -> -209 | U116: =SUM(U117:U120) -> -241 | V116: =SUM(V117:V120) -> -141 | W116: =SUM(W117:W120) -> -173 | ... AA116: =SUM(AA117:AA120) -> -269 | AB116: =SUM(P116:AA116) -> -2092
B117: Producr Owner | C117: 100 | D117: 100 | E117: 100 | F117: 100 | G117: 100 | H117: 100 | I117: 100 | J117: 100 | K117: 100 | L117: 100 | M117: 100 | N117: 100 | O117: =SUM(C117:N117) -> 1200 | P117: =C117-Расчеты!C70 -> -32 | Q117: =D117-Расчеты!D70 -> -32 | R117: =E117-Расчеты!E70 -> -32 | S117: =F117-Расчеты!F70 -> -32 | T117: =G117-Расчеты!G70 -> -32 | U117: =H117-Расчеты!H70 -> -32 | V117: =I117-Расчеты!I70 -> -32 | W117: =J117-Расчеты!J70 -> -32 | ... AA117: =N117-Расчеты!N70 -> -32 | AB117: =SUM(P117:AA117) -> -384
...

Sheet Выгрузка персонал
A1: Дата | B1: Назначение | C1: ID сотрудника | D1: Должность | E1: Направление | F1: Сумма, руб. | G1: Подсказку?
A2: 46027 | B2: аванс | C2: 100005001 | D2: Producr Owner | E2: Community | F2: 40000 | G2: Нет | H2: =IF(G2="Нет", " ", "Сформируйте сводную таблицу по представленному массиву данных.")
A3: 46027 | B3: аванс | C3: 100005002 | D3: Модератор | E3: Community | F3: 24000 | G3: Нет | H3: =IF(G3="Нет", " ", "В сводной таблице добавьте в поле Столбцы даты, в поле Строки назначение, направление и должность, в поле Значения сумму. Сравните получившиеся данные со значениями на листе Свод факта.")
A4: 46027 | B4: аванс | C4: 100005003 | D4: Инженер тех. поддержки | E4: Community | F4: 24000 | G4: Нет | H4: =IF(G4="Нет", " ", "На листе Свод факта заработная плата включает в себя основную выплату зп и аванс. Для сравнения суммируйте эти две части в сводной таблице.")
A5: 46027 | B5: аванс | C5: 100005004 | D5: Контент-мейкер | E5: Community | F5: 32000 | G5: Нет | H5: =IF(G5="Нет", " ", "Проверьте, были ли учтены в плане компенсации по питанию в расходах на персонал?")
A6: 46027 | B6: аванс | C6: 100005005 | D6: SMM | E6: Community | F6: 32000 | G6: Нет | H6: =IF(G6="Нет", " ", "Для сравнения ДМС со значениями на листе Свод факта приведите данные сводной таблицы по ДМС к месячному формату, разделив их на 12.")
A7: 46027 | B7: аванс | C7: 100005006 | D7: Producr Owner | E7: Education | F7: 40000
A8: 46027 | B8: аванс | C8: 100005009 | D8: Куратор | E8: Education | F8: 40000
A9: 46027 | B9: аванс | C9: 100005007 | D9: Инженер тех. поддержки | E9: Education | F9: 28000
A10: 46027 | B10: аванс | C10: 100005008 | D10: SMM | E10: Education | F10: 32000
A11: 46027 | B11: аванс | C11: 100005000 | D11: Бухгалтер | E11: Бухгалтерия | F11: 16000
A12: 46042 | B12: заработная плата | C12: 100005001 | D12: Producr Owner | E12: Community | F12: 60000 | H12: Сумма по полю Сумма, руб. | I12: Названия столбцов
A13: 46042 | B13: заработная плата | C13: 100005002 | D13: Модератор | E13: Community | F13: 36000 | I13: янв | J13: февр | K13: март | L13: апр | M13: май | N13: июнь | O13: июль | P13: авг | Q13: сент | R13: окт | S13: нояб | T13: дек | U13: Общий итог
A14: 46042 | B14: заработная плата | C14: 100005003 | D14: Инженер тех. поддержки | E14: Community | F14: 36000
A15: 46042 | B15: заработная плата | C15: 100005004 | D15: Контент-мейкер | E15: Community | F15: 48000 | H15: Названия строк | V15: Сумма зп+аванс
A16: 46042 | B16: заработная плата | C16: 100005005 | D16: SMM | E16: Community | F16: 48000 | H16: аванс | I16: 308000 | J16: 348000 | K16: 442193.55 | L16: 475600 | M16: 487612.9 | N16: 546400 | O16: 575741.94 | P16: 678064.52 | Q16: 666400 | R16: 736387.1 | S16: 712000 | T16: 765548.39 | U16: 6741948.4
A17: 46042 | B17: заработная плата | C17: 100005006 | D17: Producr Owner | E17: Education | F17: 60000 | H17: Бухгалтерия | I17: 16000 | J17: 16000 | K17: 26838.71 | L17: 16000 | M17: 16000 | N17: 16000 | O17: 16000 | P17: 26838.71 | Q17: 16000 | R17: 16000 | S17: 16000 | T17: 16000 | U17: 213677.42 | V17: =GETPIVOTDATA("Сумма, руб.",$H$12,"Назначение","аванс","Направление","Бухгалтерия")+GETPIVOTDATA("Сумма, руб.",$H$12,"Назначение","заработная плата","Направление","Бухгалтерия") -> 480000
A18: 46042 | B18: заработная плата | C18: 100005009 | D18: Куратор | E18: Education | F18: 60000 | H18: Бухгалтер | I18: 16000 | J18: 16000 | K18: 26838.71 | L18: 16000 | M18: 16000 | N18: 16000 | O18: 16000 | P18: 26838.71 | Q18: 16000 | R18: 16000 | S18: 16000 | T18: 16000 | U18: 213677.42 | V18: =GETPIVOTDATA("Сумма, руб.",$H$12,"Назначение","аванс","Направление","Community")+GETPIVOTDATA("Сумма, руб.",$H$12,"Назначение","заработная плата","Направление","Community") -> 4560000
A19: 46042 | B19: заработная плата | C19: 100005007 | D19: Инженер тех. поддержки | E19: Education | F19: 42000 | H19: Community | I19: 152000 | J19: 152000 | K19: 173677.42 | L19: 152000 | M19: 184516.13 | N19: 202400 | O19: 173677.42 | P19: 168258.06 | Q19: 202400 | R19: 152000 | S19: 152000 | T19: 168258.06 | U19: 2033187.1 | V19: =GETPIVOTDATA("Сумма, руб.",$H$12,"Назначение","аванс","Направление","Education")+GETPIVOTDATA("Сумма, руб.",$H$12,"Назначение","заработная плата","Направление","Education") -> 9800000
A20: 46042 | B20: заработная плата | C20: 100005008 | D20: SMM | E20: Education | F20: 48000 | H20: Инженер тех. поддержки | I20: 24000 | J20: 24000 | K20: 24000 | L20: 24000 | M20: 40258.065 | N20: 24000 | O20: 24000 | P20: 40258.065 | Q20: 24000 | R20: 24000 | S20: 24000 | T20: 24000 | U20: 320516.13
A21: 46042 | B21: заработная плата | C21: 100005000 | D21: Бухгалтер | E21: Бухгалтерия | F21: 24000 | H21: Контент-мейкер | I21: 32000 | J21: 32000 | K21: 53677.419 | L21: 32000 | M21: 32000 | N21: 54400 | O21: 32000 | P21: 32000 | Q21: 32000 | R21: 32000 | S21: 32000 | T21: 32000 | U21: 428077.42
A22: 46058 | B22: аванс | C22: 100005001 | D22: Producr Owner | E22: Community | F22: 40000 | H22: Модератор | I22: 24000 | J22: 24000 | K22: 24000 | L22: 24000 | M22: 40258.065 | N22: 24000 | O22: 24000 | P22: 24000 | Q22: 24000 | R22: 24000 | S22: 24000 | T22: 40258.065 | U22: 320516.13
A23: 46058 | B23: аванс | C23: 100005002 | D23: Модератор | E23: Community | F23: 24000 | H23: Producr Owner | I23: 40000 | J23: 40000 | K23: 40000 | L23: 40000 | M23: 40000 | N23: 68000 | O23: 40000 | P23: 40000 | Q23: 68000 | R23: 40000 | S23: 40000 | T23: 40000 | U23: 536000
A24: 46058 | B24: аванс | C24: 100005003 | D24: Инженер тех. поддержки | E24: Community | F24: 24000 | H24: SMM | I24: 32000 | J24: 32000 | K24: 32000 | L24: 32000 | M24: 32000 | N24: 32000 | O24: 53677.419 | P24: 32000 | Q24: 54400 | R24: 32000 | S24: 32000 | T24: 32000 | U24: 428077.42
A25: 46058 | B25: аванс | C25: 100005004 | D25: Контент-мейкер | E25: Community | F25: 32000 | H25: Education | I25: 140000 | J25: 180000 | K25: 241677.42 | L25: 307600 | M25: 287096.77 | N25: 328000 | O25: 386064.52 | P25: 482967.74 | Q25: 448000 | R25: 568387.1 | S25: 544000 | T25: 581290.32 | U25: 4495083.9
A26: 46058 | B26: аванс | C26: 100005005 | D26: SMM | E26: Community | F26: 32000 | H26: Инженер тех. поддержки | I26: 28000 | J26: 28000 | K26: 28000 | L26: 47600 | M26: 28000 | N26: 28000 | O26: 46967.742 | P26: 28000 | Q26: 28000 | R26: 28000 | S26: 28000 | T26: 28000 | U26: 374567.74
A27: 46058 | B27: аванс | C27: 100005006 | D27: Producr Owner | E27: Education | F27: 40000 | H27: Куратор | I27: 40000 | J27: 80000 | K27: 120000 | L27: 188000 | M27: 187096.77 | N27: 228000 | O27: 267096.77 | P27: 334193.55 | Q27: 348000 | R27: 441290.32 | S27: 444000 | T27: 481290.32 | U27: 3158967.7
A28: 46058 | B28: аванс | C28: 100005009 | D28: Куратор | E28: Education | F28: 40000 | H28: Producr Owner | I28: 40000 | J28: 40000 | K28: 40000 | L28: 40000 | M28: 40000 | N28: 40000 | O28: 40000 | P28: 67096.774 | Q28: 40000 | R28: 67096.774 | S28: 40000 | T28: 40000 | U28: 534193.55
A29: 46058 | B29: аванс | C29: 100005010 | D29: Куратор | E29: Education | F29: 40000 | H29: SMM | I29: 32000 | J29: 32000 | K29: 53677.419 | L29: 32000 | M29: 32000 | N29: 32000 | O29: 32000 | P29: 53677.419 | Q29: 32000 | R29: 32000 | S29: 32000 | T29: 32000 | U29: 427354.84
A30: 46058 | B30: аванс | C30: 100005007 | D30: Инженер тех. поддержки | E30: Education | F30: 28000 | H30: ДМС на год | I30: 240000 | J30: 24000 | K30: 24000 | L30: 24000 | N30: 24000 | O30: 24000 | P30: 24000 | Q30: 24000 | R30: 24000 | T30: 24000 | U30: 456000
A31: 46058 | B31: аванс | C31: 100005008 | D31: SMM | E31: Education | F31: 32000 | H31: Бухгалтерия | I31: 24000 | U31: 24000
A32: 46058 | B32: аванс | C32: 100005000 | D32: Бухгалтер | E32: Бухгалтерия | F32: 16000 | H32: Бухгалтер | I32: 24000 | U32: 24000
A33: 46073 | B33: заработная плата | C33: 100005001 | D33: Producr Owner | E33: Community | F33: 60000 | H33: Community | I33: 120000 | U33: 120000
A34: 46073 | B34: заработная плата | C34: 100005002 | D34: Модератор | E34: Community | F34: 36000 | H34: Инженер тех. поддержки | I34: 24000 | U34: 24000
A35: 46073 | B35: заработная плата | C35: 100005003 | D35: Инженер тех. поддержки | E35: Community | F35: 36000 | H35: Контент-мейкер | I35: 24000 | U35: 24000
A36: 46073 | B36: заработная плата | C36: 100005004 | D36: Контент-мейкер | E36: Community | F36: 48000 | H36: Модератор | I36: 24000 | U36: 24000
A37: 46073 | B37: заработная плата | C37: 100005005 | D37: SMM | E37: Community | F37: 48000 | H37: Producr Owner | I37: 24000 | U37: 24000
A38: 46073 | B38: заработная плата | C38: 100005006 | D38: Producr Owner | E38: Education | F38: 60000 | H38: SMM | I38: 24000 | U38: 24000
A39: 46073 | B39: заработная плата | C39: 100005009 | D39: Куратор | E39: Education | F39: 60000 | H39: Education | I39: 96000 | J39: 24000 | K39: 24000 | L39: 24000 | N39: 24000 | O39: 24000 | P39: 24000 | Q39: 24000 | R39: 24000 | T39: 24000 | U39: 312000
A40: 46073 | B40: заработная плата | C40: 100005010 | D40: Куратор | E40: Education | F40: 60000 | H40: Инженер тех. поддержки | I40: 24000 | U40: 24000
A41: 46073 | B41: заработная плата | C41: 100005007 | D41: Инженер тех. поддержки | E41: Education | F41: 42000 | H41: Куратор | I41: 24000 | J41: 24000 | K41: 24000 | L41: 24000 | N41: 24000 | O41: 24000 | P41: 24000 | Q41: 24000 | R41: 24000 | T41: 24000 | U41: 240000
A42: 46073 | B42: заработная плата | C42: 100005008 | D42: SMM | E42: Education | F42: 48000 | H42: Producr Owner | I42: 24000 | U42: 24000
A43: 46073 | B43: заработная плата | C43: 100005000 | D43: Бухгалтер | E43: Бухгалтерия | F43: 24000 | H43: SMM | I43: 24000 | U43: 24000
A44: 46086 | B44: аванс | C44: 100005001 | D44: Producr Owner | E44: Community | F44: 40000 | H44: заработная плата | I44: 462000 | J44: 522000 | K44: 527806.45 | L44: 594400 | M44: 582387.1 | N44: 623600 | O44: 694258.06 | P44: 691935.48 | Q44: 803600 | R44: 833612.9 | S44: 858000 | T44: 904451.61 | U44: 8098051.6
A45: 46086 | B45: аванс | C45: 100005002 | D45: Модератор | E45: Community | F45: 24000 | H45: Бухгалтерия | I45: 24000 | J45: 24000 | K45: 13161.29 | L45: 24000 | M45: 24000 | N45: 24000 | O45: 24000 | P45: 13161.29 | Q45: 24000 | R45: 24000 | S45: 24000 | T45: 24000 | U45: 266322.58
A46: 46086 | B46: аванс | C46: 100005003 | D46: Инженер тех. поддержки | E46: Community | F46: 24000 | H46: Бухгалтер | I46: 24000 | J46: 24000 | K46: 13161.29 | L46: 24000 | M46: 24000 | N46: 24000 | O46: 24000 | P46: 13161.29 | Q46: 24000 | R46: 24000 | S46: 24000 | T46: 24000 | U46: 266322.58
A47: 46086 | B47: аванс | C47: 100005004 | D47: Контент-мейкер | E47: Community | F47: 53677.419 | H47: Community | I47: 228000 | J47: 228000 | K47: 206322.58 | L47: 228000 | M47: 195483.87 | N47: 177600 | O47: 206322.58 | P47: 211741.94 | Q47: 177600 | R47: 228000 | S47: 228000 | T47: 211741.94 | U47: 2526812.9
A48: 46086 | B48: аванс | C48: 100005005 | D48: SMM | E48: Community | F48: 32000 | H48: Инженер тех. поддержки | I48: 36000 | J48: 36000 | K48: 36000 | L48: 36000 | M48: 19741.935 | N48: 36000 | O48: 36000 | P48: 19741.935 | Q48: 36000 | R48: 36000 | S48: 36000 | T48: 36000 | U48: 399483.87
A49: 46086 | B49: аванс | C49: 100005006 | D49: Producr Owner | E49: Education | F49: 40000 | H49: Контент-мейкер | I49: 48000 | J49: 48000 | K49: 26322.581 | L49: 48000 | M49: 48000 | N49: 25600 | O49: 48000 | P49: 48000 | Q49: 48000 | R49: 48000 | S49: 48000 | T49: 48000 | U49: 531922.58
A50: 46086 | B50: аванс | C50: 100005009 | D50: Куратор | E50: Education | F50: 40000 | H50: Модератор | I50: 36000 | J50: 36000 | K50: 36000 | L50: 36000 | M50: 19741.935 | N50: 36000 | O50: 36000 | P50: 36000 | Q50: 36000 | R50: 36000 | S50: 36000 | T50: 19741.935 | U50: 399483.87
A51: 46086 | B51: аванс | C51: 100005010 | D51: Куратор | E51: Education | F51: 40000 | H51: Producr Owner | I51: 60000 | J51: 60000 | K51: 60000 | L51: 60000 | M51: 60000 | N51: 32000 | O51: 60000 | P51: 60000 | Q51: 32000 | R51: 60000 | S51: 60000 | T51: 60000 | U51: 664000
A52: 46086 | B52: аванс | C52: 100005011 | D52: Куратор | E52: Education | F52: 40000 | H52: SMM | I52: 48000 | J52: 48000 | K52: 48000 | L52: 48000 | M52: 48000 | N52: 48000 | O52: 26322.581 | P52: 48000 | Q52: 25600 | R52: 48000 | S52: 48000 | T52: 48000 | U52: 531922.58
A53: 46086 | B53: аванс | C53: 100005007 | D53: Инженер тех. поддержки | E53: Education | F53: 28000 | H53: Education | I53: 210000 | J53: 270000 | K53: 308322.58 | L53: 342400 | M53: 362903.23 | N53: 422000 | O53: 463935.48 | P53: 467032.26 | Q53: 602000 | R53: 581612.9 | S53: 606000 | T53: 668709.68 | U53: 5304916.1
A54: 46086 | B54: аванс | C54: 100005008 | D54: SMM | E54: Education | F54: 53677.419 | H54: Инженер тех. поддержки | I54: 42000 | J54: 42000 | K54: 42000 | L54: 22400 | M54: 42000 | N54: 42000 | O54: 23032.258 | P54: 42000 | Q54: 42000 | R54: 42000 | S54: 42000 | T54: 42000 | U54: 465432.26
A55: 46086 | B55: аванс | C55: 100005000 | D55: Бухгалтер | E55: Бухгалтерия | F55: 26838.71 | H55: Куратор | I55: 60000 | J55: 120000 | K55: 180000 | L55: 212000 | M55: 212903.23 | N55: 272000 | O55: 332903.23 | P55: 365806.45 | Q55: 452000 | R55: 458709.68 | S55: 456000 | T55: 518709.68 | U55: 3641032.3
... A86: 46132 | B86: заработная плата | C86: 100005006 | D86: Producr Owner | E86: Education | F86: 60000 | H86: Общий итог | I86: 1275000 | J86: 1199000 | K86: 1333000 | L86: 1469600 | M86: 1443000 | N86: 1598200 | O86: 1744000 | P86: 1875400 | Q86: 2006400 | R86: 2147800 | S86: 2116600 | T86: 2274800 | U86: 20482800
A87: 46132 | B87: заработная плата | C87: 100005009 | D87: Куратор | E87: Education | F87: 32000
A88: 46132 | B88: заработная плата | C88: 100005010 | D88: Куратор | E88: Education | F88: 60000
A89: 46132 | B89: заработная плата | C89: 100005011 | D89: Куратор | E89: Education | F89: 60000 | H89: компенсация питания | I89: 34000 | J89: 44000 | K89: 48000 | L89: 54600 | M89: 52000 | N89: 53200 | O89: 69000 | P89: 70400 | Q89: 71400 | R89: 82800 | S89: 75600 | T89: 79800 | U89: 734800
A90: 46132 | B90: заработная плата | C90: 100005012 | D90: Куратор | E90: Education | F90: 60000 | H90: Бухгалтерия | I90: 3400 | J90: 4000 | K90: 4000 | L90: 4200 | M90: 4000 | N90: 3800 | O90: 4600 | P90: 4400 | Q90: 4200 | R90: 4600 | S90: 4200 | T90: 4200 | U90: 49600
A91: 46132 | B91: заработная плата | C91: 100005007 | D91: Инженер тех. поддержки | E91: Education | F91: 22400 | H91: Бухгалтер | I91: 3400 | J91: 4000 | K91: 4000 | L91: 4200 | M91: 4000 | N91: 3800 | O91: 4600 | P91: 4400 | Q91: 4200 | R91: 4600 | S91: 4200 | T91: 4200 | U91: 49600
A92: 46132 | B92: заработная плата | C92: 100005008 | D92: SMM | E92: Education | F92: 48000 | H92: Community | I92: 17000 | J92: 20000 | K92: 20000 | L92: 21000 | M92: 20000 | N92: 19000 | O92: 23000 | P92: 22000 | Q92: 21000 | R92: 23000 | S92: 21000 | T92: 21000 | U92: 248000
A93: 46132 | B93: заработная плата | C93: 100005000 | D93: Бухгалтер | E93: Бухгалтерия | F93: 24000 | H93: Инженер тех. поддержки | I93: 3400 | J93: 4000 | K93: 4000 | L93: 4200 | M93: 4000 | N93: 3800 | O93: 4600 | P93: 4400 | Q93: 4200 | R93: 4600 | S93: 4200 | T93: 4200 | U93: 49600
A94: 46147 | B94: аванс | C94: 100005001 | D94: Producr Owner | E94: Community | F94: 40000 | H94: Контент-мейкер | I94: 3400 | J94: 4000 | K94: 4000 | L94: 4200 | M94: 4000 | N94: 3800 | O94: 4600 | P94: 4400 | Q94: 4200 | R94: 4600 | S94: 4200 | T94: 4200 | U94: 49600
A95: 46147 | B95: аванс | C95: 100005002 | D95: Модератор | E95: Community | F95: 40258.065 | H95: Модератор | I95: 3400 | J95: 4000 | K95: 4000 | L95: 4200 | M95: 4000 | N95: 3800 | O95: 4600 | P95: 4400 | Q95: 4200 | R95: 4600 | S95: 4200 | T95: 4200 | U95: 49600
A96: 46147 | B96: аванс | C96: 100005003 | D96: Инженер тех. поддержки | E96: Community | F96: 40258.065 | H96: Producr Owner | I96: 3400 | J96: 4000 | K96: 4000 | L96: 4200 | M96: 4000 | N96: 3800 | O96: 4600 | P96: 4400 | Q96: 4200 | R96: 4600 | S96: 4200 | T96: 4200 | U96: 49600
A97: 46147 | B97: аванс | C97: 100005004 | D97: Контент-мейкер | E97: Community | F97: 32000 | H97: SMM | I97: 3400 | J97: 4000 | K97: 4000 | L97: 4200 | M97: 4000 | N97: 3800 | O97: 4600 | P97: 4400 | Q97: 4200 | R97: 4600 | S97: 4200 | T97: 4200 | U97: 49600
A98: 46147 | B98: аванс | C98: 100005005 | D98: SMM | E98: Community | F98: 32000 | H98: Education | I98: 13600 | J98: 20000 | K98: 24000 | L98: 29400 | M98: 28000 | N98: 30400 | O98: 41400 | P98: 44000 | Q98: 46200 | R98: 55200 | S98: 50400 | T98: 54600 | U98: 437200
A99: 46147 | B99: аванс | C99: 100005006 | D99: Producr Owner | E99: Education | F99: 40000 | H99: Инженер тех. поддержки | I99: 3400 | J99: 4000 | K99: 4000 | L99: 4200 | M99: 4000 | N99: 3800 | O99: 4600 | P99: 4400 | Q99: 4200 | R99: 4600 | S99: 4200 | T99: 4200 | U99: 49600
A100: 46147 | B100: аванс | C100: 100005009 | D100: Куратор | E100: Education | F100: 40000 | H100: Куратор | I100: 3400 | J100: 8000 | K100: 12000 | L100: 16800 | M100: 16000 | N100: 19000 | O100: 27600 | P100: 30800 | Q100: 33600 | R100: 41400 | S100: 37800 | T100: 42000 | U100: 288400
... A102: 46147 | B102: аванс | C102: 100005011 | D102: Куратор | E102: Education | F102: 40000 | H102: SMM | I102: 3400 | J102: 4000 | K102: 4000 | L102: 4200 | M102: 4000 | N102: 3800 | O102: 4600 | P102: 4400 | Q102: 4200 | R102: 4600 | S102: 4200 | T102: 4200 | U102: 49600
A103: 46147 | B103: аванс | C103: 100005012 | D103: Куратор | E103: Education | F103: 40000
A104: 46147 | B104: аванс | C104: 100005007 | D104: Инженер тех. поддержки | E104: Education | F104: 28000
A105: 46147 | B105: аванс | C105: 100005008 | D105: SMM | E105: Education | F105: 32000
A106: 46147 | B106: аванс | C106: 100005000 | D106: Бухгалтер | E106: Бухгалтерия | F106: 16000
A107: 46162 | B107: заработная плата | C107: 100005001 | D107: Producr Owner | E107: Community | F107: 60000
A108: 46162 | B108: заработная плата | C108: 100005002 | D108: Модератор | E108: Community | F108: 19741.935
A109: 46162 | B109: заработная плата | C109: 100005003 | D109: Инженер тех. поддержки | E109: Community | F109: 19741.935
A110: 46162 | B110: заработная плата | C110: 100005004 | D110: Контент-мейкер | E110: Community | F110: 48000
A111: 46162 | B111: заработная плата | C111: 100005005 | D111: SMM | E111: Community | F111: 48000
A112: 46162 | B112: заработная плата | C112: 100005006 | D112: Producr Owner | E112: Education | F112: 60000
A113: 46162 | B113: заработная плата | C113: 100005009 | D113: Куратор | E113: Education | F113: 60000
A114: 46162 | B114: заработная плата | C114: 100005010 | D114: Куратор | E114: Education | F114: 32903.226
... A900: 46361 | B900: компенсация питания | C900: 100005000 | D900: Бухгалтер | E900: Бухгалтерия | F900: 4200

Sheet Выгрузка оборудование
A1: Дата | B1: Тип | C1: Срок полезного использования | D1: ID сотрудника | E1: Должность | F1: Направление | G1: Сумма, руб. | I1: Подсказку?
A2: 46023 | B2: Комплект оборудования "Стандартный" | C2: 2 года | D2: 100005000 | E2: Бухгалтер | F2: Бухгалтерия | G2: 100000 | I2: Нет | J2: =IF(I2="Нет", " ", "Сформируйте сводную таблицу по представленному массиву данных.")
A3: 46023 | B3: Комплект оборудования "Стандартный" | C3: 2 года | D3: 100005001 | E3: Producr Owner | F3: Community | G3: 100000 | I3: Нет | J3: =IF(I3="Нет", " ", "В сводной таблице добавьте в поле Столбцы даты, в поле Строки направление, в поле Значения сумму. Сравните получившиеся данные со значениями на листе Свод факта.")
A4: 46023 | B4: Комплект оборудования "Стандартный" | C4: 2 года | D4: 100005002 | E4: Модератор | F4: Community | G4: 100000 | I4: Нет | J4: =IF(I4="Нет", " ", "Для сравнения со значениями на листе Свод факта приведите данные сводной таблицы к месячному формату, разделив их на 24.")
A5: 46023 | B5: Комплект оборудования "Стандартный" | C5: 2 года | D5: 100005003 | E5: Инженер тех. поддержки | F5: Community | G5: 100000
A6: 46023 | B6: Комплект оборудования "Стандартный" | C6: 2 года | D6: 100005004 | E6: Контент-мейкер | F6: Community | G6: 100000
A7: 46023 | B7: Комплект оборудования "Стандартный" | C7: 2 года | D7: 100005005 | E7: SMM | F7: Community | G7: 100000
A8: 46023 | B8: Комплект оборудования "Стандартный" | C8: 2 года | D8: 100005006 | E8: Producr Owner | F8: Education | G8: 100000
A9: 46023 | B9: Комплект оборудования "Стандартный" | C9: 2 года | D9: 100005007 | E9: Инженер тех. поддержки | F9: Education | G9: 100000
A10: 46023 | B10: Комплект оборудования "Стандартный" | C10: 2 года | D10: 100005008 | E10: SMM | F10: Education | G10: 100000 | I10: Сумма по полю Сумма, руб. | J10: Названия столбцов
A11: 46023 | B11: Комплект оборудования "Стандартный" | C11: 2 года | D11: 100005009 | E11: Куратор | F11: Education | G11: 100000 | I11: Названия строк | J11: 46023 | K11: 46054 | L11: 46082 | M11: 46113 | N11: 46174 | O11: 46204 | P11: 46235 | Q11: 46266 | R11: 46296 | S11: 46357 | T11: Общий итог
A12: 46054 | B12: Комплект оборудования "Стандартный" | C12: 2 года | D12: 100005010 | E12: Куратор | F12: Education | G12: 100000 | I12: Бухгалтерия | J12: 100000 | T12: 100000
A13: 46082 | B13: Комплект оборудования "Стандартный" | C13: 2 года | D13: 100005011 | E13: Куратор | F13: Education | G13: 100000 | I13: Community | J13: 500000 | T13: 500000
A14: 46113 | B14: Комплект оборудования "Стандартный" | C14: 2 года | D14: 100005012 | E14: Куратор | F14: Education | G14: 100000 | I14: Education | J14: 400000 | K14: 100000 | L14: 100000 | M14: 100000 | N14: 100000 | O14: 100000 | P14: 100000 | Q14: 100000 | R14: 100000 | S14: 100000 | T14: 1300000
A15: 46174 | B15: Комплект оборудования "Стандартный" | C15: 2 года | D15: 100005013 | E15: Куратор | F15: Education | G15: 100000 | I15: Общий итог | J15: 1000000 | K15: 100000 | L15: 100000 | M15: 100000 | N15: 100000 | O15: 100000 | P15: 100000 | Q15: 100000 | R15: 100000 | S15: 100000 | T15: 1900000
A16: 46204 | B16: Комплект оборудования "Стандартный" | C16: 2 года | D16: 100005014 | E16: Куратор | F16: Education | G16: 100000
A17: 46235 | B17: Комплект оборудования "Стандартный" | C17: 2 года | D17: 100005015 | E17: Куратор | F17: Education | G17: 100000 | I17: Месячный формат
A18: 46266 | B18: Комплект оборудования "Стандартный" | C18: 2 года | D18: 100005016 | E18: Куратор | F18: Education | G18: 100000 | J18: 46023 | K18: 46054 | L18: 46082 | M18: 46113 | N18: 46174 | O18: 46204 | P18: 46235 | Q18: 46266 | R18: 46296 | S18: 46357
A19: 46296 | B19: Комплект оборудования "Стандартный" | C19: 2 года | D19: 100005017 | E19: Куратор | F19: Education | G19: 100000 | I19: Бухгалтерия | J19: =GETPIVOTDATA("Сумма, руб.",$I$10,"Дата",DATE(2026,1,1),"Направление","Бухгалтерия")/24 -> 4166.6667 | K19: 4166.6667 | L19: 4166.6667 | M19: 4166.6667 | N19: 4166.6667 | O19: 4166.6667 | P19: 4166.6667 | Q19: 4166.6667 | R19: 4166.6667 | S19: 4166.6667
A20: 46357 | B20: Комплект оборудования "Стандартный" | C20: 2 года | D20: 100005018 | E20: Куратор | F20: Education | G20: 100000 | I20: Community | J20: =GETPIVOTDATA("Сумма, руб.",$I$10,"Дата",DATE(2026,1,1),"Направление","Community")/24 -> 20833.333 | K20: 20833.333 | L20: 20833.333 | M20: 20833.333 | N20: 20833.333 | O20: 20833.333 | P20: 20833.333 | Q20: 20833.333 | R20: 20833.333 | S20: 20833.333
I21: Education | J21: =GETPIVOTDATA("Сумма, руб.",$I$10,"Дата",DATE(2026,1,1),"Направление","Education")/24 -> 16666.667 | K21: =SUM(J14:K14)/24 -> 20833.333 | L21: =SUM(J14:L14)/24 -> 25000 | M21: =SUM(J14:M14)/24 -> 29166.667 | N21: =SUM(J14:N14)/24 -> 33333.333 | O21: =SUM(J14:O14)/24 -> 37500 | P21: =SUM(J14:P14)/24 -> 41666.667 | Q21: =SUM(J14:Q14)/24 -> 45833.333 | R21: =SUM(J14:R14)/24 -> 50000 | S21: =SUM(J14:S14)/24 -> 54166.667

Sheet Выгрузка лицензии
A1: Дата | B1: Лицензия | C1: ID сотрудника | D1: Должность | E1: Направление | F1: Стоимость за годовой доступ, $ | G1: Курс доллара | H1: Сумма, руб. | J1: Подсказку?
A2: 46023 | B2: 1С | C2: 100005000 | D2: Бухгалтер | E2: Бухгалтерия | F2: 110.99 | G2: 91 | H2: =F2*G2 -> 10100.09 | J2: Нет | K2: =IF(J2="Нет", " ", "Сформируйте сводную таблицу по представленному массиву данных.")
A3: 46023 | B3: MS Office | C3: 100005000 | D3: Бухгалтер | E3: Бухгалтерия | F3: 332.99 | G3: 91 | H3: =F3*G3 -> 30302.09 | J3: Нет | K3: =IF(J3="Нет", " ", "В сводной таблице добавьте в поле Столбцы даты, в поле Строки направление и лицензия, в поле Значения сумму. Сравните получившиеся данные со значениями на листе Свод факта.")
A4: 46023 | B4: MS Office | C4: 100005001 | D4: Producr Owner | E4: Community | F4: 332.99 | G4: 91 | H4: =F4*G4 -> 30302.09 | J4: Нет | K4: =IF(J4="Нет", " ", "Сравните стоимость отдельной лицензии с плановой.")
A5: 46023 | B5: Miro | C5: 100005001 | D5: Producr Owner | E5: Community | F5: 154.99 | G5: 91 | H5: =F5*G5 -> 14104.09 | J5: Нет | K5: =IF(J5="Нет", " ", "Для сравнения со значениями на листе Свод факта приведите данные сводной таблицы к месячному формату, разделив их на 12.")
A6: 46023 | B6: Jira | C6: 100005001 | D6: Producr Owner | E6: Community | F6: 110.99 | G6: 91 | H6: =F6*G6 -> 10100.09 | J6: Нет | K6: =IF(J6="Нет", " ", "Проверьте, был ли заложен рост курса доллара в плановой стоимости лицензий?")
A7: 46023 | B7: Доп.софт для разработки комьюнити-платформы | C7: 100005001 | D7: Producr Owner | E7: Community | F7: 732.5 | G7: 91 | H7: =F7*G7 -> 66657.5
A8: 46023 | B8: MS Office | C8: 100005002 | D8: Модератор | E8: Community | F8: 332.99 | G8: 91 | H8: =F8*G8 -> 30302.09
A9: 46023 | B9: Miro | C9: 100005002 | D9: Модератор | E9: Community | F9: 154.99 | G9: 91 | H9: =F9*G9 -> 14104.09
A10: 46023 | B10: Jira | C10: 100005002 | D10: Модератор | E10: Community | F10: 110.99 | G10: 91 | H10: =F10*G10 -> 10100.09
A11: 46023 | B11: Доп.софт для разработки комьюнити-платформы | C11: 100005002 | D11: Модератор | E11: Community | F11: 732.5 | G11: 91 | H11: =F11*G11 -> 66657.5
A12: 46023 | B12: MS Office | C12: 100005003 | D12: Инженер тех. поддержки | E12: Community | F12: 332.99 | G12: 91 | H12: =F12*G12 -> 30302.09
A13: 46023 | B13: Miro | C13: 100005003 | D13: Инженер тех. поддержки | E13: Community | F13: 154.99 | G13: 91 | H13: =F13*G13 -> 14104.09
A14: 46023 | B14: Jira | C14: 100005003 | D14: Инженер тех. поддержки | E14: Community | F14: 110.99 | G14: 91 | H14: =F14*G14 -> 10100.09 | K14: Сумма по полю Сумма, руб. | L14: Названия столбцов
A15: 46023 | B15: Доп.софт для разработки комьюнити-платформы | C15: 100005003 | D15: Инженер тех. поддержки | E15: Community | F15: 732.5 | G15: 91 | H15: =F15*G15 -> 66657.5 | K15: Названия строк | L15: 46023 | M15: 46054 | N15: 46082 | O15: 46113 | P15: 46174 | Q15: 46204 | R15: 46235 | S15: 46266 | T15: 46296 | U15: 46357 | V15: Общий итог
A16: 46023 | B16: MS Office | C16: 100005004 | D16: Контент-мейкер | E16: Community | F16: 332.99 | G16: 91 | H16: =F16*G16 -> 30302.09 | K16: Бухгалтерия | L16: 40402.18 | V16: 40402.18
A17: 46023 | B17: Miro | C17: 100005004 | D17: Контент-мейкер | E17: Community | F17: 154.99 | G17: 91 | H17: =F17*G17 -> 14104.09 | K17: Community | L17: 605818.85 | V17: 605818.85
A18: 46023 | B18: Jira | C18: 100005004 | D18: Контент-мейкер | E18: Community | F18: 110.99 | G18: 91 | H18: =F18*G18 -> 10100.09 | K18: Education | L18: 484655.08 | M18: 121163.77 | N18: 125158.18 | O18: 130484.06 | P18: 133147 | Q18: 138472.88 | R18: 143798.76 | S18: 145130.23 | T18: 145130.23 | U18: 137141.41 | V18: 1704281.6
A19: 46023 | B19: Доп.софт для разработки комьюнити-платформы | C19: 100005004 | D19: Контент-мейкер | E19: Community | F19: 732.5 | G19: 91 | H19: =F19*G19 -> 66657.5 | K19: Общий итог | L19: 1130876.1 | M19: 121163.77 | N19: 125158.18 | O19: 130484.06 | P19: 133147 | Q19: 138472.88 | R19: 143798.76 | S19: 145130.23 | T19: 145130.23 | U19: 137141.41 | V19: 2350502.6
A20: 46023 | B20: MS Office | C20: 100005005 | D20: SMM | E20: Community | F20: 332.99 | G20: 91 | H20: =F20*G20 -> 30302.09
A21: 46023 | B21: Miro | C21: 100005005 | D21: SMM | E21: Community | F21: 154.99 | G21: 91 | H21: =F21*G21 -> 14104.09
A22: 46023 | B22: Jira | C22: 100005005 | D22: SMM | E22: Community | F22: 110.99 | G22: 91 | H22: =F22*G22 -> 10100.09
A23: 46023 | B23: Доп.софт для разработки комьюнити-платформы | C23: 100005005 | D23: SMM | E23: Community | F23: 732.5 | G23: 91 | H23: =F23*G23 -> 66657.5
A24: 46023 | B24: MS Office | C24: 100005006 | D24: Producr Owner | E24: Education | F24: 332.99 | G24: 91 | H24: =F24*G24 -> 30302.09
A25: 46023 | B25: Miro | C25: 100005006 | D25: Producr Owner | E25: Education | F25: 154.99 | G25: 91 | H25: =F25*G25 -> 14104.09
A26: 46023 | B26: Jira | C26: 100005006 | D26: Producr Owner | E26: Education | F26: 110.99 | G26: 91 | H26: =F26*G26 -> 10100.09
A27: 46023 | B27: Доп.софт для разработки обучающей платформы | C27: 100005006 | D27: Producr Owner | E27: Education | F27: 732.5 | G27: 91 | H27: =F27*G27 -> 66657.5
A28: 46023 | B28: MS Office | C28: 100005007 | D28: Инженер тех. поддержки | E28: Education | F28: 332.99 | G28: 91 | H28: =F28*G28 -> 30302.09
A29: 46023 | B29: Miro | C29: 100005007 | D29: Инженер тех. поддержки | E29: Education | F29: 154.99 | G29: 91 | H29: =F29*G29 -> 14104.09
A30: 46023 | B30: Jira | C30: 100005007 | D30: Инженер тех. поддержки | E30: Education | F30: 110.99 | G30: 91 | H30: =F30*G30 -> 10100.09
A31: 46023 | B31: Доп.софт для разработки обучающей платформы | C31: 100005007 | D31: Инженер тех. поддержки | E31: Education | F31: 732.5 | G31: 91 | H31: =F31*G31 -> 66657.5
... A75: 46357 | B75: Доп.софт для разработки обучающей платформы | C75: 100005018 | D75: Куратор | E75: Education | F75: 732.5 | G75: 103 | H75: =F75*G75 -> 75447.5

Sheet Бюджет-->

Sheet Цели
B2: Таблица 10. Цели 2026-2027
C3: Community | E3: Education | G3: Итого новые направления
C4: 2026 | D4: 2027 | E4: 2026 | F4: 2027 | G4: 2026 | H4: 2027 | V4: Да
B5: Неоцифрованные | C5: Создать базу квалифицированных разработчиков, которые потенциально смогут работать в Kihi | E5: Создать сообщество с большим количеством активных пользователей | V5: Нет
C6: Самоокупаемость к концу 2027 года
B7: Нефинансовые показатели
B8: Количество активных пользователей
B9: Sticky Factor
B10: Средний срок жизни одного пользователя
B11: Стоимость привлечения пользователя
B12: Коэффициент удержания
B13: Индекс удовлетворённости
B14: Индекс дохождения до финала
B15: Количество трудоустроенных студентов
B16: Финансовые показатели, тыс.руб.
B17: Выручка | C17: =Бюджет!F5 -> 4840.5369 | D17: =Бюджет!G5 -> 16907.573 | E17: =Бюджет!I5 -> 15647.023 | F17: =Бюджет!J5 -> 34216.348 | G17: =Бюджет!C5 -> 20487.56 | H17: =Бюджет!D5 -> 51123.921
B18: Прирост год к году, % | D18: =D17/C17-1 -> 2.4929128 | F18: =F17/E17-1 -> 1.1867641 | H18: =H17/G17-1 -> 1.4953641
B19: Чистая прибыль | C19: =Бюджет!F18 -> -9802.4431 | D19: =Бюджет!G18 -> 1488.6708 | E19: =Бюджет!I18 -> -4756.9968 | F19: =Бюджет!J18 -> 2338.93 | G19: =Бюджет!C18 -> -15986.57 | H19: =Бюджет!D18 -> 1728.6027
B20: Чистая прибыль, % | D20: =D19/D17 -> 0.088047572 | F20: =F19/F17 -> 0.06835709 | H20: =H19/H17 -> 0.033812012

Sheet Аналитика
B2: Таблица 11. Рыночная цена аналогов, руб. | G2: Таблица 15. Ожидаемое количество новых пользователей, чел. | L2: Таблица 17. Прочие вводные
B3: Community | D3: Education | H3: Community | I3: Education | L3: Ежегодная индексация ЗП | M3: 0.08
B4: Первый месяц | C4: 0 | D4: Фритрек (недельный) | E4: 0 | G4: В первый месяц | H4: 500 | I4: 40 | L4: Ожидаемая инфляция 27/26 | M4: 0.07
B5: Подписка на месяц | C5: 300 | D5: Полная оплата годового курса | E5: 100000 | G5: Ежемесячный прирост | H5: 0.017 | I5: 0.02 | L5: Аренда помещения под 20-25 человек, тыс. руб./мес. | M5: 50
B6: Пакет на 3 месяца | C6: 850 | D6: Оплата курса 2 траншами | E6: 110000 | G6: Ограничения | H6: нет | I6: Не более 30 человек на одного куратора (фритрек не сопровождается куратором) | L6: Закупка мебели, тыс. руб. | M6: 150
B7: Пакет на 6 месяцев | C7: 1600 | D7: Оплата курса 3 траншами | E7: 114000 | G7: Сезонность (дополнительный прирост в летние месяцы к ежемесячному приросту) | H7: 0.03 | I7: 0.03 | L7: Закупка оборудования (компьютеры, мыши, клавиатуры), тыс. руб./чел. | M7: 100
B8: Пакет на 12 месяцев | C8: 3000 | D8: Оплата курса помесячно | E8: 120000 | L8: Непредвиденные расходы | M8: 1% от всех расходов
G9: Таблица 16. Ожидаемый уровень проникновения продаж | L9: Стоимость ДМС на 1 чел./мес., тыс. руб. | M9: 2
B10: Таблица 12. Стоимость и время аутсорс-разработки под ключ, тыс. руб. | G10: Community | I10: Education | L10: Лицензия 1С для 1 ПК/год, тыс. руб. | M10: 10
C11: Стоимость | D11: Время | G11: Подписка на месяц | H11: 0.2 | I11: Полная оплата курса | J11: 0.03 | L11: Лицензия MS Office для 1 ПК/год, тыс. руб. | M11: 30
B12: Community | C12: 8000 | D12: релиз - 10.01.26, время на доработку - 6 мес. | G12: Пакет на 3 месяца | H12: 0.15 | I12: Оплата курса 2 траншами | J12: 0.1 | L12: Лицензия Miro для 1 ПК/год, тыс. руб. | M12: 14
B13: Education | C13: 6000 | D13: релиз - 15.01.26, время на доработку - 3 мес. | G13: Пакет на 6 месяцев | H13: 0.1 | I13: Оплата курса 3 траншами | J13: 0.15 | L13: Лицензия Jira для 1 ПК/год, тыс. руб. | M13: 10
G14: Пакет на 12 месяцев | H14: 0.03 | I14: Оплата курса помесячно | J14: 0.2 | L14: Софт для разработки комьюнити-платформы 1 ПК/год, тыс. руб. | M14: 66
B15: Таблица 13. Рыночные ежемесячные расходы на рекламу, тыс. руб. | L15: Софт для разработки обучающей платформы 1 ПК/год, тыс. руб. | M15: 66
C16: Community | D16: Education
B17: SEO | C17: 40 | D17: 40
B18: SMM | C18: 60 | D18: 60
B19: PPC | C19: 40 | D19: 40
B20: App ads | C20: 70 | D20: 70
B21: Email-рассылка | C21: 40 | D21: 40
B22: Контент-маркетинг | C22: 50 | D22: 50
B24: Таблица 14. Рыночная ЗП поддерживающего персонала в мес., тыс. руб.
B25: Community | D25: Education
B26: Producr Owner | C26: 100 | D26: Producr Owner | E26: 100
B27: Модератор | C27: 60 | D27: Куратор | E27: 100
B28: Инженер тех. поддержки | C28: 60 | D28: Инженер тех. поддержки | E28: 70
B29: Контент-мейкер | C29: 80 | D29: SMM | E29: 80
B30: SMM | C30: 80
B31: Бухгалтер (на два проекта) | E31: 40

Sheet Расчеты
B2: Таблица 18. Количество дней в периоде, шт. | AD2: Допущения
C3: янв.26 | D3: фев.26 | E3: мар.26 | F3: апр.26 | G3: 46143 | H3: июн.26 | I3: июл.26 | J3: авг.26 | K3: сент.26 | L3: окт.26 | M3: ноя.26 | N3: дек.26 | O3: 2026 | P3: янв.27 | Q3: фев.27 | R3: мар.27 | S3: апр.27 | T3: 46508 | U3: июн.27 | V3: июл.27 | W3: авг.27 | X3: сент.27 | Y3: окт.27 | Z3: ноя.27 | AA3: дек.27 | AB3: 2027
C4: 31 | D4: 28 | E4: 31 | F4: 30 | G4: 31 | H4: 30 | I4: 31 | J4: 31 | K4: 30 | L4: 31 | M4: 30 | N4: 31 | O4: =SUM(C4:N4) -> 365 | P4: 31 | Q4: 28 | R4: 31 | S4: 30 | T4: 31 | U4: 30 | V4: 31 | W4: 31 | X4: 30 | Y4: 31 | Z4: 30 | AA4: 31 | AB4: =SUM(P4:AA4) -> 365
B6: Таблица 19. Выручка, тыс. руб.
C7: янв.26 | D7: фев.26 | E7: мар.26 | F7: апр.26 | G7: 46143 | H7: июн.26 | I7: июл.26 | J7: авг.26 | K7: сент.26 | L7: окт.26 | M7: ноя.26 | N7: дек.26 | O7: 2026 | P7: янв.27 | Q7: фев.27 | R7: мар.27 | S7: апр.27 | T7: 46508 | U7: июн.27 | V7: июл.27 | W7: авг.27 | X7: сент.27 | Y7: окт.27 | Z7: ноя.27 | AA7: дек.27 | AB7: 2027
B9: Community | C9: =SUM(C10:C14) -> 0 | D9: =SUM(D10:D14) -> 68.333333 | E9: =SUM(E10:E14) -> 137.82833 | F9: =SUM(F10:F14) -> 208.50475 | G9: =SUM(G10:G14) -> 280.38266 | H9: =SUM(H10:H14) -> 353.4825 | I9: =SUM(I10:I14) -> 430.05531 | J9: =SUM(J10:J14) -> 510.2661 | ... N9: =SUM(N10:N14) -> 832.89492 | O9: =SUM(C9:N9) -> 4840.5369 | P9: =SUM(P10:P14) -> 915.15006 | Q9: =SUM(Q10:Q14) -> 998.80355 | R9: =SUM(R10:R14) -> 1083.8791 | S9: =SUM(S10:S14) -> 1170.401 | T9: =SUM(T10:T14) -> 1258.3938 | U9: =SUM(U10:U14) -> 1347.8824 | V9: =SUM(V10:V14) -> 1441.6226 | W9: =SUM(W10:W14) -> 1539.8165 | ... AA9: =SUM(AA10:AA14) -> 1934.7778 | AB9: =SUM(P9:AA9) -> 16907.573
B10: Первый месяц | C10: =C26*C42/1000 -> 0 | D10: =D26*D42/1000 -> 0 | E10: =E26*E42/1000 -> 0 | F10: =F26*F42/1000 -> 0 | G10: =G26*G42/1000 -> 0 | H10: =H26*H42/1000 -> 0 | I10: =I26*I42/1000 -> 0 | J10: =J26*J42/1000 -> 0 | ... N10: =N26*N42/1000 -> 0 | O10: =SUM(C10:N10) -> 0 | P10: =P26*P42/1000 -> 0 | Q10: =Q26*Q42/1000 -> 0 | R10: =R26*R42/1000 -> 0 | S10: =S26*S42/1000 -> 0 | T10: =T26*T42/1000 -> 0 | U10: =U26*U42/1000 -> 0 | V10: =V26*V42/1000 -> 0 | W10: =W26*W42/1000 -> 0 | ... AA10: =AA26*AA42/1000 -> 0 | AB10: =SUM(P10:AA10) -> 0
B11: Подписка на месяц | C11: =C27*C43/1000 -> 0 | D11: =D27*D43/1000 -> 30 | E11: =E27*E43/1000 -> 60.51 | F11: =F27*F43/1000 -> 91.53867 | G11: =G27*G43/1000 -> 123.09483 | H11: =H27*H43/1000 -> 155.18744 | I11: =I27*I43/1000 -> 188.80477 | J11: =J27*J43/1000 -> 224.01926 | ... N11: =N27*N43/1000 -> 365.66118 | O11: =SUM(C11:N11) -> 2125.1137 | P11: =P27*P43/1000 -> 401.7732 | Q11: =Q27*Q43/1000 -> 438.49912 | R11: =R27*R43/1000 -> 475.84938 | S11: =S27*S43/1000 -> 513.8346 | T11: =T27*T43/1000 -> 552.46556 | U11: =U27*U43/1000 -> 591.75325 | V11: =V27*V43/1000 -> 632.9075 | W11: =W27*W43/1000 -> 676.01699 | ... AA11: =AA27*AA43/1000 -> 849.41465 | AB11: =SUM(P11:AA11) -> 7422.837
B12: Пакет на 3 месяца | C12: =C28*C44/1000 -> 0 | D12: =D28*D44/1000 -> 21.25 | E12: =E28*E44/1000 -> 42.86125 | F12: =F28*F44/1000 -> 64.839891 | G12: =G28*G44/1000 -> 87.192169 | H12: =H28*H44/1000 -> 109.92444 | I12: =I28*I44/1000 -> 133.73671 | J12: =J28*J44/1000 -> 158.68031 | ... N12: =N28*N44/1000 -> 259.01 | O12: =SUM(C12:N12) -> 1505.2889 | P12: =P28*P44/1000 -> 284.58935 | Q12: =Q28*Q44/1000 -> 310.60354 | R12: =R28*R44/1000 -> 337.05998 | S12: =S28*S44/1000 -> 363.96617 | T12: =T28*T44/1000 -> 391.32977 | U12: =U28*U44/1000 -> 419.15855 | V12: =V28*V44/1000 -> 448.30948 | W12: =W28*W44/1000 -> 478.84537 | ... AA12: =AA28*AA44/1000 -> 601.66871 | AB12: =SUM(P12:AA12) -> 5257.8429
B13: Пакет на 6 месяцев | C13: =C29*C45/1000 -> 0 | D13: =D29*D45/1000 -> 13.333333 | E13: =E29*E45/1000 -> 26.893333 | F13: =F29*F45/1000 -> 40.683853 | G13: =G29*G45/1000 -> 54.708812 | H13: =H29*H45/1000 -> 68.972195 | I13: =I29*I45/1000 -> 83.913232 | J13: =J29*J45/1000 -> 99.564117 | ... N13: =N29*N45/1000 -> 162.51608 | O13: =SUM(C13:N13) -> 944.495 | P13: =P29*P45/1000 -> 178.56587 | Q13: =Q29*Q45/1000 -> 194.8885 | R13: =R29*R45/1000 -> 211.48861 | S13: =S29*S45/1000 -> 228.37093 | T13: =T29*T45/1000 -> 245.54025 | U13: =U29*U45/1000 -> 263.00144 | V13: =V29*V45/1000 -> 281.29222 | W13: =W29*W45/1000 -> 300.45199 | ... AA13: =AA29*AA45/1000 -> 377.51762 | AB13: =SUM(P13:AA13) -> 3299.0387
B14: Пакет на 12 месяцев | C14: =C30*C46/1000 -> 0 | D14: =D30*D46/1000 -> 3.75 | E14: =E30*E46/1000 -> 7.56375 | F14: =F30*F46/1000 -> 11.442334 | G14: =G30*G46/1000 -> 15.386853 | H14: =H30*H46/1000 -> 19.39843 | I14: =I30*I46/1000 -> 23.600596 | J14: =J30*J46/1000 -> 28.002408 | ... N14: =N30*N46/1000 -> 45.707648 | O14: =SUM(C14:N14) -> 265.63922 | P14: =P30*P46/1000 -> 50.22165 | Q14: =Q30*Q46/1000 -> 54.81239 | R14: =R30*R46/1000 -> 59.481173 | S14: =S30*S46/1000 -> 64.229324 | T14: =T30*T46/1000 -> 69.058195 | U14: =U30*U46/1000 -> 73.969156 | V14: =V30*V46/1000 -> 79.113437 | W14: =W30*W46/1000 -> 84.502123 | ... AA14: =AA30*AA46/1000 -> 106.17683 | AB14: =SUM(P14:AA14) -> 927.85462
B15: Education | C15: =SUM(C16:C20) -> 183.66667 | D15: =SUM(D16:D20) -> 371.00667 | E15: =SUM(E16:E20) -> 562.09347 | F15: =SUM(F16:F20) -> 757.002 | G15: =SUM(G16:G20) -> 955.80871 | H15: =SUM(H16:H20) -> 1164.675 | I15: =SUM(I16:I20) -> 1384.11 | J15: =SUM(J16:J20) -> 1614.6484 | ... N15: =SUM(N16:N20) -> 2501.5969 | O15: =SUM(C15:N15) -> 15647.023 | P15: =SUM(P16:P20) -> 2550.8639 | Q15: =SUM(Q16:Q20) -> 2601.1164 | R15: =SUM(R16:R20) -> 2652.3738 | S15: =SUM(S16:S20) -> 2704.6564 | T15: =SUM(T16:T20) -> 2757.9847 | U15: =SUM(U16:U20) -> 2814.0114 | V15: =SUM(V16:V20) -> 2872.873 | W15: =SUM(W16:W20) -> 2934.713 | ... AA15: =SUM(AA16:AA20) -> 3172.6297 | AB15: =SUM(P15:AA15) -> 34216.348
B16: Фритрек | C16: =C32*C48/1000 -> 0 | D16: =D32*D48/1000 -> 0 | E16: =E32*E48/1000 -> 0 | F16: =F32*F48/1000 -> 0 | G16: =G32*G48/1000 -> 0 | H16: =H32*H48/1000 -> 0 | I16: =I32*I48/1000 -> 0 | J16: =J32*J48/1000 -> 0 | ... N16: =N32*N48/1000 -> 0 | O16: =SUM(C16:N16) -> 0 | P16: =P32*P48/1000 -> 0 | Q16: =Q32*Q48/1000 -> 0 | R16: =R32*R48/1000 -> 0 | S16: =S32*S48/1000 -> 0 | T16: =T32*T48/1000 -> 0 | U16: =U32*U48/1000 -> 0 | V16: =V32*V48/1000 -> 0 | W16: =W32*W48/1000 -> 0 | ... AA16: =AA32*AA48/1000 -> 0 | AB16: =SUM(P16:AA16) -> 0
B17: Полная оплата курса | C17: =C33*C49/1000 -> 10 | D17: =D33*D49/1000 -> 20.2 | E17: =E33*E49/1000 -> 30.604 | F17: =F33*F49/1000 -> 41.21608 | G17: =G33*G49/1000 -> 52.040402 | H17: =H33*H49/1000 -> 63.412434 | I17: =I33*I49/1000 -> 75.359891 | J17: =J33*J49/1000 -> 87.911889 | ... N17: =N33*N49/1000 -> 136.2031 | O17: =SUM(C17:N17) -> 851.92504 | P17: =P33*P49/1000 -> 138.88551 | Q17: =Q33*Q49/1000 -> 141.62158 | R17: =R33*R49/1000 -> 144.41237 | S17: =S33*S49/1000 -> 147.25897 | T17: =T33*T49/1000 -> 150.16251 | U17: =U33*U49/1000 -> 153.21296 | V17: =V33*V49/1000 -> 156.41777 | W17: =W33*W49/1000 -> 159.78474 | ... AA17: =AA33*AA49/1000 -> 172.73846 | AB17: =SUM(P17:AA17) -> 1862.9591
B18: Оплата курса 2 траншами | C18: =C34*C50/1000 -> 36.666667 | D18: =D34*D50/1000 -> 74.066667 | E18: =E34*E50/1000 -> 112.21467 | F18: =F34*F50/1000 -> 151.12563 | G18: =G34*G50/1000 -> 190.81481 | H18: =H34*H50/1000 -> 232.51226 | I18: =I34*I50/1000 -> 276.3196 | J18: =J34*J50/1000 -> 322.34359 | ... N18: =N34*N50/1000 -> 499.41135 | O18: =SUM(C18:N18) -> 3123.7251 | P18: =P34*P50/1000 -> 509.24689 | Q18: =Q34*Q50/1000 -> 519.27913 | R18: =R34*R50/1000 -> 529.51202 | S18: =S34*S50/1000 -> 539.94956 | T18: =T34*T50/1000 -> 550.59586 | U18: =U34*U50/1000 -> 561.78086 | V18: =V34*V50/1000 -> 573.53182 | W18: =W34*W50/1000 -> 585.87738 | ... AA18: =AA34*AA50/1000 -> 633.37435 | AB18: =SUM(P18:AA18) -> 6830.8499
B19: Оплата курса 3 траншами | C19: =C35*C51/1000 -> 57 | D19: =D35*D51/1000 -> 115.14 | E19: =E35*E51/1000 -> 174.4428 | F19: =F35*F51/1000 -> 234.93166 | G19: =G35*G51/1000 -> 296.63029 | H19: =H35*H51/1000 -> 361.45087 | I19: =I35*I51/1000 -> 429.55138 | J19: =J35*J51/1000 -> 501.09777 | ... N19: =N35*N51/1000 -> 776.35765 | O19: =SUM(C19:N19) -> 4855.9727 | P19: =P35*P51/1000 -> 791.64743 | Q19: =Q35*Q51/1000 -> 807.24301 | R19: =R35*R51/1000 -> 823.1505 | S19: =S35*S51/1000 -> 839.37614 | T19: =T35*T51/1000 -> 855.92629 | U19: =U35*U51/1000 -> 873.31388 | V19: =V35*V51/1000 -> 891.58128 | W19: =W35*W51/1000 -> 910.77301 | ... AA19: =AA35*AA51/1000 -> 984.60922 | AB19: =SUM(P19:AA19) -> 10618.867
B20: Оплата курса помесячно | C20: =C36*C52/1000 -> 80 | D20: =D36*D52/1000 -> 161.6 | E20: =E36*E52/1000 -> 244.832 | F20: =F36*F52/1000 -> 329.72864 | G20: =G36*G52/1000 -> 416.32321 | H20: =H36*H52/1000 -> 507.29947 | I20: =I36*I52/1000 -> 602.87913 | J20: =J36*J52/1000 -> 703.29512 | ... N20: =N36*N52/1000 -> 1089.6248 | O20: =SUM(C20:N20) -> 6815.4003 | P20: =P36*P52/1000 -> 1111.0841 | Q20: =Q36*Q52/1000 -> 1132.9726 | R20: =R36*R52/1000 -> 1155.2989 | S20: =S36*S52/1000 -> 1178.0718 | T20: =T36*T52/1000 -> 1201.3001 | U20: =U36*U52/1000 -> 1225.7037 | V20: =V36*V52/1000 -> 1251.3421 | W20: =W36*W52/1000 -> 1278.2779 | ... AA20: =AA36*AA52/1000 -> 1381.9077 | AB20: =SUM(P20:AA20) -> 14903.672
B22: Таблица 19.1. Количество пользователей, чел. | AD22: - Лояльность клиентов 100% (купленные подписки всегда продлеваются, все студенты проходят полный курс обучения) - Стоимость подписки ближайшие два года без повышения
C23: янв.26 | D23: фев.26 | E23: мар.26 | F23: апр.26 | G23: 46143 | H23: июн.26 | I23: июл.26 | J23: авг.26 | K23: сент.26 | L23: окт.26 | M23: ноя.26 | N23: дек.26 | O23: 2026 | P23: янв.27 | Q23: фев.27 | R23: мар.27 | S23: апр.27 | T23: 46508 | U23: июн.27 | V23: июл.27 | W23: авг.27 | X23: сент.27 | Y23: окт.27 | Z23: ноя.27 | AA23: дек.27 | AB23: 2027
B25: Community
B26: Первый месяц | C26: =Аналитика!H4 -> 500 | D26: =C26*(1+Аналитика!$H$5) -> 508.5 | E26: =D26*(1+Аналитика!$H$5) -> 517.1445 | F26: =E26*(1+Аналитика!$H$5) -> 525.93596 | G26: =F26*(1+Аналитика!$H$5) -> 534.87687 | H26: =G26*(1+Аналитика!$H$5)*(1+Аналитика!$H$7) -> 560.28887 | I26: =H26*(1+Аналитика!$H$5)*(1+Аналитика!$H$7) -> 586.90819 | J26: =I26*(1+Аналитика!$H$5)*(1+Аналитика!$H$7) -> 614.7922 | K26: =G26*(1+Аналитика!$H$5)*(1+Аналитика!$H$5)*(1+Аналитика!$H$5)*(1+Аналитика!$H$5) -> 572.18653 | L26: =K26*(1+Аналитика!$H$5) -> 581.9137 | M26: =L26*(1+Аналитика!$H$5) -> 591.80623 | N26: =M26*(1+Аналитика!$H$5) -> 601.86694 | P26: =N26*(1+Аналитика!$H$5) -> 612.09868 | Q26: =P26*(1+Аналитика!$H$5) -> 622.50435 | R26: =Q26*(1+Аналитика!$H$5) -> 633.08693 | S26: =R26*(1+Аналитика!$H$5) -> 643.8494 | T26: =S26*(1+Аналитика!$H$5) -> 654.79484 | U26: =T26*(1+Аналитика!$H$5)*(1+Аналитика!$H$7) -> 685.90415 | V26: =U26*(1+Аналитика!$H$5)*(1+Аналитика!$H$7) -> 718.49145 | W26: =V26*(1+Аналитика!$H$5)*(1+Аналитика!$H$7) -> 752.62698 | X26: =T26*(1+Аналитика!$H$5)*(1+Аналитика!$H$5)*(1+Аналитика!$H$5)*(1+Аналитика!$H$5) -> 700.46923 | Y26: =X26*(1+Аналитика!$H$5) -> 712.37721 | Z26: =Y26*(1+Аналитика!$H$5) -> 724.48762 | AA26: =Z26*(1+Аналитика!$H$5) -> 736.80391
B27: Подписка на месяц | C27: 0 | D27: =C$26*Аналитика!$H$11 -> 100 | E27: =D$26*Аналитика!$H$11+D27 -> 201.7 | F27: =E$26*Аналитика!$H$11+E27 -> 305.1289 | G27: =F$26*Аналитика!$H$11+F27 -> 410.31609 | H27: =G$26*Аналитика!$H$11+G27 -> 517.29146 | I27: =H$26*Аналитика!$H$11+H27 -> 629.34924 | J27: =I$26*Аналитика!$H$11+I27 -> 746.73088 | K27: =J$26*Аналитика!$H$11+J27 -> 869.68932 | L27: =K$26*Аналитика!$H$11+K27 -> 984.12662 | ... N27: =M$26*Аналитика!$H$11+M27 -> 1218.8706 | P27: =N$26*Аналитика!$H$11+N27 -> 1339.244 | Q27: =P$26*Аналитика!$H$11+P27 -> 1461.6637 | R27: =Q$26*Аналитика!$H$11+Q27 -> 1586.1646 | S27: =R$26*Аналитика!$H$11+R27 -> 1712.782 | T27: =S$26*Аналитика!$H$11+S27 -> 1841.5519 | U27: =T$26*Аналитика!$H$11+T27 -> 1972.5108 | V27: =U$26*Аналитика!$H$11+U27 -> 2109.6917 | W27: =V$26*Аналитика!$H$11+V27 -> 2253.39 | X27: =W$26*Аналитика!$H$11+W27 -> 2403.9154 | ... AA27: =Z$26*Аналитика!$H$11+Z27 -> 2831.3822
B28: Пакет на 3 месяца | C28: 0 | D28: =C$26*Аналитика!$H$12 -> 75 | E28: =D$26*Аналитика!$H$12+D28 -> 151.275 | F28: =E$26*Аналитика!$H$12+E28 -> 228.84667 | G28: =F$26*Аналитика!$H$12+F28 -> 307.73707 | H28: =G$26*Аналитика!$H$12+G28 -> 387.9686 | I28: =H$26*Аналитика!$H$12+H28 -> 472.01193 | J28: =I$26*Аналитика!$H$12+I28 -> 560.04816 | K28: =J$26*Аналитика!$H$12+J28 -> 652.26699 | L28: =K$26*Аналитика!$H$12+K28 -> 738.09497 | ... N28: =M$26*Аналитика!$H$12+M28 -> 914.15296 | P28: =N$26*Аналитика!$H$12+N28 -> 1004.433 | Q28: =P$26*Аналитика!$H$12+P28 -> 1096.2478 | R28: =Q$26*Аналитика!$H$12+Q28 -> 1189.6235 | S28: =R$26*Аналитика!$H$12+R28 -> 1284.5865 | T28: =S$26*Аналитика!$H$12+S28 -> 1381.1639 | U28: =T$26*Аналитика!$H$12+T28 -> 1479.3831 | V28: =U$26*Аналитика!$H$12+U28 -> 1582.2687 | W28: =V$26*Аналитика!$H$12+V28 -> 1690.0425 | X28: =W$26*Аналитика!$H$12+W28 -> 1802.9365 | ... AA28: =Z$26*Аналитика!$H$12+Z28 -> 2123.5366
B29: Пакет на 6 месяцев | C29: 0 | D29: =C$26*Аналитика!$H$13 -> 50 | E29: =D$26*Аналитика!$H$13+D29 -> 100.85 | F29: =E$26*Аналитика!$H$13+E29 -> 152.56445 | G29: =F$26*Аналитика!$H$13+F29 -> 205.15805 | H29: =G$26*Аналитика!$H$13+G29 -> 258.64573 | I29: =H$26*Аналитика!$H$13+H29 -> 314.67462 | J29: =I$26*Аналитика!$H$13+I29 -> 373.36544 | K29: =J$26*Аналитика!$H$13+J29 -> 434.84466 | L29: =K$26*Аналитика!$H$13+K29 -> 492.06331 | ... N29: =M$26*Аналитика!$H$13+M29 -> 609.4353 | P29: =N$26*Аналитика!$H$13+N29 -> 669.622 | Q29: =P$26*Аналитика!$H$13+P29 -> 730.83187 | R29: =Q$26*Аналитика!$H$13+Q29 -> 793.0823 | S29: =R$26*Аналитика!$H$13+R29 -> 856.39099 | T29: =S$26*Аналитика!$H$13+S29 -> 920.77593 | U29: =T$26*Аналитика!$H$13+T29 -> 986.25542 | V29: =U$26*Аналитика!$H$13+U29 -> 1054.8458 | W29: =V$26*Аналитика!$H$13+V29 -> 1126.695 | X29: =W$26*Аналитика!$H$13+W29 -> 1201.9577 | ... AA29: =Z$26*Аналитика!$H$13+Z29 -> 1415.6911
B30: Пакет на 12 месяцев | C30: 0 | D30: =C$26*Аналитика!$H$14 -> 15 | E30: =D$26*Аналитика!$H$14+D30 -> 30.255 | F30: =E$26*Аналитика!$H$14+E30 -> 45.769335 | G30: =F$26*Аналитика!$H$14+F30 -> 61.547414 | H30: =G$26*Аналитика!$H$14+G30 -> 77.59372 | I30: =H$26*Аналитика!$H$14+H30 -> 94.402386 | J30: =I$26*Аналитика!$H$14+I30 -> 112.00963 | K30: =J$26*Аналитика!$H$14+J30 -> 130.4534 | L30: =K$26*Аналитика!$H$14+K30 -> 147.61899 | ... N30: =M$26*Аналитика!$H$14+M30 -> 182.83059 | P30: =N$26*Аналитика!$H$14+N30 -> 200.8866 | Q30: =P$26*Аналитика!$H$14+P30 -> 219.24956 | R30: =Q$26*Аналитика!$H$14+Q30 -> 237.92469 | S30: =R$26*Аналитика!$H$14+R30 -> 256.9173 | T30: =S$26*Аналитика!$H$14+S30 -> 276.23278 | U30: =T$26*Аналитика!$H$14+T30 -> 295.87663 | V30: =U$26*Аналитика!$H$14+U30 -> 316.45375 | W30: =V$26*Аналитика!$H$14+V30 -> 338.00849 | X30: =W$26*Аналитика!$H$14+W30 -> 360.5873 | ... AA30: =Z$26*Аналитика!$H$14+Z30 -> 424.70732
B31: Education
B32: Фритрек | C32: =Аналитика!I4 -> 40 | D32: =C32*(1+Аналитика!$I$5) -> 40.8 | E32: =D32*(1+Аналитика!$I$5) -> 41.616 | F32: =E32*(1+Аналитика!$I$5) -> 42.44832 | G32: =F32*(1+Аналитика!$I$5) -> 43.297286 | H32: =G32*(1+Аналитика!$I$5)*(1+Аналитика!$I$7) -> 45.488129 | I32: =H32*(1+Аналитика!$I$5)*(1+Аналитика!$I$7) -> 47.789828 | J32: =I32*(1+Аналитика!$I$5)*(1+Аналитика!$I$7) -> 50.207994 | K32: =G32*(1+Аналитика!$I$5)*(1+Аналитика!$I$5)*(1+Аналитика!$I$5)*(1+Аналитика!$I$5) -> 46.866375 | L32: =K32*(1+Аналитика!$I$5) -> 47.803703 | M32: =L32*(1+Аналитика!$I$5) -> 48.759777 | N32: =M32*(1+Аналитика!$I$5) -> 49.734972 | P32: =N32*(1+Аналитика!$I$5) -> 50.729672 | Q32: =P32*(1+Аналитика!$I$5) -> 51.744265 | R32: =Q32*(1+Аналитика!$I$5) -> 52.779151 | S32: =R32*(1+Аналитика!$I$5) -> 53.834734 | T32: =S32*(1+Аналитика!$I$5) -> 54.911428 | U32: =T32*(1+Аналитика!$I$5)*(1+Аналитика!$I$7) -> 57.689946 | V32: =U32*(1+Аналитика!$I$5)*(1+Аналитика!$I$7) -> 60.609058 | W32: =V32*(1+Аналитика!$I$5)*(1+Аналитика!$I$7) -> 63.675876 | X32: =T32*(1+Аналитика!$I$5)*(1+Аналитика!$I$5)*(1+Аналитика!$I$5)*(1+Аналитика!$I$5) -> 59.437896 | Y32: =X32*(1+Аналитика!$I$5) -> 60.626654 | Z32: =Y32*(1+Аналитика!$I$5) -> 61.839187 | AA32: =Z32*(1+Аналитика!$I$5) -> 63.075971
B33: Полная оплата курса | C33: =C$32*Аналитика!$J$11 -> 1.2 | D33: =D$32*Аналитика!$J$11+C33 -> 2.424 | E33: =E$32*Аналитика!$J$11+D33 -> 3.67248 | F33: =F$32*Аналитика!$J$11+E33 -> 4.9459296 | G33: =G$32*Аналитика!$J$11+F33 -> 6.2448482 | H33: =H$32*Аналитика!$J$11+G33 -> 7.6094921 | I33: =I$32*Аналитика!$J$11+H33 -> 9.0431869 | J33: =J$32*Аналитика!$J$11+I33 -> 10.549427 | K33: =K$32*Аналитика!$J$11+J33 -> 11.955418 | ... N33: =N$32*Аналитика!$J$11+M33 -> 16.344372 | P33: =P$32*Аналитика!$J$11+N33-C33 -> 16.666262 | Q33: =Q$32*Аналитика!$J$11+P33-(D33-C33) -> 16.99459 | R33: =R$32*Аналитика!$J$11+Q33-(E33-D33) -> 17.329484 | S33: =S$32*Аналитика!$J$11+R33-(F33-E33) -> 17.671077 | T33: =T$32*Аналитика!$J$11+S33-(G33-F33) -> 18.019501 | U33: =U$32*Аналитика!$J$11+T33-(H33-G33) -> 18.385555 | V33: =V$32*Аналитика!$J$11+U33-(I33-H33) -> 18.770132 | W33: =W$32*Аналитика!$J$11+V33-(J33-I33) -> 19.174169 | X33: =X$32*Аналитика!$J$11+W33-(K33-J33) -> 19.551314 | ... AA33: =AA$32*Аналитика!$J$11+Z33-(N33-M33) -> 20.728615
B34: Оплата курса 2 траншами | C34: =C$32*Аналитика!$J$12 -> 4 | D34: =D$32*Аналитика!$J$12+C34 -> 8.08 | E34: =E$32*Аналитика!$J$12+D34 -> 12.2416 | F34: =F$32*Аналитика!$J$12+E34 -> 16.486432 | G34: =G$32*Аналитика!$J$12+F34 -> 20.816161 | H34: =H$32*Аналитика!$J$12+G34 -> 25.364974 | I34: =I$32*Аналитика!$J$12+H34 -> 30.143956 | J34: =J$32*Аналитика!$J$12+I34 -> 35.164756 | K34: =K$32*Аналитика!$J$12+J34 -> 39.851393 | ... N34: =N$32*Аналитика!$J$12+M34 -> 54.481238 | P34: =P$32*Аналитика!$J$12+N34-C34 -> 55.554206 | Q34: =Q$32*Аналитика!$J$12+P34-(D34-C34) -> 56.648632 | R34: =R$32*Аналитика!$J$12+Q34-(E34-D34) -> 57.764947 | S34: =S$32*Аналитика!$J$12+R34-(F34-E34) -> 58.903589 | T34: =T$32*Аналитика!$J$12+S34-(G34-F34) -> 60.065003 | U34: =U$32*Аналитика!$J$12+T34-(H34-G34) -> 61.285185 | V34: =V$32*Аналитика!$J$12+U34-(I34-H34) -> 62.567107 | W34: =W$32*Аналитика!$J$12+V34-(J34-I34) -> 63.913896 | X34: =X$32*Аналитика!$J$12+W34-(K34-J34) -> 65.171048 | ... AA34: =AA$32*Аналитика!$J$12+Z34-(N34-M34) -> 69.095384
B35: Оплата курса 3 траншами | C35: =C$32*Аналитика!$J$13 -> 6 | D35: =D$32*Аналитика!$J$13+C35 -> 12.12 | E35: =E$32*Аналитика!$J$13+D35 -> 18.3624 | F35: =F$32*Аналитика!$J$13+E35 -> 24.729648 | G35: =G$32*Аналитика!$J$13+F35 -> 31.224241 | H35: =H$32*Аналитика!$J$13+G35 -> 38.04746 | I35: =I$32*Аналитика!$J$13+H35 -> 45.215935 | J35: =J$32*Аналитика!$J$13+I35 -> 52.747134 | K35: =K$32*Аналитика!$J$13+J35 -> 59.77709 | ... N35: =N$32*Аналитика!$J$13+M35 -> 81.721858 | P35: =P$32*Аналитика!$J$13+N35-C35 -> 83.331308 | Q35: =Q$32*Аналитика!$J$13+P35-(D35-C35) -> 84.972948 | R35: =R$32*Аналитика!$J$13+Q35-(E35-D35) -> 86.647421 | S35: =S$32*Аналитика!$J$13+R35-(F35-E35) -> 88.355383 | T35: =T$32*Аналитика!$J$13+S35-(G35-F35) -> 90.097504 | U35: =U$32*Аналитика!$J$13+T35-(H35-G35) -> 91.927777 | V35: =V$32*Аналитика!$J$13+U35-(I35-H35) -> 93.850661 | W35: =W$32*Аналитика!$J$13+V35-(J35-I35) -> 95.870844 | X35: =X$32*Аналитика!$J$13+W35-(K35-J35) -> 97.756572 | ... AA35: =AA$32*Аналитика!$J$13+Z35-(N35-M35) -> 103.64308
B36: Оплата курса помесячно | C36: =C$32*Аналитика!$J$14 -> 8 | D36: =D$32*Аналитика!$J$14+C36 -> 16.16 | E36: =E$32*Аналитика!$J$14+D36 -> 24.4832 | F36: =F$32*Аналитика!$J$14+E36 -> 32.972864 | G36: =G$32*Аналитика!$J$14+F36 -> 41.632321 | H36: =H$32*Аналитика!$J$14+G36 -> 50.729947 | I36: =I$32*Аналитика!$J$14+H36 -> 60.287913 | J36: =J$32*Аналитика!$J$14+I36 -> 70.329512 | K36: =K$32*Аналитика!$J$14+J36 -> 79.702787 | ... N36: =N$32*Аналитика!$J$14+M36 -> 108.96248 | P36: =P$32*Аналитика!$J$14+N36-C36 -> 111.10841 | Q36: =Q$32*Аналитика!$J$14+P36-(D36-C36) -> 113.29726 | R36: =R$32*Аналитика!$J$14+Q36-(E36-D36) -> 115.52989 | S36: =S$32*Аналитика!$J$14+R36-(F36-E36) -> 117.80718 | T36: =T$32*Аналитика!$J$14+S36-(G36-F36) -> 120.13001 | U36: =U$32*Аналитика!$J$14+T36-(H36-G36) -> 122.57037 | V36: =V$32*Аналитика!$J$14+U36-(I36-H36) -> 125.13421 | W36: =W$32*Аналитика!$J$14+V36-(J36-I36) -> 127.82779 | X36: =X$32*Аналитика!$J$14+W36-(K36-J36) -> 130.3421 | ... AA36: =AA$32*Аналитика!$J$14+Z36-(N36-M36) -> 138.19077
B38: Таблица 19.2. Стоимость подписки в мес., руб.
C39: янв.26 | D39: фев.26 | E39: мар.26 | F39: апр.26 | G39: 46143 | H39: июн.26 | I39: июл.26 | J39: авг.26 | K39: сент.26 | L39: окт.26 | M39: ноя.26 | N39: дек.26 | O39: 2026 | P39: янв.27 | Q39: фев.27 | R39: мар.27 | S39: апр.27 | T39: 46508 | U39: июн.27 | V39: июл.27 | W39: авг.27 | X39: сент.27 | Y39: окт.27 | Z39: ноя.27 | AA39: дек.27 | AB39: 2027
B41: Community
B42: Первый месяц | C42: =Аналитика!C4 -> 0 | D42: =C42 -> 0 | E42: =D42 -> 0 | F42: =E42 -> 0 | G42: =F42 -> 0 | H42: =G42 -> 0 | I42: =H42 -> 0 | J42: =I42 -> 0 | K42: =J42 -> 0 | ... N42: =M42 -> 0 | P42: =N42 -> 0 | Q42: =P42 -> 0 | R42: =Q42 -> 0 | S42: =R42 -> 0 | T42: =S42 -> 0 | U42: =T42 -> 0 | V42: =U42 -> 0 | W42: =V42 -> 0 | X42: =W42 -> 0 | ... AA42: =Z42 -> 0
B43: Подписка на месяц | C43: =Аналитика!C5 -> 300 | D43: =C43 -> 300 | E43: =D43 -> 300 | F43: =E43 -> 300 | G43: =F43 -> 300 | H43: =G43 -> 300 | I43: =H43 -> 300 | J43: =I43 -> 300 | K43: =J43 -> 300 | ... N43: =M43 -> 300 | P43: =N43 -> 300 | Q43: =P43 -> 300 | R43: =Q43 -> 300 | S43: =R43 -> 300 | T43: =S43 -> 300 | U43: =T43 -> 300 | V43: =U43 -> 300 | W43: =V43 -> 300 | X43: =W43 -> 300 | ... AA43: =Z43 -> 300
B44: Пакет на 3 месяца | C44: =Аналитика!C6/3 -> 283.33333 | D44: =C44 -> 283.33333 | E44: =D44 -> 283.33333 | F44: =E44 -> 283.33333 | G44: =F44 -> 283.33333 | H44: =G44 -> 283.33333 | I44: =H44 -> 283.33333 | J44: =I44 -> 283.33333 | K44: =J44 -> 283.33333 | ... N44: =M44 -> 283.33333 | P44: =N44 -> 283.33333 | Q44: =P44 -> 283.33333 | R44: =Q44 -> 283.33333 | S44: =R44 -> 283.33333 | T44: =S44 -> 283.33333 | U44: =T44 -> 283.33333 | V44: =U44 -> 283.33333 | W44: =V44 -> 283.33333 | X44: =W44 -> 283.33333 | ... AA44: =Z44 -> 283.33333
B45: Пакет на 6 месяцев | C45: =Аналитика!C7/6 -> 266.66667 | D45: =C45 -> 266.66667 | E45: =D45 -> 266.66667 | F45: =E45 -> 266.66667 | G45: =F45 -> 266.66667 | H45: =G45 -> 266.66667 | I45: =H45 -> 266.66667 | J45: =I45 -> 266.66667 | K45: =J45 -> 266.66667 | ... N45: =M45 -> 266.66667 | P45: =N45 -> 266.66667 | Q45: =P45 -> 266.66667 | R45: =Q45 -> 266.66667 | S45: =R45 -> 266.66667 | T45: =S45 -> 266.66667 | U45: =T45 -> 266.66667 | V45: =U45 -> 266.66667 | W45: =V45 -> 266.66667 | X45: =W45 -> 266.66667 | ... AA45: =Z45 -> 266.66667
B46: Пакет на 12 месяцев | C46: =Аналитика!C8/12 -> 250 | D46: =C46 -> 250 | E46: =D46 -> 250 | F46: =E46 -> 250 | G46: =F46 -> 250 | H46: =G46 -> 250 | I46: =H46 -> 250 | J46: =I46 -> 250 | K46: =J46 -> 250 | ... N46: =M46 -> 250 | P46: =N46 -> 250 | Q46: =P46 -> 250 | R46: =Q46 -> 250 | S46: =R46 -> 250 | T46: =S46 -> 250 | U46: =T46 -> 250 | V46: =U46 -> 250 | W46: =V46 -> 250 | X46: =W46 -> 250 | ... AA46: =Z46 -> 250
B47: Education
B48: Фритрек | C48: =Аналитика!E4 -> 0 | D48: =C48 -> 0 | E48: =D48 -> 0 | F48: =E48 -> 0 | G48: =F48 -> 0 | H48: =G48 -> 0 | I48: =H48 -> 0 | J48: =I48 -> 0 | K48: =J48 -> 0 | ... N48: =M48 -> 0 | P48: =N48 -> 0 | Q48: =P48 -> 0 | R48: =Q48 -> 0 | S48: =R48 -> 0 | T48: =S48 -> 0 | U48: =T48 -> 0 | V48: =U48 -> 0 | W48: =V48 -> 0 | X48: =W48 -> 0 | ... AA48: =Z48 -> 0
B49: Полная оплата курса | C49: =Аналитика!E5/12 -> 8333.3333 | D49: =C49 -> 8333.3333 | E49: =D49 -> 8333.3333 | F49: =E49 -> 8333.3333 | G49: =F49 -> 8333.3333 | H49: =G49 -> 8333.3333 | I49: =H49 -> 8333.3333 | J49: =I49 -> 8333.3333 | K49: =J49 -> 8333.3333 | ... N49: =M49 -> 8333.3333 | P49: =N49 -> 8333.3333 | Q49: =P49 -> 8333.3333 | R49: =Q49 -> 8333.3333 | S49: =R49 -> 8333.3333 | T49: =S49 -> 8333.3333 | U49: =T49 -> 8333.3333 | V49: =U49 -> 8333.3333 | W49: =V49 -> 8333.3333 | X49: =W49 -> 8333.3333 | ... AA49: =Z49 -> 8333.3333
B50: Оплата курса 2 траншами | C50: =Аналитика!E6/12 -> 9166.6667 | D50: =C50 -> 9166.6667 | E50: =D50 -> 9166.6667 | F50: =E50 -> 9166.6667 | G50: =F50 -> 9166.6667 | H50: =G50 -> 9166.6667 | I50: =H50 -> 9166.6667 | J50: =I50 -> 9166.6667 | K50: =J50 -> 9166.6667 | ... N50: =M50 -> 9166.6667 | P50: =N50 -> 9166.6667 | Q50: =P50 -> 9166.6667 | R50: =Q50 -> 9166.6667 | S50: =R50 -> 9166.6667 | T50: =S50 -> 9166.6667 | U50: =T50 -> 9166.6667 | V50: =U50 -> 9166.6667 | W50: =V50 -> 9166.6667 | X50: =W50 -> 9166.6667 | ... AA50: =Z50 -> 9166.6667
B51: Оплата курса 3 траншами | C51: =Аналитика!E7/12 -> 9500 | D51: =C51 -> 9500 | E51: =D51 -> 9500 | F51: =E51 -> 9500 | G51: =F51 -> 9500 | H51: =G51 -> 9500 | I51: =H51 -> 9500 | J51: =I51 -> 9500 | K51: =J51 -> 9500 | ... N51: =M51 -> 9500 | P51: =N51 -> 9500 | Q51: =P51 -> 9500 | R51: =Q51 -> 9500 | S51: =R51 -> 9500 | T51: =S51 -> 9500 | U51: =T51 -> 9500 | V51: =U51 -> 9500 | W51: =V51 -> 9500 | X51: =W51 -> 9500 | ... AA51: =Z51 -> 9500
B52: Оплата курса помесячно | C52: =Аналитика!E8/12 -> 10000 | D52: =C52 -> 10000 | E52: =D52 -> 10000 | F52: =E52 -> 10000 | G52: =F52 -> 10000 | H52: =G52 -> 10000 | I52: =H52 -> 10000 | J52: =I52 -> 10000 | K52: =J52 -> 10000 | ... N52: =M52 -> 10000 | P52: =N52 -> 10000 | Q52: =P52 -> 10000 | R52: =Q52 -> 10000 | S52: =R52 -> 10000 | T52: =S52 -> 10000 | U52: =T52 -> 10000 | V52: =U52 -> 10000 | W52: =V52 -> 10000 | X52: =W52 -> 10000 | ... AA52: =Z52 -> 10000
B54: Таблица 20. Расходы на аутсорс-разработку под ключ, тыс. руб. | AD54: - Стоимость разработки распределена на 2 года (на период выхода в "0")
C55: янв.26 | D55: фев.26 | E55: мар.26 | F55: апр.26 | G55: 46143 | H55: июн.26 | I55: июл.26 | J55: авг.26 | K55: сент.26 | L55: окт.26 | M55: ноя.26 | N55: дек.26 | O55: 2026 | P55: янв.27 | Q55: фев.27 | R55: мар.27 | S55: апр.27 | T55: 46508 | U55: июн.27 | V55: июл.27 | W55: авг.27 | X55: сент.27 | Y55: окт.27 | Z55: ноя.27 | AA55: дек.27 | AB55: 2027
B57: Community | C57: =Аналитика!$C$12/24 -> 333.33333 | D57: =Аналитика!$C$12/24 -> 333.33333 | E57: =Аналитика!$C$12/24 -> 333.33333 | F57: =Аналитика!$C$12/24 -> 333.33333 | G57: =Аналитика!$C$12/24 -> 333.33333 | H57: =Аналитика!$C$12/24 -> 333.33333 | I57: =Аналитика!$C$12/24 -> 333.33333 | J57: =Аналитика!$C$12/24 -> 333.33333 | ... N57: =Аналитика!$C$12/24 -> 333.33333 | O57: =SUM(C57:N57) -> 4000 | P57: =Аналитика!$C$12/24 -> 333.33333 | Q57: =Аналитика!$C$12/24 -> 333.33333 | R57: =Аналитика!$C$12/24 -> 333.33333 | S57: =Аналитика!$C$12/24 -> 333.33333 | T57: =Аналитика!$C$12/24 -> 333.33333 | U57: =Аналитика!$C$12/24 -> 333.33333 | V57: =Аналитика!$C$12/24 -> 333.33333 | W57: =Аналитика!$C$12/24 -> 333.33333 | ... AA57: =Аналитика!$C$12/24 -> 333.33333 | AB57: =SUM(P57:AA57) -> 4000
B58: Education | C58: =Аналитика!$C$13/24 -> 250 | D58: =Аналитика!$C$13/24 -> 250 | E58: =Аналитика!$C$13/24 -> 250 | F58: =Аналитика!$C$13/24 -> 250 | G58: =Аналитика!$C$13/24 -> 250 | H58: =Аналитика!$C$13/24 -> 250 | I58: =Аналитика!$C$13/24 -> 250 | J58: =Аналитика!$C$13/24 -> 250 | ... N58: =Аналитика!$C$13/24 -> 250 | O58: =SUM(C58:N58) -> 3000 | P58: =Аналитика!$C$13/24 -> 250 | Q58: =Аналитика!$C$13/24 -> 250 | R58: =Аналитика!$C$13/24 -> 250 | S58: =Аналитика!$C$13/24 -> 250 | T58: =Аналитика!$C$13/24 -> 250 | U58: =Аналитика!$C$13/24 -> 250 | V58: =Аналитика!$C$13/24 -> 250 | W58: =Аналитика!$C$13/24 -> 250 | ... AA58: =Аналитика!$C$13/24 -> 250 | AB58: =SUM(P58:AA58) -> 3000
B60: Таблица 21. Расходы на поддерживающий персонал, тыс. руб. | AD60: - В расчёт не заложены премии (считаем, что на первоначальном этапе система премирования под вопросом)
C61: янв.26 | D61: фев.26 | E61: мар.26 | F61: апр.26 | G61: 46143 | H61: июн.26 | I61: июл.26 | J61: авг.26 | K61: сент.26 | L61: окт.26 | M61: ноя.26 | N61: дек.26 | O61: 2026 | P61: янв.27 | Q61: фев.27 | R61: мар.27 | S61: апр.27 | T61: 46508 | U61: июн.27 | V61: июл.27 | W61: авг.27 | X61: сент.27 | Y61: окт.27 | Z61: ноя.27 | AA61: дек.27 | AB61: 2027
B63: Community | C63: =SUM(C64:C68) -> 504 | D63: =SUM(D64:D68) -> 504 | E63: =SUM(E64:E68) -> 504 | F63: =SUM(F64:F68) -> 504 | G63: =SUM(G64:G68) -> 504 | H63: =SUM(H64:H68) -> 504 | I63: =SUM(I64:I68) -> 504 | J63: =SUM(J64:J68) -> 504 | ... N63: =SUM(N64:N68) -> 504 | O63: =SUM(C63:N63) -> 6048 | P63: =SUM(P64:P68) -> 543.52 | Q63: =SUM(Q64:Q68) -> 543.52 | R63: =SUM(R64:R68) -> 543.52 | S63: =SUM(S64:S68) -> 543.52 | T63: =SUM(T64:T68) -> 543.52 | U63: =SUM(U64:U68) -> 543.52 | V63: =SUM(V64:V68) -> 543.52 | W63: =SUM(W64:W68) -> 543.52 | ... AA63: =SUM(AA64:AA68) -> 543.52 | AB63: =SUM(P63:AA63) -> 6522.24
B64: Producr Owner | C64: =(C80+C112+C144)*C96 -> 132 | D64: =(D80+D112+D144)*D96 -> 132 | E64: =(E80+E112+E144)*E96 -> 132 | F64: =(F80+F112+F144)*F96 -> 132 | G64: =(G80+G112+G144)*G96 -> 132 | H64: =(H80+H112+H144)*H96 -> 132 | I64: =(I80+I112+I144)*I96 -> 132 | J64: =(J80+J112+J144)*J96 -> 132 | ... N64: =(N80+N112+N144)*N96 -> 132 | O64: =SUM(C64:N64) -> 1584 | P64: =(P80+P112+P144)*P96 -> 142.4 | Q64: =(Q80+Q112+Q144)*Q96 -> 142.4 | R64: =(R80+R112+R144)*R96 -> 142.4 | S64: =(S80+S112+S144)*S96 -> 142.4 | T64: =(T80+T112+T144)*T96 -> 142.4 | U64: =(U80+U112+U144)*U96 -> 142.4 | V64: =(V80+V112+V144)*V96 -> 142.4 | W64: =(W80+W112+W144)*W96 -> 142.4 | ... AA64: =(AA80+AA112+AA144)*AA96 -> 142.4 | AB64: =SUM(P64:AA64) -> 1708.8
B65: Модератор | C65: =(C81+C113+C145)*C97 -> 80 | D65: =(D81+D113+D145)*D97 -> 80 | E65: =(E81+E113+E145)*E97 -> 80 | F65: =(F81+F113+F145)*F97 -> 80 | G65: =(G81+G113+G145)*G97 -> 80 | H65: =(H81+H113+H145)*H97 -> 80 | I65: =(I81+I113+I145)*I97 -> 80 | J65: =(J81+J113+J145)*J97 -> 80 | ... N65: =(N81+N113+N145)*N97 -> 80 | O65: =SUM(C65:N65) -> 960 | P65: =(P81+P113+P145)*P97 -> 86.24 | Q65: =(Q81+Q113+Q145)*Q97 -> 86.24 | R65: =(R81+R113+R145)*R97 -> 86.24 | S65: =(S81+S113+S145)*S97 -> 86.24 | T65: =(T81+T113+T145)*T97 -> 86.24 | U65: =(U81+U113+U145)*U97 -> 86.24 | V65: =(V81+V113+V145)*V97 -> 86.24 | W65: =(W81+W113+W145)*W97 -> 86.24 | ... AA65: =(AA81+AA113+AA145)*AA97 -> 86.24 | AB65: =SUM(P65:AA65) -> 1034.88
B66: Инженер тех. поддержки | C66: =(C82+C114+C146)*C98 -> 80 | D66: =(D82+D114+D146)*D98 -> 80 | E66: =(E82+E114+E146)*E98 -> 80 | F66: =(F82+F114+F146)*F98 -> 80 | G66: =(G82+G114+G146)*G98 -> 80 | H66: =(H82+H114+H146)*H98 -> 80 | I66: =(I82+I114+I146)*I98 -> 80 | J66: =(J82+J114+J146)*J98 -> 80 | ... N66: =(N82+N114+N146)*N98 -> 80 | O66: =SUM(C66:N66) -> 960 | P66: =(P82+P114+P146)*P98 -> 86.24 | Q66: =(Q82+Q114+Q146)*Q98 -> 86.24 | R66: =(R82+R114+R146)*R98 -> 86.24 | S66: =(S82+S114+S146)*S98 -> 86.24 | T66: =(T82+T114+T146)*T98 -> 86.24 | U66: =(U82+U114+U146)*U98 -> 86.24 | V66: =(V82+V114+V146)*V98 -> 86.24 | W66: =(W82+W114+W146)*W98 -> 86.24 | ... AA66: =(AA82+AA114+AA146)*AA98 -> 86.24 | AB66: =SUM(P66:AA66) -> 1034.88
B67: Контент-мейкер | C67: =(C83+C115+C147)*C99 -> 106 | D67: =(D83+D115+D147)*D99 -> 106 | E67: =(E83+E115+E147)*E99 -> 106 | F67: =(F83+F115+F147)*F99 -> 106 | G67: =(G83+G115+G147)*G99 -> 106 | H67: =(H83+H115+H147)*H99 -> 106 | I67: =(I83+I115+I147)*I99 -> 106 | J67: =(J83+J115+J147)*J99 -> 106 | ... N67: =(N83+N115+N147)*N99 -> 106 | O67: =SUM(C67:N67) -> 1272 | P67: =(P83+P115+P147)*P99 -> 114.32 | Q67: =(Q83+Q115+Q147)*Q99 -> 114.32 | R67: =(R83+R115+R147)*R99 -> 114.32 | S67: =(S83+S115+S147)*S99 -> 114.32 | T67: =(T83+T115+T147)*T99 -> 114.32 | U67: =(U83+U115+U147)*U99 -> 114.32 | V67: =(V83+V115+V147)*V99 -> 114.32 | W67: =(W83+W115+W147)*W99 -> 114.32 | ... AA67: =(AA83+AA115+AA147)*AA99 -> 114.32 | AB67: =SUM(P67:AA67) -> 1371.84
B68: SMM | C68: =(C84+C116+C148)*C100 -> 106 | D68: =(D84+D116+D148)*D100 -> 106 | E68: =(E84+E116+E148)*E100 -> 106 | F68: =(F84+F116+F148)*F100 -> 106 | G68: =(G84+G116+G148)*G100 -> 106 | H68: =(H84+H116+H148)*H100 -> 106 | I68: =(I84+I116+I148)*I100 -> 106 | J68: =(J84+J116+J148)*J100 -> 106 | ... N68: =(N84+N116+N148)*N100 -> 106 | O68: =SUM(C68:N68) -> 1272 | P68: =(P84+P116+P148)*P100 -> 114.32 | Q68: =(Q84+Q116+Q148)*Q100 -> 114.32 | R68: =(R84+R116+R148)*R100 -> 114.32 | S68: =(S84+S116+S148)*S100 -> 114.32 | T68: =(T84+T116+T148)*T100 -> 114.32 | U68: =(U84+U116+U148)*U100 -> 114.32 | V68: =(V84+V116+V148)*V100 -> 114.32 | W68: =(W84+W116+W148)*W100 -> 114.32 | ... AA68: =(AA84+AA116+AA148)*AA100 -> 114.32 | AB68: =SUM(P68:AA68) -> 1371.84
B69: Education | C69: =SUM(C70:C73) -> 463 | D69: =SUM(D70:D73) -> 595 | E69: =SUM(E70:E73) -> 595 | F69: =SUM(F70:F73) -> 727 | G69: =SUM(G70:G73) -> 859 | H69: =SUM(H70:H73) -> 991 | I69: =SUM(I70:I73) -> 991 | J69: =SUM(J70:J73) -> 1123 | ... N69: =SUM(N70:N73) -> 1519 | O69: =SUM(C69:N69) -> 11892 | P69: =SUM(P70:P73) -> 1638.6 | Q69: =SUM(Q70:Q73) -> 1781 | R69: =SUM(R70:R73) -> 1781 | S69: =SUM(S70:S73) -> 1781 | T69: =SUM(T70:T73) -> 1781 | U69: =SUM(U70:U73) -> 1781 | V69: =SUM(V70:V73) -> 1923.4 | W69: =SUM(W70:W73) -> 1923.4 | ... AA69: =SUM(AA70:AA73) -> 2065.8 | AB69: =SUM(P69:AA69) -> 22226.4
B70: Producr Owner | C70: =(C86+C118+C150)*C102 -> 132 | D70: =(D86+D118+D150)*D102 -> 132 | E70: =(E86+E118+E150)*E102 -> 132 | F70: =(F86+F118+F150)*F102 -> 132 | G70: =(G86+G118+G150)*G102 -> 132 | H70: =(H86+H118+H150)*H102 -> 132 | I70: =(I86+I118+I150)*I102 -> 132 | J70: =(J86+J118+J150)*J102 -> 132 | ... N70: =(N86+N118+N150)*N102 -> 132 | O70: =SUM(C70:N70) -> 1584 | P70: =(P86+P118+P150)*P102 -> 142.4 | Q70: =(Q86+Q118+Q150)*Q102 -> 142.4 | R70: =(R86+R118+R150)*R102 -> 142.4 | S70: =(S86+S118+S150)*S102 -> 142.4 | T70: =(T86+T118+T150)*T102 -> 142.4 | U70: =(U86+U118+U150)*U102 -> 142.4 | V70: =(V86+V118+V150)*V102 -> 142.4 | W70: =(W86+W118+W150)*W102 -> 142.4 | ... AA70: =(AA86+AA118+AA150)*AA102 -> 142.4 | AB70: =SUM(P70:AA70) -> 1708.8
B71: Куратор | C71: =(C87+C119+C151)*C103 -> 132 | D71: =(D87+D119+D151)*D103 -> 264 | E71: =(E87+E119+E151)*E103 -> 264 | F71: =(F87+F119+F151)*F103 -> 396 | G71: =(G87+G119+G151)*G103 -> 528 | H71: =(H87+H119+H151)*H103 -> 660 | I71: =(I87+I119+I151)*I103 -> 660 | J71: =(J87+J119+J151)*J103 -> 792 | ... N71: =(N87+N119+N151)*N103 -> 1188 | O71: =SUM(C71:N71) -> 7920 | P71: =(P87+P119+P151)*P103 -> 1281.6 | Q71: =(Q87+Q119+Q151)*Q103 -> 1424 | R71: =(R87+R119+R151)*R103 -> 1424 | S71: =(S87+S119+S151)*S103 -> 1424 | T71: =(T87+T119+T151)*T103 -> 1424 | U71: =(U87+U119+U151)*U103 -> 1424 | V71: =(V87+V119+V151)*V103 -> 1566.4 | W71: =(W87+W119+W151)*W103 -> 1566.4 | ... AA71: =(AA87+AA119+AA151)*AA103 -> 1708.8 | AB71: =SUM(P71:AA71) -> 17942.4
B72: Инженер тех. поддержки | C72: =(C88+C120+C152)*C104 -> 93 | D72: =(D88+D120+D152)*D104 -> 93 | E72: =(E88+E120+E152)*E104 -> 93 | F72: =(F88+F120+F152)*F104 -> 93 | G72: =(G88+G120+G152)*G104 -> 93 | H72: =(H88+H120+H152)*H104 -> 93 | I72: =(I88+I120+I152)*I104 -> 93 | J72: =(J88+J120+J152)*J104 -> 93 | ... N72: =(N88+N120+N152)*N104 -> 93 | O72: =SUM(C72:N72) -> 1116 | P72: =(P88+P120+P152)*P104 -> 100.28 | Q72: =(Q88+Q120+Q152)*Q104 -> 100.28 | R72: =(R88+R120+R152)*R104 -> 100.28 | S72: =(S88+S120+S152)*S104 -> 100.28 | T72: =(T88+T120+T152)*T104 -> 100.28 | U72: =(U88+U120+U152)*U104 -> 100.28 | V72: =(V88+V120+V152)*V104 -> 100.28 | W72: =(W88+W120+W152)*W104 -> 100.28 | ... AA72: =(AA88+AA120+AA152)*AA104 -> 100.28 | AB72: =SUM(P72:AA72) -> 1203.36
B73: SMM | C73: =(C89+C121+C153)*C105 -> 106 | D73: =(D89+D121+D153)*D105 -> 106 | E73: =(E89+E121+E153)*E105 -> 106 | F73: =(F89+F121+F153)*F105 -> 106 | G73: =(G89+G121+G153)*G105 -> 106 | H73: =(H89+H121+H153)*H105 -> 106 | I73: =(I89+I121+I153)*I105 -> 106 | J73: =(J89+J121+J153)*J105 -> 106 | ... N73: =(N89+N121+N153)*N105 -> 106 | O73: =SUM(C73:N73) -> 1272 | P73: =(P89+P121+P153)*P105 -> 114.32 | Q73: =(Q89+Q121+Q153)*Q105 -> 114.32 | R73: =(R89+R121+R153)*R105 -> 114.32 | S73: =(S89+S121+S153)*S105 -> 114.32 | T73: =(T89+T121+T153)*T105 -> 114.32 | U73: =(U89+U121+U153)*U105 -> 114.32 | V73: =(V89+V121+V153)*V105 -> 114.32 | W73: =(W89+W121+W153)*W105 -> 114.32 | ... AA73: =(AA89+AA121+AA153)*AA105 -> 114.32 | AB73: =SUM(P73:AA73) -> 1371.84
B74: Бухгалтер | C74: =(C90+C122+C154)*C106 -> 54 | D74: =(D90+D122+D154)*D106 -> 54 | E74: =(E90+E122+E154)*E106 -> 54 | F74: =(F90+F122+F154)*F106 -> 54 | G74: =(G90+G122+G154)*G106 -> 54 | H74: =(H90+H122+H154)*H106 -> 54 | I74: =(I90+I122+I154)*I106 -> 54 | J74: =(J90+J122+J154)*J106 -> 54 | ... N74: =(N90+N122+N154)*N106 -> 54 | O74: =SUM(C74:N74) -> 648 | P74: =(P90+P122+P154)*P106 -> 58.16 | Q74: =(Q90+Q122+Q154)*Q106 -> 58.16 | R74: =(R90+R122+R154)*R106 -> 58.16 | S74: =(S90+S122+S154)*S106 -> 58.16 | T74: =(T90+T122+T154)*T106 -> 58.16 | U74: =(U90+U122+U154)*U106 -> 58.16 | V74: =(V90+V122+V154)*V106 -> 58.16 | W74: =(W90+W122+W154)*W106 -> 58.16 | ... AA74: =(AA90+AA122+AA154)*AA106 -> 58.16 | AB74: =SUM(P74:AA74) -> 697.92
B76: Таблица 21.1. Оклад штатной единицы, тыс. руб.
C77: янв.26 | D77: фев.26 | E77: мар.26 | F77: апр.26 | G77: 46143 | H77: июн.26 | I77: июл.26 | J77: авг.26 | K77: сент.26 | L77: окт.26 | M77: ноя.26 | N77: дек.26 | O77: 2026 | P77: янв.27 | Q77: фев.27 | R77: мар.27 | S77: апр.27 | T77: 46508 | U77: июн.27 | V77: июл.27 | W77: авг.27 | X77: сент.27 | Y77: окт.27 | Z77: ноя.27 | AA77: дек.27 | AB77: 2027
B79: Community | C79: =SUM(C80:C84) -> 380 | D79: =SUM(D80:D84) -> 380 | E79: =SUM(E80:E84) -> 380 | F79: =SUM(F80:F84) -> 380 | G79: =SUM(G80:G84) -> 380 | H79: =SUM(H80:H84) -> 380 | I79: =SUM(I80:I84) -> 380 | J79: =SUM(J80:J84) -> 380 | ... N79: =SUM(N80:N84) -> 380 | O79: =SUM(C79:N79) -> 4560 | P79: =SUM(P80:P84) -> 410.4 | Q79: =SUM(Q80:Q84) -> 410.4 | R79: =SUM(R80:R84) -> 410.4 | S79: =SUM(S80:S84) -> 410.4 | T79: =SUM(T80:T84) -> 410.4 | U79: =SUM(U80:U84) -> 410.4 | V79: =SUM(V80:V84) -> 410.4 | W79: =SUM(W80:W84) -> 410.4 | ... AA79: =SUM(AA80:AA84) -> 410.4 | AB79: =SUM(P79:AA79) -> 4924.8
B80: Producr Owner | C80: =Аналитика!$C$26 -> 100 | D80: =C80 -> 100 | E80: =D80 -> 100 | F80: =E80 -> 100 | G80: =F80 -> 100 | H80: =G80 -> 100 | I80: =H80 -> 100 | J80: =I80 -> 100 | K80: =J80 -> 100 | ... N80: =M80 -> 100 | O80: =SUM(C80:N80) -> 1200 | P80: =N80*(1+Аналитика!$M$3) -> 108 | Q80: =P80 -> 108 | R80: =Q80 -> 108 | S80: =R80 -> 108 | T80: =S80 -> 108 | U80: =T80 -> 108 | V80: =U80 -> 108 | W80: =V80 -> 108 | X80: =W80 -> 108 | ... AA80: =Z80 -> 108 | AB80: =SUM(P80:AA80) -> 1296
B81: Модератор | C81: =Аналитика!$C$27 -> 60 | D81: =C81 -> 60 | E81: =D81 -> 60 | F81: =E81 -> 60 | G81: =F81 -> 60 | H81: =G81 -> 60 | I81: =H81 -> 60 | J81: =I81 -> 60 | K81: =J81 -> 60 | ... N81: =M81 -> 60 | O81: =SUM(C81:N81) -> 720 | P81: =N81*(1+Аналитика!$M$3) -> 64.8 | Q81: =P81 -> 64.8 | R81: =Q81 -> 64.8 | S81: =R81 -> 64.8 | T81: =S81 -> 64.8 | U81: =T81 -> 64.8 | V81: =U81 -> 64.8 | W81: =V81 -> 64.8 | X81: =W81 -> 64.8 | ... AA81: =Z81 -> 64.8 | AB81: =SUM(P81:AA81) -> 777.6
B82: Инженер тех. поддержки | C82: =Аналитика!$C$28 -> 60 | D82: =C82 -> 60 | E82: =D82 -> 60 | F82: =E82 -> 60 | G82: =F82 -> 60 | H82: =G82 -> 60 | I82: =H82 -> 60 | J82: =I82 -> 60 | K82: =J82 -> 60 | ... N82: =M82 -> 60 | O82: =SUM(C82:N82) -> 720 | P82: =N82*(1+Аналитика!$M$3) -> 64.8 | Q82: =P82 -> 64.8 | R82: =Q82 -> 64.8 | S82: =R82 -> 64.8 | T82: =S82 -> 64.8 | U82: =T82 -> 64.8 | V82: =U82 -> 64.8 | W82: =V82 -> 64.8 | X82: =W82 -> 64.8 | ... AA82: =Z82 -> 64.8 | AB82: =SUM(P82:AA82) -> 777.6
B83: Контент-мейкер | C83: =Аналитика!$C$29 -> 80 | D83: =C83 -> 80 | E83: =D83 -> 80 | F83: =E83 -> 80 | G83: =F83 -> 80 | H83: =G83 -> 80 | I83: =H83 -> 80 | J83: =I83 -> 80 | K83: =J83 -> 80 | ... N83: =M83 -> 80 | O83: =SUM(C83:N83) -> 960 | P83: =N83*(1+Аналитика!$M$3) -> 86.4 | Q83: =P83 -> 86.4 | R83: =Q83 -> 86.4 | S83: =R83 -> 86.4 | T83: =S83 -> 86.4 | U83: =T83 -> 86.4 | V83: =U83 -> 86.4 | W83: =V83 -> 86.4 | X83: =W83 -> 86.4 | ... AA83: =Z83 -> 86.4 | AB83: =SUM(P83:AA83) -> 1036.8
B84: SMM | C84: =Аналитика!$C$30 -> 80 | D84: =C84 -> 80 | E84: =D84 -> 80 | F84: =E84 -> 80 | G84: =F84 -> 80 | H84: =G84 -> 80 | I84: =H84 -> 80 | J84: =I84 -> 80 | K84: =J84 -> 80 | ... N84: =M84 -> 80 | O84: =SUM(C84:N84) -> 960 | P84: =N84*(1+Аналитика!$M$3) -> 86.4 | Q84: =P84 -> 86.4 | R84: =Q84 -> 86.4 | S84: =R84 -> 86.4 | T84: =S84 -> 86.4 | U84: =T84 -> 86.4 | V84: =U84 -> 86.4 | W84: =V84 -> 86.4 | X84: =W84 -> 86.4 | ... AA84: =Z84 -> 86.4 | AB84: =SUM(P84:AA84) -> 1036.8
B85: Education | C85: =SUM(C86:C89) -> 350 | D85: =SUM(D86:D89) -> 350 | E85: =SUM(E86:E89) -> 350 | F85: =SUM(F86:F89) -> 350 | G85: =SUM(G86:G89) -> 350 | H85: =SUM(H86:H89) -> 350 | I85: =SUM(I86:I89) -> 350 | J85: =SUM(J86:J89) -> 350 | ... N85: =SUM(N86:N89) -> 350 | O85: =SUM(C85:N85) -> 4200 | P85: =SUM(P86:P89) -> 378 | Q85: =SUM(Q86:Q89) -> 378 | R85: =SUM(R86:R89) -> 378 | S85: =SUM(S86:S89) -> 378 | T85: =SUM(T86:T89) -> 378 | U85: =SUM(U86:U89) -> 378 | V85: =SUM(V86:V89) -> 378 | W85: =SUM(W86:W89) -> 378 | ... AA85: =SUM(AA86:AA89) -> 378 | AB85: =SUM(P85:AA85) -> 4536
B86: Producr Owner | C86: =Аналитика!$E$26 -> 100 | D86: =C86 -> 100 | E86: =D86 -> 100 | F86: =E86 -> 100 | G86: =F86 -> 100 | H86: =G86 -> 100 | I86: =H86 -> 100 | J86: =I86 -> 100 | K86: =J86 -> 100 | ... N86: =M86 -> 100 | O86: =SUM(C86:N86) -> 1200 | P86: =N86*(1+Аналитика!$M$3) -> 108 | Q86: =P86 -> 108 | R86: =Q86 -> 108 | S86: =R86 -> 108 | T86: =S86 -> 108 | U86: =T86 -> 108 | V86: =U86 -> 108 | W86: =V86 -> 108 | X86: =W86 -> 108 | ... AA86: =Z86 -> 108 | AB86: =SUM(P86:AA86) -> 1296
B87: Куратор | C87: =Аналитика!$E$27 -> 100 | D87: =C87 -> 100 | E87: =D87 -> 100 | F87: =E87 -> 100 | G87: =F87 -> 100 | H87: =G87 -> 100 | I87: =H87 -> 100 | J87: =I87 -> 100 | K87: =J87 -> 100 | ... N87: =M87 -> 100 | O87: =SUM(C87:N87) -> 1200 | P87: =N87*(1+Аналитика!$M$3) -> 108 | Q87: =P87 -> 108 | R87: =Q87 -> 108 | S87: =R87 -> 108 | T87: =S87 -> 108 | U87: =T87 -> 108 | V87: =U87 -> 108 | W87: =V87 -> 108 | X87: =W87 -> 108 | ... AA87: =Z87 -> 108 | AB87: =SUM(P87:AA87) -> 1296
B88: Инженер тех. поддержки | C88: =Аналитика!$E$28 -> 70 | D88: =C88 -> 70 | E88: =D88 -> 70 | F88: =E88 -> 70 | G88: =F88 -> 70 | H88: =G88 -> 70 | I88: =H88 -> 70 | J88: =I88 -> 70 | K88: =J88 -> 70 | ... N88: =M88 -> 70 | O88: =SUM(C88:N88) -> 840 | P88: =N88*(1+Аналитика!$M$3) -> 75.6 | Q88: =P88 -> 75.6 | R88: =Q88 -> 75.6 | S88: =R88 -> 75.6 | T88: =S88 -> 75.6 | U88: =T88 -> 75.6 | V88: =U88 -> 75.6 | W88: =V88 -> 75.6 | X88: =W88 -> 75.6 | ... AA88: =Z88 -> 75.6 | AB88: =SUM(P88:AA88) -> 907.2
B89: SMM | C89: =Аналитика!$E$29 -> 80 | D89: =C89 -> 80 | E89: =D89 -> 80 | F89: =E89 -> 80 | G89: =F89 -> 80 | H89: =G89 -> 80 | I89: =H89 -> 80 | J89: =I89 -> 80 | K89: =J89 -> 80 | ... N89: =M89 -> 80 | O89: =SUM(C89:N89) -> 960 | P89: =N89*(1+Аналитика!$M$3) -> 86.4 | Q89: =P89 -> 86.4 | R89: =Q89 -> 86.4 | S89: =R89 -> 86.4 | T89: =S89 -> 86.4 | U89: =T89 -> 86.4 | V89: =U89 -> 86.4 | W89: =V89 -> 86.4 | X89: =W89 -> 86.4 | ... AA89: =Z89 -> 86.4 | AB89: =SUM(P89:AA89) -> 1036.8
B90: Бухгалтер | C90: =Аналитика!$E$31 -> 40 | D90: =C90 -> 40 | E90: =D90 -> 40 | F90: =E90 -> 40 | G90: =F90 -> 40 | H90: =G90 -> 40 | I90: =H90 -> 40 | J90: =I90 -> 40 | K90: =J90 -> 40 | ... N90: =M90 -> 40 | O90: =SUM(C90:N90) -> 480 | P90: =N90*(1+Аналитика!$M$3) -> 43.2 | Q90: =P90 -> 43.2 | R90: =Q90 -> 43.2 | S90: =R90 -> 43.2 | T90: =S90 -> 43.2 | U90: =T90 -> 43.2 | V90: =U90 -> 43.2 | W90: =V90 -> 43.2 | X90: =W90 -> 43.2 | ... AA90: =Z90 -> 43.2 | AB90: =SUM(P90:AA90) -> 518.4
B92: Таблица 21.2. Количество штатных единиц, чел.
C93: янв.26 | D93: фев.26 | E93: мар.26 | F93: апр.26 | G93: 46143 | H93: июн.26 | I93: июл.26 | J93: авг.26 | K93: сент.26 | L93: окт.26 | M93: ноя.26 | N93: дек.26 | O93: 2026 | P93: янв.27 | Q93: фев.27 | R93: мар.27 | S93: апр.27 | T93: 46508 | U93: июн.27 | V93: июл.27 | W93: авг.27 | X93: сент.27 | Y93: окт.27 | Z93: ноя.27 | AA93: дек.27 | AB93: 2027
B95: Community | C95: =SUM(C96:C100) -> 5 | D95: =SUM(D96:D100) -> 5 | E95: =SUM(E96:E100) -> 5 | F95: =SUM(F96:F100) -> 5 | G95: =SUM(G96:G100) -> 5 | H95: =SUM(H96:H100) -> 5 | I95: =SUM(I96:I100) -> 5 | J95: =SUM(J96:J100) -> 5 | ... AB95: =SUM(AB96:AB100) -> 5
B96: Producr Owner | C96: 1 | D96: =C96 -> 1 | E96: =D96 -> 1 | F96: =E96 -> 1 | G96: =F96 -> 1 | H96: =G96 -> 1 | I96: =H96 -> 1 | J96: =I96 -> 1 | K96: =J96 -> 1 | ... O96: =N96 -> 1 | P96: 1 | Q96: =P96 -> 1 | R96: =Q96 -> 1 | S96: =R96 -> 1 | T96: =S96 -> 1 | U96: =T96 -> 1 | V96: =U96 -> 1 | W96: =V96 -> 1 | X96: =W96 -> 1 | ... AB96: =AA96 -> 1
B97: Модератор | C97: 1 | D97: =C97 -> 1 | E97: =D97 -> 1 | F97: =E97 -> 1 | G97: =F97 -> 1 | H97: =G97 -> 1 | I97: =H97 -> 1 | J97: =I97 -> 1 | K97: =J97 -> 1 | ... O97: =N97 -> 1 | P97: 1 | Q97: =P97 -> 1 | R97: =Q97 -> 1 | S97: =R97 -> 1 | T97: =S97 -> 1 | U97: =T97 -> 1 | V97: =U97 -> 1 | W97: =V97 -> 1 | X97: =W97 -> 1 | ... AB97: =AA97 -> 1
B98: Инженер тех. поддержки | C98: 1 | D98: =C98 -> 1 | E98: =D98 -> 1 | F98: =E98 -> 1 | G98: =F98 -> 1 | H98: =G98 -> 1 | I98: =H98 -> 1 | J98: =I98 -> 1 | K98: =J98 -> 1 | ... O98: =N98 -> 1 | P98: 1 | Q98: =P98 -> 1 | R98: =Q98 -> 1 | S98: =R98 -> 1 | T98: =S98 -> 1 | U98: =T98 -> 1 | V98: =U98 -> 1 | W98: =V98 -> 1 | X98: =W98 -> 1 | ... AB98: =AA98 -> 1
B99: Контент-мейкер | C99: 1 | D99: =C99 -> 1 | E99: =D99 -> 1 | F99: =E99 -> 1 | G99: =F99 -> 1 | H99: =G99 -> 1 | I99: =H99 -> 1 | J99: =I99 -> 1 | K99: =J99 -> 1 | ... O99: =N99 -> 1 | P99: 1 | Q99: =P99 -> 1 | R99: =Q99 -> 1 | S99: =R99 -> 1 | T99: =S99 -> 1 | U99: =T99 -> 1 | V99: =U99 -> 1 | W99: =V99 -> 1 | X99: =W99 -> 1 | ... AB99: =AA99 -> 1
B100: SMM | C100: 1 | D100: =C100 -> 1 | E100: =D100 -> 1 | F100: =E100 -> 1 | G100: =F100 -> 1 | H100: =G100 -> 1 | I100: =H100 -> 1 | J100: =I100 -> 1 | K100: =J100 -> 1 | ... O100: =N100 -> 1 | P100: 1 | Q100: =P100 -> 1 | R100: =Q100 -> 1 | S100: =R100 -> 1 | T100: =S100 -> 1 | U100: =T100 -> 1 | V100: =U100 -> 1 | W100: =V100 -> 1 | X100: =W100 -> 1 | ... AB100: =AA100 -> 1
B101: Education | C101: =SUM(C102:C105) -> 4 | D101: =SUM(D102:D105) -> 5 | E101: =SUM(E102:E105) -> 5 | F101: =SUM(F102:F105) -> 6 | G101: =SUM(G102:G105) -> 7 | H101: =SUM(H102:H105) -> 8 | I101: =SUM(I102:I105) -> 8 | J101: =SUM(J102:J105) -> 9 | ... AB101: =SUM(AB102:AB105) -> 15
B102: Producr Owner | C102: 1 | D102: =C102 -> 1 | E102: =D102 -> 1 | F102: =E102 -> 1 | G102: =F102 -> 1 | H102: =G102 -> 1 | I102: =H102 -> 1 | J102: =I102 -> 1 | K102: =J102 -> 1 | ... O102: =N102 -> 1 | P102: 1 | Q102: =P102 -> 1 | R102: =Q102 -> 1 | S102: =R102 -> 1 | T102: =S102 -> 1 | U102: =T102 -> 1 | V102: =U102 -> 1 | W102: =V102 -> 1 | X102: =W102 -> 1 | ... AB102: =AA102 -> 1
B103: Куратор | C103: =ROUNDUP(SUM(Расчеты!C33:C36)/30,0) -> 1 | D103: =ROUNDUP(SUM(Расчеты!D33:D36)/30,0) -> 2 | E103: =ROUNDUP(SUM(Расчеты!E33:E36)/30,0) -> 2 | F103: =ROUNDUP(SUM(Расчеты!F33:F36)/30,0) -> 3 | G103: =ROUNDUP(SUM(Расчеты!G33:G36)/30,0) -> 4 | H103: =ROUNDUP(SUM(Расчеты!H33:H36)/30,0) -> 5 | I103: =ROUNDUP(SUM(Расчеты!I33:I36)/30,0) -> 5 | J103: =ROUNDUP(SUM(Расчеты!J33:J36)/30,0) -> 6 | ... N103: =ROUNDUP(SUM(Расчеты!N33:N36)/30,0) -> 9 | O103: =N103 -> 9 | P103: =ROUNDUP(SUM(Расчеты!P33:P36)/30,0) -> 9 | Q103: =ROUNDUP(SUM(Расчеты!Q33:Q36)/30,0) -> 10 | R103: =ROUNDUP(SUM(Расчеты!R33:R36)/30,0) -> 10 | S103: =ROUNDUP(SUM(Расчеты!S33:S36)/30,0) -> 10 | T103: =ROUNDUP(SUM(Расчеты!T33:T36)/30,0) -> 10 | U103: =ROUNDUP(SUM(Расчеты!U33:U36)/30,0) -> 10 | V103: =ROUNDUP(SUM(Расчеты!V33:V36)/30,0) -> 11 | W103: =ROUNDUP(SUM(Расчеты!W33:W36)/30,0) -> 11 | ... AA103: =ROUNDUP(SUM(Расчеты!AA33:AA36)/30,0) -> 12 | AB103: =AA103 -> 12
B104: Инженер тех. поддержки | C104: 1 | D104: =C104 -> 1 | E104: =D104 -> 1 | F104: =E104 -> 1 | G104: =F104 -> 1 | H104: =G104 -> 1 | I104: =H104 -> 1 | J104: =I104 -> 1 | K104: =J104 -> 1 | ... O104: =N104 -> 1 | P104: 1 | Q104: =P104 -> 1 | R104: =Q104 -> 1 | S104: =R104 -> 1 | T104: =S104 -> 1 | U104: =T104 -> 1 | V104: =U104 -> 1 | W104: =V104 -> 1 | X104: =W104 -> 1 | ... AB104: =AA104 -> 1
B105: SMM | C105: 1 | D105: =C105 -> 1 | E105: =D105 -> 1 | F105: =E105 -> 1 | G105: =F105 -> 1 | H105: =G105 -> 1 | I105: =H105 -> 1 | J105: =I105 -> 1 | K105: =J105 -> 1 | ... O105: =N105 -> 1 | P105: 1 | Q105: =P105 -> 1 | R105: =Q105 -> 1 | S105: =R105 -> 1 | T105: =S105 -> 1 | U105: =T105 -> 1 | V105: =U105 -> 1 | W105: =V105 -> 1 | X105: =W105 -> 1 | ... AB105: =AA105 -> 1
B106: Бухгалтер | C106: 1 | D106: =C106 -> 1 | E106: =D106 -> 1 | F106: =E106 -> 1 | G106: =F106 -> 1 | H106: =G106 -> 1 | I106: =H106 -> 1 | J106: =I106 -> 1 | K106: =J106 -> 1 | ... O106: =N106 -> 1 | P106: 1 | Q106: =P106 -> 1 | R106: =Q106 -> 1 | S106: =R106 -> 1 | T106: =S106 -> 1 | U106: =T106 -> 1 | V106: =U106 -> 1 | W106: =V106 -> 1 | X106: =W106 -> 1 | ... AB106: =AA106 -> 1
B108: Таблица 21.3. ДМС штатной единицы, тыс. руб. | AD108: - Без учёта инфляции (считаем, что договор ДМС заключён на 2 года)
C109: янв.26 | D109: фев.26 | E109: мар.26 | F109: апр.26 | G109: 46143 | H109: июн.26 | I109: июл.26 | J109: авг.26 | K109: сент.26 | L109: окт.26 | M109: ноя.26 | N109: дек.26 | O109: 2026 | P109: янв.27 | Q109: фев.27 | R109: мар.27 | S109: апр.27 | T109: 46508 | U109: июн.27 | V109: июл.27 | W109: авг.27 | X109: сент.27 | Y109: окт.27 | Z109: ноя.27 | AA109: дек.27 | AB109: 2027
B111: Community | C111: =SUM(C112:C116) -> 10 | D111: =SUM(D112:D116) -> 10 | E111: =SUM(E112:E116) -> 10 | F111: =SUM(F112:F116) -> 10 | G111: =SUM(G112:G116) -> 10 | H111: =SUM(H112:H116) -> 10 | I111: =SUM(I112:I116) -> 10 | J111: =SUM(J112:J116) -> 10 | ... N111: =SUM(N112:N116) -> 10 | O111: =SUM(C111:N111) -> 120 | P111: =SUM(P112:P116) -> 10 | Q111: =SUM(Q112:Q116) -> 10 | R111: =SUM(R112:R116) -> 10 | S111: =SUM(S112:S116) -> 10 | T111: =SUM(T112:T116) -> 10 | U111: =SUM(U112:U116) -> 10 | V111: =SUM(V112:V116) -> 10 | W111: =SUM(W112:W116) -> 10 | ... AA111: =SUM(AA112:AA116) -> 10 | AB111: =SUM(P111:AA111) -> 120
B112: Producr Owner | C112: =Аналитика!$M$9 -> 2 | D112: =Аналитика!$M$9 -> 2 | E112: =Аналитика!$M$9 -> 2 | F112: =Аналитика!$M$9 -> 2 | G112: =Аналитика!$M$9 -> 2 | H112: =Аналитика!$M$9 -> 2 | I112: =Аналитика!$M$9 -> 2 | J112: =Аналитика!$M$9 -> 2 | ... N112: =Аналитика!$M$9 -> 2 | O112: =SUM(C112:N112) -> 24 | P112: =Аналитика!$M$9 -> 2 | Q112: =Аналитика!$M$9 -> 2 | R112: =Аналитика!$M$9 -> 2 | S112: =Аналитика!$M$9 -> 2 | T112: =Аналитика!$M$9 -> 2 | U112: =Аналитика!$M$9 -> 2 | V112: =Аналитика!$M$9 -> 2 | W112: =Аналитика!$M$9 -> 2 | ... AA112: =Аналитика!$M$9 -> 2 | AB112: =SUM(P112:AA112) -> 24
B113: Модератор | C113: =Аналитика!$M$9 -> 2 | D113: =Аналитика!$M$9 -> 2 | E113: =Аналитика!$M$9 -> 2 | F113: =Аналитика!$M$9 -> 2 | G113: =Аналитика!$M$9 -> 2 | H113: =Аналитика!$M$9 -> 2 | I113: =Аналитика!$M$9 -> 2 | J113: =Аналитика!$M$9 -> 2 | ... N113: =Аналитика!$M$9 -> 2 | O113: =SUM(C113:N113) -> 24 | P113: =Аналитика!$M$9 -> 2 | Q113: =Аналитика!$M$9 -> 2 | R113: =Аналитика!$M$9 -> 2 | S113: =Аналитика!$M$9 -> 2 | T113: =Аналитика!$M$9 -> 2 | U113: =Аналитика!$M$9 -> 2 | V113: =Аналитика!$M$9 -> 2 | W113: =Аналитика!$M$9 -> 2 | ... AA113: =Аналитика!$M$9 -> 2 | AB113: =SUM(P113:AA113) -> 24
B114: Инженер тех. поддержки | C114: =Аналитика!$M$9 -> 2 | D114: =Аналитика!$M$9 -> 2 | E114: =Аналитика!$M$9 -> 2 | F114: =Аналитика!$M$9 -> 2 | G114: =Аналитика!$M$9 -> 2 | H114: =Аналитика!$M$9 -> 2 | I114: =Аналитика!$M$9 -> 2 | J114: =Аналитика!$M$9 -> 2 | ... N114: =Аналитика!$M$9 -> 2 | O114: =SUM(C114:N114) -> 24 | P114: =Аналитика!$M$9 -> 2 | Q114: =Аналитика!$M$9 -> 2 | R114: =Аналитика!$M$9 -> 2 | S114: =Аналитика!$M$9 -> 2 | T114: =Аналитика!$M$9 -> 2 | U114: =Аналитика!$M$9 -> 2 | V114: =Аналитика!$M$9 -> 2 | W114: =Аналитика!$M$9 -> 2 | ... AA114: =Аналитика!$M$9 -> 2 | AB114: =SUM(P114:AA114) -> 24
B115: Контент-мейкер | C115: =Аналитика!$M$9 -> 2 | D115: =Аналитика!$M$9 -> 2 | E115: =Аналитика!$M$9 -> 2 | F115: =Аналитика!$M$9 -> 2 | G115: =Аналитика!$M$9 -> 2 | H115: =Аналитика!$M$9 -> 2 | I115: =Аналитика!$M$9 -> 2 | J115: =Аналитика!$M$9 -> 2 | ... N115: =Аналитика!$M$9 -> 2 | O115: =SUM(C115:N115) -> 24 | P115: =Аналитика!$M$9 -> 2 | Q115: =Аналитика!$M$9 -> 2 | R115: =Аналитика!$M$9 -> 2 | S115: =Аналитика!$M$9 -> 2 | T115: =Аналитика!$M$9 -> 2 | U115: =Аналитика!$M$9 -> 2 | V115: =Аналитика!$M$9 -> 2 | W115: =Аналитика!$M$9 -> 2 | ... AA115: =Аналитика!$M$9 -> 2 | AB115: =SUM(P115:AA115) -> 24
B116: SMM | C116: =Аналитика!$M$9 -> 2 | D116: =Аналитика!$M$9 -> 2 | E116: =Аналитика!$M$9 -> 2 | F116: =Аналитика!$M$9 -> 2 | G116: =Аналитика!$M$9 -> 2 | H116: =Аналитика!$M$9 -> 2 | I116: =Аналитика!$M$9 -> 2 | J116: =Аналитика!$M$9 -> 2 | ... N116: =Аналитика!$M$9 -> 2 | O116: =SUM(C116:N116) -> 24 | P116: =Аналитика!$M$9 -> 2 | Q116: =Аналитика!$M$9 -> 2 | R116: =Аналитика!$M$9 -> 2 | S116: =Аналитика!$M$9 -> 2 | T116: =Аналитика!$M$9 -> 2 | U116: =Аналитика!$M$9 -> 2 | V116: =Аналитика!$M$9 -> 2 | W116: =Аналитика!$M$9 -> 2 | ... AA116: =Аналитика!$M$9 -> 2 | AB116: =SUM(P116:AA116) -> 24
B117: Education | C117: =SUM(C118:C121) -> 8 | D117: =SUM(D118:D121) -> 8 | E117: =SUM(E118:E121) -> 8 | F117: =SUM(F118:F121) -> 8 | G117: =SUM(G118:G121) -> 8 | H117: =SUM(H118:H121) -> 8 | I117: =SUM(I118:I121) -> 8 | J117: =SUM(J118:J121) -> 8 | ... N117: =SUM(N118:N121) -> 8 | O117: =SUM(C117:N117) -> 96 | P117: =SUM(P118:P121) -> 8 | Q117: =SUM(Q118:Q121) -> 8 | R117: =SUM(R118:R121) -> 8 | S117: =SUM(S118:S121) -> 8 | T117: =SUM(T118:T121) -> 8 | U117: =SUM(U118:U121) -> 8 | V117: =SUM(V118:V121) -> 8 | W117: =SUM(W118:W121) -> 8 | ... AA117: =SUM(AA118:AA121) -> 8 | AB117: =SUM(P117:AA117) -> 96
...

Sheet Бюджет
B2: Таблица 26. Бюджет доходов и расходов 2026-2027, тыс. руб.
C3: Итого новые проекты | F3: Community | I3: Education
C4: 2026 | D4: 2027 | F4: 2026 | G4: 2027 | I4: 2026 | J4: 2027
B5: Выручка | C5: =F5+I5 -> 20487.56 | D5: =G5+J5 -> 51123.921 | F5: =Расчеты!O9 -> 4840.5369 | G5: =Расчеты!AB9 -> 16907.573 | I5: =Расчеты!O15 -> 15647.023 | J5: =Расчеты!AB15 -> 34216.348
B6: Себестоимость | C6: =F6+I6 -> 27500 | D6: =G6+J6 -> 39124.04 | F6: =(Расчеты!O57+Расчеты!O63+Расчеты!O172+Расчеты!O179) -> 10898 | G6: =(Расчеты!AB57+Расчеты!AB63+Расчеты!AB172+Расчеты!AB179) -> 11414.24 | I6: =(Расчеты!O58+Расчеты!O69+Расчеты!O173+Расчеты!O184) -> 16602 | J6: =(Расчеты!AB58+Расчеты!AB69+Расчеты!AB173+Расчеты!AB184) -> 27709.8
B7: Валовая прибыль | C7: =C5-C6 -> -7012.44 | D7: =D5-D6 -> 11999.881 | F7: =F5-F6 -> -6057.4631 | G7: =G5-G6 -> 5493.3332 | I7: =I5-I6 -> -954.97681 | J7: =J5-J6 -> 6506.548
B8: Валовая прибыль, % | C8: =C7/C5 -> -0.34227795 | D8: =D7/D5 -> 0.23472145 | F8: =F7/F5 -> -1.2514032 | G8: =G7/G5 -> 0.3249037 | I8: =I7/I5 -> -0.061032492 | J8: =J7/J5 -> 0.19015904
B9: Операционные расходы | C9: =SUM(C10:C14) -> 8974.13 | D9: =SUM(D10:D14) -> 9695.0776 | F9: =SUM(F10:F14) -> 3744.98 | G9: =SUM(G10:G14) -> 4004.6624 | I9: =SUM(I10:I14) -> 3802.02 | J9: =SUM(J10:J14) -> 4167.618
B10: Расходы на персонал | C10: =Расчеты!O74+F10+I10 -> 648 | D10: =Расчеты!AB74+G10+J10 -> 697.92 | F10: 0 | G10: 0 | I10: 0 | J10: 0
B11: Аренда | C11: =Расчеты!O159+F11+I11 -> 675 | D11: =Расчеты!AB159+G11+J11 -> 717 | F11: 0 | G11: 0 | I11: 0 | J11: 0
B12: Реклама и маркетинг | C12: =F12+I12 -> 7200 | D12: =G12+J12 -> 7704 | F12: =Расчеты!O166 -> 3600 | G12: =Расчеты!AB166 -> 3852 | I12: =Расчеты!O167 -> 3600 | J12: =Расчеты!AB167 -> 3852
B13: Оборудование, лицензии и программное обеспечение | C13: =Расчеты!O174+Расчеты!O189+Бюджет!F13+Бюджет!I13 -> 90 | D13: =Расчеты!AB174+Бюджет!G13+Бюджет!J13+Расчеты!AB189 -> 92.8 | F13: 0 | G13: 0 | I13: 0 | J13: 0
B14: Прочие и непредвиденные расходы | C14: =(SUM(C10:C13)+C6)*0.01 -> 361.13 | D14: =(SUM(D10:D13)+D6)*0.01 -> 483.3576 | F14: =(SUM(F10:F13)+F6)*0.01 -> 144.98 | G14: =(SUM(G10:G13)+G6)*0.01 -> 152.6624 | I14: =(SUM(I10:I13)+I6)*0.01 -> 202.02 | J14: =(SUM(J10:J13)+J6)*0.01 -> 315.618
B15: Операционная прибыль | C15: =C7-C9 -> -15986.57 | D15: =D7-D9 -> 2304.8035 | F15: =F7-F9 -> -9802.4431 | G15: =G7-G9 -> 1488.6708 | I15: =I7-I9 -> -4756.9968 | J15: =J7-J9 -> 2338.93
B16: Операционная прибыль, % | C16: =C15/C5 -> -0.78030619 | D16: =D15/D5 -> 0.045082683 | F16: =F15/F5 -> -2.0250735 | G16: =G15/G5 -> 0.088047572 | I16: =I15/I5 -> -0.30401929 | J16: =J15/J5 -> 0.06835709
B17: Налог на прибыль | C17: =IF(C15>0, C15*25%, 0) -> 0 | D17: =IF(D15>0, D15*25%, 0) -> 576.20089 | F17: 0 | G17: 0 | I17: 0 | J17: 0
B18: Чистая прибыль | C18: =C15-C17 -> -15986.57 | D18: =D15-D17 -> 1728.6027 | F18: =F15-F17 -> -9802.4431 | G18: =G15-G17 -> 1488.6708 | I18: =I15-I17 -> -4756.9968 | J18: =J15-J17 -> 2338.93
B19: Чистая прибыль, % | C19: =C18/C5 -> -0.78030619 | D19: =D18/D5 -> 0.033812012 | F19: =F18/F5 -> -2.0250735 | G19: =G18/G5 -> 0.088047572 | I19: =I18/I5 -> -0.30401929 | J19: =J18/J5 -> 0.06835709
