Workbook

Sheet Цели
B2: Таблица 1. Цели 2026–2027 | J2: Подсказку?
C3: Community | E3: Education | G3: Итого новые направления
C4: 2026 | D4: 2027 | E4: 2026 | F4: 2027 | G4: 2026 | H4: 2027 | V4: Да
B5: Неоцифрованные | C5: Создать сообщество с большим количеством активных пользователей | E5: Создать базу квалифицированных разработчиков, которые потенциально смогут работать в Kihi | V5: Нет
C6: Самоокупаемость к концу 2027 года
B7: Финансовые показатели, тыс. руб.
B8: Выручка | C8: ='Бюджет'!F5 -> 4840.5369 | D8: ='Бюджет'!G5 -> 16907.573 | E8: ='Бюджет'!I5 -> 15642.711 | F8: ='Бюджет'!J5 -> 34206.016 | G8: ='Бюджет'!C5 -> 20483.248 | H8: ='Бюджет'!D5 -> 51113.589 | J8: Нет | K8: =IF(J8="Нет", " ", "Цели по выручке заполните из листа Бюджет после всех расчётов")
B9: Прирост год к году, % | D9: =D8/C8-1 -> 2.4929128 | F9: =F8/E8-1 -> 1.1867064 | H9: =H8/G8-1 -> 1.495385 | J9: Нет | K9: =IF(J9="Нет", " ", "Рассчитывается как показатель 2027 / показатель 2026 - 1")
B10: Чистая прибыль | C10: ='Бюджет'!F18 -> -9802.4431 | D10: ='Бюджет'!G18 -> 1488.6708 | E10: ='Бюджет'!I18 -> -4761.309 | F10: ='Бюджет'!J18 -> 2328.598 | G10: ='Бюджет'!C18 -> -15990.882 | H10: ='Бюджет'!D18 -> 1720.8536 | J10: Нет | K10: =IF(J10="Нет", " ", "Цели по прибыли заполните из листа Бюджет после всех расчётов")
B11: Чистая прибыль, % | C11: =C10/C8 -> -2.0250735 | D11: =D10/D8 -> 0.088047572 | E11: =E10/E8 -> -0.30437876 | F11: =F10/F8 -> 0.068075685 | G11: =G10/G8 -> -0.78068099 | H11: =H10/H8 -> 0.033667243 | J11: Нет | K11: =IF(J11="Нет", " ", "Рассчитывается как Чистая прибыль / Выручку")

Sheet Аналитика
B2: Таблица 2. Рыночная цена аналогов, руб. | G2: Таблица 6. Ожидаемое количество новых пользователей, чел. | L2: Таблица 8. Прочие вводные
B3: Community | D3: Education | H3: Community | I3: Education | L3: Ежегодная индексация ЗП | M3: 0.08
B4: Первый месяц | C4: 0 | D4: Фритрек (недельный) | E4: 0 | G4: В первый месяц | H4: 500 | I4: 40 | L4: Ожидаемая инфляция 27/26 | M4: 0.07
B5: Подписка на месяц | C5: 300 | D5: Полная оплата годового курса | E5: 100000 | G5: Ежемесячный прирост | H5: 0.017 | I5: 0.02 | L5: Аренда помещения под 20–25 человек, тыс. руб./мес. | M5: 50
B6: Пакет на 3 месяца | C6: 850 | D6: Оплата курса 2 траншами | E6: 110000 | G6: Ограничения | H6: нет | I6: Не более 30 человек на одного куратора (фритрек не сопровождается куратором) | L6: Закупка мебели, тыс. руб. | M6: 150
B7: Пакет на 6 месяцев | C7: 1600 | D7: Оплата курса 3 траншами | E7: 114000 | G7: Сезонность (дополнительный прирост в летние месяцы к ежемесячному приросту) | H7: 0.03 | I7: 0.03 | L7: Закупка оборудования (компьютеры, мыши, клавиатуры), тыс. руб./чел. | M7: 100
B8: Пакет на 12 месяцев | C8: 3000 | D8: Оплата курса помесячно | E8: 120000 | L8: Непредвиденные расходы | M8: 1% от всех расходов
G9: Таблица 7. Ожидаемый уровень проникновения продаж | L9: Стоимость ДМС на 1 чел./мес., тыс. руб. | M9: 2
B10: Таблица 3. Стоимость и время аутсорс-разработки «под ключ», тыс. руб. | G10: Community | I10: Education | L10: Лицензия 1С для 1 ПК/год, тыс. руб. | M10: 10
C11: Стоимость | D11: Время | G11: Подписка на месяц | H11: 0.2 | I11: Полная оплата курса | J11: 0.03 | L11: Лицензия MS Office для 1 ПК/год, тыс. руб. | M11: 30
B12: Community | C12: 8000 | D12: релиз — 10.01.26 | G12: Пакет на 3 месяца | H12: 0.15 | I12: Оплата курса 2 траншами | J12: 0.1 | L12: Лицензия Miro для 1 ПК/год, тыс. руб. | M12: 14
B13: Education | C13: 6000 | D13: релиз — 15.01.26 | G13: Пакет на 6 месяцев | H13: 0.1 | I13: Оплата курса 3 траншами | J13: 0.15 | L13: Лицензия Jira для 1 ПК/год, тыс. руб. | M13: 10
G14: Пакет на 12 месяцев | H14: 0.03 | I14: Оплата курса помесячно | J14: 0.2 | L14: Софт для разработки комьюнити-платформы 1 ПК/год, тыс. руб. | M14: 66
B15: Таблица 4. Рыночные ежемесячные расходы на рекламу, тыс. руб. | L15: Софт для разработки обучающей платформы 1 ПК/год, тыс. руб. | M15: 66
C16: Community | D16: Education
B17: SEO | C17: 40 | D17: 40
B18: SMM | C18: 60 | D18: 60
B19: PPC | C19: 40 | D19: 40
B20: App ads | C20: 70 | D20: 70
B21: Email-рассылка | C21: 40 | D21: 40
B22: Контент-маркетинг | C22: 50 | D22: 50
B24: Таблица 5. Рыночная ЗП поддерживающего персонала в мес., тыс. руб.
B25: Community | D25: Education
B26: Producr Owner | C26: 100 | D26: Producr Owner | E26: 100
B27: Модератор | C27: 60 | D27: Куратор | E27: 100
B28: Инженер тех. поддержки | C28: 60 | D28: Инженер тех. поддержки | E28: 70
B29: Контент-мейкер | C29: 80 | D29: SMM | E29: 80
B30: SMM | C30: 80
B31: Бухгалтер (на два проекта) | E31: 40

Sheet Расчёты
B2: Таблица 9. Количество дней в периоде, шт. | AD2: Допущения | AF2: Подсказку?
C3: янв.26 | D3: фев.26 | E3: мар.26 | F3: апр.26 | G3: 46143 | H3: июн.26 | I3: июл.26 | J3: авг.26 | K3: сент.26 | L3: окт.26 | M3: ноя.26 | N3: дек.26 | O3: 2026 | P3: янв.27 | Q3: фев.27 | R3: мар.27 | S3: апр.27 | T3: 46508 | U3: июн.27 | V3: июл.27 | W3: авг.27 | X3: сент.27 | Y3: окт.27 | Z3: ноя.27 | AA3: дек.27 | AB3: 2027
C4: 31 | D4: 28 | E4: 31 | F4: 30 | G4: 31 | H4: 30 | I4: 31 | J4: 31 | K4: 30 | L4: 31 | M4: 30 | N4: 31 | O4: =SUM(C4:N4) -> 365 | P4: 31 | Q4: 28 | R4: 31 | S4: 30 | T4: 31 | U4: 30 | V4: 31 | W4: 31 | X4: 30 | Y4: 31 | Z4: 30 | AA4: 31 | AB4: =SUM(P4:AA4) -> 365
B6: Таблица 10. Выручка, тыс. руб. | AF6: Нет | AG6: =IF(AF6="Нет", " ", "Показатель рассчитывается по формуле Количество пользователей * Стоимость подписки")
C7: янв.26 | D7: фев.26 | E7: мар.26 | F7: апр.26 | G7: 46143 | H7: июн.26 | I7: июл.26 | J7: авг.26 | K7: сент.26 | L7: окт.26 | M7: ноя.26 | N7: дек.26 | O7: 2026 | P7: янв.27 | Q7: фев.27 | R7: мар.27 | S7: апр.27 | T7: 46508 | U7: июн.27 | V7: июл.27 | W7: авг.27 | X7: сент.27 | Y7: окт.27 | Z7: ноя.27 | AA7: дек.27 | AB7: 2027
B9: Community | C9: =SUM(C10:C14) -> 0 | D9: =SUM(D10:D14) -> 68.333333 | E9: =SUM(E10:E14) -> 137.82833 | F9: =SUM(F10:F14) -> 208.50475 | G9: =SUM(G10:G14) -> 280.38266 | H9: =SUM(H10:H14) -> 353.4825 | I9: =SUM(I10:I14) -> 430.05531 | J9: =SUM(J10:J14) -> 510.2661 | ... N9: =SUM(N10:N14) -> 832.89492 | O9: =SUM(C9:N9) -> 4840.5369 | P9: =SUM(P10:P14) -> 915.15006 | Q9: =SUM(Q10:Q14) -> 998.80355 | R9: =SUM(R10:R14) -> 1083.8791 | S9: =SUM(S10:S14) -> 1170.401 | T9: =SUM(T10:T14) -> 1258.3938 | U9: =SUM(U10:U14) -> 1347.8824 | V9: =SUM(V10:V14) -> 1441.6226 | W9: =SUM(W10:W14) -> 1539.8165 | ... AA9: =SUM(AA10:AA14) -> 1934.7778 | AB9: =SUM(P9:AA9) -> 16907.573
B10: Первый месяц | C10: =C26*C42/1000 -> 0 | D10: 0 | E10: 0 | F10: 0 | G10: 0 | H10: 0 | I10: 0 | J10: 0 | K10: 0 | L10: 0 | M10: 0 | N10: 0 | O10: =SUM(C10:N10) -> 0 | P10: =P26*P42/1000 -> 0 | Q10: =Q26*Q42/1000 -> 0 | R10: =R26*R42/1000 -> 0 | S10: =S26*S42/1000 -> 0 | T10: =T26*T42/1000 -> 0 | U10: =U26*U42/1000 -> 0 | V10: =V26*V42/1000 -> 0 | W10: =W26*W42/1000 -> 0 | ... AA10: =AA26*AA42/1000 -> 0 | AB10: =SUM(P10:AA10) -> 0
B11: Подписка на месяц | C11: =C27*C43/1000 -> 0 | D11: =D27*D43/1000 -> 30 | E11: =E27*E43/1000 -> 60.51 | F11: =F27*F43/1000 -> 91.53867 | G11: =G27*G43/1000 -> 123.09483 | H11: =H27*H43/1000 -> 155.18744 | I11: =I27*I43/1000 -> 188.80477 | J11: =J27*J43/1000 -> 224.01926 | ... N11: =N27*N43/1000 -> 365.66118 | O11: =SUM(C11:N11) -> 2125.1137 | P11: =P27*P43/1000 -> 401.7732 | Q11: =Q27*Q43/1000 -> 438.49912 | R11: =R27*R43/1000 -> 475.84938 | S11: =S27*S43/1000 -> 513.8346 | T11: =T27*T43/1000 -> 552.46556 | U11: =U27*U43/1000 -> 591.75325 | V11: =V27*V43/1000 -> 632.9075 | W11: =W27*W43/1000 -> 676.01699 | ... AA11: =AA27*AA43/1000 -> 849.41465 | AB11: =SUM(P11:AA11) -> 7422.837
B12: Пакет на 3 месяца | C12: =C28*C44/1000 -> 0 | D12: =D28*D44/1000 -> 21.25 | E12: =E28*E44/1000 -> 42.86125 | F12: =F28*F44/1000 -> 64.839891 | G12: =G28*G44/1000 -> 87.192169 | H12: =H28*H44/1000 -> 109.92444 | I12: =I28*I44/1000 -> 133.73671 | J12: =J28*J44/1000 -> 158.68031 | ... N12: =N28*N44/1000 -> 259.01 | O12: =SUM(C12:N12) -> 1505.2889 | P12: =P28*P44/1000 -> 284.58935 | Q12: =Q28*Q44/1000 -> 310.60354 | R12: =R28*R44/1000 -> 337.05998 | S12: =S28*S44/1000 -> 363.96617 | T12: =T28*T44/1000 -> 391.32977 | U12: =U28*U44/1000 -> 419.15855 | V12: =V28*V44/1000 -> 448.30948 | W12: =W28*W44/1000 -> 478.84537 | ... AA12: =AA28*AA44/1000 -> 601.66871 | AB12: =SUM(P12:AA12) -> 5257.8429
B13: Пакет на 6 месяцев | C13: =C29*C45/1000 -> 0 | D13: =D29*D45/1000 -> 13.333333 | E13: =E29*E45/1000 -> 26.893333 | F13: =F29*F45/1000 -> 40.683853 | G13: =G29*G45/1000 -> 54.708812 | H13: =H29*H45/1000 -> 68.972195 | I13: =I29*I45/1000 -> 83.913232 | J13: =J29*J45/1000 -> 99.564117 | ... N13: =N29*N45/1000 -> 162.51608 | O13: =SUM(C13:N13) -> 944.495 | P13: =P29*P45/1000 -> 178.56587 | Q13: =Q29*Q45/1000 -> 194.8885 | R13: =R29*R45/1000 -> 211.48861 | S13: =S29*S45/1000 -> 228.37093 | T13: =T29*T45/1000 -> 245.54025 | U13: =U29*U45/1000 -> 263.00144 | V13: =V29*V45/1000 -> 281.29222 | W13: =W29*W45/1000 -> 300.45199 | ... AA13: =AA29*AA45/1000 -> 377.51762 | AB13: =SUM(P13:AA13) -> 3299.0387
B14: Пакет на 12 месяцев | C14: =C30*C46/1000 -> 0 | D14: =D30*D46/1000 -> 3.75 | E14: =E30*E46/1000 -> 7.56375 | F14: =F30*F46/1000 -> 11.442334 | G14: =G30*G46/1000 -> 15.386853 | H14: =H30*H46/1000 -> 19.39843 | I14: =I30*I46/1000 -> 23.600596 | J14: =J30*J46/1000 -> 28.002408 | ... N14: =N30*N46/1000 -> 45.707648 | O14: =SUM(C14:N14) -> 265.63922 | P14: =P30*P46/1000 -> 50.22165 | Q14: =Q30*Q46/1000 -> 54.81239 | R14: =R30*R46/1000 -> 59.481173 | S14: =S30*S46/1000 -> 64.229324 | T14: =T30*T46/1000 -> 69.058195 | U14: =U30*U46/1000 -> 73.969156 | V14: =V30*V46/1000 -> 79.113437 | W14: =W30*W46/1000 -> 84.502123 | ... AA14: =AA30*AA46/1000 -> 106.17683 | AB14: =SUM(P14:AA14) -> 927.85462
B15: Education | C15: =SUM(C16:C20) -> 183.66667 | D15: =SUM(D16:D20) -> 371.00667 | E15: =SUM(E16:E20) -> 562.09347 | F15: =SUM(F16:F20) -> 757.002 | G15: =SUM(G16:G20) -> 955.80871 | H15: =SUM(H16:H20) -> 1164.5558 | I15: =SUM(I16:I20) -> 1383.7401 | J15: =SUM(J16:J20) -> 1613.8838 | ... N15: =SUM(N16:N20) -> 2500.8323 | O15: =SUM(C15:N15) -> 15642.711 | P15: =SUM(P16:P20) -> 2550.0993 | Q15: =SUM(Q16:Q20) -> 2600.3518 | R15: =SUM(R16:R20) -> 2651.6092 | S15: =SUM(S16:S20) -> 2703.8918 | T15: =SUM(T16:T20) -> 2757.2201 | U15: =SUM(U16:U20) -> 2813.2148 | V15: =SUM(V16:V20) -> 2872.0092 | W15: =SUM(W16:W20) -> 2933.7433 | ... AA15: =SUM(AA16:AA20) -> 3171.66 | AB15: =SUM(P15:AA15) -> 34206.016
B16: Фритрек | C16: =C32*C48/1000 -> 0 | D16: 0 | E16: 0 | F16: 0 | G16: 0 | H16: 0 | I16: 0 | J16: 0 | K16: 0 | L16: 0 | M16: 0 | N16: 0 | O16: =SUM(C16:N16) -> 0 | P16: =P32*P48/1000 -> 0 | Q16: =Q32*Q48/1000 -> 0 | R16: =R32*R48/1000 -> 0 | S16: =S32*S48/1000 -> 0 | T16: =T32*T48/1000 -> 0 | U16: =U32*U48/1000 -> 0 | V16: =V32*V48/1000 -> 0 | W16: =W32*W48/1000 -> 0 | ... AA16: =AA32*AA48/1000 -> 0 | AB16: =SUM(P16:AA16) -> 0
B17: Полная оплата курса | C17: =C33*C49/1000 -> 10 | D17: =D33*D49/1000 -> 20.2 | E17: =E33*E49/1000 -> 30.604 | F17: =F33*F49/1000 -> 41.21608 | G17: =G33*G49/1000 -> 52.040402 | H17: =H33*H49/1000 -> 63.405939 | I17: =I33*I49/1000 -> 75.339754 | J17: =J33*J49/1000 -> 87.870259 | ... N17: =N33*N49/1000 -> 136.16147 | O17: =SUM(C17:N17) -> 851.69025 | P17: =P33*P49/1000 -> 138.84388 | Q17: =Q33*Q49/1000 -> 141.57995 | R17: =R33*R49/1000 -> 144.37074 | S17: =S33*S49/1000 -> 147.21734 | T17: =T33*T49/1000 -> 150.12088 | U17: =U33*U49/1000 -> 153.16959 | V17: =V33*V49/1000 -> 156.37074 | W17: =W33*W49/1000 -> 159.73194 | ... AA17: =AA33*AA49/1000 -> 172.68566 | AB17: =SUM(P17:AA17) -> 1862.3965
B18: Оплата курса 2 траншами | C18: =C34*C50/1000 -> 36.666667 | D18: =D34*D50/1000 -> 74.066667 | E18: =E34*E50/1000 -> 112.21467 | F18: =F34*F50/1000 -> 151.12563 | G18: =G34*G50/1000 -> 190.81481 | H18: =H34*H50/1000 -> 232.48844 | I18: =I34*I50/1000 -> 276.24576 | J18: =J34*J50/1000 -> 322.19095 | ... N18: =N34*N50/1000 -> 499.25871 | O18: =SUM(C18:N18) -> 3122.8643 | P18: =P34*P50/1000 -> 509.09424 | Q18: =Q34*Q50/1000 -> 519.12648 | R18: =R34*R50/1000 -> 529.35937 | S18: =S34*S50/1000 -> 539.79692 | T18: =T34*T50/1000 -> 550.44321 | U18: =U34*U50/1000 -> 561.62183 | V18: =V34*V50/1000 -> 573.35937 | W18: =W34*W50/1000 -> 585.68379 | ... AA18: =AA34*AA50/1000 -> 633.18076 | AB18: =SUM(P18:AA18) -> 6828.7872
B19: Оплата курса 3 траншами | C19: =C35*C51/1000 -> 57 | D19: =D35*D51/1000 -> 115.14 | E19: =E35*E51/1000 -> 174.4428 | F19: =F35*F51/1000 -> 234.93166 | G19: =G35*G51/1000 -> 296.63029 | H19: =H35*H51/1000 -> 361.41385 | I19: =I35*I51/1000 -> 429.4366 | J19: =J35*J51/1000 -> 500.86048 | ... N19: =N35*N51/1000 -> 776.12036 | O19: =SUM(C19:N19) -> 4854.6344 | P19: =P35*P51/1000 -> 791.41014 | Q19: =Q35*Q51/1000 -> 807.00572 | R19: =R35*R51/1000 -> 822.91321 | S19: =S35*S51/1000 -> 839.13884 | T19: =T35*T51/1000 -> 855.689 | U19: =U35*U51/1000 -> 873.06666 | V19: =V35*V51/1000 -> 891.3132 | W19: =W35*W51/1000 -> 910.47207 | ... AA19: =AA35*AA51/1000 -> 984.30827 | AB19: =SUM(P19:AA19) -> 10615.66
B20: Оплата курса помесячно | C20: =C36*C52/1000 -> 80 | D20: =D36*D52/1000 -> 161.6 | E20: =E36*E52/1000 -> 244.832 | F20: =F36*F52/1000 -> 329.72864 | G20: =G36*G52/1000 -> 416.32321 | H20: =H36*H52/1000 -> 507.24751 | I20: =I36*I52/1000 -> 602.71803 | J20: =J36*J52/1000 -> 702.96207 | ... N20: =N36*N52/1000 -> 1089.2917 | O20: =SUM(C20:N20) -> 6813.522 | P20: =P36*P52/1000 -> 1110.7511 | Q20: =Q36*Q52/1000 -> 1132.6396 | R20: =R36*R52/1000 -> 1154.9659 | S20: =S36*S52/1000 -> 1177.7387 | T20: =T36*T52/1000 -> 1200.967 | U20: =U36*U52/1000 -> 1225.3567 | V20: =V36*V52/1000 -> 1250.9659 | W20: =W36*W52/1000 -> 1277.8555 | ... AA20: =AA36*AA52/1000 -> 1381.4853 | AB20: =SUM(P20:AA20) -> 14899.172
B22: Таблица 10.1. Количество пользователей, чел. | AD22: - Лояльность клиентов 100% (купленные подписки всегда продлеваются, все студенты проходят полный курс обучения) - Стоимость подписки ближайшие два года без повышения | AF22: Нет | AG22: =IF(AF22="Нет", " ", "Начните с заполнения информации о количестве новых пользователей в первый месяц - новые пользователи начнут с бесплатных версий продуктов: первого месяца подписки на комьюнити и фритрека в обучении")
C23: янв.26 | D23: фев.26 | E23: мар.26 | F23: апр.26 | G23: 46143 | H23: июн.26 | I23: июл.26 | J23: авг.26 | K23: сент.26 | L23: окт.26 | M23: ноя.26 | N23: дек.26 | O23: 2026 | P23: янв.27 | Q23: фев.27 | R23: мар.27 | S23: апр.27 | T23: 46508 | U23: июн.27 | V23: июл.27 | W23: авг.27 | X23: сент.27 | Y23: окт.27 | Z23: ноя.27 | AA23: дек.27 | AB23: 2027 | AF23: Нет | AG23: =IF(AF23="Нет", " ", "Посчитайте прогнозное количество пользователей по бесплатным продуктам с учётом коэффициента ежемесячного прироста и сезонного прироста в летние месяцы")
B25: Community | AF25: Нет | AG25: =IF(AF25="Нет", " ", "Посчитайте прогнозное количество пользователей по платным продуктам с учётом уровня проникновения продаж")
B26: Первый месяц | C26: 500 | D26: =C26*(1+'Аналитика'!$H$5) -> 508.5 | E26: =D26*(1+'Аналитика'!$H$5) -> 517.1445 | F26: =E26*(1+'Аналитика'!$H$5) -> 525.93596 | G26: =F26*(1+'Аналитика'!$H$5) -> 534.87687 | H26: =G26*(1+'Аналитика'!$H$5)*(1+'Аналитика'!$H$7) -> 560.28887 | I26: =H26*(1+'Аналитика'!$H$5)*(1+'Аналитика'!$H$7) -> 586.90819 | J26: =I26*(1+'Аналитика'!$H$5)*(1+'Аналитика'!$H$7) -> 614.7922 | K26: =G26*(1+'Аналитика'!$H$5)^4 -> 572.18653 | L26: =K26*(1+'Аналитика'!$H$5) -> 581.9137 | M26: =L26*(1+'Аналитика'!$H$5) -> 591.80623 | N26: =M26*(1+'Аналитика'!$H$5) -> 601.86694 | O26: =N26 -> 601.86694 | P26: =N26*(1+'Аналитика'!H5) -> 612.09867 | Q26: =P26*(1+'Аналитика'!$H$5) -> 622.50435 | R26: =Q26*(1+'Аналитика'!$H$5) -> 633.08693 | S26: =R26*(1+'Аналитика'!$H$5) -> 643.8494 | T26: =S26*(1+'Аналитика'!$H$5) -> 654.79484 | U26: =T26*(1+'Аналитика'!$H$5)*(1+'Аналитика'!$H$7) -> 685.90415 | V26: =U26*(1+'Аналитика'!$H$5)*(1+'Аналитика'!$H$7) -> 718.49145 | W26: =V26*(1+'Аналитика'!$H$5)*(1+'Аналитика'!$H$7) -> 752.62698 | X26: =T26*(1+'Аналитика'!$H$5)^4 -> 700.46923 | Y26: =X26*(1+'Аналитика'!$H$5) -> 712.37721 | Z26: =Y26*(1+'Аналитика'!$H$5) -> 724.48762 | AA26: =Z26*(1+'Аналитика'!$H$5) -> 736.80391 | AB26: =AA26 -> 736.80391 | AF26: Нет | AG26: =IF(AF26="Нет", " ", "Уровень проникновения продаж необходимо применять к количеству пользователей на бесплатных продуктах")
B27: Подписка на месяц | C27: 0 | D27: =C26*'Аналитика'!$H$11 -> 100 | E27: =D26*'Аналитика'!$H$11+D27 -> 201.7 | F27: =E26*'Аналитика'!$H$11+E27 -> 305.1289 | G27: =F26*'Аналитика'!$H$11+F27 -> 410.31609 | H27: =G26*'Аналитика'!$H$11+G27 -> 517.29146 | I27: =H26*'Аналитика'!$H$11+H27 -> 629.34924 | J27: =I26*'Аналитика'!$H$11+I27 -> 746.73088 | K27: =J26*'Аналитика'!$H$11+J27 -> 869.68932 | L27: =K26*'Аналитика'!$H$11+K27 -> 984.12662 | ... N27: =M26*'Аналитика'!$H$11+M27 -> 1218.8706 | O27: =N27 -> 1218.8706 | P27: =N26*'Аналитика'!$H$11+'Расчёты'!N27 -> 1339.244 | Q27: =P26*'Аналитика'!$H$11+'Расчёты'!P27 -> 1461.6637 | R27: =Q26*'Аналитика'!$H$11+'Расчёты'!Q27 -> 1586.1646 | S27: =R26*'Аналитика'!$H$11+'Расчёты'!R27 -> 1712.782 | T27: =S26*'Аналитика'!$H$11+'Расчёты'!S27 -> 1841.5519 | U27: =T26*'Аналитика'!$H$11+'Расчёты'!T27 -> 1972.5108 | V27: =U26*'Аналитика'!$H$11+'Расчёты'!U27 -> 2109.6917 | W27: =V26*'Аналитика'!$H$11+'Расчёты'!V27 -> 2253.39 | X27: =W26*'Аналитика'!$H$11+'Расчёты'!W27 -> 2403.9154 | ... AA27: =Z26*'Аналитика'!$H$11+'Расчёты'!Z27 -> 2831.3822 | AB27: =AA27 -> 2831.3822 | AF27: Нет | AG27: =IF(AF27="Нет", " ", "При расчёте участников сообщества учтите лаг в 1 месяц бесплатного пользования (пример: пользователи в феврале=пользоватали на пакете первого месяца в январе * уровень проникновения продаж)")
B28: Пакет на 3 месяца | C28: 0 | D28: =C26*'Аналитика'!$H$12 -> 75 | E28: =D26*'Аналитика'!$H$12+'Расчёты'!D28 -> 151.275 | F28: =E26*'Аналитика'!$H$12+'Расчёты'!E28 -> 228.84668 | G28: =F26*'Аналитика'!$H$12+'Расчёты'!F28 -> 307.73707 | H28: =G26*'Аналитика'!$H$12+'Расчёты'!G28 -> 387.9686 | I28: =H26*'Аналитика'!$H$12+'Расчёты'!H28 -> 472.01193 | J28: =I26*'Аналитика'!$H$12+'Расчёты'!I28 -> 560.04816 | K28: =J26*'Аналитика'!$H$12+'Расчёты'!J28 -> 652.26699 | L28: =K26*'Аналитика'!$H$12+'Расчёты'!K28 -> 738.09497 | ... N28: =M26*'Аналитика'!$H$12+'Расчёты'!M28 -> 914.15296 | O28: =N28 -> 914.15296 | P28: =N26*'Аналитика'!$H$12+'Расчёты'!N28 -> 1004.433 | Q28: =P26*'Аналитика'!$H$12+'Расчёты'!P28 -> 1096.2478 | R28: =Q26*'Аналитика'!$H$12+'Расчёты'!Q28 -> 1189.6235 | S28: =R26*'Аналитика'!$H$12+'Расчёты'!R28 -> 1284.5865 | T28: =S26*'Аналитика'!$H$12+'Расчёты'!S28 -> 1381.1639 | U28: =T26*'Аналитика'!$H$12+'Расчёты'!T28 -> 1479.3831 | V28: =U26*'Аналитика'!$H$12+'Расчёты'!U28 -> 1582.2687 | W28: =V26*'Аналитика'!$H$12+'Расчёты'!V28 -> 1690.0425 | X28: =W26*'Аналитика'!$H$12+'Расчёты'!W28 -> 1802.9365 | ... AA28: =Z26*'Аналитика'!$H$12+'Расчёты'!Z28 -> 2123.5366 | AB28: =AA28 -> 2123.5366 | AF28: Нет | AG28: =IF(AF28="Нет", " ", "Поскольку мы сделали допущение, что клиенты лояльны 100% - к клиентам текущего месяца необходимо прибавлять клиентов предыдущего месяца")
B29: Пакет на 6 месяцев | C29: 0 | D29: =C26*'Аналитика'!H13 -> 50 | E29: =D26*'Аналитика'!$H$13+'Расчёты'!D29 -> 100.85 | F29: =E26*'Аналитика'!$H$13+'Расчёты'!E29 -> 152.56445 | G29: =F26*'Аналитика'!$H$13+'Расчёты'!F29 -> 205.15805 | H29: =G26*'Аналитика'!$H$13+'Расчёты'!G29 -> 258.64573 | I29: =H26*'Аналитика'!$H$13+'Расчёты'!H29 -> 314.67462 | J29: =I26*'Аналитика'!$H$13+'Расчёты'!I29 -> 373.36544 | K29: =J26*'Аналитика'!$H$13+'Расчёты'!J29 -> 434.84466 | L29: =K26*'Аналитика'!$H$13+'Расчёты'!K29 -> 492.06331 | ... N29: =M26*'Аналитика'!$H$13+'Расчёты'!M29 -> 609.4353 | O29: =N29 -> 609.4353 | P29: =N26*'Аналитика'!$H$13+'Расчёты'!N29 -> 669.622 | Q29: =P26*'Аналитика'!$H$13+'Расчёты'!P29 -> 730.83187 | R29: =Q26*'Аналитика'!$H$13+'Расчёты'!Q29 -> 793.0823 | S29: =R26*'Аналитика'!$H$13+'Расчёты'!R29 -> 856.39099 | T29: =S26*'Аналитика'!$H$13+'Расчёты'!S29 -> 920.77593 | U29: =T26*'Аналитика'!$H$13+'Расчёты'!T29 -> 986.25542 | V29: =U26*'Аналитика'!$H$13+'Расчёты'!U29 -> 1054.8458 | W29: =V26*'Аналитика'!$H$13+'Расчёты'!V29 -> 1126.695 | X29: =W26*'Аналитика'!$H$13+'Расчёты'!W29 -> 1201.9577 | ... AA29: =Z26*'Аналитика'!$H$13+'Расчёты'!Z29 -> 1415.6911 | AB29: =AA29 -> 1415.6911 | AF29: Нет | AG29: =IF(AF29="Нет", " ", "Не забывайте, что образовательный курс длится 12 мес., а значит с января 2027 нужно будет вычитать выпускников, окончивших обучение (например, в январе 2027 нужно вычесть студентов января 2026)")
B30: Пакет на 12 месяцев | C30: 0 | D30: =C26*'Аналитика'!H14 -> 15 | E30: =D26*'Аналитика'!$H$14+'Расчёты'!D30 -> 30.255 | F30: =E26*'Аналитика'!$H$14+'Расчёты'!E30 -> 45.769335 | G30: =F26*'Аналитика'!$H$14+'Расчёты'!F30 -> 61.547414 | H30: =G26*'Аналитика'!$H$14+'Расчёты'!G30 -> 77.59372 | I30: =H26*'Аналитика'!$H$14+'Расчёты'!H30 -> 94.402386 | J30: =I26*'Аналитика'!$H$14+'Расчёты'!I30 -> 112.00963 | K30: =J26*'Аналитика'!$H$14+'Расчёты'!J30 -> 130.4534 | L30: =K26*'Аналитика'!$H$14+'Расчёты'!K30 -> 147.61899 | ... N30: =M26*'Аналитика'!$H$14+'Расчёты'!M30 -> 182.83059 | O30: =N30 -> 182.83059 | P30: =N26*'Аналитика'!$H$14+'Расчёты'!N30 -> 200.8866 | Q30: =P26*'Аналитика'!$H$14+'Расчёты'!P30 -> 219.24956 | R30: =Q26*'Аналитика'!$H$14+'Расчёты'!Q30 -> 237.92469 | S30: =R26*'Аналитика'!$H$14+'Расчёты'!R30 -> 256.9173 | T30: =S26*'Аналитика'!$H$14+'Расчёты'!S30 -> 276.23278 | U30: =T26*'Аналитика'!$H$14+'Расчёты'!T30 -> 295.87663 | V30: =U26*'Аналитика'!$H$14+'Расчёты'!U30 -> 316.45375 | W30: =V26*'Аналитика'!$H$14+'Расчёты'!V30 -> 338.00849 | X30: =W26*'Аналитика'!$H$14+'Расчёты'!W30 -> 360.5873 | ... AA30: =Z26*'Аналитика'!$H$14+'Расчёты'!Z30 -> 424.70732 | AB30: =AA30 -> 424.70732
B31: Education
B32: Фритрек | C32: 40 | D32: =C32*(1+'Аналитика'!$I$5) -> 40.8 | E32: =D32*(1+'Аналитика'!$I$5) -> 41.616 | F32: =E32*(1+'Аналитика'!$I$5) -> 42.44832 | G32: =F32*(1+'Аналитика'!$I$5) -> 43.297286 | H32: =G32*(1+'Аналитика'!$I$5+'Аналитика'!$I$7) -> 45.462151 | I32: =H32*(1+'Аналитика'!$I$5+'Аналитика'!$I$7) -> 47.735258 | J32: =I32*(1+'Аналитика'!$I$5+'Аналитика'!$I$7) -> 50.122021 | K32: =G32*(1+'Аналитика'!$I$5)^4 -> 46.866375 | L32: =K32*(1+'Аналитика'!$I$5) -> 47.803703 | M32: =L32*(1+'Аналитика'!$I$5) -> 48.759777 | N32: =M32*(1+'Аналитика'!$I$5) -> 49.734972 | O32: =N32 -> 49.734972 | P32: =N32*(1+'Аналитика'!$I$5) -> 50.729672 | Q32: =P32*(1+'Аналитика'!$I$5) -> 51.744265 | R32: =Q32*(1+'Аналитика'!$I$5) -> 52.779151 | S32: =R32*(1+'Аналитика'!$I$5) -> 53.834734 | T32: =S32*(1+'Аналитика'!$I$5) -> 54.911428 | U32: =T32*(1+'Аналитика'!$I$5+'Аналитика'!$I$7) -> 57.657 | V32: =U32*(1+'Аналитика'!$I$5+'Аналитика'!$I$7) -> 60.53985 | W32: =V32*(1+'Аналитика'!$I$5+'Аналитика'!$I$7) -> 63.566842 | X32: =T32*(1+'Аналитика'!I5)^4 -> 59.437896 | Y32: =X32*(1+'Аналитика'!$I$5) -> 60.626654 | Z32: =Y32*(1+'Аналитика'!$I$5) -> 61.839187 | AA32: =Z32*(1+'Аналитика'!$I$5) -> 63.075971 | AB32: =AA32 -> 63.075971
B33: Полная оплата курса | C33: =C32*'Аналитика'!$J$11 -> 1.2 | D33: =C33+D32*'Аналитика'!$J$11 -> 2.424 | E33: =D33+E32*'Аналитика'!$J$11 -> 3.67248 | F33: =E33+F32*'Аналитика'!$J$11 -> 4.9459296 | G33: =F33+G32*'Аналитика'!$J$11 -> 6.2448482 | H33: =G33+H32*'Аналитика'!$J$11 -> 7.6087127 | I33: =H33+I32*'Аналитика'!$J$11 -> 9.0407705 | J33: =I33+J32*'Аналитика'!$J$11 -> 10.544431 | K33: =J33+K32*'Аналитика'!$J$11 -> 11.950422 | ... N33: =M33+N32*'Аналитика'!$J$11 -> 16.339376 | O33: =N33 -> 16.339376 | P33: =N33+P32*'Аналитика'!$J$11-C33 -> 16.661266 | Q33: =P33+Q32*'Аналитика'!$J$11-('Расчёты'!D33-'Расчёты'!C33) -> 16.989594 | R33: =Q33+R32*'Аналитика'!$J$11-('Расчёты'!E33-'Расчёты'!D33) -> 17.324489 | S33: =R33+S32*'Аналитика'!$J$11-('Расчёты'!F33-'Расчёты'!E33) -> 17.666081 | T33: =S33+T32*'Аналитика'!$J$11-('Расчёты'!G33-'Расчёты'!F33) -> 18.014505 | U33: =T33+U32*'Аналитика'!$J$11-('Расчёты'!H33-'Расчёты'!G33) -> 18.380351 | V33: =U33+V32*'Аналитика'!$J$11-('Расчёты'!I33-'Расчёты'!H33) -> 18.764488 | W33: =V33+W32*'Аналитика'!$J$11-('Расчёты'!J33-'Расчёты'!I33) -> 19.167833 | X33: =W33+X32*'Аналитика'!$J$11-('Расчёты'!K33-'Расчёты'!J33) -> 19.544979 | ... AA33: =Z33+AA32*'Аналитика'!$J$11-('Расчёты'!N33-'Расчёты'!M33) -> 20.722279 | AB33: =AA33 -> 20.722279
B34: Оплата курса 2 траншами | C34: =C32*'Аналитика'!J12 -> 4 | D34: =C34+D32*'Аналитика'!$J$12 -> 8.08 | E34: =D34+E32*'Аналитика'!$J$12 -> 12.2416 | F34: =E34+F32*'Аналитика'!$J$12 -> 16.486432 | G34: =F34+G32*'Аналитика'!$J$12 -> 20.816161 | H34: =G34+H32*'Аналитика'!$J$12 -> 25.362376 | I34: =H34+I32*'Аналитика'!$J$12 -> 30.135902 | J34: =I34+J32*'Аналитика'!$J$12 -> 35.148104 | K34: =J34+K32*'Аналитика'!$J$12 -> 39.834741 | ... N34: =M34+N32*'Аналитика'!$J$12 -> 54.464586 | O34: =N34 -> 54.464586 | P34: =N34+P32*'Аналитика'!$J$12-C34 -> 55.537554 | Q34: =P34+Q32*'Аналитика'!$J$12-('Расчёты'!D34-'Расчёты'!C34) -> 56.63198 | R34: =Q34+R32*'Аналитика'!$J$12-('Расчёты'!E34-'Расчёты'!D34) -> 57.748295 | S34: =R34+S32*'Аналитика'!$J$12-('Расчёты'!F34-'Расчёты'!E34) -> 58.886936 | T34: =S34+T32*'Аналитика'!$J$12-('Расчёты'!G34-'Расчёты'!F34) -> 60.048351 | U34: =T34+U32*'Аналитика'!$J$12-('Расчёты'!H34-'Расчёты'!G34) -> 61.267836 | V34: =U34+V32*'Аналитика'!$J$12-('Расчёты'!I34-'Расчёты'!H34) -> 62.548295 | W34: =V34+W32*'Аналитика'!$J$12-('Расчёты'!J34-'Расчёты'!I34) -> 63.892777 | X34: =W34+X32*'Аналитика'!$J$12-('Расчёты'!K34-'Расчёты'!J34) -> 65.149929 | ... AA34: =Z34+AA32*'Аналитика'!$J$12-('Расчёты'!N34-'Расчёты'!M34) -> 69.074265 | AB34: =AA34 -> 69.074265
B35: Оплата курса 3 траншами | C35: =C32*'Аналитика'!J13 -> 6 | D35: =C35+D32*'Аналитика'!$J$13 -> 12.12 | E35: =D35+E32*'Аналитика'!$J$13 -> 18.3624 | F35: =E35+F32*'Аналитика'!$J$13 -> 24.729648 | G35: =F35+G32*'Аналитика'!$J$13 -> 31.224241 | H35: =G35+H32*'Аналитика'!$J$13 -> 38.043564 | I35: =H35+I32*'Аналитика'!$J$13 -> 45.203852 | J35: =I35+J32*'Аналитика'!$J$13 -> 52.722155 | K35: =J35+K32*'Аналитика'!$J$13 -> 59.752112 | ... N35: =M35+N32*'Аналитика'!$J$13 -> 81.69688 | O35: =N35 -> 81.69688 | P35: =N35+P32*'Аналитика'!$J$13-'Расчёты'!C35 -> 83.30633 | Q35: =P35+Q32*'Аналитика'!$J$13-('Расчёты'!D35-'Расчёты'!C35) -> 84.94797 | R35: =Q35+R32*'Аналитика'!$J$13-('Расчёты'!E35-'Расчёты'!D35) -> 86.622443 | S35: =R35+S32*'Аналитика'!$J$13-('Расчёты'!F35-'Расчёты'!E35) -> 88.330405 | T35: =S35+T32*'Аналитика'!$J$13-('Расчёты'!G35-'Расчёты'!F35) -> 90.072526 | U35: =T35+U32*'Аналитика'!$J$13-('Расчёты'!H35-'Расчёты'!G35) -> 91.901753 | V35: =U35+V32*'Аналитика'!$J$13-('Расчёты'!I35-'Расчёты'!H35) -> 93.822442 | W35: =V35+W32*'Аналитика'!$J$13-('Расчёты'!J35-'Расчёты'!I35) -> 95.839165 | X35: =W35+X32*'Аналитика'!$J$13-('Расчёты'!K35-'Расчёты'!J35) -> 97.724893 | ... AA35: =Z35+AA32*'Аналитика'!$J$13-('Расчёты'!N35-'Расчёты'!M35) -> 103.6114 | AB35: =AA35 -> 103.6114
B36: Оплата курса помесячно | C36: =C32*'Аналитика'!J14 -> 8 | D36: =C36+D32*'Аналитика'!$J$14 -> 16.16 | E36: =D36+E32*'Аналитика'!$J$14 -> 24.4832 | F36: =E36+F32*'Аналитика'!$J$14 -> 32.972864 | G36: =F36+G32*'Аналитика'!$J$14 -> 41.632321 | H36: =G36+H32*'Аналитика'!$J$14 -> 50.724751 | I36: =H36+I32*'Аналитика'!$J$14 -> 60.271803 | J36: =I36+J32*'Аналитика'!$J$14 -> 70.296207 | K36: =J36+K32*'Аналитика'!$J$14 -> 79.669482 | ... N36: =M36+N32*'Аналитика'!$J$14 -> 108.92917 | O36: =N36 -> 108.92917 | P36: =N36+P32*'Аналитика'!$J$14-C36 -> 111.07511 | Q36: =P36+Q32*'Аналитика'!$J$14-('Расчёты'!D36-'Расчёты'!C36) -> 113.26396 | R36: =Q36+R32*'Аналитика'!$J$14-('Расчёты'!E36-'Расчёты'!D36) -> 115.49659 | S36: =R36+S32*'Аналитика'!$J$14-('Расчёты'!F36-'Расчёты'!E36) -> 117.77387 | T36: =S36+T32*'Аналитика'!$J$14-('Расчёты'!G36-'Расчёты'!F36) -> 120.0967 | U36: =T36+U32*'Аналитика'!$J$14-('Расчёты'!H36-'Расчёты'!G36) -> 122.53567 | V36: =U36+V32*'Аналитика'!$J$14-('Расчёты'!I36-'Расчёты'!H36) -> 125.09659 | W36: =V36+W32*'Аналитика'!$J$14-('Расчёты'!J36-'Расчёты'!I36) -> 127.78555 | X36: =W36+X32*'Аналитика'!$J$14-('Расчёты'!K36-'Расчёты'!J36) -> 130.29986 | ... AA36: =Z36+AA32*'Аналитика'!$J$14-('Расчёты'!N36-'Расчёты'!M36) -> 138.14853 | AB36: =AA36 -> 138.14853
B38: Таблица 10.2. Стоимость подписки в мес., руб. | AF38: Нет | AG38: =IF(AF38="Нет", " ", "Для каждого вида оплаты нужно рассчитать месячную стоимость (например, стоимость пакета на 3 месяца нужно разделить на 3, а оплату курса 2 траншами - на 12)")
C39: янв.26 | D39: фев.26 | E39: мар.26 | F39: апр.26 | G39: 46143 | H39: июн.26 | I39: июл.26 | J39: авг.26 | K39: сент.26 | L39: окт.26 | M39: ноя.26 | N39: дек.26 | O39: 2026 | P39: янв.27 | Q39: фев.27 | R39: мар.27 | S39: апр.27 | T39: 46508 | U39: июн.27 | V39: июл.27 | W39: авг.27 | X39: сент.27 | Y39: окт.27 | Z39: ноя.27 | AA39: дек.27 | AB39: 2027
B41: Community
B42: Первый месяц | C42: 0 | D42: 0 | E42: 0 | F42: 0 | G42: 0 | H42: 0 | I42: 0 | J42: 0 | K42: 0 | L42: 0 | M42: 0 | N42: 0 | O42: 0 | P42: 0 | Q42: 0 | R42: 0 | S42: 0 | T42: 0 | U42: 0 | V42: 0 | W42: 0 | X42: 0 | Y42: 0 | Z42: 0 | AA42: 0 | AB42: =AA42 -> 0
B43: Подписка на месяц | C43: ='Аналитика'!C5 -> 300 | D43: 300 | E43: 300 | F43: 300 | G43: 300 | H43: 300 | I43: 300 | J43: 300 | K43: 300 | L43: 300 | M43: 300 | N43: 300 | O43: 300 | P43: 300 | Q43: 300 | R43: 300 | S43: 300 | T43: 300 | U43: 300 | V43: 300 | W43: 300 | X43: 300 | Y43: 300 | Z43: 300 | AA43: 300 | AB43: 300
B44: Пакет на 3 месяца | C44: ='Аналитика'!$C$6/3 -> 283.33333 | D44: 283.33333 | E44: 283.33333 | F44: 283.33333 | G44: 283.33333 | H44: 283.33333 | I44: 283.33333 | J44: 283.33333 | K44: 283.33333 | L44: 283.33333 | M44: 283.33333 | N44: 283.33333 | O44: 283.33333 | P44: 283.33333 | Q44: 283.33333 | R44: 283.33333 | S44: 283.33333 | T44: 283.33333 | U44: 283.33333 | V44: 283.33333 | W44: 283.33333 | X44: 283.33333 | Y44: 283.33333 | Z44: 283.33333 | AA44: 283.33333 | AB44: 283
B45: Пакет на 6 месяцев | C45: ='Аналитика'!$C$7/6 -> 266.66667 | D45: 266.66667 | E45: 266.66667 | F45: 266.66667 | G45: 266.66667 | H45: 266.66667 | I45: 266.66667 | J45: 266.66667 | K45: 266.66667 | L45: 266.66667 | M45: 266.66667 | N45: 266.66667 | O45: 266.66667 | P45: 266.66667 | Q45: 266.66667 | R45: 266.66667 | S45: 266.66667 | T45: 266.66667 | U45: 266.66667 | V45: 266.66667 | W45: 266.66667 | X45: 266.66667 | Y45: 266.66667 | Z45: 266.66667 | AA45: 266.66667 | AB45: 266.66667
B46: Пакет на 12 месяцев | C46: ='Аналитика'!$C$8/12 -> 250 | D46: 250 | E46: 250 | F46: 250 | G46: 250 | H46: 250 | I46: 250 | J46: 250 | K46: 250 | L46: 250 | M46: 250 | N46: 250 | O46: 250 | P46: 250 | Q46: 250 | R46: 250 | S46: 250 | T46: 250 | U46: 250 | V46: 250 | W46: 250 | X46: 250 | Y46: 250 | Z46: 250 | AA46: 250 | AB46: 250
B47: Education
B48: Фритрек | C48: 0 | D48: 0 | E48: 0 | F48: 0 | G48: 0 | H48: 0 | I48: 0 | J48: 0 | K48: 0 | L48: 0 | M48: 0 | N48: 0 | O48: 0 | P48: 0 | Q48: 0 | R48: 0 | S48: 0 | T48: 0 | U48: 0 | V48: 0 | W48: 0 | X48: 0 | Y48: 0 | Z48: 0 | AA48: 0 | AB48: 0
B49: Полная оплата курса | C49: ='Аналитика'!$E$5/12 -> 8333.3333 | D49: 8333.3333 | E49: 8333.3333 | F49: 8333.3333 | G49: 8333.3333 | H49: 8333.3333 | I49: 8333.3333 | J49: 8333.3333 | K49: 8333.3333 | L49: 8333.3333 | M49: 8333.3333 | N49: 8333.3333 | O49: =N49 -> 8333.3333 | P49: 8333.3333 | Q49: 8333.3333 | R49: 8333.3333 | S49: 8333.3333 | T49: 8333.3333 | U49: 8333.3333 | V49: 8333.3333 | W49: 8333.3333 | X49: 8333.3333 | Y49: 8333.3333 | Z49: 8333.3333 | AA49: 8333.3333 | AB49: =AA49 -> 8333.3333
B50: Оплата курса 2 траншами | C50: ='Аналитика'!$E$6/12 -> 9166.6667 | D50: 9166.6667 | E50: 9166.6667 | F50: 9166.6667 | G50: 9166.6667 | H50: 9166.6667 | I50: 9166.6667 | J50: 9166.6667 | K50: 9166.6667 | L50: 9166.6667 | M50: 9166.6667 | N50: 9166.6667 | O50: 9166.6667 | P50: 9166.6667 | Q50: 9166.6667 | R50: 9166.6667 | S50: 9166.6667 | T50: 9166.6667 | U50: 9166.6667 | V50: 9166.6667 | W50: 9166.6667 | X50: 9166.6667 | Y50: 9166.6667 | Z50: 9166.6667 | AA50: 9166.6667 | AB50: 9166.6667
B51: Оплата курса 3 траншами | C51: ='Аналитика'!$E$7/12 -> 9500 | D51: 9500 | E51: 9500 | F51: 9500 | G51: 9500 | H51: 9500 | I51: 9500 | J51: 9500 | K51: 9500 | L51: 9500 | M51: 9500 | N51: 9500 | O51: =N51 -> 9500 | P51: 9500 | Q51: 9500 | R51: 9500 | S51: 9500 | T51: 9500 | U51: 9500 | V51: 9500 | W51: 9500 | X51: 9500 | Y51: 9500 | Z51: 9500 | AA51: 9500 | AB51: =AA51 -> 9500
B52: Оплата курса помесячно | C52: ='Аналитика'!$E$8/12 -> 10000 | D52: 10000 | E52: 10000 | F52: 10000 | G52: 10000 | H52: 10000 | I52: 10000 | J52: 10000 | K52: 10000 | L52: 10000 | M52: 10000 | N52: 10000 | O52: =N52 -> 10000 | P52: 10000 | Q52: 10000 | R52: 10000 | S52: 10000 | T52: 10000 | U52: 10000 | V52: 10000 | W52: 10000 | X52: 10000 | Y52: 10000 | Z52: 10000 | AA52: 10000 | AB52: =AA52 -> 10000
B54: Таблица 11. Расходы на аутсорс-разработку «под ключ», тыс. руб. | AD54: - Стоимость разработки распределена на 2 года (на период выхода в «0») | AF54: Нет | AG54: =IF(AF54="Нет", " ", "Чтобы распределить стоимость разработки на 2 года, нужно её поделить на 24 месяца")
C55: янв.26 | D55: фев.26 | E55: мар.26 | F55: апр.26 | G55: 46143 | H55: июн.26 | I55: июл.26 | J55: авг.26 | K55: сент.26 | L55: окт.26 | M55: ноя.26 | N55: дек.26 | O55: 2026 | P55: янв.27 | Q55: фев.27 | R55: мар.27 | S55: апр.27 | T55: 46508 | U55: июн.27 | V55: июл.27 | W55: авг.27 | X55: сент.27 | Y55: окт.27 | Z55: ноя.27 | AA55: дек.27 | AB55: 2027
B57: Community | C57: ='Аналитика'!$C$12/24 -> 333.33333 | D57: 333.33333 | E57: 333.33333 | F57: 333.33333 | G57: 333.33333 | H57: 333.33333 | I57: 333.33333 | J57: 333.33333 | K57: 333.33333 | L57: 333.33333 | M57: 333.33333 | N57: 333.33333 | O57: =SUM(C57:N57) -> 4000 | P57: ='Аналитика'!$C$12/24 -> 333.33333 | Q57: 333.33333 | R57: 333.33333 | S57: 333.33333 | T57: 333.33333 | U57: 333.33333 | V57: 333.33333 | W57: 333.33333 | X57: 333.33333 | Y57: 333.33333 | Z57: 333.33333 | AA57: 333.33333 | AB57: =SUM(P57:AA57) -> 4000
B58: Education | C58: ='Аналитика'!$C$13/24 -> 250 | D58: 250 | E58: 250 | F58: 250 | G58: 250 | H58: 250 | I58: 250 | J58: 250 | K58: 250 | L58: 250 | M58: 250 | N58: 250 | O58: =SUM(C58:N58) -> 3000 | P58: ='Аналитика'!$C$13/24 -> 250 | Q58: ='Аналитика'!$C$13/24 -> 250 | R58: ='Аналитика'!$C$13/24 -> 250 | S58: ='Аналитика'!$C$13/24 -> 250 | T58: ='Аналитика'!$C$13/24 -> 250 | U58: ='Аналитика'!$C$13/24 -> 250 | V58: ='Аналитика'!$C$13/24 -> 250 | W58: ='Аналитика'!$C$13/24 -> 250 | ... AA58: ='Аналитика'!$C$13/24 -> 250 | AB58: =SUM(P58:AA58) -> 3000
B60: Таблица 12. Расходы на поддерживающий персонал, тыс. руб. | AD60: - В расчёт не заложены премии (считаем, что на первоначальном этапе система премирования под вопросом) | AF60: Нет | AG60: =IF(AF60="Нет", " ", "Показатель рассчитывается по формуле (Оклад + ДМС + Страховые взносы) * Количество штатных единиц. Отпускные в расчёте не учитываются, так как оклады заложены без учёта отпусков.")
C61: янв.26 | D61: фев.26 | E61: мар.26 | F61: апр.26 | G61: 46143 | H61: июн.26 | I61: июл.26 | J61: авг.26 | K61: сент.26 | L61: окт.26 | M61: ноя.26 | N61: дек.26 | O61: 2026 | P61: янв.27 | Q61: фев.27 | R61: мар.27 | S61: апр.27 | T61: 46508 | U61: июн.27 | V61: июл.27 | W61: авг.27 | X61: сент.27 | Y61: окт.27 | Z61: ноя.27 | AA61: дек.27 | AB61: 2027
B63: Community | C63: =SUM(C64:C68) -> 504 | D63: =SUM(D64:D68) -> 504 | E63: =SUM(E64:E68) -> 504 | F63: =SUM(F64:F68) -> 504 | G63: =SUM(G64:G68) -> 504 | H63: =SUM(H64:H68) -> 504 | I63: =SUM(I64:I68) -> 504 | J63: =SUM(J64:J68) -> 504 | ... N63: =SUM(N64:N68) -> 504 | O63: =SUM(C63:N63) -> 6048 | P63: =SUM(P64:P68) -> 543.52 | Q63: =SUM(Q64:Q68) -> 543.52 | R63: =SUM(R64:R68) -> 543.52 | S63: =SUM(S64:S68) -> 543.52 | T63: =SUM(T64:T68) -> 543.52 | U63: =SUM(U64:U68) -> 543.52 | V63: =SUM(V64:V68) -> 543.52 | W63: =SUM(W64:W68) -> 543.52 | ... AA63: =SUM(AA64:AA68) -> 543.52 | AB63: =SUM(P63:AA63) -> 6522.24
B64: Producr Owner | C64: =(C80+C112+C144)*C96 -> 132 | D64: =(D80+D112+D144)*D96 -> 132 | E64: =(E80+E112+E144)*E96 -> 132 | F64: =(F80+F112+F144)*F96 -> 132 | G64: =(G80+G112+G144)*G96 -> 132 | H64: =(H80+H112+H144)*H96 -> 132 | I64: =(I80+I112+I144)*I96 -> 132 | J64: =(J80+J112+J144)*J96 -> 132 | ... N64: =(N80+N112+N144)*N96 -> 132 | O64: =SUM(C64:N64) -> 1584 | P64: =(P80+P112+P144)*P96 -> 142.4 | Q64: =(Q80+Q112+Q144)*Q96 -> 142.4 | R64: =(R80+R112+R144)*R96 -> 142.4 | S64: =(S80+S112+S144)*S96 -> 142.4 | T64: =(T80+T112+T144)*T96 -> 142.4 | U64: =(U80+U112+U144)*U96 -> 142.4 | V64: =(V80+V112+V144)*V96 -> 142.4 | W64: =(W80+W112+W144)*W96 -> 142.4 | ... AA64: =(AA80+AA112+AA144)*AA96 -> 142.4 | AB64: =SUM(P64:AA64) -> 1708.8
B65: Модератор | C65: =(C81+C113+C145)*C97 -> 80 | D65: =(D81+D113+D145)*D97 -> 80 | E65: =(E81+E113+E145)*E97 -> 80 | F65: =(F81+F113+F145)*F97 -> 80 | G65: =(G81+G113+G145)*G97 -> 80 | H65: =(H81+H113+H145)*H97 -> 80 | I65: =(I81+I113+I145)*I97 -> 80 | J65: =(J81+J113+J145)*J97 -> 80 | ... N65: =(N81+N113+N145)*N97 -> 80 | O65: =SUM(C65:N65) -> 960 | P65: =(P81+P113+P145)*P97 -> 86.24 | Q65: =(Q81+Q113+Q145)*Q97 -> 86.24 | R65: =(R81+R113+R145)*R97 -> 86.24 | S65: =(S81+S113+S145)*S97 -> 86.24 | T65: =(T81+T113+T145)*T97 -> 86.24 | U65: =(U81+U113+U145)*U97 -> 86.24 | V65: =(V81+V113+V145)*V97 -> 86.24 | W65: =(W81+W113+W145)*W97 -> 86.24 | ... AA65: =(AA81+AA113+AA145)*AA97 -> 86.24 | AB65: =SUM(P65:AA65) -> 1034.88
B66: Инженер тех. поддержки | C66: =(C82+C114+C146)*C98 -> 80 | D66: =(D82+D114+D146)*D98 -> 80 | E66: =(E82+E114+E146)*E98 -> 80 | F66: =(F82+F114+F146)*F98 -> 80 | G66: =(G82+G114+G146)*G98 -> 80 | H66: =(H82+H114+H146)*H98 -> 80 | I66: =(I82+I114+I146)*I98 -> 80 | J66: =(J82+J114+J146)*J98 -> 80 | ... N66: =(N82+N114+N146)*N98 -> 80 | O66: =SUM(C66:N66) -> 960 | P66: =(P82+P114+P146)*P98 -> 86.24 | Q66: =(Q82+Q114+Q146)*Q98 -> 86.24 | R66: =(R82+R114+R146)*R98 -> 86.24 | S66: =(S82+S114+S146)*S98 -> 86.24 | T66: =(T82+T114+T146)*T98 -> 86.24 | U66: =(U82+U114+U146)*U98 -> 86.24 | V66: =(V82+V114+V146)*V98 -> 86.24 | W66: =(W82+W114+W146)*W98 -> 86.24 | ... AA66: =(AA82+AA114+AA146)*AA98 -> 86.24 | AB66: =SUM(P66:AA66) -> 1034.88
B67: Контент-мейкер | C67: =(C83+C115+C147)*C99 -> 106 | D67: =(D83+D115+D147)*D99 -> 106 | E67: =(E83+E115+E147)*E99 -> 106 | F67: =(F83+F115+F147)*F99 -> 106 | G67: =(G83+G115+G147)*G99 -> 106 | H67: =(H83+H115+H147)*H99 -> 106 | I67: =(I83+I115+I147)*I99 -> 106 | J67: =(J83+J115+J147)*J99 -> 106 | ... N67: =(N83+N115+N147)*N99 -> 106 | O67: =SUM(C67:N67) -> 1272 | P67: =(P83+P115+P147)*P99 -> 114.32 | Q67: =(Q83+Q115+Q147)*Q99 -> 114.32 | R67: =(R83+R115+R147)*R99 -> 114.32 | S67: =(S83+S115+S147)*S99 -> 114.32 | T67: =(T83+T115+T147)*T99 -> 114.32 | U67: =(U83+U115+U147)*U99 -> 114.32 | V67: =(V83+V115+V147)*V99 -> 114.32 | W67: =(W83+W115+W147)*W99 -> 114.32 | ... AA67: =(AA83+AA115+AA147)*AA99 -> 114.32 | AB67: =SUM(P67:AA67) -> 1371.84
B68: SMM | C68: =(C84+C116+C148)*C100 -> 106 | D68: =(D84+D116+D148)*D100 -> 106 | E68: =(E84+E116+E148)*E100 -> 106 | F68: =(F84+F116+F148)*F100 -> 106 | G68: =(G84+G116+G148)*G100 -> 106 | H68: =(H84+H116+H148)*H100 -> 106 | I68: =(I84+I116+I148)*I100 -> 106 | J68: =(J84+J116+J148)*J100 -> 106 | ... N68: =(N84+N116+N148)*N100 -> 106 | O68: =SUM(C68:N68) -> 1272 | P68: =(P84+P116+P148)*P100 -> 114.32 | Q68: =(Q84+Q116+Q148)*Q100 -> 114.32 | R68: =(R84+R116+R148)*R100 -> 114.32 | S68: =(S84+S116+S148)*S100 -> 114.32 | T68: =(T84+T116+T148)*T100 -> 114.32 | U68: =(U84+U116+U148)*U100 -> 114.32 | V68: =(V84+V116+V148)*V100 -> 114.32 | W68: =(W84+W116+W148)*W100 -> 114.32 | ... AA68: =(AA84+AA116+AA148)*AA100 -> 114.32 | AB68: =SUM(P68:AA68) -> 1371.84
B69: Education | C69: =SUM(C70:C73) -> 463 | D69: =SUM(D70:D73) -> 595 | E69: =SUM(E70:E73) -> 595 | F69: =SUM(F70:F73) -> 727 | G69: =SUM(G70:G73) -> 859 | H69: =SUM(H70:H73) -> 991 | I69: =SUM(I70:I73) -> 991 | J69: =SUM(J70:J73) -> 1123 | ... N69: =SUM(N70:N73) -> 1519 | O69: =SUM(C69:N69) -> 11892 | P69: =SUM(P70:P73) -> 1638.6 | Q69: =SUM(Q70:Q73) -> 1781 | R69: =SUM(R70:R73) -> 1781 | S69: =SUM(S70:S73) -> 1781 | T69: =SUM(T70:T73) -> 1781 | U69: =SUM(U70:U73) -> 1781 | V69: =SUM(V70:V73) -> 1923.4 | W69: =SUM(W70:W73) -> 1923.4 | ... AA69: =SUM(AA70:AA73) -> 2065.8 | AB69: =SUM(P69:AA69) -> 22226.4
B70: Producr Owner | C70: =(C86+C118+C150)*C102 -> 132 | D70: =(D86+D112+D150)*D102 -> 132 | E70: =(E86+E112+E150)*E102 -> 132 | F70: =(F86+F112+F150)*F102 -> 132 | G70: =(G86+G112+G150)*G102 -> 132 | H70: =(H86+H112+H150)*H102 -> 132 | I70: =(I86+I112+I150)*I102 -> 132 | J70: =(J86+J112+J150)*J102 -> 132 | K70: =(K86+K112+K150)*K102 -> 132 | ... N70: =(N86+N112+N150)*N102 -> 132 | O70: =SUM(C70:N70) -> 1584 | P70: =(P86+P118+P150)*P102 -> 142.4 | Q70: =(Q86+Q118+Q150)*Q102 -> 142.4 | R70: =(R86+R118+R150)*R102 -> 142.4 | S70: =(S86+S118+S150)*S102 -> 142.4 | T70: =(T86+T118+T150)*T102 -> 142.4 | U70: =(U86+U118+U150)*U102 -> 142.4 | V70: =(V86+V118+V150)*V102 -> 142.4 | W70: =(W86+W118+W150)*W102 -> 142.4 | ... AA70: =(AA86+AA118+AA150)*AA102 -> 142.4 | AB70: =SUM(P70:AA70) -> 1708.8
B71: Куратор | C71: =(C87+C119+C151)*C103 -> 132 | D71: =(D87+D119+D151)*D103 -> 264 | E71: =(E87+E119+E151)*E103 -> 264 | F71: =(F87+F119+F151)*F103 -> 396 | G71: =(G87+G119+G151)*G103 -> 528 | H71: =(H87+H119+H151)*H103 -> 660 | I71: =(I87+I119+I151)*I103 -> 660 | J71: =(J87+J119+J151)*J103 -> 792 | ... N71: =(N87+N119+N151)*N103 -> 1188 | O71: =SUM(C71:N71) -> 7920 | P71: =(P87+P119+P151)*P103 -> 1281.6 | Q71: =(Q87+Q119+Q151)*Q103 -> 1424 | R71: =(R87+R119+R151)*R103 -> 1424 | S71: =(S87+S119+S151)*S103 -> 1424 | T71: =(T87+T119+T151)*T103 -> 1424 | U71: =(U87+U119+U151)*U103 -> 1424 | V71: =(V87+V119+V151)*V103 -> 1566.4 | W71: =(W87+W119+W151)*W103 -> 1566.4 | ... AA71: =(AA87+AA119+AA151)*AA103 -> 1708.8 | AB71: =SUM(P71:AA71) -> 17942.4
B72: Инженер тех. поддержки | C72: =(C88+C120+C152)*C104 -> 93 | D72: =(D88+D120+D152)*D104 -> 93 | E72: =(E88+E120+E152)*E104 -> 93 | F72: =(F88+F120+F152)*F104 -> 93 | G72: =(G88+G120+G152)*G104 -> 93 | H72: =(H88+H120+H152)*H104 -> 93 | I72: =(I88+I120+I152)*I104 -> 93 | J72: =(J88+J120+J152)*J104 -> 93 | ... N72: =(N88+N120+N152)*N104 -> 93 | O72: =SUM(C72:N72) -> 1116 | P72: =(P88+P120+P152)*P104 -> 100.28 | Q72: =(Q88+Q120+Q152)*Q104 -> 100.28 | R72: =(R88+R120+R152)*R104 -> 100.28 | S72: =(S88+S120+S152)*S104 -> 100.28 | T72: =(T88+T120+T152)*T104 -> 100.28 | U72: =(U88+U120+U152)*U104 -> 100.28 | V72: =(V88+V120+V152)*V104 -> 100.28 | W72: =(W88+W120+W152)*W104 -> 100.28 | ... AA72: =(AA88+AA120+AA152)*AA104 -> 100.28 | AB72: =SUM(P72:AA72) -> 1203.36
B73: SMM | C73: =(C89+C121+C153)*C105 -> 106 | D73: =(D89+D121+D153)*D105 -> 106 | E73: =(E89+E121+E153)*E105 -> 106 | F73: =(F89+F121+F153)*F105 -> 106 | G73: =(G89+G121+G153)*G105 -> 106 | H73: =(H89+H121+H153)*H105 -> 106 | I73: =(I89+I121+I153)*I105 -> 106 | J73: =(J89+J121+J153)*J105 -> 106 | ... N73: =(N89+N121+N153)*N105 -> 106 | O73: =SUM(C73:N73) -> 1272 | P73: =(P89+P121+P153)*P105 -> 114.32 | Q73: =(Q89+Q121+Q153)*Q105 -> 114.32 | R73: =(R89+R121+R153)*R105 -> 114.32 | S73: =(S89+S121+S153)*S105 -> 114.32 | T73: =(T89+T121+T153)*T105 -> 114.32 | U73: =(U89+U121+U153)*U105 -> 114.32 | V73: =(V89+V121+V153)*V105 -> 114.32 | W73: =(W89+W121+W153)*W105 -> 114.32 | ... AA73: =(AA89+AA121+AA153)*AA105 -> 114.32 | AB73: =SUM(P73:AA73) -> 1371.84
B74: Бухгалтер | C74: =(C90+C122+C154)*C106 -> 54 | D74: 54 | E74: 54 | F74: 54 | G74: 54 | H74: 54 | I74: 54 | J74: 54 | K74: 54 | L74: 54 | M74: 54 | N74: 54 | O74: =SUM(C74:N74) -> 648 | P74: =(P90+P122+P154)*P106 -> 58.16 | Q74: =(Q90+Q122+Q154)*Q106 -> 58.16 | R74: =(R90+R122+R154)*R106 -> 58.16 | S74: =(S90+S122+S154)*S106 -> 58.16 | T74: =(T90+T122+T154)*T106 -> 58.16 | U74: =(U90+U122+U154)*U106 -> 58.16 | V74: =(V90+V122+V154)*V106 -> 58.16 | W74: =(W90+W122+W154)*W106 -> 58.16 | ... AA74: =(AA90+AA122+AA154)*AA106 -> 58.16 | AB74: =SUM(P74:AA74) -> 697.92
B76: Таблица 12.1. Оклад штатной единицы, тыс. руб. | AF76: Нет | AG76: =IF(AF76="Нет", " ", "Оклады занесите из листа Аналитика, в 2027 году учтите ежегодную индексацию")
C77: янв.26 | D77: фев.26 | E77: мар.26 | F77: апр.26 | G77: 46143 | H77: июн.26 | I77: июл.26 | J77: авг.26 | K77: сент.26 | L77: окт.26 | M77: ноя.26 | N77: дек.26 | O77: 2026 | P77: янв.27 | Q77: фев.27 | R77: мар.27 | S77: апр.27 | T77: 46508 | U77: июн.27 | V77: июл.27 | W77: авг.27 | X77: сент.27 | Y77: окт.27 | Z77: ноя.27 | AA77: дек.27 | AB77: 2027
B79: Community | C79: =SUM(C80:C84) -> 380 | D79: =SUM(D80:D84) -> 380 | E79: =SUM(E80:E84) -> 380 | F79: =SUM(F80:F84) -> 380 | G79: =SUM(G80:G84) -> 380 | H79: =SUM(H80:H84) -> 380 | I79: =SUM(I80:I84) -> 380 | J79: =SUM(J80:J84) -> 380 | ... N79: =SUM(N80:N84) -> 380 | O79: =SUM(C79:N79) -> 4560 | P79: =SUM(P80:P84) -> 410.4 | Q79: =SUM(Q80:Q84) -> 410.4 | R79: =SUM(R80:R84) -> 410.4 | S79: =SUM(S80:S84) -> 410.4 | T79: =SUM(T80:T84) -> 410.4 | U79: =SUM(U80:U84) -> 410.4 | V79: =SUM(V80:V84) -> 410.4 | W79: =SUM(W80:W84) -> 410.4 | ... AA79: =SUM(AA80:AA84) -> 410.4 | AB79: =SUM(P79:AA79) -> 4924.8
B80: Producr Owner | C80: ='Аналитика'!C26 -> 100 | D80: 100 | E80: 100 | F80: 100 | G80: 100 | H80: 100 | I80: 100 | J80: 100 | K80: 100 | L80: 100 | M80: 100 | N80: 100 | O80: =SUM(C80:N80) -> 1200 | P80: =C80*(1+'Аналитика'!$M$3) -> 108 | Q80: =D80*(1+'Аналитика'!$M$3) -> 108 | R80: =E80*(1+'Аналитика'!$M$3) -> 108 | S80: =F80*(1+'Аналитика'!$M$3) -> 108 | T80: =G80*(1+'Аналитика'!$M$3) -> 108 | U80: =H80*(1+'Аналитика'!$M$3) -> 108 | V80: =I80*(1+'Аналитика'!$M$3) -> 108 | W80: =J80*(1+'Аналитика'!$M$3) -> 108 | ... AA80: =N80*(1+'Аналитика'!$M$3) -> 108 | AB80: =SUM(P80:AA80) -> 1296
B81: Модератор | C81: ='Аналитика'!C27 -> 60 | D81: 60 | E81: 60 | F81: 60 | G81: 60 | H81: 60 | I81: 60 | J81: 60 | K81: 60 | L81: 60 | M81: 60 | N81: 60 | O81: =SUM(C81:N81) -> 720 | P81: =C81*(1+'Аналитика'!$M$3) -> 64.8 | Q81: =D81*(1+'Аналитика'!$M$3) -> 64.8 | R81: =E81*(1+'Аналитика'!$M$3) -> 64.8 | S81: =F81*(1+'Аналитика'!$M$3) -> 64.8 | T81: =G81*(1+'Аналитика'!$M$3) -> 64.8 | U81: =H81*(1+'Аналитика'!$M$3) -> 64.8 | V81: =I81*(1+'Аналитика'!$M$3) -> 64.8 | W81: =J81*(1+'Аналитика'!$M$3) -> 64.8 | ... AA81: =N81*(1+'Аналитика'!$M$3) -> 64.8 | AB81: =SUM(P81:AA81) -> 777.6
B82: Инженер тех. поддержки | C82: ='Аналитика'!C28 -> 60 | D82: 60 | E82: 60 | F82: 60 | G82: 60 | H82: 60 | I82: 60 | J82: 60 | K82: 60 | L82: 60 | M82: 60 | N82: 60 | O82: =SUM(C82:N82) -> 720 | P82: =C82*(1+'Аналитика'!$M$3) -> 64.8 | Q82: =D82*(1+'Аналитика'!$M$3) -> 64.8 | R82: =E82*(1+'Аналитика'!$M$3) -> 64.8 | S82: =F82*(1+'Аналитика'!$M$3) -> 64.8 | T82: =G82*(1+'Аналитика'!$M$3) -> 64.8 | U82: =H82*(1+'Аналитика'!$M$3) -> 64.8 | V82: =I82*(1+'Аналитика'!$M$3) -> 64.8 | W82: =J82*(1+'Аналитика'!$M$3) -> 64.8 | ... AA82: =N82*(1+'Аналитика'!$M$3) -> 64.8 | AB82: =SUM(P82:AA82) -> 777.6
B83: Контент-мейкер | C83: ='Аналитика'!C29 -> 80 | D83: 80 | E83: 80 | F83: 80 | G83: 80 | H83: 80 | I83: 80 | J83: 80 | K83: 80 | L83: 80 | M83: 80 | N83: 80 | O83: =SUM(C83:N83) -> 960 | P83: =C83*(1+'Аналитика'!$M$3) -> 86.4 | Q83: =D83*(1+'Аналитика'!$M$3) -> 86.4 | R83: =E83*(1+'Аналитика'!$M$3) -> 86.4 | S83: =F83*(1+'Аналитика'!$M$3) -> 86.4 | T83: =G83*(1+'Аналитика'!$M$3) -> 86.4 | U83: =H83*(1+'Аналитика'!$M$3) -> 86.4 | V83: =I83*(1+'Аналитика'!$M$3) -> 86.4 | W83: =J83*(1+'Аналитика'!$M$3) -> 86.4 | ... AA83: =N83*(1+'Аналитика'!$M$3) -> 86.4 | AB83: =SUM(P83:AA83) -> 1036.8
B84: SMM | C84: ='Аналитика'!C30 -> 80 | D84: 80 | E84: 80 | F84: 80 | G84: 80 | H84: 80 | I84: 80 | J84: 80 | K84: 80 | L84: 80 | M84: 80 | N84: 80 | O84: =SUM(C84:N84) -> 960 | P84: =C84*(1+'Аналитика'!$M$3) -> 86.4 | Q84: =D84*(1+'Аналитика'!$M$3) -> 86.4 | R84: =E84*(1+'Аналитика'!$M$3) -> 86.4 | S84: =F84*(1+'Аналитика'!$M$3) -> 86.4 | T84: =G84*(1+'Аналитика'!$M$3) -> 86.4 | U84: =H84*(1+'Аналитика'!$M$3) -> 86.4 | V84: =I84*(1+'Аналитика'!$M$3) -> 86.4 | W84: =J84*(1+'Аналитика'!$M$3) -> 86.4 | ... AA84: =N84*(1+'Аналитика'!$M$3) -> 86.4 | AB84: =SUM(P84:AA84) -> 1036.8
B85: Education | C85: =SUM(C86:C89) -> 350 | D85: =SUM(D86:D89) -> 350 | E85: =SUM(E86:E89) -> 350 | F85: =SUM(F86:F89) -> 350 | G85: =SUM(G86:G89) -> 350 | H85: =SUM(H86:H89) -> 350 | I85: =SUM(I86:I89) -> 350 | J85: =SUM(J86:J89) -> 350 | ... N85: =SUM(N86:N89) -> 350 | O85: =SUM(C85:N85) -> 4200 | P85: =SUM(P86:P89) -> 378 | Q85: =SUM(Q86:Q89) -> 378 | R85: =SUM(R86:R89) -> 378 | S85: =SUM(S86:S89) -> 378 | T85: =SUM(T86:T89) -> 378 | U85: =SUM(U86:U89) -> 378 | V85: =SUM(V86:V89) -> 378 | W85: =SUM(W86:W89) -> 378 | ... AA85: =SUM(AA86:AA89) -> 378 | AB85: =SUM(P85:AA85) -> 4536
B86: Producr Owner | C86: ='Аналитика'!E26 -> 100 | D86: 100 | E86: 100 | F86: 100 | G86: 100 | H86: 100 | I86: 100 | J86: 100 | K86: 100 | L86: 100 | M86: 100 | N86: 100 | O86: =SUM(C86:N86) -> 1200 | P86: =C86*(1+'Аналитика'!$M$3) -> 108 | Q86: =D86*(1+'Аналитика'!$M$3) -> 108 | R86: =E86*(1+'Аналитика'!$M$3) -> 108 | S86: =F86*(1+'Аналитика'!$M$3) -> 108 | T86: =G86*(1+'Аналитика'!$M$3) -> 108 | U86: =H86*(1+'Аналитика'!$M$3) -> 108 | V86: =I86*(1+'Аналитика'!$M$3) -> 108 | W86: =J86*(1+'Аналитика'!$M$3) -> 108 | ... AA86: =N86*(1+'Аналитика'!$M$3) -> 108 | AB86: =SUM(P86:AA86) -> 1296
B87: Куратор | C87: ='Аналитика'!E27 -> 100 | D87: 100 | E87: 100 | F87: 100 | G87: 100 | H87: 100 | I87: 100 | J87: 100 | K87: 100 | L87: 100 | M87: 100 | N87: 100 | O87: =SUM(C87:N87) -> 1200 | P87: =C87*(1+'Аналитика'!$M$3) -> 108 | Q87: =D87*(1+'Аналитика'!$M$3) -> 108 | R87: =E87*(1+'Аналитика'!$M$3) -> 108 | S87: =F87*(1+'Аналитика'!$M$3) -> 108 | T87: =G87*(1+'Аналитика'!$M$3) -> 108 | U87: =H87*(1+'Аналитика'!$M$3) -> 108 | V87: =I87*(1+'Аналитика'!$M$3) -> 108 | W87: =J87*(1+'Аналитика'!$M$3) -> 108 | ... AA87: =N87*(1+'Аналитика'!$M$3) -> 108 | AB87: =SUM(P87:AA87) -> 1296
B88: Инженер тех. поддержки | C88: ='Аналитика'!E28 -> 70 | D88: 70 | E88: 70 | F88: 70 | G88: 70 | H88: 70 | I88: 70 | J88: 70 | K88: 70 | L88: 70 | M88: 70 | N88: 70 | O88: =SUM(C88:N88) -> 840 | P88: =C88*(1+'Аналитика'!$M$3) -> 75.6 | Q88: =D88*(1+'Аналитика'!$M$3) -> 75.6 | R88: =E88*(1+'Аналитика'!$M$3) -> 75.6 | S88: =F88*(1+'Аналитика'!$M$3) -> 75.6 | T88: =G88*(1+'Аналитика'!$M$3) -> 75.6 | U88: =H88*(1+'Аналитика'!$M$3) -> 75.6 | V88: =I88*(1+'Аналитика'!$M$3) -> 75.6 | W88: =J88*(1+'Аналитика'!$M$3) -> 75.6 | ... AA88: =N88*(1+'Аналитика'!$M$3) -> 75.6 | AB88: =SUM(P88:AA88) -> 907.2
B89: SMM | C89: ='Аналитика'!E29 -> 80 | D89: 80 | E89: 80 | F89: 80 | G89: 80 | H89: 80 | I89: 80 | J89: 80 | K89: 80 | L89: 80 | M89: 80 | N89: 80 | O89: =SUM(C89:N89) -> 960 | P89: =C89*(1+'Аналитика'!$M$3) -> 86.4 | Q89: =D89*(1+'Аналитика'!$M$3) -> 86.4 | R89: =E89*(1+'Аналитика'!$M$3) -> 86.4 | S89: =F89*(1+'Аналитика'!$M$3) -> 86.4 | T89: =G89*(1+'Аналитика'!$M$3) -> 86.4 | U89: =H89*(1+'Аналитика'!$M$3) -> 86.4 | V89: =I89*(1+'Аналитика'!$M$3) -> 86.4 | W89: =J89*(1+'Аналитика'!$M$3) -> 86.4 | ... AA89: =N89*(1+'Аналитика'!$M$3) -> 86.4 | AB89: =SUM(P89:AA89) -> 1036.8
B90: Бухгалтер | C90: ='Аналитика'!E31 -> 40 | D90: 40 | E90: 40 | F90: 40 | G90: 40 | H90: 40 | I90: 40 | J90: 40 | K90: 40 | L90: 40 | M90: 40 | N90: 40 | O90: =SUM(C90:N90) -> 480 | P90: =C90*(1+'Аналитика'!$M$3) -> 43.2 | Q90: 43.2 | R90: 43.2 | S90: 43.2 | T90: 43.2 | U90: 43.2 | V90: 43.2 | W90: 43.2 | X90: 43.2 | Y90: 43.2 | Z90: 43.2 | AA90: 43.2 | AB90: =SUM(P90:AA90) -> 518.4
B92: Таблица 12.2. Количество штатных единиц, чел. | AF92: Нет | AG92: =IF(AF92="Нет", " ", "Каждой штатной единицы - по одной. Рост штатных единиц заложите только по куратором, исходя из ограничения на листе Аналитика - не более 30 студентов на одного куратора")
C93: янв.26 | D93: фев.26 | E93: мар.26 | F93: апр.26 | G93: 46143 | H93: июн.26 | I93: июл.26 | J93: авг.26 | K93: сент.26 | L93: окт.26 | M93: ноя.26 | N93: дек.26 | O93: 2026 | P93: янв.27 | Q93: фев.27 | R93: мар.27 | S93: апр.27 | T93: 46508 | U93: июн.27 | V93: июл.27 | W93: авг.27 | X93: сент.27 | Y93: окт.27 | Z93: ноя.27 | AA93: дек.27 | AB93: 2027 | AF93: Нет | AG93: =IF(AF93="Нет", " ", "Ограничение по кураторам с учётом количества студентов можно учесть с помощью формулы: ROUNDUP(SUM(Количество пользователей платных обучающих курсов)/30,0)")
B95: Community | C95: =SUM(C96:C100) -> 5 | D95: =SUM(D96:D100) -> 5 | E95: =SUM(E96:E100) -> 5 | F95: =SUM(F96:F100) -> 5 | G95: =SUM(G96:G100) -> 5 | H95: =SUM(H96:H100) -> 5 | I95: =SUM(I96:I100) -> 5 | J95: =SUM(J96:J100) -> 5 | ... AB95: =SUM(AB96:AB100) -> 5
B96: Producr Owner | C96: 1 | D96: 1 | E96: 1 | F96: 1 | G96: 1 | H96: 1 | I96: 1 | J96: 1 | K96: 1 | L96: 1 | M96: 1 | N96: 1 | O96: =N96 -> 1 | P96: 1 | Q96: 1 | R96: 1 | S96: 1 | T96: 1 | U96: 1 | V96: 1 | W96: 1 | X96: 1 | Y96: 1 | Z96: 1 | AA96: 1 | AB96: =AA96 -> 1
B97: Модератор | C97: 1 | D97: 1 | E97: 1 | F97: 1 | G97: 1 | H97: 1 | I97: 1 | J97: 1 | K97: 1 | L97: 1 | M97: 1 | N97: 1 | O97: =N97 -> 1 | P97: 1 | Q97: 1 | R97: 1 | S97: 1 | T97: 1 | U97: 1 | V97: 1 | W97: 1 | X97: 1 | Y97: 1 | Z97: 1 | AA97: 1 | AB97: =AA97 -> 1
B98: Инженер тех. поддержки | C98: 1 | D98: 1 | E98: 1 | F98: 1 | G98: 1 | H98: 1 | I98: 1 | J98: 1 | K98: 1 | L98: 1 | M98: 1 | N98: 1 | O98: =N98 -> 1 | P98: 1 | Q98: 1 | R98: 1 | S98: 1 | T98: 1 | U98: 1 | V98: 1 | W98: 1 | X98: 1 | Y98: 1 | Z98: 1 | AA98: 1 | AB98: =AA98 -> 1
B99: Контент-мейкер | C99: 1 | D99: 1 | E99: 1 | F99: 1 | G99: 1 | H99: 1 | I99: 1 | J99: 1 | K99: 1 | L99: 1 | M99: 1 | N99: 1 | O99: =N99 -> 1 | P99: 1 | Q99: 1 | R99: 1 | S99: 1 | T99: 1 | U99: 1 | V99: 1 | W99: 1 | X99: 1 | Y99: 1 | Z99: 1 | AA99: 1 | AB99: =AA99 -> 1
B100: SMM | C100: 1 | D100: 1 | E100: 1 | F100: 1 | G100: 1 | H100: 1 | I100: 1 | J100: 1 | K100: 1 | L100: 1 | M100: 1 | N100: 1 | O100: =N100 -> 1 | P100: 1 | Q100: 1 | R100: 1 | S100: 1 | T100: 1 | U100: 1 | V100: 1 | W100: 1 | X100: 1 | Y100: 1 | Z100: 1 | AA100: 1 | AB100: =AA100 -> 1
B101: Education | C101: =SUM(C102:C105) -> 4 | D101: =SUM(D102:D105) -> 5 | E101: =SUM(E102:E105) -> 5 | F101: =SUM(F102:F105) -> 6 | G101: =SUM(G102:G105) -> 7 | H101: =SUM(H102:H105) -> 8 | I101: =SUM(I102:I105) -> 8 | J101: =SUM(J102:J105) -> 9 | ... AB101: =SUM(AB102:AB105) -> 15
B102: Producr Owner | C102: 1 | D102: 1 | E102: 1 | F102: 1 | G102: 1 | H102: 1 | I102: 1 | J102: 1 | K102: 1 | L102: 1 | M102: 1 | N102: 1 | O102: =N102 -> 1 | P102: 1 | Q102: 1 | R102: 1 | S102: 1 | T102: 1 | U102: 1 | V102: 1 | W102: 1 | X102: 1 | Y102: 1 | Z102: 1 | AA102: 1 | AB102: =AA102 -> 1
B103: Куратор | C103: =ROUNDUP(SUM(C33:C36)/30,0) -> 1 | D103: =ROUNDUP(SUM(D33:D36)/30,0) -> 2 | E103: =ROUNDUP(SUM(E33:E36)/30,0) -> 2 | F103: =ROUNDUP(SUM(F33:F36)/30,0) -> 3 | G103: =ROUNDUP(SUM(G33:G36)/30,0) -> 4 | H103: =ROUNDUP(SUM(H33:H36)/30,0) -> 5 | I103: =ROUNDUP(SUM(I33:I36)/30,0) -> 5 | J103: =ROUNDUP(SUM(J33:J36)/30,0) -> 6 | ... N103: =ROUNDUP(SUM(N33:N36)/30,0) -> 9 | O103: =N103 -> 9 | P103: =ROUNDUP(SUM(P33:P36)/30,0) -> 9 | Q103: =ROUNDUP(SUM(Q33:Q36)/30,0) -> 10 | R103: =ROUNDUP(SUM(R33:R36)/30,0) -> 10 | S103: =ROUNDUP(SUM(S33:S36)/30,0) -> 10 | T103: =ROUNDUP(SUM(T33:T36)/30,0) -> 10 | U103: =ROUNDUP(SUM(U33:U36)/30,0) -> 10 | V103: =ROUNDUP(SUM(V33:V36)/30,0) -> 11 | W103: =ROUNDUP(SUM(W33:W36)/30,0) -> 11 | ... AA103: =ROUNDUP(SUM(AA33:AA36)/30,0) -> 12 | AB103: =AA103 -> 12
B104: Инженер тех. поддержки | C104: 1 | D104: 1 | E104: 1 | F104: 1 | G104: 1 | H104: 1 | I104: 1 | J104: 1 | K104: 1 | L104: 1 | M104: 1 | N104: 1 | O104: =N104 -> 1 | P104: 1 | Q104: 1 | R104: 1 | S104: 1 | T104: 1 | U104: 1 | V104: 1 | W104: 1 | X104: 1 | Y104: 1 | Z104: 1 | AA104: 1 | AB104: =AA104 -> 1
B105: SMM | C105: 1 | D105: 1 | E105: 1 | F105: 1 | G105: 1 | H105: 1 | I105: 1 | J105: 1 | K105: 1 | L105: 1 | M105: 1 | N105: 1 | O105: =N105 -> 1 | P105: 1 | Q105: 1 | R105: 1 | S105: 1 | T105: 1 | U105: 1 | V105: 1 | W105: 1 | X105: 1 | Y105: 1 | Z105: 1 | AA105: 1 | AB105: =AA105 -> 1
B106: Бухгалтер | C106: 1 | D106: 1 | E106: 1 | F106: 1 | G106: 1 | H106: 1 | I106: 1 | J106: 1 | K106: 1 | L106: 1 | M106: 1 | N106: 1 | O106: =N106 -> 1 | P106: 1 | Q106: 1 | R106: 1 | S106: 1 | T106: 1 | U106: 1 | V106: 1 | W106: 1 | X106: 1 | Y106: 1 | Z106: 1 | AA106: 1 | AB106: =AA106 -> 1
B108: Таблица 12.3. ДМС штатной единицы, тыс. руб. | AD108: - Без учёта инфляции (считаем, что договор ДМС заключён на 2 года) | AF108: Нет | AG108: =IF(AF108="Нет", " ", "Стоимость ДМС - 2 тыс.руб./чел.")
C109: янв.26 | D109: фев.26 | E109: мар.26 | F109: апр.26 | G109: 46143 | H109: июн.26 | I109: июл.26 | J109: авг.26 | K109: сент.26 | L109: окт.26 | M109: ноя.26 | N109: дек.26 | O109: 2026 | P109: янв.27 | Q109: фев.27 | R109: мар.27 | S109: апр.27 | T109: 46508 | U109: июн.27 | V109: июл.27 | W109: авг.27 | X109: сент.27 | Y109: окт.27 | Z109: ноя.27 | AA109: дек.27 | AB109: 2027
B111: Community | C111: =SUM(C112:C116) -> 10 | D111: =SUM(D112:D116) -> 10 | E111: =SUM(E112:E116) -> 10 | F111: =SUM(F112:F116) -> 10 | G111: =SUM(G112:G116) -> 10 | H111: =SUM(H112:H116) -> 10 | I111: =SUM(I112:I116) -> 10 | J111: =SUM(J112:J116) -> 10 | ... N111: =SUM(N112:N116) -> 10 | O111: =SUM(C111:N111) -> 120 | P111: =SUM(P112:P116) -> 10 | Q111: =SUM(Q112:Q116) -> 10 | R111: =SUM(R112:R116) -> 10 | S111: =SUM(S112:S116) -> 10 | T111: =SUM(T112:T116) -> 10 | U111: =SUM(U112:U116) -> 10 | V111: =SUM(V112:V116) -> 10 | W111: =SUM(W112:W116) -> 10 | ... AA111: =SUM(AA112:AA116) -> 10 | AB111: =SUM(P111:AA111) -> 120
B112: Producr Owner | C112: =C96*'Аналитика'!$M$9 -> 2 | D112: =D96*'Аналитика'!$M$9 -> 2 | E112: =E96*'Аналитика'!$M$9 -> 2 | F112: =F96*'Аналитика'!$M$9 -> 2 | G112: =G96*'Аналитика'!$M$9 -> 2 | H112: =H96*'Аналитика'!$M$9 -> 2 | I112: =I96*'Аналитика'!$M$9 -> 2 | J112: =J96*'Аналитика'!$M$9 -> 2 | ... N112: =N96*'Аналитика'!$M$9 -> 2 | O112: =SUM(C112:N112) -> 24 | P112: =P96*'Аналитика'!$M$9 -> 2 | Q112: =Q96*'Аналитика'!$M$9 -> 2 | R112: =R96*'Аналитика'!$M$9 -> 2 | S112: =S96*'Аналитика'!$M$9 -> 2 | T112: =T96*'Аналитика'!$M$9 -> 2 | U112: =U96*'Аналитика'!$M$9 -> 2 | V112: =V96*'Аналитика'!$M$9 -> 2 | W112: =W96*'Аналитика'!$M$9 -> 2 | ... AA112: =AA96*'Аналитика'!$M$9 -> 2 | AB112: =SUM(P112:AA112) -> 24
B113: Модератор | C113: =C97*'Аналитика'!$M$9 -> 2 | D113: =D97*'Аналитика'!$M$9 -> 2 | E113: =E97*'Аналитика'!$M$9 -> 2 | F113: =F97*'Аналитика'!$M$9 -> 2 | G113: =G97*'Аналитика'!$M$9 -> 2 | H113: =H97*'Аналитика'!$M$9 -> 2 | I113: =I97*'Аналитика'!$M$9 -> 2 | J113: =J97*'Аналитика'!$M$9 -> 2 | ... N113: =N97*'Аналитика'!$M$9 -> 2 | O113: =SUM(C113:N113) -> 24 | P113: =P97*'Аналитика'!$M$9 -> 2 | Q113: =Q97*'Аналитика'!$M$9 -> 2 | R113: =R97*'Аналитика'!$M$9 -> 2 | S113: =S97*'Аналитика'!$M$9 -> 2 | T113: =T97*'Аналитика'!$M$9 -> 2 | U113: =U97*'Аналитика'!$M$9 -> 2 | V113: =V97*'Аналитика'!$M$9 -> 2 | W113: =W97*'Аналитика'!$M$9 -> 2 | ... AA113: =AA97*'Аналитика'!$M$9 -> 2 | AB113: =SUM(P113:AA113) -> 24
B114: Инженер тех. поддержки | C114: =C98*'Аналитика'!$M$9 -> 2 | D114: =D98*'Аналитика'!$M$9 -> 2 | E114: =E98*'Аналитика'!$M$9 -> 2 | F114: =F98*'Аналитика'!$M$9 -> 2 | G114: =G98*'Аналитика'!$M$9 -> 2 | H114: =H98*'Аналитика'!$M$9 -> 2 | I114: =I98*'Аналитика'!$M$9 -> 2 | J114: =J98*'Аналитика'!$M$9 -> 2 | ... N114: =N98*'Аналитика'!$M$9 -> 2 | O114: =SUM(C114:N114) -> 24 | P114: =P98*'Аналитика'!$M$9 -> 2 | Q114: =Q98*'Аналитика'!$M$9 -> 2 | R114: =R98*'Аналитика'!$M$9 -> 2 | S114: =S98*'Аналитика'!$M$9 -> 2 | T114: =T98*'Аналитика'!$M$9 -> 2 | U114: =U98*'Аналитика'!$M$9 -> 2 | V114: =V98*'Аналитика'!$M$9 -> 2 | W114: =W98*'Аналитика'!$M$9 -> 2 | ... AA114: =AA98*'Аналитика'!$M$9 -> 2 | AB114: =SUM(P114:AA114) -> 24
B115: Контент-мейкер | C115: =C99*'Аналитика'!$M$9 -> 2 | D115: =D99*'Аналитика'!$M$9 -> 2 | E115: =E99*'Аналитика'!$M$9 -> 2 | F115: =F99*'Аналитика'!$M$9 -> 2 | G115: =G99*'Аналитика'!$M$9 -> 2 | H115: =H99*'Аналитика'!$M$9 -> 2 | I115: =I99*'Аналитика'!$M$9 -> 2 | J115: =J99*'Аналитика'!$M$9 -> 2 | ... N115: =N99*'Аналитика'!$M$9 -> 2 | O115: =SUM(C115:N115) -> 24 | P115: =P99*'Аналитика'!$M$9 -> 2 | Q115: =Q99*'Аналитика'!$M$9 -> 2 | R115: =R99*'Аналитика'!$M$9 -> 2 | S115: =S99*'Аналитика'!$M$9 -> 2 | T115: =T99*'Аналитика'!$M$9 -> 2 | U115: =U99*'Аналитика'!$M$9 -> 2 | V115: =V99*'Аналитика'!$M$9 -> 2 | W115: =W99*'Аналитика'!$M$9 -> 2 | ... AA115: =AA99*'Аналитика'!$M$9 -> 2 | AB115: =SUM(P115:AA115) -> 24
B116: SMM | C116: =C100*'Аналитика'!$M$9 -> 2 | D116: =D100*'Аналитика'!$M$9 -> 2 | E116: =E100*'Аналитика'!$M$9 -> 2 | F116: =F100*'Аналитика'!$M$9 -> 2 | G116: =G100*'Аналитика'!$M$9 -> 2 | H116: =H100*'Аналитика'!$M$9 -> 2 | I116: =I100*'Аналитика'!$M$9 -> 2 | J116: =J100*'Аналитика'!$M$9 -> 2 | ... N116: =N100*'Аналитика'!$M$9 -> 2 | O116: =SUM(C116:N116) -> 24 | P116: =P100*'Аналитика'!$M$9 -> 2 | Q116: =Q100*'Аналитика'!$M$9 -> 2 | R116: =R100*'Аналитика'!$M$9 -> 2 | S116: =S100*'Аналитика'!$M$9 -> 2 | T116: =T100*'Аналитика'!$M$9 -> 2 | U116: =U100*'Аналитика'!$M$9 -> 2 | V116: =V100*'Аналитика'!$M$9 -> 2 | W116: =W100*'Аналитика'!$M$9 -> 2 | ... AA116: =AA100*'Аналитика'!$M$9 -> 2 | AB116: =SUM(P116:AA116) -> 24
B117: Education | C117: =SUM(C118:C121) -> 8 | D117: =SUM(D118:D121) -> 8 | E117: =SUM(E118:E121) -> 8 | F117: =SUM(F118:F121) -> 8 | G117: =SUM(G118:G121) -> 8 | H117: =SUM(H118:H121) -> 8 | I117: =SUM(I118:I121) -> 8 | J117: =SUM(J118:J121) -> 8 | ... N117: =SUM(N118:N121) -> 8 | O117: =SUM(C117:N117) -> 96 | P117: =SUM(P118:P121) -> 8 | Q117: =SUM(Q118:Q121) -> 8 | R117: =SUM(R118:R121) -> 8 | S117: =SUM(S118:S121) -> 8 | T117: =SUM(T118:T121) -> 8 | U117: =SUM(U118:U121) -> 8 | V117: =SUM(V118:V121) -> 8 | W117: =SUM(W118:W121) -> 8 | ... AA117: =SUM(AA118:AA121) -> 8 | AB117: =SUM(P117:AA117) -> 96
...

Sheet Бюджет
B2: Таблица 17. Бюджет доходов и расходов 2026–2027, тыс. руб. | L2: Подсказку?
C3: Итого новые проекты | F3: Community | I3: Education
C4: 2026 | D4: 2027 | F4: 2026 | G4: 2027 | I4: 2026 | J4: 2027
B5: Выручка | C5: =F5+I5 -> 20483.248 | D5: =G5+J5 -> 51113.589 | F5: ='Расчёты'!O9 -> 4840.5369 | G5: ='Расчёты'!AB9 -> 16907.573 | I5: ='Расчёты'!O15 -> 15642.711 | J5: ='Расчёты'!AB15 -> 34206.016 | L5: Нет | M5: =IF(L5="Нет", " ", "Для Community и Education выручку заберите с листа Расчёты из таблицы 10. Выручка Итого рассчитывается путём сложения выручки Community и Education")
B6: Себестоимость | C6: =F6+I6 -> 27500 | D6: =G6+J6 -> 39124.04 | F6: ='Расчёты'!O57+'Расчёты'!O63+'Расчёты'!O172+'Расчёты'!O179 -> 10898 | G6: ='Расчёты'!AB57+'Расчёты'!AB63+'Расчёты'!AB172+'Расчёты'!AB179 -> 11414.24 | I6: ='Расчёты'!O58+'Расчёты'!O69+'Расчёты'!O173+'Расчёты'!O184 -> 16602 | J6: ='Расчёты'!AB58+'Расчёты'!AB69+'Расчёты'!AB173+'Расчёты'!AB184 -> 27709.8 | L6: Нет | M6: =IF(L6="Нет", " ", "Для Community и Education в себестоимость заберите расходы на аутсорс-разработку под ключ (таб.11), расходы на поддерж.персонал (таб.12), расходы на оборуд. (таб.15) и расходы на софт (таб.16) с листа Расчёты. Итого = Community + Education")
B7: Валовая прибыль | C7: =C5-C6 -> -7016.7521 | D7: =D5-D6 -> 11989.549 | F7: =F5-F6 -> -6057.4631 | G7: =G5-G6 -> 5493.3332 | I7: =I5-I6 -> -959.289 | J7: =J5-J6 -> 6496.216 | L7: Нет | M7: =IF(L7="Нет", " ", "Показатель рассчитывается по формуле Выручка - Себестоимость")
B8: Валовая прибыль, % | C8: =C7/C5 -> -0.34256052 | D8: =D7/D5 -> 0.23456676 | F8: =F7/F5 -> -1.2514032 | G8: =G7/G5 -> 0.3249037 | I8: =I7/I5 -> -0.061324984 | J8: =J7/J5 -> 0.18991443 | L8: Нет | M8: =IF(L8="Нет", " ", "Показатель рассчитывается по формуле Валовая прибыль / Выручка")
B9: Операционные расходы | C9: =SUM(C10:C14) -> 8974.13 | D9: =SUM(D10:D14) -> 9695.0776 | F9: =SUM(F10:F14) -> 3744.98 | G9: =SUM(G10:G14) -> 4004.6624 | I9: =SUM(I10:I14) -> 3802.02 | J9: =SUM(J10:J14) -> 4167.618 | L9: Нет | M9: =IF(L9="Нет", " ", "Показатель рассчитывается по формуле Расходы на персонал + Аренда + Реклама и маркетинг + Оборудование и сфот + Прочие и непредвиденные расходы")
B10: Расходы на персонал | C10: ='Расчёты'!O74 -> 648 | D10: ='Расчёты'!AB74 -> 697.92 | F10: 0 | G10: 0 | I10: 0 | J10: 0 | L10: Нет | M10: =IF(L10="Нет", " ", "Для Community и Education расходов на персонал в опер.расходах нет, т.к.они все в себестоимости. В Расходы на персонал Итого заберите расходы на бухгалтера из таблицы 12 с листа Расчёты")
B11: Аренда | C11: ='Расчёты'!O160+'Расчёты'!O161 -> 675 | D11: ='Расчёты'!AB160+'Расчёты'!AB161 -> 717 | F11: 0 | G11: 0 | I11: 0 | J11: 0 | L11: Нет | M11: =IF(L11="Нет", " ", "Расходы на аренду не распределены на Community и Education. Поэтому все расходы на аренду из таблицы 13 с листа Расчёты заберите в Расходы на аренду Итого ")
B12: Реклама и маркетинг | C12: =F12+I12 -> 7200 | D12: =G12+J12 -> 7704 | F12: ='Расчёты'!O166 -> 3600 | G12: ='Расчёты'!AB166 -> 3852 | I12: ='Расчёты'!O167 -> 3600 | J12: ='Расчёты'!AB167 -> 3852 | L12: Нет | M12: =IF(L12="Нет", " ", "Для Community и Education расходы на рекламу заберите с листа Расчёты из таблицы 14. Расходы на рекламу и маркетинг Итого рассчитывается путём сложения расходов на рекламу и маркетинг Community и Education")
B13: Оборудование, лицензии и ПО | C13: ='Расчёты'!O174+'Расчёты'!O189 -> 90 | D13: ='Расчёты'!AB174+'Расчёты'!AB189 -> 92.8 | F13: 0 | G13: 0 | I13: 0 | J13: 0 | L13: Нет | M13: =IF(L13="Нет", " ", "Расходы включают в себя расходы Бухгалтерии, указанные в таблицах 15 и 16. Расходы Community и Education должны быть отражены в себестоимости.")
B14: Прочие и непредвиденные расходы | C14: =(C6+C10+C11+C12+C13)*1% -> 361.13 | D14: =(D6+D10+D11+D12+D13)*1% -> 483.3576 | F14: =(F6+F10+F11+F12+F13)*1% -> 144.98 | G14: =(G6+G10+G11+G12+G13)*1% -> 152.6624 | I14: =(I6+I10+I11+I12+I13)*1% -> 202.02 | J14: =(J6+J10+J11+J12+J13)*1% -> 315.618 | L14: Нет | M14: =IF(L14="Нет", " ", "Показатель рассчитывается по формуле (Себестоимость + Расходы на персонал + Аренда + Реклама и маркетинг + Оборудование и софт) * 1%")
B15: Операционная прибыль | C15: =C7-C9 -> -15990.882 | D15: =D7-D9 -> 2294.4715 | F15: =F7-F9 -> -9802.4431 | G15: =G7-G9 -> 1488.6708 | I15: =I7-I9 -> -4761.309 | J15: =J7-J9 -> 2328.598 | L15: Нет | M15: =IF(L15="Нет", " ", "Показатель рассчитывается по формуле Валовая прибыль - Операционные расходы")
B16: Операционная прибыль, % | C16: =C15/C5 -> -0.78068099 | D16: =D15/D5 -> 0.044889658 | F16: =F15/F5 -> -2.0250735 | G16: =G15/G5 -> 0.088047572 | I16: =I15/I5 -> -0.30437876 | J16: =J15/J5 -> 0.068075685 | L16: Нет | M16: =IF(L16="Нет", " ", "Показатель рассчитывается по формуле Операционная прибыль / Выручка")
B17: Налог на прибыль | D17: =D15*25% -> 573.61788 | F17: 0 | G17: 0 | I17: 0 | J17: 0 | L17: Нет | M17: =IF(L17="Нет", " ", "Для Community и Education показатель не рассчитывается. Налог Итого рассчитывается по формуле Операционная прибыль * 25%")
B18: Чистая прибыль | C18: =C15-C17 -> -15990.882 | D18: =D15-D17 -> 1720.8536 | F18: =F15-F17 -> -9802.4431 | G18: =G15-G17 -> 1488.6708 | I18: =I15-I17 -> -4761.309 | J18: =J15-J17 -> 2328.598 | L18: Нет | M18: =IF(L18="Нет", " ", "Показатель рассчитывается по формуле Операционная прибыль - Налог на прибыль")
B19: Чистая прибыль, % | C19: =C18/C5 -> -0.78068099 | D19: =D18/D5 -> 0.033667243 | F19: =F18/F5 -> -2.0250735 | G19: =G18/G5 -> 0.088047572 | I19: =I18/I5 -> -0.30437876 | J19: =J18/J5 -> 0.068075685 | L19: Нет | M19: =IF(L19="Нет", " ", "Показатель рассчитывается по формуле Чистая прибыль / Выручка")

Sheet Последовательность расчётов
B2: Последовательность расчётов
C3: Лист «Расчёты»
B4: [1] | C4: Рассчитать ожидаемое количество пользователей — таблица 10.1
B5: [2] | C5: Рассчитать стоимость подписки — таблица 10.2
B6: [3] | C6: Рассчитать выручку — таблица 10
B7: [4] | C7: Рассчитать расходы на аутсорс-разработку «под ключ» — таблица 11
B8: [5] | C8: Рассчитать оклады штатных единиц — таблица 12.1
B9: [6] | C9: Рассчитать количество штатных единиц — таблица 12.2
B10: [7] | C10: Рассчитать ДМС - таблица 12.3
B11: [8] | C11: Рассчитать отпускные - таблица 12.4
B12: [9] | C12: Рассчитать страховые взносы - таблица 12.5
B13: [10] | C13: Рассчитать расходы на поддерживающий персонал — таблица 12
B14: [11] | C14: Рассчитать расходы на аренду — таблица 13
B15: [12] | C15: Рассчитать расходы на маркетинг и рекламу — таблица 14
... B17: [14] | C17: Рассчитать расходы на лицензии и софт — таблица 16
C18: Лист «Бюджет»
B19: [15] | C19: Заполнить последовательно все показатели БДР — таблица 17
C20: Лист «Цели»
B21: [16] | C21: Заполнить последовательно все финансовые показатели — таблица 1

Sheet Решение
A1: Таблица 1: Отчёт о прибылях и убытках за год, тыс.руб. | E1: Таблица 2: Управленческий баланс, тыс.руб. | I1: Показатель | J1: Значение | K1: Значение | L1: Вывод | M1: Формула
B2: 2023 | C2: 2022 | F2: 31.12.23 | G2: 31.12.22 | J2: 2023 | K2: 2022
A3: Выручка | B3: 1.8798537e+08 | C3: 85447896 | E3: АКТИВЫ | F3: 39722350 | G3: 20510095 | I3: Показатели рентабельности
A4: реклама | B4: 56395611 | C4: 25634369 | E4: Внеоборотные активы: | F4: 11975600 | G4: 7998000 | I4: Рентабельность продаж по валовой прибыли | J4: =B11/B3 -> 0.53 | K4: =C11/C3 -> 0.56 | L4: Показатели рентабельности Kihi в 2023 году немного снизились по сравнению с 2022 годом. Однако сохраняются на достаточно хоршем уровне. | M4: Валовая прибыль / Выручка * 100%
A5: внутриигровые транзакции | B5: 28197806 | C5: 12817184 | E5: Основные средства | F5: 3592680 | G5: 3199200 | I5: Рентабельность продаж по EBITDA | J5: =B18/B3 -> 0.23 | K5: =C18/C3 -> 0.26 | M5: EBITDA / Выручка * 100%
A6: процент с продаж | B6: 37597074 | C6: 17089579 | E6: Нематериальные активы | F6: 8382920 | G6: 4798800 | I6: Рентабельность продаж по чистой прибыли | J6: =B20/B3 -> 0.184 | K6: =C20/C3 -> 0.208 | M6: Чистая прибыль / Выручка * 100%
A7: разработка под ключ | B7: 65794880 | C7: 29906764 | E7: Долгосрочные финансовые вложения | F7: 0 | G7: 0 | I7: Рентабельность затрат (ROCS) | J7: =B20/B12 -> 0.61333333 | K7: =C20/C12 -> 0.69333333 | M7: Чистая прибыль / Расходы * 100%
A8: Себестоимость | B8: 88353124 | C8: 37597074 | I8: Рентабельность собственного капитала (ROE) | J8: =B20/F17 -> 1.3127793 | K8: =C20/G17 -> 1.2057703 | L8: Рентабельность капитала выросла - это хорошо, доходность бизнеса растёт. | M8: Чистая прибыль / Собственный капитал
A9: разработка | B9: 88176418 | C9: 37521880 | E9: Оборотные активы: | F9: 27746750 | G9: 12512095 | I9: Рентабельность активов (ROA) | J9: =B20/F3 -> 0.870777 | K9: =C20/G3 -> 0.8665568 | L9: Рентабельность активов растёт - отлично, значит, Kihi эффективно использует ресурсы в своих процессах. | M9: Чистая прибыль / Стоимость активов * 100%
A10: комиссии плаёжных систем | B10: 176706.25 | C10: 75194.148 | E10: Запасы | F10: 1181166.8 | G10: 536894 | I10: Показатели деловой активности
A11: Валовая прибыль (маржинальный доход) | B11: 99632247 | C11: 47850822 | E11: Дебиторская задолженность | F11: 3352800 | G11: 1524000 | I11: Оборачиваемость кредиторской задолженности | J11: =(((G25+F25)/2)/B8)*365 -> 23.086968 | L11: В среднем Kihi оплачивал счета поставщикам через 23 дня | M11: (Среднее арифметическое значение кредиторской задолженности / Себестоимость продукции в августе) * Количество дней в периоде
A12: Операционные расходы | B12: 56395611 | C12: 25634369 | E12: Краткосрочные финансовые вложения | F12: 14563560 | G12: 6619800 | I12: Оборачиваемость запасов | J12: =(((G10+F10)/2)/B8)*365 -> 3.5487833 | L12: В среднем в 2023 году запасы в Kihi обновлялись каждые 4 дня | M12: (Среднее арифметическое значение запасов / Себестоимость) * Количество дней в периоде
A13: Расходы на персонал | B13: 20040095 | C13: 8527700 | E13: Авансы выданные | F13: 3586000 | G13: 1630000 | I13: Показатели ликвидности и платежеспособности
A14: Аренда | B14: 3383736.7 | C14: 1538062.1 | E14: Денежные средства | F14: 5063222.8 | G14: 2201401.2 | I14: Коэффициент текущей ликвидности | J14: =F9/F25 -> 3.6961108 | K14: =G9/G25 -> 3.409285 | L14: Показатель больше 2 - это говорит о том, что текущие обязательства обеспечены оборотными активами в достаточной мере | M14: Оборотные активы / Краткосрочные обязательства
A15: Реклама и маркетинг | B15: 29889674 | C15: 14098903 | I15: Коэффициент срочной ликвидности | J15: =(F9-F10)/F25 -> 3.538769 | K15: =(G9-G10)/G25 -> 3.2629926 | L15: Показатель больше 1, значит в ближайшей перспективе при любых обстоятельствах компания способна расплатиться по своим долгам | M15: (Денежные Средства + Финансовые вложения + Дебиторская задолженность) / Краткосрочные обязательства
A16: Оборудование и софт | B16: 2255824.5 | C16: 1025374.8 | E16: ПАССИВЫ | F16: 33855165 | G16: 18410095 | I16: Коэффициент мгновенной ликвидности | J16: =F14/F25 -> 0.67446576 | K16: =G14/G25 -> 0.59983592 | L16: Показатель больше 0.2 - это хороший показатель, говорит о том, что компания может погасить большую часть долгов прямо сейчас | M16: Денежные средства / Краткосрочные обязательства
A17: Прочие расходы | B17: 826281.15 | C17: 444329.06 | E17: Капитал и резервы | F17: 26348152 | G17: 14740090 | I17: Показатели финансовой устойчивости компании
A18: EBITDA | B18: 43236635 | C18: 22216453 | E18: Уставный капитал | F18: 132000 | G18: 60000 | I18: Коэффициент финансовой независимости | J18: =F17/F3 -> 0.663308 | K18: =G17/G3 -> 0.71867485 | L18: Показатель больше 0.6 - это хорошо, компания не особо зависит от сторонних кредитов | M18: Собственный Капитал / Активы
A19: Налог на прибыль | B19: 8647327.1 | C19: 4443290.6 | E19: Резервный капитал | F19: 5544000 | G19: 2520000 | I19: Коэффициент финансовой устойчивости | J19: =(F17+F22)/F3 -> 0.663308 | K19: =(G17+G22)/G3 -> 0.71867485 | L19: Показатель говорит о том, что большая часть активов компании сформирована за счёт долгосрочных источников финансирования, а это хорошо. | M19: (Собственный Капитал + Долгосрочные Обязательства) / Активы
A20: Чистая прибыль | B20: 34589308 | C20: 17773162 | E20: Нераспределенная прибыль | F20: 20672152 | G20: 12160090 | I20: Коэффициент обеспеченности собственными оборотными средствами | J20: =(F9-F25)/F9 -> 0.72944534 | K20: =(G9-G25)/G9 -> 0.70668337 | L20: Показатель больше 0.1 - это хорошо. У Kihi достаточно собственных оборотных средств, необходимых для финансовой устойчивости. | M20: (Оборотные активы – Краткосрочные обязательства) / Оборотные активы
I21: Коэффициент маневренности собственного капитала | J21: =(F9-F25)/F17 -> 0.76816533 | K21: =(G9-G25)/G17 -> 0.59986675 | L21: Показатель больше 0.2 - хороший результат, большая часть собственного капитала используется для финансирования текущей деятельности | M21: (Оборотные активы – Краткосрочные обязательства) / Собственный Капитал
E22: Долгосрочные обязательства | F22: 0 | G22: 0 | I22: Общий вывод
E23: Долгосрочные кредиты и займы | F23: 0 | G23: 0 | I23: В целом у Kihi отличные показатели рентабельности, деловой активности, ликвидности, платежеспособности и финансовой устойчивости. Всё говорит о том, что бизнес развивается и готов к расширению.
E25: Краткосрочные обязательства | F25: 7507012.3 | G25: 3670005.6
E26: Кредиторская задолженность по расчётам с бюджетом | F26: 1837012.3 | G26: 835005.6
E27: Кредиторская задолженность по расчётам с персоналом | F27: 5670000 | G27: 2835000
